Workbook

Sheet READ ME
B2: AUSTRALIA DIVIDEND & FRANKING STUDY
B3: S&P/ASX 200 (AS51) and MSCI Australia (MXAU) | Bloomberg BDP / BDS | v2
B5: CHANGES IN THIS VERSION
B6: Franking field confirmed | C6: EQY_DVD_PCT_FRANKED is now hardcoded as the confirmed field. The other candidates have been removed.
B7: Data tabs trimmed | C7: Dropped GICS sector, currency, price, market cap, consensus yield and payout ratio. That is 6 fewer BDP calls per row, roughly 1,600 fewer calls across both tabs, so it also refreshes much faster.
B8: #N/A now handled | C8: Non-payers no longer break the totals. See the section below - this matters more than it looks.
B9: Status column added | C9: Column M labels every row as OK, No dividend, or Franking n/a, so you can see instantly what the data is doing.
B11: ABOUT THE #N/A ROWS - READ THIS ONE
B12: #N/A is usually correct | C12: A stock that pays no dividend has no dividend yield to return. Bloomberg is answering honestly. This is not a formula bug and not something to fix at source.
B13: DO NOT delete those rows | C13: This is the trap. A non-payer has a genuine yield of zero and still occupies index weight. Delete it and you divide the same dividends by a smaller index, which overstates the index yield. On the ASX 200 the non-payers are concentrated in resources and tech, so dropping them biases the answer in a direction someone will notice.
B14: So they are floored at zero, not excluded | C14: Column J wraps the yield in IFERROR(...,0). Non-payers keep their index weight in column I but contribute zero dividend. That is the economically correct treatment and it is what the index itself does.
B15: Franking gaps are treated differently | C15: A stock that pays a dividend but returns no franking value is EXCLUDED from the franked/unfranked split rather than assumed unfranked - assuming zero would silently push the answer toward 'unfranked'. Those rows are flagged 'Franking n/a' and the coverage ratio on row 4 tells you how much dividend they represent.
B16: Check coverage before quoting the split | C16: Cell M4 on each data tab, and the coverage row on Index Summary. Above ~95% you are fine. Materially below that and the split is describing your data gaps, not the market.
B18: TABS
B19: Field Check | C19: Mnemonic tester. Confirmed fields, plus the open question on next-dividend fields.
B20: AS51 / MXAU | C20: Members, weights, DPS, yield, franking. Steps 1 and 2.
B21: Index Summary | C21: Index yield top-down vs bottom-up, and the franked/unfranked split. Steps 3 and 4.
B22: Dvd History | C22: Per-event dividend history - the ground truth for franking.
B24: STILL TRUE FROM LAST TIME
B25: Open on a terminal, then Ctrl+Alt+F9 | C25: Off-terminal everything reads as a name error. That is the add-in not being loaded.
B26: Bloomberg percentages are not fractions | C26: EQY_DVD_YLD_IND returns 3.85 meaning 3.85%. Raw columns are plain-formatted with (%) in the header and divided by 100 in the maths.
B27: Franking is per-dividend, not per-company | C27: An interim can be 100% franked and the final 50%. Use the Dvd History tab to test whether the company-level number holds.
B28: MXAU is quoted in USD | C28: Yields are currency-neutral so the ratio is fine, but confirm the index variant (Standard vs IMI) with your index desk.
B29: Members are a live snapshot | C29: For a fixed date use INDX_MWEIGHT_HIST with END_DATE_OVERRIDE - syntax on Field Check.
B31: COLOUR KEY
B32: Blue text | C32: Hardcoded input - safe to edit.
B33: Black text | C33: Formula - do not overwrite.
B34: Green text | C34: Link to another tab.
B35: Yellow fill | C35: Key assumption needing your sign-off.
B37: Assumptions log
B38: Corporate tax rate 30% | C38: Used for the franking gross-up. Base rate entities (turnover < AUD 50m) are 25% - immaterial at ASX 200 level. Set at 'Index Summary'!C6.
B39: Franking scale = 100 | C39: Assumes EQY_DVD_PCT_FRANKED returns 100 for fully franked. Confirm on Field Check; override at 'Index Summary'!C7.
B40: Yield basis = indicated | C40: Bottom-up uses EQY_DVD_YLD_IND (column G). Trailing 12M is carried in column F if you prefer that basis - repoint column J.
B41: Non-payers floored at zero | C41: Rather than excluded. See the #N/A section above.

Sheet Field Check
B2: FIELD MNEMONIC TESTER
B3: Test ticker | C3: BHP AU Equity | E3: BHP pays fully franked dividends, so a working franking field should return 100 here.
B4: FRANKING FIELD (CONFIRMED) | C4: EQY_DVD_PCT_FRANKED | E4: Confirmed working on terminal. Both data tabs read their franking mnemonic from this cell - change it here and it flows everywhere.
B7: Field | C7: Result | D7: Status | E7: Notes
B8: --- IN USE (all confirmed working) ---
B9: EQY_DVD_PCT_FRANKED | C9: =BDP($C$3,$B9) | D9: =IF(ISNUMBER(C9),"OK - numeric",IF(C9="","blank / no data",IF(ISTEXT(C9),"OK - text","INVALID or error"))) | E9: Franked %. Returns 100 for fully franked. Confirmed.
B10: EQY_DVD_SH_12M | C10: =BDP($C$3,$B10) | D10: =IF(ISNUMBER(C10),"OK - numeric",IF(C10="","blank / no data",IF(ISTEXT(C10),"OK - text","INVALID or error"))) | E10: Gross DPS paid over trailing 12 months, in trading currency.
B11: EQY_DVD_YLD_12M | C11: =BDP($C$3,$B11) | D11: =IF(ISNUMBER(C11),"OK - numeric",IF(C11="","blank / no data",IF(ISTEXT(C11),"OK - text","INVALID or error"))) | E11: Trailing 12-month gross dividend yield, %.
B12: EQY_DVD_YLD_IND | C12: =BDP($C$3,$B12) | D12: =IF(ISNUMBER(C12),"OK - numeric",IF(C12="","blank / no data",IF(ISTEXT(C12),"OK - text","INVALID or error"))) | E12: Indicated gross dividend yield, %. Primary bottom-up input.
B13: NAME | C13: =BDP($C$3,$B13) | D13: =IF(ISNUMBER(C13),"OK - numeric",IF(C13="","blank / no data",IF(ISTEXT(C13),"OK - text","INVALID or error"))) | E13: Company name. If this fails, the ticker or the add-in is the problem, not the field.
B14: --- NEXT / UPCOMING DIVIDEND: open question ---
B15: BDVD_PROJ_DIV_AMT | C15: =BDP($C$3,$B15) | D15: =IF(ISNUMBER(C15),"OK - numeric",IF(C15="","blank / no data",IF(ISTEXT(C15),"OK - text","INVALID or error"))) | E15: Bloomberg Dividend Forecast projected amount. Most likely replacement for what you wanted. Needs the BDVD entitlement.
B16: BDVD_PROJ_DIV_EX_DT | C16: =BDP($C$3,$B16) | D16: =IF(ISNUMBER(C16),"OK - numeric",IF(C16="","blank / no data",IF(ISTEXT(C16),"OK - text","INVALID or error"))) | E16: Projected ex-date to go with the above.
B17: EQY_DVD_SH_LAST | C17: =BDP($C$3,$B17) | D17: =IF(ISNUMBER(C17),"OK - numeric",IF(C17="","blank / no data",IF(ISTEXT(C17),"OK - text","INVALID or error"))) | E17: Most recent declared gross DPS. Not forward-looking, but it always works and is often close enough.
B18: DVD_SH_LAST | C18: =BDP($C$3,$B18) | D18: =IF(ISNUMBER(C18),"OK - numeric",IF(C18="","blank / no data",IF(ISTEXT(C18),"OK - text","INVALID or error"))) | E18: Shorter variant of the above - test which one your terminal takes.
B19: EQY_DVD_SH_NEXT | C19: =BDP($C$3,$B19) | D19: =IF(ISNUMBER(C19),"OK - numeric",IF(C19="","blank / no data",IF(ISTEXT(C19),"OK - text","INVALID or error"))) | E19: YOUR ATTEMPT - returns Invalid Field. Kept here only so nobody retries it.
B20: --- DROPPED IN V2 (were cluttering the data tab) ---
B21: GICS_SECTOR_NAME | D21: not pulled | E21: Only needed if you later want franking cut by sector. Easy to add back.
B22: CUR_MKT_CAP / PX_LAST / CRNCY | D22: not pulled | E22: Not used by any calculation. Weights already come from INDX_MWEIGHT.
B23: BEST_DIV_YLD / DVD_PAYOUT_RATIO | D23: not pulled | E23: Forward and context metrics. Not part of steps 1-4.
B25: ON 'EQY_DVD_SH_NEXT - INVALID FIELD'
B26: - | C26: Invalid Field means the mnemonic does not exist. That is different from a permissions problem - a field you exist but are not entitled to returns N.A. or a 'not licensed' message, not Invalid Field. So this is a naming issue, not an entitlement one, and no amount of retrying will fix it.
B27: - | C27: Forward dividends on Bloomberg live in the BDVD (Bloomberg Dividend Forecast) family rather than the EQY_DVD family. Test BDVD_PROJ_DIV_AMT above. If it returns nothing, you probably lack the forecast entitlement - check with your rep before assuming the field is wrong.
B28: - | C28: Cheapest workaround, needing no new field at all: indicated annual DPS = PX_LAST x EQY_DVD_YLD_IND / 100. The indicated yield already embeds Bloomberg's view of the forward annualised dividend, so you can back the DPS out of it.
B29: - | C29: Authoritative check either way: FLDS<GO> from any ASX ticker, search 'dividend', and read the field descriptions. Two minutes there beats guessing, which is what got us here.
B31: OTHER SYNTAX
B32: Purpose | C32: Formula | D32: Notes
B33: Members at a past date | C33: '=BDS("AS51 Index","INDX_MWEIGHT_HIST","END_DATE_OVERRIDE","20260630") | E33: Frozen membership + weights. Use for any point-in-time study.
B34: Dividend history | C34: '=BDS($C$3,"DVD_HIST_ALL","DVD_START_DT","20250801","DVD_END_DT","20260803") | E34: Per-event. Check whether the returned columns carry franking for ASX names.
B35: Index yield direct | C35: '=BDP("AS51 Index","EQY_DVD_YLD_IND") | E35: Bloomberg's own index yield - reconcile bottom-up against this.
B36: Suppress errors at source | C36: '=IFERROR(BDP($C$3,"EQY_DVD_YLD_IND"),0) | E36: Excel-side, always works. Preferred over Bloomberg's own fill parameters, which vary by add-in version.
B38: Formulas shown as text - copy and drop the leading apostrophe.

Sheet AS51
A1: S&P/ASX 200 (AS51) - MEMBERS, DIVIDENDS & FRANKING
A2: Index ticker | B2: AS51 Index | C2: 200 members; rows 6:275 pre-built for headroom. | E2: Members returned | G2: =COUNTIF($A$6:$A$275,"?*") | I2: No dividend | J2: =COUNTIF($M$6:$M$275,"No dividend") | K2: <- expected, not errors. | L2: =IF($G$2=$G$3+$J$2,"reconciles","CHECK: status counts do not sum to members")
A3: Weight scale | B3: =IF(SUM($B$6:$B$275)>2,100,1) | C3: Auto: 100 if weights came back as percentages, 1 if as fractions. | E3: Dividend payers | G3: =COUNTIF($M$6:$M$275,"OK")+COUNTIF($M$6:$M$275,"Franking n/a") | I3: Franking n/a | J3: =COUNTIF($M$6:$M$275,"Franking n/a") | K3: <- these are excluded from the split.
A4: TOTALS | I4: =IFERROR(SUM($I$6:$I$275),"") | J4: =IFERROR(SUM($J$6:$J$275),"") | K4: =IFERROR(SUM($K$6:$K$275),"") | L4: =IFERROR(SUM($L$6:$L$275),"") | M4: =IFERROR(($K$4+$L$4)/$J$4,"") | N4: <- FRANKING COVERAGE: share of index dividends with a known franking status. Check this before quoting the split.
A5: Member Ticker | B5: Raw Weight | C5: Bloomberg Ticker | D5: Company Name | E5: DPS 12M | F5: Div Yld 12M (%) | G5: Div Yld Ind (%) | H5: Franked (%) | I5: Weight | J5: Yld Contrib | K5: Franked Contrib | L5: Unfranked Contrib | M5: Status
A6: =BDS($B$2,"INDX_MWEIGHT") | C6: =IF($A6="","",$A6&" Equity") | D6: =IF($A6="","",BDP($C6,"NAME")) | E6: =IF($A6="","",BDP($C6,"EQY_DVD_SH_12M")) | F6: =IF($A6="","",BDP($C6,"EQY_DVD_YLD_12M")) | G6: =IF($A6="","",BDP($C6,"EQY_DVD_YLD_IND")) | H6: =IF($A6="","",BDP($C6,'Field Check'!$C$4)) | I6: =IFERROR(IF($B6="","",$B6/$B$3),"") | J6: =IFERROR(IF($I6="","",$I6*IFERROR($G6,0)/100),"") | K6: =IFERROR(IF($J6="","",IF(ISNUMBER($H6),$J6*$H6/'Index Summary'!$C$7,"")),"") | L6: =IFERROR(IF($K6="","",$J6-$K6),"") | M6: =IF($C6="","",IF(NOT(ISNUMBER($G6)),"No dividend",IF($G6=0,"No dividend",IF(ISNUMBER($H6),"OK","Franking n/a"))))
C7: =IF($A7="","",$A7&" Equity") | D7: =IF($A7="","",BDP($C7,"NAME")) | E7: =IF($A7="","",BDP($C7,"EQY_DVD_SH_12M")) | F7: =IF($A7="","",BDP($C7,"EQY_DVD_YLD_12M")) | G7: =IF($A7="","",BDP($C7,"EQY_DVD_YLD_IND")) | H7: =IF($A7="","",BDP($C7,'Field Check'!$C$4)) | I7: =IFERROR(IF($B7="","",$B7/$B$3),"") | J7: =IFERROR(IF($I7="","",$I7*IFERROR($G7,0)/100),"") | K7: =IFERROR(IF($J7="","",IF(ISNUMBER($H7),$J7*$H7/'Index Summary'!$C$7,"")),"") | L7: =IFERROR(IF($K7="","",$J7-$K7),"") | M7: =IF($C7="","",IF(NOT(ISNUMBER($G7)),"No dividend",IF($G7=0,"No dividend",IF(ISNUMBER($H7),"OK","Franking n/a"))))
C8: =IF($A8="","",$A8&" Equity") | D8: =IF($A8="","",BDP($C8,"NAME")) | E8: =IF($A8="","",BDP($C8,"EQY_DVD_SH_12M")) | F8: =IF($A8="","",BDP($C8,"EQY_DVD_YLD_12M")) | G8: =IF($A8="","",BDP($C8,"EQY_DVD_YLD_IND")) | H8: =IF($A8="","",BDP($C8,'Field Check'!$C$4)) | I8: =IFERROR(IF($B8="","",$B8/$B$3),"") | J8: =IFERROR(IF($I8="","",$I8*IFERROR($G8,0)/100),"") | K8: =IFERROR(IF($J8="","",IF(ISNUMBER($H8),$J8*$H8/'Index Summary'!$C$7,"")),"") | L8: =IFERROR(IF($K8="","",$J8-$K8),"") | M8: =IF($C8="","",IF(NOT(ISNUMBER($G8)),"No dividend",IF($G8=0,"No dividend",IF(ISNUMBER($H8),"OK","Franking n/a"))))
C9: =IF($A9="","",$A9&" Equity") | D9: =IF($A9="","",BDP($C9,"NAME")) | E9: =IF($A9="","",BDP($C9,"EQY_DVD_SH_12M")) | F9: =IF($A9="","",BDP($C9,"EQY_DVD_YLD_12M")) | G9: =IF($A9="","",BDP($C9,"EQY_DVD_YLD_IND")) | H9: =IF($A9="","",BDP($C9,'Field Check'!$C$4)) | I9: =IFERROR(IF($B9="","",$B9/$B$3),"") | J9: =IFERROR(IF($I9="","",$I9*IFERROR($G9,0)/100),"") | K9: =IFERROR(IF($J9="","",IF(ISNUMBER($H9),$J9*$H9/'Index Summary'!$C$7,"")),"") | L9: =IFERROR(IF($K9="","",$J9-$K9),"") | M9: =IF($C9="","",IF(NOT(ISNUMBER($G9)),"No dividend",IF($G9=0,"No dividend",IF(ISNUMBER($H9),"OK","Franking n/a"))))
C10: =IF($A10="","",$A10&" Equity") | D10: =IF($A10="","",BDP($C10,"NAME")) | E10: =IF($A10="","",BDP($C10,"EQY_DVD_SH_12M")) | F10: =IF($A10="","",BDP($C10,"EQY_DVD_YLD_12M")) | G10: =IF($A10="","",BDP($C10,"EQY_DVD_YLD_IND")) | H10: =IF($A10="","",BDP($C10,'Field Check'!$C$4)) | I10: =IFERROR(IF($B10="","",$B10/$B$3),"") | J10: =IFERROR(IF($I10="","",$I10*IFERROR($G10,0)/100),"") | K10: =IFERROR(IF($J10="","",IF(ISNUMBER($H10),$J10*$H10/'Index Summary'!$C$7,"")),"") | L10: =IFERROR(IF($K10="","",$J10-$K10),"") | M10: =IF($C10="","",IF(NOT(ISNUMBER($G10)),"No dividend",IF($G10=0,"No dividend",IF(ISNUMBER($H10),"OK","Franking n/a"))))
C11: =IF($A11="","",$A11&" Equity") | D11: =IF($A11="","",BDP($C11,"NAME")) | E11: =IF($A11="","",BDP($C11,"EQY_DVD_SH_12M")) | F11: =IF($A11="","",BDP($C11,"EQY_DVD_YLD_12M")) | G11: =IF($A11="","",BDP($C11,"EQY_DVD_YLD_IND")) | H11: =IF($A11="","",BDP($C11,'Field Check'!$C$4)) | I11: =IFERROR(IF($B11="","",$B11/$B$3),"") | J11: =IFERROR(IF($I11="","",$I11*IFERROR($G11,0)/100),"") | K11: =IFERROR(IF($J11="","",IF(ISNUMBER($H11),$J11*$H11/'Index Summary'!$C$7,"")),"") | L11: =IFERROR(IF($K11="","",$J11-$K11),"") | M11: =IF($C11="","",IF(NOT(ISNUMBER($G11)),"No dividend",IF($G11=0,"No dividend",IF(ISNUMBER($H11),"OK","Franking n/a"))))
C12: =IF($A12="","",$A12&" Equity") | D12: =IF($A12="","",BDP($C12,"NAME")) | E12: =IF($A12="","",BDP($C12,"EQY_DVD_SH_12M")) | F12: =IF($A12="","",BDP($C12,"EQY_DVD_YLD_12M")) | G12: =IF($A12="","",BDP($C12,"EQY_DVD_YLD_IND")) | H12: =IF($A12="","",BDP($C12,'Field Check'!$C$4)) | I12: =IFERROR(IF($B12="","",$B12/$B$3),"") | J12: =IFERROR(IF($I12="","",$I12*IFERROR($G12,0)/100),"") | K12: =IFERROR(IF($J12="","",IF(ISNUMBER($H12),$J12*$H12/'Index Summary'!$C$7,"")),"") | L12: =IFERROR(IF($K12="","",$J12-$K12),"") | M12: =IF($C12="","",IF(NOT(ISNUMBER($G12)),"No dividend",IF($G12=0,"No dividend",IF(ISNUMBER($H12),"OK","Franking n/a"))))
C13: =IF($A13="","",$A13&" Equity") | D13: =IF($A13="","",BDP($C13,"NAME")) | E13: =IF($A13="","",BDP($C13,"EQY_DVD_SH_12M")) | F13: =IF($A13="","",BDP($C13,"EQY_DVD_YLD_12M")) | G13: =IF($A13="","",BDP($C13,"EQY_DVD_YLD_IND")) | H13: =IF($A13="","",BDP($C13,'Field Check'!$C$4)) | I13: =IFERROR(IF($B13="","",$B13/$B$3),"") | J13: =IFERROR(IF($I13="","",$I13*IFERROR($G13,0)/100),"") | K13: =IFERROR(IF($J13="","",IF(ISNUMBER($H13),$J13*$H13/'Index Summary'!$C$7,"")),"") | L13: =IFERROR(IF($K13="","",$J13-$K13),"") | M13: =IF($C13="","",IF(NOT(ISNUMBER($G13)),"No dividend",IF($G13=0,"No dividend",IF(ISNUMBER($H13),"OK","Franking n/a"))))
C14: =IF($A14="","",$A14&" Equity") | D14: =IF($A14="","",BDP($C14,"NAME")) | E14: =IF($A14="","",BDP($C14,"EQY_DVD_SH_12M")) | F14: =IF($A14="","",BDP($C14,"EQY_DVD_YLD_12M")) | G14: =IF($A14="","",BDP($C14,"EQY_DVD_YLD_IND")) | H14: =IF($A14="","",BDP($C14,'Field Check'!$C$4)) | I14: =IFERROR(IF($B14="","",$B14/$B$3),"") | J14: =IFERROR(IF($I14="","",$I14*IFERROR($G14,0)/100),"") | K14: =IFERROR(IF($J14="","",IF(ISNUMBER($H14),$J14*$H14/'Index Summary'!$C$7,"")),"") | L14: =IFERROR(IF($K14="","",$J14-$K14),"") | M14: =IF($C14="","",IF(NOT(ISNUMBER($G14)),"No dividend",IF($G14=0,"No dividend",IF(ISNUMBER($H14),"OK","Franking n/a"))))
C15: =IF($A15="","",$A15&" Equity") | D15: =IF($A15="","",BDP($C15,"NAME")) | E15: =IF($A15="","",BDP($C15,"EQY_DVD_SH_12M")) | F15: =IF($A15="","",BDP($C15,"EQY_DVD_YLD_12M")) | G15: =IF($A15="","",BDP($C15,"EQY_DVD_YLD_IND")) | H15: =IF($A15="","",BDP($C15,'Field Check'!$C$4)) | I15: =IFERROR(IF($B15="","",$B15/$B$3),"") | J15: =IFERROR(IF($I15="","",$I15*IFERROR($G15,0)/100),"") | K15: =IFERROR(IF($J15="","",IF(ISNUMBER($H15),$J15*$H15/'Index Summary'!$C$7,"")),"") | L15: =IFERROR(IF($K15="","",$J15-$K15),"") | M15: =IF($C15="","",IF(NOT(ISNUMBER($G15)),"No dividend",IF($G15=0,"No dividend",IF(ISNUMBER($H15),"OK","Franking n/a"))))
C16: =IF($A16="","",$A16&" Equity") | D16: =IF($A16="","",BDP($C16,"NAME")) | E16: =IF($A16="","",BDP($C16,"EQY_DVD_SH_12M")) | F16: =IF($A16="","",BDP($C16,"EQY_DVD_YLD_12M")) | G16: =IF($A16="","",BDP($C16,"EQY_DVD_YLD_IND")) | H16: =IF($A16="","",BDP($C16,'Field Check'!$C$4)) | I16: =IFERROR(IF($B16="","",$B16/$B$3),"") | J16: =IFERROR(IF($I16="","",$I16*IFERROR($G16,0)/100),"") | K16: =IFERROR(IF($J16="","",IF(ISNUMBER($H16),$J16*$H16/'Index Summary'!$C$7,"")),"") | L16: =IFERROR(IF($K16="","",$J16-$K16),"") | M16: =IF($C16="","",IF(NOT(ISNUMBER($G16)),"No dividend",IF($G16=0,"No dividend",IF(ISNUMBER($H16),"OK","Franking n/a"))))
C17: =IF($A17="","",$A17&" Equity") | D17: =IF($A17="","",BDP($C17,"NAME")) | E17: =IF($A17="","",BDP($C17,"EQY_DVD_SH_12M")) | F17: =IF($A17="","",BDP($C17,"EQY_DVD_YLD_12M")) | G17: =IF($A17="","",BDP($C17,"EQY_DVD_YLD_IND")) | H17: =IF($A17="","",BDP($C17,'Field Check'!$C$4)) | I17: =IFERROR(IF($B17="","",$B17/$B$3),"") | J17: =IFERROR(IF($I17="","",$I17*IFERROR($G17,0)/100),"") | K17: =IFERROR(IF($J17="","",IF(ISNUMBER($H17),$J17*$H17/'Index Summary'!$C$7,"")),"") | L17: =IFERROR(IF($K17="","",$J17-$K17),"") | M17: =IF($C17="","",IF(NOT(ISNUMBER($G17)),"No dividend",IF($G17=0,"No dividend",IF(ISNUMBER($H17),"OK","Franking n/a"))))
C18: =IF($A18="","",$A18&" Equity") | D18: =IF($A18="","",BDP($C18,"NAME")) | E18: =IF($A18="","",BDP($C18,"EQY_DVD_SH_12M")) | F18: =IF($A18="","",BDP($C18,"EQY_DVD_YLD_12M")) | G18: =IF($A18="","",BDP($C18,"EQY_DVD_YLD_IND")) | H18: =IF($A18="","",BDP($C18,'Field Check'!$C$4)) | I18: =IFERROR(IF($B18="","",$B18/$B$3),"") | J18: =IFERROR(IF($I18="","",$I18*IFERROR($G18,0)/100),"") | K18: =IFERROR(IF($J18="","",IF(ISNUMBER($H18),$J18*$H18/'Index Summary'!$C$7,"")),"") | L18: =IFERROR(IF($K18="","",$J18-$K18),"") | M18: =IF($C18="","",IF(NOT(ISNUMBER($G18)),"No dividend",IF($G18=0,"No dividend",IF(ISNUMBER($H18),"OK","Franking n/a"))))
... C275: =IF($A275="","",$A275&" Equity") | D275: =IF($A275="","",BDP($C275,"NAME")) | E275: =IF($A275="","",BDP($C275,"EQY_DVD_SH_12M")) | F275: =IF($A275="","",BDP($C275,"EQY_DVD_YLD_12M")) | G275: =IF($A275="","",BDP($C275,"EQY_DVD_YLD_IND")) | H275: =IF($A275="","",BDP($C275,'Field Check'!$C$4)) | I275: =IFERROR(IF($B275="","",$B275/$B$3),"") | J275: =IFERROR(IF($I275="","",$I275*IFERROR($G275,0)/100),"") | K275: =IFERROR(IF($J275="","",IF(ISNUMBER($H275),$J275*$H275/'Index Summary'!$C$7,"")),"") | L275: =IFERROR(IF($K275="","",$J275-$K275),"") | M275: =IF($C275="","",IF(NOT(ISNUMBER($G275)),"No dividend",IF($G275=0,"No dividend",IF(ISNUMBER($H275),"OK","Franking n/a"))))

Sheet MXAU
A1: MSCI Australia (MXAU) - MEMBERS, DIVIDENDS & FRANKING
A2: Index ticker | B2: MXAU Index | C2: ~55-65 members; rows 6:175 pre-built. | E2: Members returned | G2: =COUNTIF($A$6:$A$175,"?*") | I2: No dividend | J2: =COUNTIF($M$6:$M$175,"No dividend") | K2: <- expected, not errors. | L2: =IF($G$2=$G$3+$J$2,"reconciles","CHECK: status counts do not sum to members")
A3: Weight scale | B3: =IF(SUM($B$6:$B$175)>2,100,1) | C3: Auto: 100 if weights came back as percentages, 1 if as fractions. | E3: Dividend payers | G3: =COUNTIF($M$6:$M$175,"OK")+COUNTIF($M$6:$M$175,"Franking n/a") | I3: Franking n/a | J3: =COUNTIF($M$6:$M$175,"Franking n/a") | K3: <- these are excluded from the split.
A4: TOTALS | I4: =IFERROR(SUM($I$6:$I$175),"") | J4: =IFERROR(SUM($J$6:$J$175),"") | K4: =IFERROR(SUM($K$6:$K$175),"") | L4: =IFERROR(SUM($L$6:$L$175),"") | M4: =IFERROR(($K$4+$L$4)/$J$4,"") | N4: <- FRANKING COVERAGE: share of index dividends with a known franking status. Check this before quoting the split.
A5: Member Ticker | B5: Raw Weight | C5: Bloomberg Ticker | D5: Company Name | E5: DPS 12M | F5: Div Yld 12M (%) | G5: Div Yld Ind (%) | H5: Franked (%) | I5: Weight | J5: Yld Contrib | K5: Franked Contrib | L5: Unfranked Contrib | M5: Status
A6: =BDS($B$2,"INDX_MWEIGHT") | C6: =IF($A6="","",$A6&" Equity") | D6: =IF($A6="","",BDP($C6,"NAME")) | E6: =IF($A6="","",BDP($C6,"EQY_DVD_SH_12M")) | F6: =IF($A6="","",BDP($C6,"EQY_DVD_YLD_12M")) | G6: =IF($A6="","",BDP($C6,"EQY_DVD_YLD_IND")) | H6: =IF($A6="","",BDP($C6,'Field Check'!$C$4)) | I6: =IFERROR(IF($B6="","",$B6/$B$3),"") | J6: =IFERROR(IF($I6="","",$I6*IFERROR($G6,0)/100),"") | K6: =IFERROR(IF($J6="","",IF(ISNUMBER($H6),$J6*$H6/'Index Summary'!$C$7,"")),"") | L6: =IFERROR(IF($K6="","",$J6-$K6),"") | M6: =IF($C6="","",IF(NOT(ISNUMBER($G6)),"No dividend",IF($G6=0,"No dividend",IF(ISNUMBER($H6),"OK","Franking n/a"))))
C7: =IF($A7="","",$A7&" Equity") | D7: =IF($A7="","",BDP($C7,"NAME")) | E7: =IF($A7="","",BDP($C7,"EQY_DVD_SH_12M")) | F7: =IF($A7="","",BDP($C7,"EQY_DVD_YLD_12M")) | G7: =IF($A7="","",BDP($C7,"EQY_DVD_YLD_IND")) | H7: =IF($A7="","",BDP($C7,'Field Check'!$C$4)) | I7: =IFERROR(IF($B7="","",$B7/$B$3),"") | J7: =IFERROR(IF($I7="","",$I7*IFERROR($G7,0)/100),"") | K7: =IFERROR(IF($J7="","",IF(ISNUMBER($H7),$J7*$H7/'Index Summary'!$C$7,"")),"") | L7: =IFERROR(IF($K7="","",$J7-$K7),"") | M7: =IF($C7="","",IF(NOT(ISNUMBER($G7)),"No dividend",IF($G7=0,"No dividend",IF(ISNUMBER($H7),"OK","Franking n/a"))))
C8: =IF($A8="","",$A8&" Equity") | D8: =IF($A8="","",BDP($C8,"NAME")) | E8: =IF($A8="","",BDP($C8,"EQY_DVD_SH_12M")) | F8: =IF($A8="","",BDP($C8,"EQY_DVD_YLD_12M")) | G8: =IF($A8="","",BDP($C8,"EQY_DVD_YLD_IND")) | H8: =IF($A8="","",BDP($C8,'Field Check'!$C$4)) | I8: =IFERROR(IF($B8="","",$B8/$B$3),"") | J8: =IFERROR(IF($I8="","",$I8*IFERROR($G8,0)/100),"") | K8: =IFERROR(IF($J8="","",IF(ISNUMBER($H8),$J8*$H8/'Index Summary'!$C$7,"")),"") | L8: =IFERROR(IF($K8="","",$J8-$K8),"") | M8: =IF($C8="","",IF(NOT(ISNUMBER($G8)),"No dividend",IF($G8=0,"No dividend",IF(ISNUMBER($H8),"OK","Franking n/a"))))
C9: =IF($A9="","",$A9&" Equity") | D9: =IF($A9="","",BDP($C9,"NAME")) | E9: =IF($A9="","",BDP($C9,"EQY_DVD_SH_12M")) | F9: =IF($A9="","",BDP($C9,"EQY_DVD_YLD_12M")) | G9: =IF($A9="","",BDP($C9,"EQY_DVD_YLD_IND")) | H9: =IF($A9="","",BDP($C9,'Field Check'!$C$4)) | I9: =IFERROR(IF($B9="","",$B9/$B$3),"") | J9: =IFERROR(IF($I9="","",$I9*IFERROR($G9,0)/100),"") | K9: =IFERROR(IF($J9="","",IF(ISNUMBER($H9),$J9*$H9/'Index Summary'!$C$7,"")),"") | L9: =IFERROR(IF($K9="","",$J9-$K9),"") | M9: =IF($C9="","",IF(NOT(ISNUMBER($G9)),"No dividend",IF($G9=0,"No dividend",IF(ISNUMBER($H9),"OK","Franking n/a"))))
C10: =IF($A10="","",$A10&" Equity") | D10: =IF($A10="","",BDP($C10,"NAME")) | E10: =IF($A10="","",BDP($C10,"EQY_DVD_SH_12M")) | F10: =IF($A10="","",BDP($C10,"EQY_DVD_YLD_12M")) | G10: =IF($A10="","",BDP($C10,"EQY_DVD_YLD_IND")) | H10: =IF($A10="","",BDP($C10,'Field Check'!$C$4)) | I10: =IFERROR(IF($B10="","",$B10/$B$3),"") | J10: =IFERROR(IF($I10="","",$I10*IFERROR($G10,0)/100),"") | K10: =IFERROR(IF($J10="","",IF(ISNUMBER($H10),$J10*$H10/'Index Summary'!$C$7,"")),"") | L10: =IFERROR(IF($K10="","",$J10-$K10),"") | M10: =IF($C10="","",IF(NOT(ISNUMBER($G10)),"No dividend",IF($G10=0,"No dividend",IF(ISNUMBER($H10),"OK","Franking n/a"))))
C11: =IF($A11="","",$A11&" Equity") | D11: =IF($A11="","",BDP($C11,"NAME")) | E11: =IF($A11="","",BDP($C11,"EQY_DVD_SH_12M")) | F11: =IF($A11="","",BDP($C11,"EQY_DVD_YLD_12M")) | G11: =IF($A11="","",BDP($C11,"EQY_DVD_YLD_IND")) | H11: =IF($A11="","",BDP($C11,'Field Check'!$C$4)) | I11: =IFERROR(IF($B11="","",$B11/$B$3),"") | J11: =IFERROR(IF($I11="","",$I11*IFERROR($G11,0)/100),"") | K11: =IFERROR(IF($J11="","",IF(ISNUMBER($H11),$J11*$H11/'Index Summary'!$C$7,"")),"") | L11: =IFERROR(IF($K11="","",$J11-$K11),"") | M11: =IF($C11="","",IF(NOT(ISNUMBER($G11)),"No dividend",IF($G11=0,"No dividend",IF(ISNUMBER($H11),"OK","Franking n/a"))))
C12: =IF($A12="","",$A12&" Equity") | D12: =IF($A12="","",BDP($C12,"NAME")) | E12: =IF($A12="","",BDP($C12,"EQY_DVD_SH_12M")) | F12: =IF($A12="","",BDP($C12,"EQY_DVD_YLD_12M")) | G12: =IF($A12="","",BDP($C12,"EQY_DVD_YLD_IND")) | H12: =IF($A12="","",BDP($C12,'Field Check'!$C$4)) | I12: =IFERROR(IF($B12="","",$B12/$B$3),"") | J12: =IFERROR(IF($I12="","",$I12*IFERROR($G12,0)/100),"") | K12: =IFERROR(IF($J12="","",IF(ISNUMBER($H12),$J12*$H12/'Index Summary'!$C$7,"")),"") | L12: =IFERROR(IF($K12="","",$J12-$K12),"") | M12: =IF($C12="","",IF(NOT(ISNUMBER($G12)),"No dividend",IF($G12=0,"No dividend",IF(ISNUMBER($H12),"OK","Franking n/a"))))
C13: =IF($A13="","",$A13&" Equity") | D13: =IF($A13="","",BDP($C13,"NAME")) | E13: =IF($A13="","",BDP($C13,"EQY_DVD_SH_12M")) | F13: =IF($A13="","",BDP($C13,"EQY_DVD_YLD_12M")) | G13: =IF($A13="","",BDP($C13,"EQY_DVD_YLD_IND")) | H13: =IF($A13="","",BDP($C13,'Field Check'!$C$4)) | I13: =IFERROR(IF($B13="","",$B13/$B$3),"") | J13: =IFERROR(IF($I13="","",$I13*IFERROR($G13,0)/100),"") | K13: =IFERROR(IF($J13="","",IF(ISNUMBER($H13),$J13*$H13/'Index Summary'!$C$7,"")),"") | L13: =IFERROR(IF($K13="","",$J13-$K13),"") | M13: =IF($C13="","",IF(NOT(ISNUMBER($G13)),"No dividend",IF($G13=0,"No dividend",IF(ISNUMBER($H13),"OK","Franking n/a"))))
C14: =IF($A14="","",$A14&" Equity") | D14: =IF($A14="","",BDP($C14,"NAME")) | E14: =IF($A14="","",BDP($C14,"EQY_DVD_SH_12M")) | F14: =IF($A14="","",BDP($C14,"EQY_DVD_YLD_12M")) | G14: =IF($A14="","",BDP($C14,"EQY_DVD_YLD_IND")) | H14: =IF($A14="","",BDP($C14,'Field Check'!$C$4)) | I14: =IFERROR(IF($B14="","",$B14/$B$3),"") | J14: =IFERROR(IF($I14="","",$I14*IFERROR($G14,0)/100),"") | K14: =IFERROR(IF($J14="","",IF(ISNUMBER($H14),$J14*$H14/'Index Summary'!$C$7,"")),"") | L14: =IFERROR(IF($K14="","",$J14-$K14),"") | M14: =IF($C14="","",IF(NOT(ISNUMBER($G14)),"No dividend",IF($G14=0,"No dividend",IF(ISNUMBER($H14),"OK","Franking n/a"))))
C15: =IF($A15="","",$A15&" Equity") | D15: =IF($A15="","",BDP($C15,"NAME")) | E15: =IF($A15="","",BDP($C15,"EQY_DVD_SH_12M")) | F15: =IF($A15="","",BDP($C15,"EQY_DVD_YLD_12M")) | G15: =IF($A15="","",BDP($C15,"EQY_DVD_YLD_IND")) | H15: =IF($A15="","",BDP($C15,'Field Check'!$C$4)) | I15: =IFERROR(IF($B15="","",$B15/$B$3),"") | J15: =IFERROR(IF($I15="","",$I15*IFERROR($G15,0)/100),"") | K15: =IFERROR(IF($J15="","",IF(ISNUMBER($H15),$J15*$H15/'Index Summary'!$C$7,"")),"") | L15: =IFERROR(IF($K15="","",$J15-$K15),"") | M15: =IF($C15="","",IF(NOT(ISNUMBER($G15)),"No dividend",IF($G15=0,"No dividend",IF(ISNUMBER($H15),"OK","Franking n/a"))))
C16: =IF($A16="","",$A16&" Equity") | D16: =IF($A16="","",BDP($C16,"NAME")) | E16: =IF($A16="","",BDP($C16,"EQY_DVD_SH_12M")) | F16: =IF($A16="","",BDP($C16,"EQY_DVD_YLD_12M")) | G16: =IF($A16="","",BDP($C16,"EQY_DVD_YLD_IND")) | H16: =IF($A16="","",BDP($C16,'Field Check'!$C$4)) | I16: =IFERROR(IF($B16="","",$B16/$B$3),"") | J16: =IFERROR(IF($I16="","",$I16*IFERROR($G16,0)/100),"") | K16: =IFERROR(IF($J16="","",IF(ISNUMBER($H16),$J16*$H16/'Index Summary'!$C$7,"")),"") | L16: =IFERROR(IF($K16="","",$J16-$K16),"") | M16: =IF($C16="","",IF(NOT(ISNUMBER($G16)),"No dividend",IF($G16=0,"No dividend",IF(ISNUMBER($H16),"OK","Franking n/a"))))
C17: =IF($A17="","",$A17&" Equity") | D17: =IF($A17="","",BDP($C17,"NAME")) | E17: =IF($A17="","",BDP($C17,"EQY_DVD_SH_12M")) | F17: =IF($A17="","",BDP($C17,"EQY_DVD_YLD_12M")) | G17: =IF($A17="","",BDP($C17,"EQY_DVD_YLD_IND")) | H17: =IF($A17="","",BDP($C17,'Field Check'!$C$4)) | I17: =IFERROR(IF($B17="","",$B17/$B$3),"") | J17: =IFERROR(IF($I17="","",$I17*IFERROR($G17,0)/100),"") | K17: =IFERROR(IF($J17="","",IF(ISNUMBER($H17),$J17*$H17/'Index Summary'!$C$7,"")),"") | L17: =IFERROR(IF($K17="","",$J17-$K17),"") | M17: =IF($C17="","",IF(NOT(ISNUMBER($G17)),"No dividend",IF($G17=0,"No dividend",IF(ISNUMBER($H17),"OK","Franking n/a"))))
C18: =IF($A18="","",$A18&" Equity") | D18: =IF($A18="","",BDP($C18,"NAME")) | E18: =IF($A18="","",BDP($C18,"EQY_DVD_SH_12M")) | F18: =IF($A18="","",BDP($C18,"EQY_DVD_YLD_12M")) | G18: =IF($A18="","",BDP($C18,"EQY_DVD_YLD_IND")) | H18: =IF($A18="","",BDP($C18,'Field Check'!$C$4)) | I18: =IFERROR(IF($B18="","",$B18/$B$3),"") | J18: =IFERROR(IF($I18="","",$I18*IFERROR($G18,0)/100),"") | K18: =IFERROR(IF($J18="","",IF(ISNUMBER($H18),$J18*$H18/'Index Summary'!$C$7,"")),"") | L18: =IFERROR(IF($K18="","",$J18-$K18),"") | M18: =IF($C18="","",IF(NOT(ISNUMBER($G18)),"No dividend",IF($G18=0,"No dividend",IF(ISNUMBER($H18),"OK","Franking n/a"))))
... C175: =IF($A175="","",$A175&" Equity") | D175: =IF($A175="","",BDP($C175,"NAME")) | E175: =IF($A175="","",BDP($C175,"EQY_DVD_SH_12M")) | F175: =IF($A175="","",BDP($C175,"EQY_DVD_YLD_12M")) | G175: =IF($A175="","",BDP($C175,"EQY_DVD_YLD_IND")) | H175: =IF($A175="","",BDP($C175,'Field Check'!$C$4)) | I175: =IFERROR(IF($B175="","",$B175/$B$3),"") | J175: =IFERROR(IF($I175="","",$I175*IFERROR($G175,0)/100),"") | K175: =IFERROR(IF($J175="","",IF(ISNUMBER($H175),$J175*$H175/'Index Summary'!$C$7,"")),"") | L175: =IFERROR(IF($K175="","",$J175-$K175),"") | M175: =IF($C175="","",IF(NOT(ISNUMBER($G175)),"No dividend",IF($G175=0,"No dividend",IF(ISNUMBER($H175),"OK","Franking n/a"))))

Sheet Index Summary
B2: INDEX DIVIDEND YIELD & FRANKING SPLIT
B3: Steps 3 and 4, driven entirely off the AS51 and MXAU tabs.
B5: ASSUMPTIONS
B6: Australian corporate tax rate | C6: 0.3 | F6: Standard company rate. Base rate entities are 25% - not material at index level.
B7: Franking scale (100 or 1) | C7: 100 | F7: EQY_DVD_PCT_FRANKED returns 100 for fully franked, so 100. Change only if your terminal returns 1.0.
B10: Metric | C10: AS51 | D10: MXAU | F10: Notes
B11: STEP 3 - INDEX DIVIDEND YIELD
B12: Bloomberg index yield, indicated (%) | C12: =BDP(AS51!$B$2,"EQY_DVD_YLD_IND") | D12: =BDP(MXAU!$B$2,"EQY_DVD_YLD_IND") | F12: Top-down: Bloomberg's own figure. Returns 3.85 for 3.85%.
B13: Bottom-up weighted yield | C13: =IFERROR(AS51!$J$4,"") | D13: =IFERROR(MXAU!$J$4,"") | F13: SUM of member weight x member indicated yield, with non-payers included at zero.
B14: Reconciliation gap (bottom-up less top-down) | C14: =IFERROR(C13-C12/100,"") | D14: =IFERROR(D13-D12/100,"") | F14: Should be within roughly 20bp. Wider means missing members, float vs full-cap weights, or stale prices.
B15: Total index weight captured | C15: =IFERROR(AS51!$I$4,"") | D15: =IFERROR(MXAU!$I$4,"") | F15: Should be ~100%. If not, BDS did not return every member.
B16: STEP 4 - FRANKED vs UNFRANKED
B17: Franked yield contribution | C17: =IFERROR(AS51!$K$4,"") | D17: =IFERROR(MXAU!$K$4,"") | F17: Portion of index yield carrying franking credits.
B18: Unfranked yield contribution | C18: =IFERROR(AS51!$L$4,"") | D18: =IFERROR(MXAU!$L$4,"") | F18: Portion with no franking credits attached.
B19: Franked % of index dividends | C19: =IFERROR(C17/(C17+C18),"") | D19: =IFERROR(D17/(D17+D18),"") | F19: THE HEADLINE NUMBER for step 4. Share of index dividend income that is franked.
B20: Unfranked % of index dividends | C20: =IFERROR(1-C19,"") | D20: =IFERROR(1-D19,"") | F20: Complement of the above.
B21: Franking coverage (% of dividends) | C21: =IFERROR(AS51!$M$4,"") | D21: =IFERROR(MXAU!$M$4,"") | F21: READ BEFORE QUOTING THE SPLIT. Share of index dividends with a known franking status. Below ~95% and the two rows above are partly describing data gaps.
B22: GROSS-UP FOR FRANKING CREDITS
B23: Franking credit yield | C23: =IFERROR(C17*$C$6/(1-$C$6),"") | D23: =IFERROR(D17*$C$6/(1-$C$6),"") | F23: Imputation credit on the franked portion: franked yield x t/(1-t). At t=30%, x 0.4286.
B24: Grossed-up yield (cash + credits) | C24: =IFERROR(C13+C23,"") | D24: =IFERROR(D13+D23,"") | F24: What a resident investor who can use the credits effectively receives. This is why franking matters.
B25: Gross-up uplift | C25: =IFERROR(C24/C13-1,"") | D25: =IFERROR(D24/D13-1,"") | F25: Percentage uplift from imputation.
B26: DATA QUALITY
B27: Members returned | C27: =IFERROR(AS51!$G$2,"") | D27: =IFERROR(MXAU!$G$2,"") | F27: AS51 should be 200. MXAU Standard typically 55-65. Short count means BDS truncated - extend the rows.
B28: Dividend payers | C28: =IFERROR(AS51!$G$3,"") | D28: =IFERROR(MXAU!$G$3,"") | F28: Members returning a positive indicated yield.
B29: Non-payers (no dividend) | C29: =IFERROR(AS51!$J$2,"") | D29: =IFERROR(MXAU!$J$2,"") | F29: Held at zero yield, NOT excluded. Dropping them would overstate the index yield.
B30: Payers missing franking data | C30: =IFERROR(AS51!$J$3,"") | D30: =IFERROR(MXAU!$J$3,"") | F30: Excluded from the franked/unfranked split rather than assumed unfranked. Drives the coverage ratio above.
B32: Method note
B33: Index yield = SUM(w_i x y_i). This identity is exact for a cap-weighted index because SUM(w_i x D_i/P_i) = SUM(n_i x D_i)/total market cap. Non-payers enter with y_i = 0 and their full weight - excluding them shrinks the denominator and overstates the yield. Franked share = SUM(w_i x y_i x f_i) / SUM(w_i x y_i) over members with known franking, so it is weighted by dividend dollars rather than market cap: a large unfranked payer moves it far more than a small one.

Sheet Dvd History
B2: PER-EVENT DIVIDEND HISTORY (FRANKING GROUND TRUTH)
B3: Company-level franking flattens a real complication: franking is set per dividend, so an interim can be 100% franked and the final 50%. Use this tab to test whether the single EQY_DVD_PCT_FRANKED value is defensible for a given name.
B6: Ticker | C6: BHP AU Equity | E6: YYYYMMDD as text. Bloomberg overrides reject real Excel dates.
B7: Start date | C7: 20230101
B8: End date | C8: 20260803
B10: Dividend history
B11: =BDS($C$6,"DVD_HIST_ALL","DVD_START_DT",$C$7,"DVD_END_DT",$C$8)
B30: WHAT TO LOOK FOR
B31: 1. | C31: Check whether the returned columns carry franking for ASX names. If so, that beats any company-level field.
B32: 2. | C32: Compare the dividend-weighted franking over the last 12 months against EQY_DVD_PCT_FRANKED for the same name. If they disagree materially, say so when you present rather than quietly picking the convenient one.
B33: 3. | C33: Cross-check visually against DVD<GO>. Two minutes there saves an awkward correction later.
B36: Manual trailing-12M franking check (fill from the history above)
B37: Ex-date | C37: DPS | D37: Franked % | E37: Franked $ | F37: Unfranked $
B38: 20250903 | C38: 0.6 | D38: 100 | E38: =IFERROR(IF($C38="","",$C38*$D38/'Index Summary'!$C$7),"") | F38: =IFERROR(IF($C38="","",$C38-$E38),"") | H38: <- example row showing expected format. Overwrite it.
E39: =IFERROR(IF($C39="","",$C39*$D39/'Index Summary'!$C$7),"") | F39: =IFERROR(IF($C39="","",$C39-$E39),"")
E40: =IFERROR(IF($C40="","",$C40*$D40/'Index Summary'!$C$7),"") | F40: =IFERROR(IF($C40="","",$C40-$E40),"")
E41: =IFERROR(IF($C41="","",$C41*$D41/'Index Summary'!$C$7),"") | F41: =IFERROR(IF($C41="","",$C41-$E41),"")
E42: =IFERROR(IF($C42="","",$C42*$D42/'Index Summary'!$C$7),"") | F42: =IFERROR(IF($C42="","",$C42-$E42),"")
E43: =IFERROR(IF($C43="","",$C43*$D43/'Index Summary'!$C$7),"") | F43: =IFERROR(IF($C43="","",$C43-$E43),"")
E44: =IFERROR(IF($C44="","",$C44*$D44/'Index Summary'!$C$7),"") | F44: =IFERROR(IF($C44="","",$C44-$E44),"")
E45: =IFERROR(IF($C45="","",$C45*$D45/'Index Summary'!$C$7),"") | F45: =IFERROR(IF($C45="","",$C45-$E45),"")
B46: TOTAL | C46: =IFERROR(SUM(C38:C45),"") | D46: =IFERROR(E46/C46,"") | E46: =IFERROR(SUM(E38:E45),"") | F46: =IFERROR(SUM(F38:F45),"") | H46: Dividend-weighted franked %. Compare against EQY_DVD_PCT_FRANKED for the same ticker.
