Workbook

Sheet Expiries
M1: START HERE | N1: 1. Paste INDEX SHARES into column B and the INDEX DIVISOR into B3 on the AS51 and MXAU tabs (blue).
B2: CONTRACT EXPIRY CALENDAR - MASTER CONTROL | N2: 2. Set the two inputs below, then refresh on a Bloomberg terminal (Ctrl+Alt+F9).
B3: Everything downstream keys off this tab. Change the two inputs here, nothing else. | N3: 3. Read Div by Expiry for the dividend points and spreads; Futures FV to price a contract; Override to put your own numbers in.
B5: INPUTS
B6: Valuation date | C6: =TODAY() | N6: Today by default. Type a date to freeze the study.
B7: Contracts to build | C7: 13 | N7: 13 = a full year of monthly expiries. Max 16.
B9: AUTO
B10: First contract month | C10: =IF(DATE(YEAR($C$6),MONTH($C$6),1)+MOD(5-WEEKDAY(DATE(YEAR($C$6),MONTH($C$6),1),1)+7,7)+14>=$C$6,DATE(YEAR($C$6),MONTH($C$6),1),EDATE(DATE(YEAR($C$6),MONTH($C$6),1),1)) | N10: Rolls to the next month once the front expiry has passed.
B11: Projections run to | C11: ='Dvd Calendar'!$K$3 | N11: Last projected ex-date found in the data. Contracts expiring after it are flagged CHECK.
B12: Contracts covered | C12: =COUNTIF($L$16:$L$31,"OK")
B13: Contracts flagged CHECK | C13: =COUNTIF($L$16:$L$31,"CHECK") | N13: CHECK = Bloomberg's projections stop before that expiry, so its dividends are understated.
B15: # | C15: Contract | D15: AS51 expiry (auto 3rd Thu) | E15: Override | F15: AS51 EXPIRY | G15: MXAU expiry (auto 3rd Fri) | H15: Override | I15: MXAU EXPIRY | J15: AS51 window start | K15: MXAU window start | L15: Covered? | N15: Blue cells are optional. Fill one only if your contract expires on a different day.
B16: =IF(1>$C$7,"",1) | C16: =IF($B16="","",UPPER(TEXT(EDATE($C$10,$B16-1),"mmmyy"))) | D16: =IF($B16="","",EDATE($C$10,$B16-1)+MOD(5-WEEKDAY(EDATE($C$10,$B16-1),1)+7,7)+14) | F16: =IF($B16="","",IF($E16="",$D16,$E16)) | G16: =IF($B16="","",EDATE($C$10,$B16-1)+MOD(6-WEEKDAY(EDATE($C$10,$B16-1),1)+7,7)+14) | I16: =IF($B16="","",IF($H16="",$G16,$H16)) | J16: =IF($B16="","",IF($B16=1,$C$6,$F15)) | K16: =IF($B16="","",IF($B16=1,$C$6,$I15)) | L16: =IF($B16="","",IF($C$11="","CHECK",IF($F16<=$C$11,"OK","CHECK")))
B17: =IF(2>$C$7,"",2) | C17: =IF($B17="","",UPPER(TEXT(EDATE($C$10,$B17-1),"mmmyy"))) | D17: =IF($B17="","",EDATE($C$10,$B17-1)+MOD(5-WEEKDAY(EDATE($C$10,$B17-1),1)+7,7)+14) | F17: =IF($B17="","",IF($E17="",$D17,$E17)) | G17: =IF($B17="","",EDATE($C$10,$B17-1)+MOD(6-WEEKDAY(EDATE($C$10,$B17-1),1)+7,7)+14) | I17: =IF($B17="","",IF($H17="",$G17,$H17)) | J17: =IF($B17="","",IF($B17=1,$C$6,$F16)) | K17: =IF($B17="","",IF($B17=1,$C$6,$I16)) | L17: =IF($B17="","",IF($C$11="","CHECK",IF($F17<=$C$11,"OK","CHECK")))
B18: =IF(3>$C$7,"",3) | C18: =IF($B18="","",UPPER(TEXT(EDATE($C$10,$B18-1),"mmmyy"))) | D18: =IF($B18="","",EDATE($C$10,$B18-1)+MOD(5-WEEKDAY(EDATE($C$10,$B18-1),1)+7,7)+14) | F18: =IF($B18="","",IF($E18="",$D18,$E18)) | G18: =IF($B18="","",EDATE($C$10,$B18-1)+MOD(6-WEEKDAY(EDATE($C$10,$B18-1),1)+7,7)+14) | I18: =IF($B18="","",IF($H18="",$G18,$H18)) | J18: =IF($B18="","",IF($B18=1,$C$6,$F17)) | K18: =IF($B18="","",IF($B18=1,$C$6,$I17)) | L18: =IF($B18="","",IF($C$11="","CHECK",IF($F18<=$C$11,"OK","CHECK")))
B19: =IF(4>$C$7,"",4) | C19: =IF($B19="","",UPPER(TEXT(EDATE($C$10,$B19-1),"mmmyy"))) | D19: =IF($B19="","",EDATE($C$10,$B19-1)+MOD(5-WEEKDAY(EDATE($C$10,$B19-1),1)+7,7)+14) | F19: =IF($B19="","",IF($E19="",$D19,$E19)) | G19: =IF($B19="","",EDATE($C$10,$B19-1)+MOD(6-WEEKDAY(EDATE($C$10,$B19-1),1)+7,7)+14) | I19: =IF($B19="","",IF($H19="",$G19,$H19)) | J19: =IF($B19="","",IF($B19=1,$C$6,$F18)) | K19: =IF($B19="","",IF($B19=1,$C$6,$I18)) | L19: =IF($B19="","",IF($C$11="","CHECK",IF($F19<=$C$11,"OK","CHECK")))
B20: =IF(5>$C$7,"",5) | C20: =IF($B20="","",UPPER(TEXT(EDATE($C$10,$B20-1),"mmmyy"))) | D20: =IF($B20="","",EDATE($C$10,$B20-1)+MOD(5-WEEKDAY(EDATE($C$10,$B20-1),1)+7,7)+14) | F20: =IF($B20="","",IF($E20="",$D20,$E20)) | G20: =IF($B20="","",EDATE($C$10,$B20-1)+MOD(6-WEEKDAY(EDATE($C$10,$B20-1),1)+7,7)+14) | I20: =IF($B20="","",IF($H20="",$G20,$H20)) | J20: =IF($B20="","",IF($B20=1,$C$6,$F19)) | K20: =IF($B20="","",IF($B20=1,$C$6,$I19)) | L20: =IF($B20="","",IF($C$11="","CHECK",IF($F20<=$C$11,"OK","CHECK")))
B21: =IF(6>$C$7,"",6) | C21: =IF($B21="","",UPPER(TEXT(EDATE($C$10,$B21-1),"mmmyy"))) | D21: =IF($B21="","",EDATE($C$10,$B21-1)+MOD(5-WEEKDAY(EDATE($C$10,$B21-1),1)+7,7)+14) | F21: =IF($B21="","",IF($E21="",$D21,$E21)) | G21: =IF($B21="","",EDATE($C$10,$B21-1)+MOD(6-WEEKDAY(EDATE($C$10,$B21-1),1)+7,7)+14) | I21: =IF($B21="","",IF($H21="",$G21,$H21)) | J21: =IF($B21="","",IF($B21=1,$C$6,$F20)) | K21: =IF($B21="","",IF($B21=1,$C$6,$I20)) | L21: =IF($B21="","",IF($C$11="","CHECK",IF($F21<=$C$11,"OK","CHECK")))
B22: =IF(7>$C$7,"",7) | C22: =IF($B22="","",UPPER(TEXT(EDATE($C$10,$B22-1),"mmmyy"))) | D22: =IF($B22="","",EDATE($C$10,$B22-1)+MOD(5-WEEKDAY(EDATE($C$10,$B22-1),1)+7,7)+14) | F22: =IF($B22="","",IF($E22="",$D22,$E22)) | G22: =IF($B22="","",EDATE($C$10,$B22-1)+MOD(6-WEEKDAY(EDATE($C$10,$B22-1),1)+7,7)+14) | I22: =IF($B22="","",IF($H22="",$G22,$H22)) | J22: =IF($B22="","",IF($B22=1,$C$6,$F21)) | K22: =IF($B22="","",IF($B22=1,$C$6,$I21)) | L22: =IF($B22="","",IF($C$11="","CHECK",IF($F22<=$C$11,"OK","CHECK")))
B23: =IF(8>$C$7,"",8) | C23: =IF($B23="","",UPPER(TEXT(EDATE($C$10,$B23-1),"mmmyy"))) | D23: =IF($B23="","",EDATE($C$10,$B23-1)+MOD(5-WEEKDAY(EDATE($C$10,$B23-1),1)+7,7)+14) | F23: =IF($B23="","",IF($E23="",$D23,$E23)) | G23: =IF($B23="","",EDATE($C$10,$B23-1)+MOD(6-WEEKDAY(EDATE($C$10,$B23-1),1)+7,7)+14) | I23: =IF($B23="","",IF($H23="",$G23,$H23)) | J23: =IF($B23="","",IF($B23=1,$C$6,$F22)) | K23: =IF($B23="","",IF($B23=1,$C$6,$I22)) | L23: =IF($B23="","",IF($C$11="","CHECK",IF($F23<=$C$11,"OK","CHECK")))
B24: =IF(9>$C$7,"",9) | C24: =IF($B24="","",UPPER(TEXT(EDATE($C$10,$B24-1),"mmmyy"))) | D24: =IF($B24="","",EDATE($C$10,$B24-1)+MOD(5-WEEKDAY(EDATE($C$10,$B24-1),1)+7,7)+14) | F24: =IF($B24="","",IF($E24="",$D24,$E24)) | G24: =IF($B24="","",EDATE($C$10,$B24-1)+MOD(6-WEEKDAY(EDATE($C$10,$B24-1),1)+7,7)+14) | I24: =IF($B24="","",IF($H24="",$G24,$H24)) | J24: =IF($B24="","",IF($B24=1,$C$6,$F23)) | K24: =IF($B24="","",IF($B24=1,$C$6,$I23)) | L24: =IF($B24="","",IF($C$11="","CHECK",IF($F24<=$C$11,"OK","CHECK")))
B25: =IF(10>$C$7,"",10) | C25: =IF($B25="","",UPPER(TEXT(EDATE($C$10,$B25-1),"mmmyy"))) | D25: =IF($B25="","",EDATE($C$10,$B25-1)+MOD(5-WEEKDAY(EDATE($C$10,$B25-1),1)+7,7)+14) | F25: =IF($B25="","",IF($E25="",$D25,$E25)) | G25: =IF($B25="","",EDATE($C$10,$B25-1)+MOD(6-WEEKDAY(EDATE($C$10,$B25-1),1)+7,7)+14) | I25: =IF($B25="","",IF($H25="",$G25,$H25)) | J25: =IF($B25="","",IF($B25=1,$C$6,$F24)) | K25: =IF($B25="","",IF($B25=1,$C$6,$I24)) | L25: =IF($B25="","",IF($C$11="","CHECK",IF($F25<=$C$11,"OK","CHECK")))
B26: =IF(11>$C$7,"",11) | C26: =IF($B26="","",UPPER(TEXT(EDATE($C$10,$B26-1),"mmmyy"))) | D26: =IF($B26="","",EDATE($C$10,$B26-1)+MOD(5-WEEKDAY(EDATE($C$10,$B26-1),1)+7,7)+14) | F26: =IF($B26="","",IF($E26="",$D26,$E26)) | G26: =IF($B26="","",EDATE($C$10,$B26-1)+MOD(6-WEEKDAY(EDATE($C$10,$B26-1),1)+7,7)+14) | I26: =IF($B26="","",IF($H26="",$G26,$H26)) | J26: =IF($B26="","",IF($B26=1,$C$6,$F25)) | K26: =IF($B26="","",IF($B26=1,$C$6,$I25)) | L26: =IF($B26="","",IF($C$11="","CHECK",IF($F26<=$C$11,"OK","CHECK")))
B27: =IF(12>$C$7,"",12) | C27: =IF($B27="","",UPPER(TEXT(EDATE($C$10,$B27-1),"mmmyy"))) | D27: =IF($B27="","",EDATE($C$10,$B27-1)+MOD(5-WEEKDAY(EDATE($C$10,$B27-1),1)+7,7)+14) | F27: =IF($B27="","",IF($E27="",$D27,$E27)) | G27: =IF($B27="","",EDATE($C$10,$B27-1)+MOD(6-WEEKDAY(EDATE($C$10,$B27-1),1)+7,7)+14) | I27: =IF($B27="","",IF($H27="",$G27,$H27)) | J27: =IF($B27="","",IF($B27=1,$C$6,$F26)) | K27: =IF($B27="","",IF($B27=1,$C$6,$I26)) | L27: =IF($B27="","",IF($C$11="","CHECK",IF($F27<=$C$11,"OK","CHECK")))
B28: =IF(13>$C$7,"",13) | C28: =IF($B28="","",UPPER(TEXT(EDATE($C$10,$B28-1),"mmmyy"))) | D28: =IF($B28="","",EDATE($C$10,$B28-1)+MOD(5-WEEKDAY(EDATE($C$10,$B28-1),1)+7,7)+14) | F28: =IF($B28="","",IF($E28="",$D28,$E28)) | G28: =IF($B28="","",EDATE($C$10,$B28-1)+MOD(6-WEEKDAY(EDATE($C$10,$B28-1),1)+7,7)+14) | I28: =IF($B28="","",IF($H28="",$G28,$H28)) | J28: =IF($B28="","",IF($B28=1,$C$6,$F27)) | K28: =IF($B28="","",IF($B28=1,$C$6,$I27)) | L28: =IF($B28="","",IF($C$11="","CHECK",IF($F28<=$C$11,"OK","CHECK")))
B29: =IF(14>$C$7,"",14) | C29: =IF($B29="","",UPPER(TEXT(EDATE($C$10,$B29-1),"mmmyy"))) | D29: =IF($B29="","",EDATE($C$10,$B29-1)+MOD(5-WEEKDAY(EDATE($C$10,$B29-1),1)+7,7)+14) | F29: =IF($B29="","",IF($E29="",$D29,$E29)) | G29: =IF($B29="","",EDATE($C$10,$B29-1)+MOD(6-WEEKDAY(EDATE($C$10,$B29-1),1)+7,7)+14) | I29: =IF($B29="","",IF($H29="",$G29,$H29)) | J29: =IF($B29="","",IF($B29=1,$C$6,$F28)) | K29: =IF($B29="","",IF($B29=1,$C$6,$I28)) | L29: =IF($B29="","",IF($C$11="","CHECK",IF($F29<=$C$11,"OK","CHECK")))
B30: =IF(15>$C$7,"",15) | C30: =IF($B30="","",UPPER(TEXT(EDATE($C$10,$B30-1),"mmmyy"))) | D30: =IF($B30="","",EDATE($C$10,$B30-1)+MOD(5-WEEKDAY(EDATE($C$10,$B30-1),1)+7,7)+14) | F30: =IF($B30="","",IF($E30="",$D30,$E30)) | G30: =IF($B30="","",EDATE($C$10,$B30-1)+MOD(6-WEEKDAY(EDATE($C$10,$B30-1),1)+7,7)+14) | I30: =IF($B30="","",IF($H30="",$G30,$H30)) | J30: =IF($B30="","",IF($B30=1,$C$6,$F29)) | K30: =IF($B30="","",IF($B30=1,$C$6,$I29)) | L30: =IF($B30="","",IF($C$11="","CHECK",IF($F30<=$C$11,"OK","CHECK")))
B31: =IF(16>$C$7,"",16) | C31: =IF($B31="","",UPPER(TEXT(EDATE($C$10,$B31-1),"mmmyy"))) | D31: =IF($B31="","",EDATE($C$10,$B31-1)+MOD(5-WEEKDAY(EDATE($C$10,$B31-1),1)+7,7)+14) | F31: =IF($B31="","",IF($E31="",$D31,$E31)) | G31: =IF($B31="","",EDATE($C$10,$B31-1)+MOD(6-WEEKDAY(EDATE($C$10,$B31-1),1)+7,7)+14) | I31: =IF($B31="","",IF($H31="",$G31,$H31)) | J31: =IF($B31="","",IF($B31=1,$C$6,$F30)) | K31: =IF($B31="","",IF($B31=1,$C$6,$I30)) | L31: =IF($B31="","",IF($C$11="","CHECK",IF($F31<=$C$11,"OK","CHECK")))
B33: Window | C33: A contract holds the dividends with an ex-date after the previous expiry and on or before its own. The front contract's window opens on the valuation date, so it carries only what is still to come.

Sheet Div by Expiry
B2: INDEX DIVIDEND BY FUTURES EXPIRY
B3: Projected dividends bucketed into each contract window - index points, yield and annualized yield, both indices, and the spread between them.
B5: AS51 index level | C5: =_xll.BDP('AS51'!$B$2,"LAST_PRICE") | E5: MXAU is quoted in USD, so its points are USD points. Yields and the bps spreads are currency-consistent - each index is divided by its own level.
B6: MXAU index level | C6: =_xll.BDP(MXAU!$B$2,"LAST_PRICE") | E6: Everything here is Bloomberg's BDVD projection (plus your overrides when ON). Covered? flags contracts past the projected horizon.
B7: Valuation date | C7: =Expiries!$C$6 | E7: Ann. = cum yield x 365 / days to that expiry (ACT/365, per leg). The front contract divides by only a few days - noisy, read with care.
B8: Projections run to | C8: =Expiries!$C$11
B9: Overrides | C9: =IF(Override!$C$4="ON","ON - "&Override!$E$4&" row(s) live - Accrual uses YOUR numbers where set (Override tab).","OFF - pure Bloomberg projections.")
E11: S&P/ASX 200 (AS51) | K11: MSCI AUSTRALIA (MXAU) | P11: SPREAD
B12: Contract | C12: Expiry | D12: Days | E12: Period DPS (pts) | F12: Period yld (%) | G12: Cum DPS (pts) | H12: Cum yld (%) | I12: Ann cum yld (%) | J12: Expiry | K12: Period DPS (pts) | L12: Period yld (%) | M12: Cum DPS (pts) | N12: Cum yld (%) | O12: Ann cum yld (%) | P12: AS51-MXAU cum (bps) | Q12: Ann sprd (bps) | R12: Covered?
B13: =IF(Expiries!$B16="","",Expiries!$C16) | C13: =IF($B13="","",Expiries!$F16) | D13: =IF($B13="","",$C13-$C$7) | E13: =IF($B13="","",IFERROR(Accrual!F$221,"")) | F13: =IF($B13="","",IFERROR($E13/$C$5,"")) | G13: =IF($B13="","",SUM($E$13:$E13)) | H13: =IF($B13="","",IFERROR($G13/$C$5,"")) | I13: =IF($B13="","",IFERROR($H13*365/$D13,"")) | J13: =IF($B13="","",Expiries!$I16) | K13: =IF($B13="","",IFERROR(Accrual!F$309,"")) | L13: =IF($B13="","",IFERROR($K13/$C$6,"")) | M13: =IF($B13="","",SUM($K$13:$K13)) | N13: =IF($B13="","",IFERROR($M13/$C$6,"")) | O13: =IF($B13="","",IFERROR($N13*365/($J13-$C$7),"")) | P13: =IF($B13="","",IFERROR(($H13-$N13)*10000,"")) | Q13: =IF($B13="","",IFERROR(($I13-$O13)*10000,"")) | R13: =IF($B13="","",Expiries!$L16)
B14: =IF(Expiries!$B17="","",Expiries!$C17) | C14: =IF($B14="","",Expiries!$F17) | D14: =IF($B14="","",$C14-$C$7) | E14: =IF($B14="","",IFERROR(Accrual!G$221,"")) | F14: =IF($B14="","",IFERROR($E14/$C$5,"")) | G14: =IF($B14="","",SUM($E$13:$E14)) | H14: =IF($B14="","",IFERROR($G14/$C$5,"")) | I14: =IF($B14="","",IFERROR($H14*365/$D14,"")) | J14: =IF($B14="","",Expiries!$I17) | K14: =IF($B14="","",IFERROR(Accrual!G$309,"")) | L14: =IF($B14="","",IFERROR($K14/$C$6,"")) | M14: =IF($B14="","",SUM($K$13:$K14)) | N14: =IF($B14="","",IFERROR($M14/$C$6,"")) | O14: =IF($B14="","",IFERROR($N14*365/($J14-$C$7),"")) | P14: =IF($B14="","",IFERROR(($H14-$N14)*10000,"")) | Q14: =IF($B14="","",IFERROR(($I14-$O14)*10000,"")) | R14: =IF($B14="","",Expiries!$L17)
B15: =IF(Expiries!$B18="","",Expiries!$C18) | C15: =IF($B15="","",Expiries!$F18) | D15: =IF($B15="","",$C15-$C$7) | E15: =IF($B15="","",IFERROR(Accrual!H$221,"")) | F15: =IF($B15="","",IFERROR($E15/$C$5,"")) | G15: =IF($B15="","",SUM($E$13:$E15)) | H15: =IF($B15="","",IFERROR($G15/$C$5,"")) | I15: =IF($B15="","",IFERROR($H15*365/$D15,"")) | J15: =IF($B15="","",Expiries!$I18) | K15: =IF($B15="","",IFERROR(Accrual!H$309,"")) | L15: =IF($B15="","",IFERROR($K15/$C$6,"")) | M15: =IF($B15="","",SUM($K$13:$K15)) | N15: =IF($B15="","",IFERROR($M15/$C$6,"")) | O15: =IF($B15="","",IFERROR($N15*365/($J15-$C$7),"")) | P15: =IF($B15="","",IFERROR(($H15-$N15)*10000,"")) | Q15: =IF($B15="","",IFERROR(($I15-$O15)*10000,"")) | R15: =IF($B15="","",Expiries!$L18)
B16: =IF(Expiries!$B19="","",Expiries!$C19) | C16: =IF($B16="","",Expiries!$F19) | D16: =IF($B16="","",$C16-$C$7) | E16: =IF($B16="","",IFERROR(Accrual!I$221,"")) | F16: =IF($B16="","",IFERROR($E16/$C$5,"")) | G16: =IF($B16="","",SUM($E$13:$E16)) | H16: =IF($B16="","",IFERROR($G16/$C$5,"")) | I16: =IF($B16="","",IFERROR($H16*365/$D16,"")) | J16: =IF($B16="","",Expiries!$I19) | K16: =IF($B16="","",IFERROR(Accrual!I$309,"")) | L16: =IF($B16="","",IFERROR($K16/$C$6,"")) | M16: =IF($B16="","",SUM($K$13:$K16)) | N16: =IF($B16="","",IFERROR($M16/$C$6,"")) | O16: =IF($B16="","",IFERROR($N16*365/($J16-$C$7),"")) | P16: =IF($B16="","",IFERROR(($H16-$N16)*10000,"")) | Q16: =IF($B16="","",IFERROR(($I16-$O16)*10000,"")) | R16: =IF($B16="","",Expiries!$L19)
B17: =IF(Expiries!$B20="","",Expiries!$C20) | C17: =IF($B17="","",Expiries!$F20) | D17: =IF($B17="","",$C17-$C$7) | E17: =IF($B17="","",IFERROR(Accrual!J$221,"")) | F17: =IF($B17="","",IFERROR($E17/$C$5,"")) | G17: =IF($B17="","",SUM($E$13:$E17)) | H17: =IF($B17="","",IFERROR($G17/$C$5,"")) | I17: =IF($B17="","",IFERROR($H17*365/$D17,"")) | J17: =IF($B17="","",Expiries!$I20) | K17: =IF($B17="","",IFERROR(Accrual!J$309,"")) | L17: =IF($B17="","",IFERROR($K17/$C$6,"")) | M17: =IF($B17="","",SUM($K$13:$K17)) | N17: =IF($B17="","",IFERROR($M17/$C$6,"")) | O17: =IF($B17="","",IFERROR($N17*365/($J17-$C$7),"")) | P17: =IF($B17="","",IFERROR(($H17-$N17)*10000,"")) | Q17: =IF($B17="","",IFERROR(($I17-$O17)*10000,"")) | R17: =IF($B17="","",Expiries!$L20)
B18: =IF(Expiries!$B21="","",Expiries!$C21) | C18: =IF($B18="","",Expiries!$F21) | D18: =IF($B18="","",$C18-$C$7) | E18: =IF($B18="","",IFERROR(Accrual!K$221,"")) | F18: =IF($B18="","",IFERROR($E18/$C$5,"")) | G18: =IF($B18="","",SUM($E$13:$E18)) | H18: =IF($B18="","",IFERROR($G18/$C$5,"")) | I18: =IF($B18="","",IFERROR($H18*365/$D18,"")) | J18: =IF($B18="","",Expiries!$I21) | K18: =IF($B18="","",IFERROR(Accrual!K$309,"")) | L18: =IF($B18="","",IFERROR($K18/$C$6,"")) | M18: =IF($B18="","",SUM($K$13:$K18)) | N18: =IF($B18="","",IFERROR($M18/$C$6,"")) | O18: =IF($B18="","",IFERROR($N18*365/($J18-$C$7),"")) | P18: =IF($B18="","",IFERROR(($H18-$N18)*10000,"")) | Q18: =IF($B18="","",IFERROR(($I18-$O18)*10000,"")) | R18: =IF($B18="","",Expiries!$L21)
B19: =IF(Expiries!$B22="","",Expiries!$C22) | C19: =IF($B19="","",Expiries!$F22) | D19: =IF($B19="","",$C19-$C$7) | E19: =IF($B19="","",IFERROR(Accrual!L$221,"")) | F19: =IF($B19="","",IFERROR($E19/$C$5,"")) | G19: =IF($B19="","",SUM($E$13:$E19)) | H19: =IF($B19="","",IFERROR($G19/$C$5,"")) | I19: =IF($B19="","",IFERROR($H19*365/$D19,"")) | J19: =IF($B19="","",Expiries!$I22) | K19: =IF($B19="","",IFERROR(Accrual!L$309,"")) | L19: =IF($B19="","",IFERROR($K19/$C$6,"")) | M19: =IF($B19="","",SUM($K$13:$K19)) | N19: =IF($B19="","",IFERROR($M19/$C$6,"")) | O19: =IF($B19="","",IFERROR($N19*365/($J19-$C$7),"")) | P19: =IF($B19="","",IFERROR(($H19-$N19)*10000,"")) | Q19: =IF($B19="","",IFERROR(($I19-$O19)*10000,"")) | R19: =IF($B19="","",Expiries!$L22)
B20: =IF(Expiries!$B23="","",Expiries!$C23) | C20: =IF($B20="","",Expiries!$F23) | D20: =IF($B20="","",$C20-$C$7) | E20: =IF($B20="","",IFERROR(Accrual!M$221,"")) | F20: =IF($B20="","",IFERROR($E20/$C$5,"")) | G20: =IF($B20="","",SUM($E$13:$E20)) | H20: =IF($B20="","",IFERROR($G20/$C$5,"")) | I20: =IF($B20="","",IFERROR($H20*365/$D20,"")) | J20: =IF($B20="","",Expiries!$I23) | K20: =IF($B20="","",IFERROR(Accrual!M$309,"")) | L20: =IF($B20="","",IFERROR($K20/$C$6,"")) | M20: =IF($B20="","",SUM($K$13:$K20)) | N20: =IF($B20="","",IFERROR($M20/$C$6,"")) | O20: =IF($B20="","",IFERROR($N20*365/($J20-$C$7),"")) | P20: =IF($B20="","",IFERROR(($H20-$N20)*10000,"")) | Q20: =IF($B20="","",IFERROR(($I20-$O20)*10000,"")) | R20: =IF($B20="","",Expiries!$L23)
B21: =IF(Expiries!$B24="","",Expiries!$C24) | C21: =IF($B21="","",Expiries!$F24) | D21: =IF($B21="","",$C21-$C$7) | E21: =IF($B21="","",IFERROR(Accrual!N$221,"")) | F21: =IF($B21="","",IFERROR($E21/$C$5,"")) | G21: =IF($B21="","",SUM($E$13:$E21)) | H21: =IF($B21="","",IFERROR($G21/$C$5,"")) | I21: =IF($B21="","",IFERROR($H21*365/$D21,"")) | J21: =IF($B21="","",Expiries!$I24) | K21: =IF($B21="","",IFERROR(Accrual!N$309,"")) | L21: =IF($B21="","",IFERROR($K21/$C$6,"")) | M21: =IF($B21="","",SUM($K$13:$K21)) | N21: =IF($B21="","",IFERROR($M21/$C$6,"")) | O21: =IF($B21="","",IFERROR($N21*365/($J21-$C$7),"")) | P21: =IF($B21="","",IFERROR(($H21-$N21)*10000,"")) | Q21: =IF($B21="","",IFERROR(($I21-$O21)*10000,"")) | R21: =IF($B21="","",Expiries!$L24)
B22: =IF(Expiries!$B25="","",Expiries!$C25) | C22: =IF($B22="","",Expiries!$F25) | D22: =IF($B22="","",$C22-$C$7) | E22: =IF($B22="","",IFERROR(Accrual!O$221,"")) | F22: =IF($B22="","",IFERROR($E22/$C$5,"")) | G22: =IF($B22="","",SUM($E$13:$E22)) | H22: =IF($B22="","",IFERROR($G22/$C$5,"")) | I22: =IF($B22="","",IFERROR($H22*365/$D22,"")) | J22: =IF($B22="","",Expiries!$I25) | K22: =IF($B22="","",IFERROR(Accrual!O$309,"")) | L22: =IF($B22="","",IFERROR($K22/$C$6,"")) | M22: =IF($B22="","",SUM($K$13:$K22)) | N22: =IF($B22="","",IFERROR($M22/$C$6,"")) | O22: =IF($B22="","",IFERROR($N22*365/($J22-$C$7),"")) | P22: =IF($B22="","",IFERROR(($H22-$N22)*10000,"")) | Q22: =IF($B22="","",IFERROR(($I22-$O22)*10000,"")) | R22: =IF($B22="","",Expiries!$L25)
B23: =IF(Expiries!$B26="","",Expiries!$C26) | C23: =IF($B23="","",Expiries!$F26) | D23: =IF($B23="","",$C23-$C$7) | E23: =IF($B23="","",IFERROR(Accrual!P$221,"")) | F23: =IF($B23="","",IFERROR($E23/$C$5,"")) | G23: =IF($B23="","",SUM($E$13:$E23)) | H23: =IF($B23="","",IFERROR($G23/$C$5,"")) | I23: =IF($B23="","",IFERROR($H23*365/$D23,"")) | J23: =IF($B23="","",Expiries!$I26) | K23: =IF($B23="","",IFERROR(Accrual!P$309,"")) | L23: =IF($B23="","",IFERROR($K23/$C$6,"")) | M23: =IF($B23="","",SUM($K$13:$K23)) | N23: =IF($B23="","",IFERROR($M23/$C$6,"")) | O23: =IF($B23="","",IFERROR($N23*365/($J23-$C$7),"")) | P23: =IF($B23="","",IFERROR(($H23-$N23)*10000,"")) | Q23: =IF($B23="","",IFERROR(($I23-$O23)*10000,"")) | R23: =IF($B23="","",Expiries!$L26)
B24: =IF(Expiries!$B27="","",Expiries!$C27) | C24: =IF($B24="","",Expiries!$F27) | D24: =IF($B24="","",$C24-$C$7) | E24: =IF($B24="","",IFERROR(Accrual!Q$221,"")) | F24: =IF($B24="","",IFERROR($E24/$C$5,"")) | G24: =IF($B24="","",SUM($E$13:$E24)) | H24: =IF($B24="","",IFERROR($G24/$C$5,"")) | I24: =IF($B24="","",IFERROR($H24*365/$D24,"")) | J24: =IF($B24="","",Expiries!$I27) | K24: =IF($B24="","",IFERROR(Accrual!Q$309,"")) | L24: =IF($B24="","",IFERROR($K24/$C$6,"")) | M24: =IF($B24="","",SUM($K$13:$K24)) | N24: =IF($B24="","",IFERROR($M24/$C$6,"")) | O24: =IF($B24="","",IFERROR($N24*365/($J24-$C$7),"")) | P24: =IF($B24="","",IFERROR(($H24-$N24)*10000,"")) | Q24: =IF($B24="","",IFERROR(($I24-$O24)*10000,"")) | R24: =IF($B24="","",Expiries!$L27)
B25: =IF(Expiries!$B28="","",Expiries!$C28) | C25: =IF($B25="","",Expiries!$F28) | D25: =IF($B25="","",$C25-$C$7) | E25: =IF($B25="","",IFERROR(Accrual!R$221,"")) | F25: =IF($B25="","",IFERROR($E25/$C$5,"")) | G25: =IF($B25="","",SUM($E$13:$E25)) | H25: =IF($B25="","",IFERROR($G25/$C$5,"")) | I25: =IF($B25="","",IFERROR($H25*365/$D25,"")) | J25: =IF($B25="","",Expiries!$I28) | K25: =IF($B25="","",IFERROR(Accrual!R$309,"")) | L25: =IF($B25="","",IFERROR($K25/$C$6,"")) | M25: =IF($B25="","",SUM($K$13:$K25)) | N25: =IF($B25="","",IFERROR($M25/$C$6,"")) | O25: =IF($B25="","",IFERROR($N25*365/($J25-$C$7),"")) | P25: =IF($B25="","",IFERROR(($H25-$N25)*10000,"")) | Q25: =IF($B25="","",IFERROR(($I25-$O25)*10000,"")) | R25: =IF($B25="","",Expiries!$L28)
B26: =IF(Expiries!$B29="","",Expiries!$C29) | C26: =IF($B26="","",Expiries!$F29) | D26: =IF($B26="","",$C26-$C$7) | E26: =IF($B26="","",IFERROR(Accrual!S$221,"")) | F26: =IF($B26="","",IFERROR($E26/$C$5,"")) | G26: =IF($B26="","",SUM($E$13:$E26)) | H26: =IF($B26="","",IFERROR($G26/$C$5,"")) | I26: =IF($B26="","",IFERROR($H26*365/$D26,"")) | J26: =IF($B26="","",Expiries!$I29) | K26: =IF($B26="","",IFERROR(Accrual!S$309,"")) | L26: =IF($B26="","",IFERROR($K26/$C$6,"")) | M26: =IF($B26="","",SUM($K$13:$K26)) | N26: =IF($B26="","",IFERROR($M26/$C$6,"")) | O26: =IF($B26="","",IFERROR($N26*365/($J26-$C$7),"")) | P26: =IF($B26="","",IFERROR(($H26-$N26)*10000,"")) | Q26: =IF($B26="","",IFERROR(($I26-$O26)*10000,"")) | R26: =IF($B26="","",Expiries!$L29)
B27: =IF(Expiries!$B30="","",Expiries!$C30) | C27: =IF($B27="","",Expiries!$F30) | D27: =IF($B27="","",$C27-$C$7) | E27: =IF($B27="","",IFERROR(Accrual!T$221,"")) | F27: =IF($B27="","",IFERROR($E27/$C$5,"")) | G27: =IF($B27="","",SUM($E$13:$E27)) | H27: =IF($B27="","",IFERROR($G27/$C$5,"")) | I27: =IF($B27="","",IFERROR($H27*365/$D27,"")) | J27: =IF($B27="","",Expiries!$I30) | K27: =IF($B27="","",IFERROR(Accrual!T$309,"")) | L27: =IF($B27="","",IFERROR($K27/$C$6,"")) | M27: =IF($B27="","",SUM($K$13:$K27)) | N27: =IF($B27="","",IFERROR($M27/$C$6,"")) | O27: =IF($B27="","",IFERROR($N27*365/($J27-$C$7),"")) | P27: =IF($B27="","",IFERROR(($H27-$N27)*10000,"")) | Q27: =IF($B27="","",IFERROR(($I27-$O27)*10000,"")) | R27: =IF($B27="","",Expiries!$L30)
B28: =IF(Expiries!$B31="","",Expiries!$C31) | C28: =IF($B28="","",Expiries!$F31) | D28: =IF($B28="","",$C28-$C$7) | E28: =IF($B28="","",IFERROR(Accrual!U$221,"")) | F28: =IF($B28="","",IFERROR($E28/$C$5,"")) | G28: =IF($B28="","",SUM($E$13:$E28)) | H28: =IF($B28="","",IFERROR($G28/$C$5,"")) | I28: =IF($B28="","",IFERROR($H28*365/$D28,"")) | J28: =IF($B28="","",Expiries!$I31) | K28: =IF($B28="","",IFERROR(Accrual!U$309,"")) | L28: =IF($B28="","",IFERROR($K28/$C$6,"")) | M28: =IF($B28="","",SUM($K$13:$K28)) | N28: =IF($B28="","",IFERROR($M28/$C$6,"")) | O28: =IF($B28="","",IFERROR($N28*365/($J28-$C$7),"")) | P28: =IF($B28="","",IFERROR(($H28-$N28)*10000,"")) | Q28: =IF($B28="","",IFERROR(($I28-$O28)*10000,"")) | R28: =IF($B28="","",Expiries!$L31)
B32: FRANKING VIEW - CREDIT VALUE BY CONTRACT
B33: Franked share uses each stock's company-level franked % (blank = 100%). Credit = franked dividend x t/(1-t) with t = 'Index Summary'!C6. Grossed-up = cash + credit.
C34: S&P/ASX 200 (AS51) | H34: MSCI AUSTRALIA (MXAU) | M34: SPREAD | T34: o/w SPECIALS + CAPITAL RETURNS (divisor-adjusted: the index does not drop; futures FV excludes them unless toggled on)
B35: Contract | C35: Franked (% of dvd) | D35: Credit (pts) | E35: Cum credit (pts) | F35: Grossed cum yld (%) | G35: Ann grossed yld (%) | H35: Franked (% of dvd) | I35: Credit (pts) | J35: Cum credit (pts) | K35: Grossed cum yld (%) | L35: Ann grossed yld (%) | M35: Grossed sprd (bps) | N35: Ann grossed sprd (bps) | T35: A: period sp (pts) | U35: A: cum sp (pts) | V35: A: period sp credits (pts) | W35: A: cum sp credits (pts) | X35: M: period sp (pts) | Y35: M: cum sp (pts) | Z35: M: period sp credits (pts) | AA35: M: cum sp credits (pts)
B36: =IF(Expiries!$B16="","",Expiries!$C16) | C36: =IF($B36="","",IFERROR(Accrual!W$221/Accrual!F$221,"")) | D36: =IF($B36="","",IFERROR(Accrual!W$221*'Index Summary'!$C$6/(1-'Index Summary'!$C$6),"")) | E36: =IF($B36="","",SUM($D$36:$D36)) | F36: =IF($B36="","",IFERROR(($G13+$E36)/$C$5,"")) | G36: =IF($B36="","",IFERROR($F36*365/$D13,"")) | H36: =IF($B36="","",IFERROR(Accrual!W$309/Accrual!F$309,"")) | I36: =IF($B36="","",IFERROR(Accrual!W$309*'Index Summary'!$C$6/(1-'Index Summary'!$C$6),"")) | J36: =IF($B36="","",SUM($I$36:$I36)) | K36: =IF($B36="","",IFERROR(($M13+$J36)/$C$6,"")) | L36: =IF($B36="","",IFERROR($K36*365/($J13-$C$7),"")) | M36: =IF($B36="","",IFERROR(($F36-$K36)*10000,"")) | N36: =IF($B36="","",IFERROR(($G36-$L36)*10000,"")) | T36: =IF($B36="","",IFERROR(Accrual!AQ$221,"")) | U36: =IF($B36="","",SUM($T$36:$T36)) | V36: =IF($B36="","",IFERROR(Accrual!BH$221*'Index Summary'!$C$6/(1-'Index Summary'!$C$6),"")) | W36: =IF($B36="","",SUM($V$36:$V36)) | X36: =IF($B36="","",IFERROR(Accrual!AQ$309,"")) | Y36: =IF($B36="","",SUM($X$36:$X36)) | Z36: =IF($B36="","",IFERROR(Accrual!BH$309*'Index Summary'!$C$6/(1-'Index Summary'!$C$6),"")) | AA36: =IF($B36="","",SUM($Z$36:$Z36))
B37: =IF(Expiries!$B17="","",Expiries!$C17) | C37: =IF($B37="","",IFERROR(Accrual!X$221/Accrual!G$221,"")) | D37: =IF($B37="","",IFERROR(Accrual!X$221*'Index Summary'!$C$6/(1-'Index Summary'!$C$6),"")) | E37: =IF($B37="","",SUM($D$36:$D37)) | F37: =IF($B37="","",IFERROR(($G14+$E37)/$C$5,"")) | G37: =IF($B37="","",IFERROR($F37*365/$D14,"")) | H37: =IF($B37="","",IFERROR(Accrual!X$309/Accrual!G$309,"")) | I37: =IF($B37="","",IFERROR(Accrual!X$309*'Index Summary'!$C$6/(1-'Index Summary'!$C$6),"")) | J37: =IF($B37="","",SUM($I$36:$I37)) | K37: =IF($B37="","",IFERROR(($M14+$J37)/$C$6,"")) | L37: =IF($B37="","",IFERROR($K37*365/($J14-$C$7),"")) | M37: =IF($B37="","",IFERROR(($F37-$K37)*10000,"")) | N37: =IF($B37="","",IFERROR(($G37-$L37)*10000,"")) | T37: =IF($B37="","",IFERROR(Accrual!AR$221,"")) | U37: =IF($B37="","",SUM($T$36:$T37)) | V37: =IF($B37="","",IFERROR(Accrual!BI$221*'Index Summary'!$C$6/(1-'Index Summary'!$C$6),"")) | W37: =IF($B37="","",SUM($V$36:$V37)) | X37: =IF($B37="","",IFERROR(Accrual!AR$309,"")) | Y37: =IF($B37="","",SUM($X$36:$X37)) | Z37: =IF($B37="","",IFERROR(Accrual!BI$309*'Index Summary'!$C$6/(1-'Index Summary'!$C$6),"")) | AA37: =IF($B37="","",SUM($Z$36:$Z37))
B38: =IF(Expiries!$B18="","",Expiries!$C18) | C38: =IF($B38="","",IFERROR(Accrual!Y$221/Accrual!H$221,"")) | D38: =IF($B38="","",IFERROR(Accrual!Y$221*'Index Summary'!$C$6/(1-'Index Summary'!$C$6),"")) | E38: =IF($B38="","",SUM($D$36:$D38)) | F38: =IF($B38="","",IFERROR(($G15+$E38)/$C$5,"")) | G38: =IF($B38="","",IFERROR($F38*365/$D15,"")) | H38: =IF($B38="","",IFERROR(Accrual!Y$309/Accrual!H$309,"")) | I38: =IF($B38="","",IFERROR(Accrual!Y$309*'Index Summary'!$C$6/(1-'Index Summary'!$C$6),"")) | J38: =IF($B38="","",SUM($I$36:$I38)) | K38: =IF($B38="","",IFERROR(($M15+$J38)/$C$6,"")) | L38: =IF($B38="","",IFERROR($K38*365/($J15-$C$7),"")) | M38: =IF($B38="","",IFERROR(($F38-$K38)*10000,"")) | N38: =IF($B38="","",IFERROR(($G38-$L38)*10000,"")) | T38: =IF($B38="","",IFERROR(Accrual!AS$221,"")) | U38: =IF($B38="","",SUM($T$36:$T38)) | V38: =IF($B38="","",IFERROR(Accrual!BJ$221*'Index Summary'!$C$6/(1-'Index Summary'!$C$6),"")) | W38: =IF($B38="","",SUM($V$36:$V38)) | X38: =IF($B38="","",IFERROR(Accrual!AS$309,"")) | Y38: =IF($B38="","",SUM($X$36:$X38)) | Z38: =IF($B38="","",IFERROR(Accrual!BJ$309*'Index Summary'!$C$6/(1-'Index Summary'!$C$6),"")) | AA38: =IF($B38="","",SUM($Z$36:$Z38))
B39: =IF(Expiries!$B19="","",Expiries!$C19) | C39: =IF($B39="","",IFERROR(Accrual!Z$221/Accrual!I$221,"")) | D39: =IF($B39="","",IFERROR(Accrual!Z$221*'Index Summary'!$C$6/(1-'Index Summary'!$C$6),"")) | E39: =IF($B39="","",SUM($D$36:$D39)) | F39: =IF($B39="","",IFERROR(($G16+$E39)/$C$5,"")) | G39: =IF($B39="","",IFERROR($F39*365/$D16,"")) | H39: =IF($B39="","",IFERROR(Accrual!Z$309/Accrual!I$309,"")) | I39: =IF($B39="","",IFERROR(Accrual!Z$309*'Index Summary'!$C$6/(1-'Index Summary'!$C$6),"")) | J39: =IF($B39="","",SUM($I$36:$I39)) | K39: =IF($B39="","",IFERROR(($M16+$J39)/$C$6,"")) | L39: =IF($B39="","",IFERROR($K39*365/($J16-$C$7),"")) | M39: =IF($B39="","",IFERROR(($F39-$K39)*10000,"")) | N39: =IF($B39="","",IFERROR(($G39-$L39)*10000,"")) | T39: =IF($B39="","",IFERROR(Accrual!AT$221,"")) | U39: =IF($B39="","",SUM($T$36:$T39)) | V39: =IF($B39="","",IFERROR(Accrual!BK$221*'Index Summary'!$C$6/(1-'Index Summary'!$C$6),"")) | W39: =IF($B39="","",SUM($V$36:$V39)) | X39: =IF($B39="","",IFERROR(Accrual!AT$309,"")) | Y39: =IF($B39="","",SUM($X$36:$X39)) | Z39: =IF($B39="","",IFERROR(Accrual!BK$309*'Index Summary'!$C$6/(1-'Index Summary'!$C$6),"")) | AA39: =IF($B39="","",SUM($Z$36:$Z39))
B40: =IF(Expiries!$B20="","",Expiries!$C20) | C40: =IF($B40="","",IFERROR(Accrual!AA$221/Accrual!J$221,"")) | D40: =IF($B40="","",IFERROR(Accrual!AA$221*'Index Summary'!$C$6/(1-'Index Summary'!$C$6),"")) | E40: =IF($B40="","",SUM($D$36:$D40)) | F40: =IF($B40="","",IFERROR(($G17+$E40)/$C$5,"")) | G40: =IF($B40="","",IFERROR($F40*365/$D17,"")) | H40: =IF($B40="","",IFERROR(Accrual!AA$309/Accrual!J$309,"")) | I40: =IF($B40="","",IFERROR(Accrual!AA$309*'Index Summary'!$C$6/(1-'Index Summary'!$C$6),"")) | J40: =IF($B40="","",SUM($I$36:$I40)) | K40: =IF($B40="","",IFERROR(($M17+$J40)/$C$6,"")) | L40: =IF($B40="","",IFERROR($K40*365/($J17-$C$7),"")) | M40: =IF($B40="","",IFERROR(($F40-$K40)*10000,"")) | N40: =IF($B40="","",IFERROR(($G40-$L40)*10000,"")) | T40: =IF($B40="","",IFERROR(Accrual!AU$221,"")) | U40: =IF($B40="","",SUM($T$36:$T40)) | V40: =IF($B40="","",IFERROR(Accrual!BL$221*'Index Summary'!$C$6/(1-'Index Summary'!$C$6),"")) | W40: =IF($B40="","",SUM($V$36:$V40)) | X40: =IF($B40="","",IFERROR(Accrual!AU$309,"")) | Y40: =IF($B40="","",SUM($X$36:$X40)) | Z40: =IF($B40="","",IFERROR(Accrual!BL$309*'Index Summary'!$C$6/(1-'Index Summary'!$C$6),"")) | AA40: =IF($B40="","",SUM($Z$36:$Z40))
B41: =IF(Expiries!$B21="","",Expiries!$C21) | C41: =IF($B41="","",IFERROR(Accrual!AB$221/Accrual!K$221,"")) | D41: =IF($B41="","",IFERROR(Accrual!AB$221*'Index Summary'!$C$6/(1-'Index Summary'!$C$6),"")) | E41: =IF($B41="","",SUM($D$36:$D41)) | F41: =IF($B41="","",IFERROR(($G18+$E41)/$C$5,"")) | G41: =IF($B41="","",IFERROR($F41*365/$D18,"")) | H41: =IF($B41="","",IFERROR(Accrual!AB$309/Accrual!K$309,"")) | I41: =IF($B41="","",IFERROR(Accrual!AB$309*'Index Summary'!$C$6/(1-'Index Summary'!$C$6),"")) | J41: =IF($B41="","",SUM($I$36:$I41)) | K41: =IF($B41="","",IFERROR(($M18+$J41)/$C$6,"")) | L41: =IF($B41="","",IFERROR($K41*365/($J18-$C$7),"")) | M41: =IF($B41="","",IFERROR(($F41-$K41)*10000,"")) | N41: =IF($B41="","",IFERROR(($G41-$L41)*10000,"")) | T41: =IF($B41="","",IFERROR(Accrual!AV$221,"")) | U41: =IF($B41="","",SUM($T$36:$T41)) | V41: =IF($B41="","",IFERROR(Accrual!BM$221*'Index Summary'!$C$6/(1-'Index Summary'!$C$6),"")) | W41: =IF($B41="","",SUM($V$36:$V41)) | X41: =IF($B41="","",IFERROR(Accrual!AV$309,"")) | Y41: =IF($B41="","",SUM($X$36:$X41)) | Z41: =IF($B41="","",IFERROR(Accrual!BM$309*'Index Summary'!$C$6/(1-'Index Summary'!$C$6),"")) | AA41: =IF($B41="","",SUM($Z$36:$Z41))
B42: =IF(Expiries!$B22="","",Expiries!$C22) | C42: =IF($B42="","",IFERROR(Accrual!AC$221/Accrual!L$221,"")) | D42: =IF($B42="","",IFERROR(Accrual!AC$221*'Index Summary'!$C$6/(1-'Index Summary'!$C$6),"")) | E42: =IF($B42="","",SUM($D$36:$D42)) | F42: =IF($B42="","",IFERROR(($G19+$E42)/$C$5,"")) | G42: =IF($B42="","",IFERROR($F42*365/$D19,"")) | H42: =IF($B42="","",IFERROR(Accrual!AC$309/Accrual!L$309,"")) | I42: =IF($B42="","",IFERROR(Accrual!AC$309*'Index Summary'!$C$6/(1-'Index Summary'!$C$6),"")) | J42: =IF($B42="","",SUM($I$36:$I42)) | K42: =IF($B42="","",IFERROR(($M19+$J42)/$C$6,"")) | L42: =IF($B42="","",IFERROR($K42*365/($J19-$C$7),"")) | M42: =IF($B42="","",IFERROR(($F42-$K42)*10000,"")) | N42: =IF($B42="","",IFERROR(($G42-$L42)*10000,"")) | T42: =IF($B42="","",IFERROR(Accrual!AW$221,"")) | U42: =IF($B42="","",SUM($T$36:$T42)) | V42: =IF($B42="","",IFERROR(Accrual!BN$221*'Index Summary'!$C$6/(1-'Index Summary'!$C$6),"")) | W42: =IF($B42="","",SUM($V$36:$V42)) | X42: =IF($B42="","",IFERROR(Accrual!AW$309,"")) | Y42: =IF($B42="","",SUM($X$36:$X42)) | Z42: =IF($B42="","",IFERROR(Accrual!BN$309*'Index Summary'!$C$6/(1-'Index Summary'!$C$6),"")) | AA42: =IF($B42="","",SUM($Z$36:$Z42))
B43: =IF(Expiries!$B23="","",Expiries!$C23) | C43: =IF($B43="","",IFERROR(Accrual!AD$221/Accrual!M$221,"")) | D43: =IF($B43="","",IFERROR(Accrual!AD$221*'Index Summary'!$C$6/(1-'Index Summary'!$C$6),"")) | E43: =IF($B43="","",SUM($D$36:$D43)) | F43: =IF($B43="","",IFERROR(($G20+$E43)/$C$5,"")) | G43: =IF($B43="","",IFERROR($F43*365/$D20,"")) | H43: =IF($B43="","",IFERROR(Accrual!AD$309/Accrual!M$309,"")) | I43: =IF($B43="","",IFERROR(Accrual!AD$309*'Index Summary'!$C$6/(1-'Index Summary'!$C$6),"")) | J43: =IF($B43="","",SUM($I$36:$I43)) | K43: =IF($B43="","",IFERROR(($M20+$J43)/$C$6,"")) | L43: =IF($B43="","",IFERROR($K43*365/($J20-$C$7),"")) | M43: =IF($B43="","",IFERROR(($F43-$K43)*10000,"")) | N43: =IF($B43="","",IFERROR(($G43-$L43)*10000,"")) | T43: =IF($B43="","",IFERROR(Accrual!AX$221,"")) | U43: =IF($B43="","",SUM($T$36:$T43)) | V43: =IF($B43="","",IFERROR(Accrual!BO$221*'Index Summary'!$C$6/(1-'Index Summary'!$C$6),"")) | W43: =IF($B43="","",SUM($V$36:$V43)) | X43: =IF($B43="","",IFERROR(Accrual!AX$309,"")) | Y43: =IF($B43="","",SUM($X$36:$X43)) | Z43: =IF($B43="","",IFERROR(Accrual!BO$309*'Index Summary'!$C$6/(1-'Index Summary'!$C$6),"")) | AA43: =IF($B43="","",SUM($Z$36:$Z43))
B44: =IF(Expiries!$B24="","",Expiries!$C24) | C44: =IF($B44="","",IFERROR(Accrual!AE$221/Accrual!N$221,"")) | D44: =IF($B44="","",IFERROR(Accrual!AE$221*'Index Summary'!$C$6/(1-'Index Summary'!$C$6),"")) | E44: =IF($B44="","",SUM($D$36:$D44)) | F44: =IF($B44="","",IFERROR(($G21+$E44)/$C$5,"")) | G44: =IF($B44="","",IFERROR($F44*365/$D21,"")) | H44: =IF($B44="","",IFERROR(Accrual!AE$309/Accrual!N$309,"")) | I44: =IF($B44="","",IFERROR(Accrual!AE$309*'Index Summary'!$C$6/(1-'Index Summary'!$C$6),"")) | J44: =IF($B44="","",SUM($I$36:$I44)) | K44: =IF($B44="","",IFERROR(($M21+$J44)/$C$6,"")) | L44: =IF($B44="","",IFERROR($K44*365/($J21-$C$7),"")) | M44: =IF($B44="","",IFERROR(($F44-$K44)*10000,"")) | N44: =IF($B44="","",IFERROR(($G44-$L44)*10000,"")) | T44: =IF($B44="","",IFERROR(Accrual!AY$221,"")) | U44: =IF($B44="","",SUM($T$36:$T44)) | V44: =IF($B44="","",IFERROR(Accrual!BP$221*'Index Summary'!$C$6/(1-'Index Summary'!$C$6),"")) | W44: =IF($B44="","",SUM($V$36:$V44)) | X44: =IF($B44="","",IFERROR(Accrual!AY$309,"")) | Y44: =IF($B44="","",SUM($X$36:$X44)) | Z44: =IF($B44="","",IFERROR(Accrual!BP$309*'Index Summary'!$C$6/(1-'Index Summary'!$C$6),"")) | AA44: =IF($B44="","",SUM($Z$36:$Z44))
B45: =IF(Expiries!$B25="","",Expiries!$C25) | C45: =IF($B45="","",IFERROR(Accrual!AF$221/Accrual!O$221,"")) | D45: =IF($B45="","",IFERROR(Accrual!AF$221*'Index Summary'!$C$6/(1-'Index Summary'!$C$6),"")) | E45: =IF($B45="","",SUM($D$36:$D45)) | F45: =IF($B45="","",IFERROR(($G22+$E45)/$C$5,"")) | G45: =IF($B45="","",IFERROR($F45*365/$D22,"")) | H45: =IF($B45="","",IFERROR(Accrual!AF$309/Accrual!O$309,"")) | I45: =IF($B45="","",IFERROR(Accrual!AF$309*'Index Summary'!$C$6/(1-'Index Summary'!$C$6),"")) | J45: =IF($B45="","",SUM($I$36:$I45)) | K45: =IF($B45="","",IFERROR(($M22+$J45)/$C$6,"")) | L45: =IF($B45="","",IFERROR($K45*365/($J22-$C$7),"")) | M45: =IF($B45="","",IFERROR(($F45-$K45)*10000,"")) | N45: =IF($B45="","",IFERROR(($G45-$L45)*10000,"")) | T45: =IF($B45="","",IFERROR(Accrual!AZ$221,"")) | U45: =IF($B45="","",SUM($T$36:$T45)) | V45: =IF($B45="","",IFERROR(Accrual!BQ$221*'Index Summary'!$C$6/(1-'Index Summary'!$C$6),"")) | W45: =IF($B45="","",SUM($V$36:$V45)) | X45: =IF($B45="","",IFERROR(Accrual!AZ$309,"")) | Y45: =IF($B45="","",SUM($X$36:$X45)) | Z45: =IF($B45="","",IFERROR(Accrual!BQ$309*'Index Summary'!$C$6/(1-'Index Summary'!$C$6),"")) | AA45: =IF($B45="","",SUM($Z$36:$Z45))
B46: =IF(Expiries!$B26="","",Expiries!$C26) | C46: =IF($B46="","",IFERROR(Accrual!AG$221/Accrual!P$221,"")) | D46: =IF($B46="","",IFERROR(Accrual!AG$221*'Index Summary'!$C$6/(1-'Index Summary'!$C$6),"")) | E46: =IF($B46="","",SUM($D$36:$D46)) | F46: =IF($B46="","",IFERROR(($G23+$E46)/$C$5,"")) | G46: =IF($B46="","",IFERROR($F46*365/$D23,"")) | H46: =IF($B46="","",IFERROR(Accrual!AG$309/Accrual!P$309,"")) | I46: =IF($B46="","",IFERROR(Accrual!AG$309*'Index Summary'!$C$6/(1-'Index Summary'!$C$6),"")) | J46: =IF($B46="","",SUM($I$36:$I46)) | K46: =IF($B46="","",IFERROR(($M23+$J46)/$C$6,"")) | L46: =IF($B46="","",IFERROR($K46*365/($J23-$C$7),"")) | M46: =IF($B46="","",IFERROR(($F46-$K46)*10000,"")) | N46: =IF($B46="","",IFERROR(($G46-$L46)*10000,"")) | T46: =IF($B46="","",IFERROR(Accrual!BA$221,"")) | U46: =IF($B46="","",SUM($T$36:$T46)) | V46: =IF($B46="","",IFERROR(Accrual!BR$221*'Index Summary'!$C$6/(1-'Index Summary'!$C$6),"")) | W46: =IF($B46="","",SUM($V$36:$V46)) | X46: =IF($B46="","",IFERROR(Accrual!BA$309,"")) | Y46: =IF($B46="","",SUM($X$36:$X46)) | Z46: =IF($B46="","",IFERROR(Accrual!BR$309*'Index Summary'!$C$6/(1-'Index Summary'!$C$6),"")) | AA46: =IF($B46="","",SUM($Z$36:$Z46))
B47: =IF(Expiries!$B27="","",Expiries!$C27) | C47: =IF($B47="","",IFERROR(Accrual!AH$221/Accrual!Q$221,"")) | D47: =IF($B47="","",IFERROR(Accrual!AH$221*'Index Summary'!$C$6/(1-'Index Summary'!$C$6),"")) | E47: =IF($B47="","",SUM($D$36:$D47)) | F47: =IF($B47="","",IFERROR(($G24+$E47)/$C$5,"")) | G47: =IF($B47="","",IFERROR($F47*365/$D24,"")) | H47: =IF($B47="","",IFERROR(Accrual!AH$309/Accrual!Q$309,"")) | I47: =IF($B47="","",IFERROR(Accrual!AH$309*'Index Summary'!$C$6/(1-'Index Summary'!$C$6),"")) | J47: =IF($B47="","",SUM($I$36:$I47)) | K47: =IF($B47="","",IFERROR(($M24+$J47)/$C$6,"")) | L47: =IF($B47="","",IFERROR($K47*365/($J24-$C$7),"")) | M47: =IF($B47="","",IFERROR(($F47-$K47)*10000,"")) | N47: =IF($B47="","",IFERROR(($G47-$L47)*10000,"")) | T47: =IF($B47="","",IFERROR(Accrual!BB$221,"")) | U47: =IF($B47="","",SUM($T$36:$T47)) | V47: =IF($B47="","",IFERROR(Accrual!BS$221*'Index Summary'!$C$6/(1-'Index Summary'!$C$6),"")) | W47: =IF($B47="","",SUM($V$36:$V47)) | X47: =IF($B47="","",IFERROR(Accrual!BB$309,"")) | Y47: =IF($B47="","",SUM($X$36:$X47)) | Z47: =IF($B47="","",IFERROR(Accrual!BS$309*'Index Summary'!$C$6/(1-'Index Summary'!$C$6),"")) | AA47: =IF($B47="","",SUM($Z$36:$Z47))
B48: =IF(Expiries!$B28="","",Expiries!$C28) | C48: =IF($B48="","",IFERROR(Accrual!AI$221/Accrual!R$221,"")) | D48: =IF($B48="","",IFERROR(Accrual!AI$221*'Index Summary'!$C$6/(1-'Index Summary'!$C$6),"")) | E48: =IF($B48="","",SUM($D$36:$D48)) | F48: =IF($B48="","",IFERROR(($G25+$E48)/$C$5,"")) | G48: =IF($B48="","",IFERROR($F48*365/$D25,"")) | H48: =IF($B48="","",IFERROR(Accrual!AI$309/Accrual!R$309,"")) | I48: =IF($B48="","",IFERROR(Accrual!AI$309*'Index Summary'!$C$6/(1-'Index Summary'!$C$6),"")) | J48: =IF($B48="","",SUM($I$36:$I48)) | K48: =IF($B48="","",IFERROR(($M25+$J48)/$C$6,"")) | L48: =IF($B48="","",IFERROR($K48*365/($J25-$C$7),"")) | M48: =IF($B48="","",IFERROR(($F48-$K48)*10000,"")) | N48: =IF($B48="","",IFERROR(($G48-$L48)*10000,"")) | T48: =IF($B48="","",IFERROR(Accrual!BC$221,"")) | U48: =IF($B48="","",SUM($T$36:$T48)) | V48: =IF($B48="","",IFERROR(Accrual!BT$221*'Index Summary'!$C$6/(1-'Index Summary'!$C$6),"")) | W48: =IF($B48="","",SUM($V$36:$V48)) | X48: =IF($B48="","",IFERROR(Accrual!BC$309,"")) | Y48: =IF($B48="","",SUM($X$36:$X48)) | Z48: =IF($B48="","",IFERROR(Accrual!BT$309*'Index Summary'!$C$6/(1-'Index Summary'!$C$6),"")) | AA48: =IF($B48="","",SUM($Z$36:$Z48))
B49: =IF(Expiries!$B29="","",Expiries!$C29) | C49: =IF($B49="","",IFERROR(Accrual!AJ$221/Accrual!S$221,"")) | D49: =IF($B49="","",IFERROR(Accrual!AJ$221*'Index Summary'!$C$6/(1-'Index Summary'!$C$6),"")) | E49: =IF($B49="","",SUM($D$36:$D49)) | F49: =IF($B49="","",IFERROR(($G26+$E49)/$C$5,"")) | G49: =IF($B49="","",IFERROR($F49*365/$D26,"")) | H49: =IF($B49="","",IFERROR(Accrual!AJ$309/Accrual!S$309,"")) | I49: =IF($B49="","",IFERROR(Accrual!AJ$309*'Index Summary'!$C$6/(1-'Index Summary'!$C$6),"")) | J49: =IF($B49="","",SUM($I$36:$I49)) | K49: =IF($B49="","",IFERROR(($M26+$J49)/$C$6,"")) | L49: =IF($B49="","",IFERROR($K49*365/($J26-$C$7),"")) | M49: =IF($B49="","",IFERROR(($F49-$K49)*10000,"")) | N49: =IF($B49="","",IFERROR(($G49-$L49)*10000,"")) | T49: =IF($B49="","",IFERROR(Accrual!BD$221,"")) | U49: =IF($B49="","",SUM($T$36:$T49)) | V49: =IF($B49="","",IFERROR(Accrual!BU$221*'Index Summary'!$C$6/(1-'Index Summary'!$C$6),"")) | W49: =IF($B49="","",SUM($V$36:$V49)) | X49: =IF($B49="","",IFERROR(Accrual!BD$309,"")) | Y49: =IF($B49="","",SUM($X$36:$X49)) | Z49: =IF($B49="","",IFERROR(Accrual!BU$309*'Index Summary'!$C$6/(1-'Index Summary'!$C$6),"")) | AA49: =IF($B49="","",SUM($Z$36:$Z49))
B50: =IF(Expiries!$B30="","",Expiries!$C30) | C50: =IF($B50="","",IFERROR(Accrual!AK$221/Accrual!T$221,"")) | D50: =IF($B50="","",IFERROR(Accrual!AK$221*'Index Summary'!$C$6/(1-'Index Summary'!$C$6),"")) | E50: =IF($B50="","",SUM($D$36:$D50)) | F50: =IF($B50="","",IFERROR(($G27+$E50)/$C$5,"")) | G50: =IF($B50="","",IFERROR($F50*365/$D27,"")) | H50: =IF($B50="","",IFERROR(Accrual!AK$309/Accrual!T$309,"")) | I50: =IF($B50="","",IFERROR(Accrual!AK$309*'Index Summary'!$C$6/(1-'Index Summary'!$C$6),"")) | J50: =IF($B50="","",SUM($I$36:$I50)) | K50: =IF($B50="","",IFERROR(($M27+$J50)/$C$6,"")) | L50: =IF($B50="","",IFERROR($K50*365/($J27-$C$7),"")) | M50: =IF($B50="","",IFERROR(($F50-$K50)*10000,"")) | N50: =IF($B50="","",IFERROR(($G50-$L50)*10000,"")) | T50: =IF($B50="","",IFERROR(Accrual!BE$221,"")) | U50: =IF($B50="","",SUM($T$36:$T50)) | V50: =IF($B50="","",IFERROR(Accrual!BV$221*'Index Summary'!$C$6/(1-'Index Summary'!$C$6),"")) | W50: =IF($B50="","",SUM($V$36:$V50)) | X50: =IF($B50="","",IFERROR(Accrual!BE$309,"")) | Y50: =IF($B50="","",SUM($X$36:$X50)) | Z50: =IF($B50="","",IFERROR(Accrual!BV$309*'Index Summary'!$C$6/(1-'Index Summary'!$C$6),"")) | AA50: =IF($B50="","",SUM($Z$36:$Z50))
B51: =IF(Expiries!$B31="","",Expiries!$C31) | C51: =IF($B51="","",IFERROR(Accrual!AL$221/Accrual!U$221,"")) | D51: =IF($B51="","",IFERROR(Accrual!AL$221*'Index Summary'!$C$6/(1-'Index Summary'!$C$6),"")) | E51: =IF($B51="","",SUM($D$36:$D51)) | F51: =IF($B51="","",IFERROR(($G28+$E51)/$C$5,"")) | G51: =IF($B51="","",IFERROR($F51*365/$D28,"")) | H51: =IF($B51="","",IFERROR(Accrual!AL$309/Accrual!U$309,"")) | I51: =IF($B51="","",IFERROR(Accrual!AL$309*'Index Summary'!$C$6/(1-'Index Summary'!$C$6),"")) | J51: =IF($B51="","",SUM($I$36:$I51)) | K51: =IF($B51="","",IFERROR(($M28+$J51)/$C$6,"")) | L51: =IF($B51="","",IFERROR($K51*365/($J28-$C$7),"")) | M51: =IF($B51="","",IFERROR(($F51-$K51)*10000,"")) | N51: =IF($B51="","",IFERROR(($G51-$L51)*10000,"")) | T51: =IF($B51="","",IFERROR(Accrual!BF$221,"")) | U51: =IF($B51="","",SUM($T$36:$T51)) | V51: =IF($B51="","",IFERROR(Accrual!BW$221*'Index Summary'!$C$6/(1-'Index Summary'!$C$6),"")) | W51: =IF($B51="","",SUM($V$36:$V51)) | X51: =IF($B51="","",IFERROR(Accrual!BF$309,"")) | Y51: =IF($B51="","",SUM($X$36:$X51)) | Z51: =IF($B51="","",IFERROR(Accrual!BW$309*'Index Summary'!$C$6/(1-'Index Summary'!$C$6),"")) | AA51: =IF($B51="","",SUM($Z$36:$Z51))
B53: BEFORE YOU TRADE OFF THIS
B54: - | C54: The front contract annualizes off a handful of days - use the annualized spread (Q) across contracts.
B55: - | C55: Covered? = CHECK means Bloomberg's projections stop before that expiry: its dividends are understated.
B56: - | C56: The Futures FV tab turns this into trade form: implied dividends from each traded futures price against these columns, and the franking % the market is paying. Fill the market prices there.

Sheet Futures FV
B2: FUTURES FAIR VALUE - AND THE FRANKING CREDIT PRICED IN
B3: Fair value = spot x (1 + rate x days/basis) - dividends to expiry. Type the traded futures price per contract: implied dividends = spot + carry - price, and the excess over your CASH dividend forecast, as a share of the franking credits available, is the franking the market is paying for.
B4: Overrides | C4: =IF(Override!$C$4="ON","ON - "&Override!$E$4&" row(s) live - the dividend columns below include YOUR numbers.","OFF - pure Bloomberg projections.")
AK5: AUD OIS CURVE (ICVS 159) | AP5: SPI FUTURES ROOT
B6: INPUTS | C6: AS51 (SPI, AUD) | D6: MXAU (USD) | AK6: curve tkr | AL6: YCSW0159 Index | AP6: root | AQ6: XP
B7: Spot - live (from Div by Expiry) | C7: ='Div by Expiry'!$C$5 | D7: ='Div by Expiry'!$C$6 | AK7: Tenor | AL7: Days | AM7: Ticker | AN7: % (live) | AO7: % zero
B8: Spot - override (optional) | G8: Type a spot here to match the moment you marked the futures - basis noise otherwise. | AK8: 1W | AL8: 7 | AM8: ADSO1Z Curncy | AN8: =IF($AM8="","",BDP($AM8,"PX_LAST")) | AO8: =IF($AN8="","",IF($AL8<=365,$AN8,IFERROR((1/((1-$AN8/100*(1/(1+INDEX($AN$8:$AN$17,MATCH(365,$AL$8:$AL$17,0))/100)))/(1+$AN8/100*($AL8-365)/365))-1)*365/$AL8*100,"")))
B9: SPOT USED | C9: =IF(ISNUMBER($C$8),$C$8,$C$7) | D9: =IF(ISNUMBER($D$8),$D$8,$D$7) | AK9: 1M | AL9: 30 | AM9: ADSOA Curncy | AN9: =IF($AM9="","",BDP($AM9,"PX_LAST")) | AO9: =IF($AN9="","",IF($AL9<=365,$AN9,IFERROR((1/((1-$AN9/100*(1/(1+INDEX($AN$8:$AN$17,MATCH(365,$AL$8:$AL$17,0))/100)))/(1+$AN9/100*($AL9-365)/365))-1)*365/$AL9*100,"")))
B10: Funding (% p.a.) - blank = AUD OIS curve | G10: BOTH legs price off the AUD OIS curve at the right, interpolated to each contract's own days (cols AI / AJ) - your MXAU basket is AUD-denominated. Type a number here to force one flat rate for that leg (this is how you replicate the exact rate a FAIR screen shows). Your bank's funding for a SPECIFIC expiry goes in the 'YOUR funding %' columns at the far right - a number there beats everything else for that contract only. | AK10: 2M | AL10: 61 | AM10: ADSOB Curncy | AN10: =IF($AM10="","",BDP($AM10,"PX_LAST")) | AO10: =IF($AN10="","",IF($AL10<=365,$AN10,IFERROR((1/((1-$AN10/100*(1/(1+INDEX($AN$8:$AN$17,MATCH(365,$AL$8:$AL$17,0))/100)))/(1+$AN10/100*($AL10-365)/365))-1)*365/$AL10*100,"")))
B11: Day-count basis | C11: 365 | D11: 365 | G11: AUD convention ACT/365 - both legs (the MXAU basket is AUD now). | AK11: 3M | AL11: 91 | AM11: ADSOC Curncy | AN11: =IF($AM11="","",BDP($AM11,"PX_LAST")) | AO11: =IF($AN11="","",IF($AL11<=365,$AN11,IFERROR((1/((1-$AN11/100*(1/(1+INDEX($AN$8:$AN$17,MATCH(365,$AL$8:$AL$17,0))/100)))/(1+$AN11/100*($AL11-365)/365))-1)*365/$AL11*100,"")))
B12: YOUR franking assumption (% of credits, 0-100) | C12: 0 | D12: 0 | G12: Drives the 'FV at your %' and 'mispricing' columns only. The offshore marginal investor in MXAU futures cannot use franking - 0 is the natural starting point there. | AK12: 4M | AL12: 122 | AM12: ADSOD Curncy | AN12: =IF($AM12="","",BDP($AM12,"PX_LAST")) | AO12: =IF($AN12="","",IF($AL12<=365,$AN12,IFERROR((1/((1-$AN12/100*(1/(1+INDEX($AN$8:$AN$17,MATCH(365,$AL$8:$AL$17,0))/100)))/(1+$AN12/100*($AL12-365)/365))-1)*365/$AL12*100,"")))
B13: Carry dividends to expiry? (Y/N) | C13: N | D13: =$C$13 | G13: One toggle for both legs (the MXAU cell mirrors it). Y future-values each period's dividends from the middle of its window to expiry at the funding rate - a few points on the far contracts. N is the plain desk convention. | AK13: 5M | AL13: 152 | AM13: ADSOE Curncy | AN13: =IF($AM13="","",BDP($AM13,"PX_LAST")) | AO13: =IF($AN13="","",IF($AL13<=365,$AN13,IFERROR((1/((1-$AN13/100*(1/(1+INDEX($AN$8:$AN$17,MATCH(365,$AL$8:$AL$17,0))/100)))/(1+$AN13/100*($AL13-365)/365))-1)*365/$AL13*100,"")))
B14: Funding spread over OIS (bp) | C14: 0 | D14: 0 | G14: Added on top of the interpolated OIS zero (ignored when a flat rate is typed above). Your real repo / TRS funding goes here; screen fair values often run off a bank-bill style rate ~10-25bp above OIS. | AK14: 6M | AL14: 183 | AM14: ADSOF Curncy | AN14: =IF($AM14="","",BDP($AM14,"PX_LAST")) | AO14: =IF($AN14="","",IF($AL14<=365,$AN14,IFERROR((1/((1-$AN14/100*(1/(1+INDEX($AN$8:$AN$17,MATCH(365,$AL$8:$AL$17,0))/100)))/(1+$AN14/100*($AL14-365)/365))-1)*365/$AL14*100,"")))
B15: MARKET price per row = your manual price (col AQ, far right) if typed, else the LIVE pull on the auto-built SPI ticker (root XP + month code F G H J K M N Q U V X Z + year digit: Aug26 = XPQ6). Serial months list on ASX but the volume sits in Mar / Jun / Sep / Dec. | T15: MXAU: NO listed price-index future exists. Eurex FMAU (ZTOA Index, USD) tracks MSCI Australia NET TOTAL RETURN - dividends are reinvested in it, so it prices no dividends and cannot be compared to these fair values. Type OTC / dealer price-index forward quotes only. | AK15: 9M | AL15: 274 | AM15: ADSOI Curncy | AN15: =IF($AM15="","",BDP($AM15,"PX_LAST")) | AO15: =IF($AN15="","",IF($AL15<=365,$AN15,IFERROR((1/((1-$AN15/100*(1/(1+INDEX($AN$8:$AN$17,MATCH(365,$AL$8:$AL$17,0))/100)))/(1+$AN15/100*($AL15-365)/365))-1)*365/$AL15*100,"")))
B16: Count SPECIAL dividends in FV? (Y/N) | C16: N | D16: N | G16: S&P and MSCI adjust the index DIVISOR for special dividends and capital returns - the index does not drop, so futures never price them: N excludes them (Div by Expiry keeps them, with an 'o/w specials' block showing exactly how much). MSCI only adjusts specials >=5% of the share price - set the MXAU cell to Y if the specials in window are small. | AK16: 1Y | AL16: 365 | AM16: ADSO1 Curncy | AN16: =IF($AM16="","",BDP($AM16,"PX_LAST")) | AO16: =IF($AN16="","",IF($AL16<=365,$AN16,IFERROR((1/((1-$AN16/100*(1/(1+INDEX($AN$8:$AN$17,MATCH(365,$AL$8:$AL$17,0))/100)))/(1+$AN16/100*($AL16-365)/365))-1)*365/$AL16*100,"")))
E17: S&P/ASX 200 (AS51 / SPI) | T17: MSCI AUSTRALIA (MXAU) | AG17: A vs M | AK17: 18M | AL17: 548 | AM17: ADSO1F Curncy | AN17: =IF($AM17="","",BDP($AM17,"PX_LAST")) | AO17: =IF($AN17="","",IF($AL17<=365,$AN17,IFERROR((1/((1-$AN17/100*(1/(1+INDEX($AN$8:$AN$17,MATCH(365,$AL$8:$AL$17,0))/100)))/(1+$AN17/100*($AL17-365)/365))-1)*365/$AL17*100,""))) | AP17: SPI PRICE FEED
B18: Contract | C18: Expiry | D18: Days | E18: Carry (pts) | F18: Divs to expiry (pts) | G18: Credits to expiry (pts) | H18: FV - no franking | I18: FV - full franking | J18: FV at YOUR % | K18: MARKET price | L18: Implied divs (pts) | M18: Franking priced (pts) | N18: FRANKING PRICED (%) | O18: Rich(+) / Cheap(-) vs your % (pts) | P18: same (bps) | R18: Expiry | S18: Days | T18: Carry (pts) | U18: Divs to expiry (pts) | V18: Credits to expiry (pts) | W18: FV - no franking | X18: FV - full franking | Y18: FV at YOUR % | Z18: MARKET price | AA18: Implied divs (pts) | AB18: Franking priced (pts) | AC18: FRANKING PRICED (%) | AD18: Rich(+) / Cheap(-) vs your % (pts) | AE18: same (bps) | AG18: Franking % A - M (pp) | AI18: AUD OIS % (AS51 exp) | AJ18: AUD OIS % (MXAU exp) | AK18: Tickers/days editable (blue) - confirm each ticker against the curve pull below or ICVS 159; keep Days ascending. '% zero' = the rate the maths uses: equal to the quote up to 1Y (AUD OIS pays once at maturity, ACT/365), bootstrapped past 1Y (annual coupon). | AP18: SPI ticker (auto) | AQ18: manual px (wins) | AR18: live px (LAST_PRICE) | AS18: YOUR funding % (AS51 exp) | AT18: YOUR funding % (MXAU exp) | AV18: net edge cash&carry (pts) | AW18: net edge reverse (pts) | AX18: ACTION (after costs)
B19: =IF('Div by Expiry'!$B13="","",'Div by Expiry'!$B13) | C19: =IF($B19="","",'Div by Expiry'!$C13) | D19: =IF($B19="","",'Div by Expiry'!$D13) | E19: =IF($B19="","",IF($AI19="","",$C$9*$AI19/100*$D19/$C$11)) | F19: =IF($B19="","",IF($C$13="N",'Div by Expiry'!$G13-IF($C$16="Y",0,'Div by Expiry'!$U36),IF($AI19="","",SUMPRODUCT('Div by Expiry'!$E$13:$E13,1+$AI19/100*($C19-(Expiries!$J$16:$J16+Expiries!$F$16:$F16)/2)/$C$11)-IF($C$16="Y",0,SUMPRODUCT('Div by Expiry'!$T$36:$T36,1+$AI19/100*($C19-(Expiries!$J$16:$J16+Expiries!$F$16:$F16)/2)/$C$11))))) | G19: =IF($B19="","",IF($C$13="N",'Div by Expiry'!$E36-IF($C$16="Y",0,'Div by Expiry'!$W36),IF($AI19="","",SUMPRODUCT('Div by Expiry'!$D$36:$D36,1+$AI19/100*($C19-(Expiries!$J$16:$J16+Expiries!$F$16:$F16)/2)/$C$11)-IF($C$16="Y",0,SUMPRODUCT('Div by Expiry'!$V$36:$V36,1+$AI19/100*($C19-(Expiries!$J$16:$J16+Expiries!$F$16:$F16)/2)/$C$11))))) | H19: =IF($B19="","",IF($E19="","",$C$9+$E19-$F19)) | I19: =IF($B19="","",IF($H19="","",$H19-$G19)) | J19: =IF($B19="","",IF($H19="","",$H19-$C$12/100*$G19)) | K19: =IF($B19="","",IF(ISNUMBER($AQ19),$AQ19,IF(ISNUMBER($AR19),$AR19,""))) | L19: =IF($B19="","",IF(N($K19)=0,"",IF($E19="","",$C$9+$E19-$K19))) | M19: =IF($L19="","",$L19-$F19) | N19: =IF($L19="","",IF($G19=0,"",$M19/$G19)) | O19: =IF($L19="","",$K19-$J19) | P19: =IF($L19="","",$O19/$C$9*10000) | R19: =IF($B19="","",'Div by Expiry'!$J13) | S19: =IF($B19="","",$R19-'Div by Expiry'!$C$7) | T19: =IF($B19="","",IF($AJ19="","",$D$9*$AJ19/100*$S19/$D$11)) | U19: =IF($B19="","",IF($C$13="N",'Div by Expiry'!$M13-IF($D$16="Y",0,'Div by Expiry'!$Y36),IF($AJ19="","",SUMPRODUCT('Div by Expiry'!$K$13:$K13,1+$AJ19/100*($R19-(Expiries!$K$16:$K16+Expiries!$I$16:$I16)/2)/$D$11)-IF($D$16="Y",0,SUMPRODUCT('Div by Expiry'!$X$36:$X36,1+$AJ19/100*($R19-(Expiries!$K$16:$K16+Expiries!$I$16:$I16)/2)/$D$11))))) | V19: =IF($B19="","",IF($C$13="N",'Div by Expiry'!$J36-IF($D$16="Y",0,'Div by Expiry'!$AA36),IF($AJ19="","",SUMPRODUCT('Div by Expiry'!$I$36:$I36,1+$AJ19/100*($R19-(Expiries!$K$16:$K16+Expiries!$I$16:$I16)/2)/$D$11)-IF($D$16="Y",0,SUMPRODUCT('Div by Expiry'!$Z$36:$Z36,1+$AJ19/100*($R19-(Expiries!$K$16:$K16+Expiries!$I$16:$I16)/2)/$D$11))))) | W19: =IF($B19="","",IF($T19="","",$D$9+$T19-$U19)) | X19: =IF($B19="","",IF($W19="","",$W19-$V19)) | Y19: =IF($B19="","",IF($W19="","",$W19-$D$12/100*$V19)) | AA19: =IF($B19="","",IF(N($Z19)=0,"",IF($T19="","",$D$9+$T19-$Z19))) | AB19: =IF($AA19="","",$AA19-$U19) | AC19: =IF($AA19="","",IF($V19=0,"",$AB19/$V19)) | AD19: =IF($AA19="","",$Z19-$Y19) | AE19: =IF($AA19="","",$AD19/$D$9*10000) | AG19: =IF($N19="","",IF($AC19="","",($N19-$AC19)*100)) | AI19: =IF($B19="","",IF(ISNUMBER($AS19),$AS19,IF(ISNUMBER($C$10),$C$10,IFERROR(IF(COUNTIF($AL$8:$AL$17,"<="&$D19)=0,$AO$8,IF(COUNTIF($AL$8:$AL$17,"<="&$D19)>=COUNT($AL$8:$AL$17),INDEX($AO$8:$AO$17,COUNT($AL$8:$AL$17)),INDEX($AO$8:$AO$17,COUNTIF($AL$8:$AL$17,"<="&$D19))+(INDEX($AO$8:$AO$17,COUNTIF($AL$8:$AL$17,"<="&$D19)+1)-INDEX($AO$8:$AO$17,COUNTIF($AL$8:$AL$17,"<="&$D19)))*($D19-INDEX($AL$8:$AL$17,COUNTIF($AL$8:$AL$17,"<="&$D19)))/(INDEX($AL$8:$AL$17,COUNTIF($AL$8:$AL$17,"<="&$D19)+1)-INDEX($AL$8:$AL$17,COUNTIF($AL$8:$AL$17,"<="&$D19)))))+N($C$14)/100,"")))) | AJ19: =IF($B19="","",IF(ISNUMBER($AT19),$AT19,IF(ISNUMBER($D$10),$D$10,IFERROR(IF(COUNTIF($AL$8:$AL$17,"<="&$S19)=0,$AO$8,IF(COUNTIF($AL$8:$AL$17,"<="&$S19)>=COUNT($AL$8:$AL$17),INDEX($AO$8:$AO$17,COUNT($AL$8:$AL$17)),INDEX($AO$8:$AO$17,COUNTIF($AL$8:$AL$17,"<="&$S19))+(INDEX($AO$8:$AO$17,COUNTIF($AL$8:$AL$17,"<="&$S19)+1)-INDEX($AO$8:$AO$17,COUNTIF($AL$8:$AL$17,"<="&$S19)))*($S19-INDEX($AL$8:$AL$17,COUNTIF($AL$8:$AL$17,"<="&$S19)))/(INDEX($AL$8:$AL$17,COUNTIF($AL$8:$AL$17,"<="&$S19)+1)-INDEX($AL$8:$AL$17,COUNTIF($AL$8:$AL$17,"<="&$S19)))))+N($D$14)/100,"")))) | AP19: =IF($B19="","",$AQ$6&CHOOSE(MONTH($C19),"F","G","H","J","K","M","N","Q","U","V","X","Z")&RIGHT(YEAR($C19),1)&" Index") | AR19: =IF($AP19="","",BDP($AP19,"LAST_PRICE")) | AV19: =IF($L19="","",$O19-$C$49) | AW19: =IF($L19="","",$H19-$K19-$C$50-$C$45/10000*$C$9*$D19/365) | AX19: =IF($L19="","",IF($AV19>0,"SELL FUT / BUY CASH +"&TEXT($AV19,"0.0")&" pts net",IF($AW19>0,"BUY FUT / SHORT CASH +"&TEXT($AW19,"0.0")&" pts net","no edge after costs")))
B20: =IF('Div by Expiry'!$B14="","",'Div by Expiry'!$B14) | C20: =IF($B20="","",'Div by Expiry'!$C14) | D20: =IF($B20="","",'Div by Expiry'!$D14) | E20: =IF($B20="","",IF($AI20="","",$C$9*$AI20/100*$D20/$C$11)) | F20: =IF($B20="","",IF($C$13="N",'Div by Expiry'!$G14-IF($C$16="Y",0,'Div by Expiry'!$U37),IF($AI20="","",SUMPRODUCT('Div by Expiry'!$E$13:$E14,1+$AI20/100*($C20-(Expiries!$J$16:$J17+Expiries!$F$16:$F17)/2)/$C$11)-IF($C$16="Y",0,SUMPRODUCT('Div by Expiry'!$T$36:$T37,1+$AI20/100*($C20-(Expiries!$J$16:$J17+Expiries!$F$16:$F17)/2)/$C$11))))) | G20: =IF($B20="","",IF($C$13="N",'Div by Expiry'!$E37-IF($C$16="Y",0,'Div by Expiry'!$W37),IF($AI20="","",SUMPRODUCT('Div by Expiry'!$D$36:$D37,1+$AI20/100*($C20-(Expiries!$J$16:$J17+Expiries!$F$16:$F17)/2)/$C$11)-IF($C$16="Y",0,SUMPRODUCT('Div by Expiry'!$V$36:$V37,1+$AI20/100*($C20-(Expiries!$J$16:$J17+Expiries!$F$16:$F17)/2)/$C$11))))) | H20: =IF($B20="","",IF($E20="","",$C$9+$E20-$F20)) | I20: =IF($B20="","",IF($H20="","",$H20-$G20)) | J20: =IF($B20="","",IF($H20="","",$H20-$C$12/100*$G20)) | K20: =IF($B20="","",IF(ISNUMBER($AQ20),$AQ20,IF(ISNUMBER($AR20),$AR20,""))) | L20: =IF($B20="","",IF(N($K20)=0,"",IF($E20="","",$C$9+$E20-$K20))) | M20: =IF($L20="","",$L20-$F20) | N20: =IF($L20="","",IF($G20=0,"",$M20/$G20)) | O20: =IF($L20="","",$K20-$J20) | P20: =IF($L20="","",$O20/$C$9*10000) | R20: =IF($B20="","",'Div by Expiry'!$J14) | S20: =IF($B20="","",$R20-'Div by Expiry'!$C$7) | T20: =IF($B20="","",IF($AJ20="","",$D$9*$AJ20/100*$S20/$D$11)) | U20: =IF($B20="","",IF($C$13="N",'Div by Expiry'!$M14-IF($D$16="Y",0,'Div by Expiry'!$Y37),IF($AJ20="","",SUMPRODUCT('Div by Expiry'!$K$13:$K14,1+$AJ20/100*($R20-(Expiries!$K$16:$K17+Expiries!$I$16:$I17)/2)/$D$11)-IF($D$16="Y",0,SUMPRODUCT('Div by Expiry'!$X$36:$X37,1+$AJ20/100*($R20-(Expiries!$K$16:$K17+Expiries!$I$16:$I17)/2)/$D$11))))) | V20: =IF($B20="","",IF($C$13="N",'Div by Expiry'!$J37-IF($D$16="Y",0,'Div by Expiry'!$AA37),IF($AJ20="","",SUMPRODUCT('Div by Expiry'!$I$36:$I37,1+$AJ20/100*($R20-(Expiries!$K$16:$K17+Expiries!$I$16:$I17)/2)/$D$11)-IF($D$16="Y",0,SUMPRODUCT('Div by Expiry'!$Z$36:$Z37,1+$AJ20/100*($R20-(Expiries!$K$16:$K17+Expiries!$I$16:$I17)/2)/$D$11))))) | W20: =IF($B20="","",IF($T20="","",$D$9+$T20-$U20)) | X20: =IF($B20="","",IF($W20="","",$W20-$V20)) | Y20: =IF($B20="","",IF($W20="","",$W20-$D$12/100*$V20)) | AA20: =IF($B20="","",IF(N($Z20)=0,"",IF($T20="","",$D$9+$T20-$Z20))) | AB20: =IF($AA20="","",$AA20-$U20) | AC20: =IF($AA20="","",IF($V20=0,"",$AB20/$V20)) | AD20: =IF($AA20="","",$Z20-$Y20) | AE20: =IF($AA20="","",$AD20/$D$9*10000) | AG20: =IF($N20="","",IF($AC20="","",($N20-$AC20)*100)) | AI20: =IF($B20="","",IF(ISNUMBER($AS20),$AS20,IF(ISNUMBER($C$10),$C$10,IFERROR(IF(COUNTIF($AL$8:$AL$17,"<="&$D20)=0,$AO$8,IF(COUNTIF($AL$8:$AL$17,"<="&$D20)>=COUNT($AL$8:$AL$17),INDEX($AO$8:$AO$17,COUNT($AL$8:$AL$17)),INDEX($AO$8:$AO$17,COUNTIF($AL$8:$AL$17,"<="&$D20))+(INDEX($AO$8:$AO$17,COUNTIF($AL$8:$AL$17,"<="&$D20)+1)-INDEX($AO$8:$AO$17,COUNTIF($AL$8:$AL$17,"<="&$D20)))*($D20-INDEX($AL$8:$AL$17,COUNTIF($AL$8:$AL$17,"<="&$D20)))/(INDEX($AL$8:$AL$17,COUNTIF($AL$8:$AL$17,"<="&$D20)+1)-INDEX($AL$8:$AL$17,COUNTIF($AL$8:$AL$17,"<="&$D20)))))+N($C$14)/100,"")))) | AJ20: =IF($B20="","",IF(ISNUMBER($AT20),$AT20,IF(ISNUMBER($D$10),$D$10,IFERROR(IF(COUNTIF($AL$8:$AL$17,"<="&$S20)=0,$AO$8,IF(COUNTIF($AL$8:$AL$17,"<="&$S20)>=COUNT($AL$8:$AL$17),INDEX($AO$8:$AO$17,COUNT($AL$8:$AL$17)),INDEX($AO$8:$AO$17,COUNTIF($AL$8:$AL$17,"<="&$S20))+(INDEX($AO$8:$AO$17,COUNTIF($AL$8:$AL$17,"<="&$S20)+1)-INDEX($AO$8:$AO$17,COUNTIF($AL$8:$AL$17,"<="&$S20)))*($S20-INDEX($AL$8:$AL$17,COUNTIF($AL$8:$AL$17,"<="&$S20)))/(INDEX($AL$8:$AL$17,COUNTIF($AL$8:$AL$17,"<="&$S20)+1)-INDEX($AL$8:$AL$17,COUNTIF($AL$8:$AL$17,"<="&$S20)))))+N($D$14)/100,"")))) | AP20: =IF($B20="","",$AQ$6&CHOOSE(MONTH($C20),"F","G","H","J","K","M","N","Q","U","V","X","Z")&RIGHT(YEAR($C20),1)&" Index") | AR20: =IF($AP20="","",BDP($AP20,"LAST_PRICE")) | AV20: =IF($L20="","",$O20-$C$49) | AW20: =IF($L20="","",$H20-$K20-$C$50-$C$45/10000*$C$9*$D20/365) | AX20: =IF($L20="","",IF($AV20>0,"SELL FUT / BUY CASH +"&TEXT($AV20,"0.0")&" pts net",IF($AW20>0,"BUY FUT / SHORT CASH +"&TEXT($AW20,"0.0")&" pts net","no edge after costs")))
B21: =IF('Div by Expiry'!$B15="","",'Div by Expiry'!$B15) | C21: =IF($B21="","",'Div by Expiry'!$C15) | D21: =IF($B21="","",'Div by Expiry'!$D15) | E21: =IF($B21="","",IF($AI21="","",$C$9*$AI21/100*$D21/$C$11)) | F21: =IF($B21="","",IF($C$13="N",'Div by Expiry'!$G15-IF($C$16="Y",0,'Div by Expiry'!$U38),IF($AI21="","",SUMPRODUCT('Div by Expiry'!$E$13:$E15,1+$AI21/100*($C21-(Expiries!$J$16:$J18+Expiries!$F$16:$F18)/2)/$C$11)-IF($C$16="Y",0,SUMPRODUCT('Div by Expiry'!$T$36:$T38,1+$AI21/100*($C21-(Expiries!$J$16:$J18+Expiries!$F$16:$F18)/2)/$C$11))))) | G21: =IF($B21="","",IF($C$13="N",'Div by Expiry'!$E38-IF($C$16="Y",0,'Div by Expiry'!$W38),IF($AI21="","",SUMPRODUCT('Div by Expiry'!$D$36:$D38,1+$AI21/100*($C21-(Expiries!$J$16:$J18+Expiries!$F$16:$F18)/2)/$C$11)-IF($C$16="Y",0,SUMPRODUCT('Div by Expiry'!$V$36:$V38,1+$AI21/100*($C21-(Expiries!$J$16:$J18+Expiries!$F$16:$F18)/2)/$C$11))))) | H21: =IF($B21="","",IF($E21="","",$C$9+$E21-$F21)) | I21: =IF($B21="","",IF($H21="","",$H21-$G21)) | J21: =IF($B21="","",IF($H21="","",$H21-$C$12/100*$G21)) | K21: =IF($B21="","",IF(ISNUMBER($AQ21),$AQ21,IF(ISNUMBER($AR21),$AR21,""))) | L21: =IF($B21="","",IF(N($K21)=0,"",IF($E21="","",$C$9+$E21-$K21))) | M21: =IF($L21="","",$L21-$F21) | N21: =IF($L21="","",IF($G21=0,"",$M21/$G21)) | O21: =IF($L21="","",$K21-$J21) | P21: =IF($L21="","",$O21/$C$9*10000) | R21: =IF($B21="","",'Div by Expiry'!$J15) | S21: =IF($B21="","",$R21-'Div by Expiry'!$C$7) | T21: =IF($B21="","",IF($AJ21="","",$D$9*$AJ21/100*$S21/$D$11)) | U21: =IF($B21="","",IF($C$13="N",'Div by Expiry'!$M15-IF($D$16="Y",0,'Div by Expiry'!$Y38),IF($AJ21="","",SUMPRODUCT('Div by Expiry'!$K$13:$K15,1+$AJ21/100*($R21-(Expiries!$K$16:$K18+Expiries!$I$16:$I18)/2)/$D$11)-IF($D$16="Y",0,SUMPRODUCT('Div by Expiry'!$X$36:$X38,1+$AJ21/100*($R21-(Expiries!$K$16:$K18+Expiries!$I$16:$I18)/2)/$D$11))))) | V21: =IF($B21="","",IF($C$13="N",'Div by Expiry'!$J38-IF($D$16="Y",0,'Div by Expiry'!$AA38),IF($AJ21="","",SUMPRODUCT('Div by Expiry'!$I$36:$I38,1+$AJ21/100*($R21-(Expiries!$K$16:$K18+Expiries!$I$16:$I18)/2)/$D$11)-IF($D$16="Y",0,SUMPRODUCT('Div by Expiry'!$Z$36:$Z38,1+$AJ21/100*($R21-(Expiries!$K$16:$K18+Expiries!$I$16:$I18)/2)/$D$11))))) | W21: =IF($B21="","",IF($T21="","",$D$9+$T21-$U21)) | X21: =IF($B21="","",IF($W21="","",$W21-$V21)) | Y21: =IF($B21="","",IF($W21="","",$W21-$D$12/100*$V21)) | AA21: =IF($B21="","",IF(N($Z21)=0,"",IF($T21="","",$D$9+$T21-$Z21))) | AB21: =IF($AA21="","",$AA21-$U21) | AC21: =IF($AA21="","",IF($V21=0,"",$AB21/$V21)) | AD21: =IF($AA21="","",$Z21-$Y21) | AE21: =IF($AA21="","",$AD21/$D$9*10000) | AG21: =IF($N21="","",IF($AC21="","",($N21-$AC21)*100)) | AI21: =IF($B21="","",IF(ISNUMBER($AS21),$AS21,IF(ISNUMBER($C$10),$C$10,IFERROR(IF(COUNTIF($AL$8:$AL$17,"<="&$D21)=0,$AO$8,IF(COUNTIF($AL$8:$AL$17,"<="&$D21)>=COUNT($AL$8:$AL$17),INDEX($AO$8:$AO$17,COUNT($AL$8:$AL$17)),INDEX($AO$8:$AO$17,COUNTIF($AL$8:$AL$17,"<="&$D21))+(INDEX($AO$8:$AO$17,COUNTIF($AL$8:$AL$17,"<="&$D21)+1)-INDEX($AO$8:$AO$17,COUNTIF($AL$8:$AL$17,"<="&$D21)))*($D21-INDEX($AL$8:$AL$17,COUNTIF($AL$8:$AL$17,"<="&$D21)))/(INDEX($AL$8:$AL$17,COUNTIF($AL$8:$AL$17,"<="&$D21)+1)-INDEX($AL$8:$AL$17,COUNTIF($AL$8:$AL$17,"<="&$D21)))))+N($C$14)/100,"")))) | AJ21: =IF($B21="","",IF(ISNUMBER($AT21),$AT21,IF(ISNUMBER($D$10),$D$10,IFERROR(IF(COUNTIF($AL$8:$AL$17,"<="&$S21)=0,$AO$8,IF(COUNTIF($AL$8:$AL$17,"<="&$S21)>=COUNT($AL$8:$AL$17),INDEX($AO$8:$AO$17,COUNT($AL$8:$AL$17)),INDEX($AO$8:$AO$17,COUNTIF($AL$8:$AL$17,"<="&$S21))+(INDEX($AO$8:$AO$17,COUNTIF($AL$8:$AL$17,"<="&$S21)+1)-INDEX($AO$8:$AO$17,COUNTIF($AL$8:$AL$17,"<="&$S21)))*($S21-INDEX($AL$8:$AL$17,COUNTIF($AL$8:$AL$17,"<="&$S21)))/(INDEX($AL$8:$AL$17,COUNTIF($AL$8:$AL$17,"<="&$S21)+1)-INDEX($AL$8:$AL$17,COUNTIF($AL$8:$AL$17,"<="&$S21)))))+N($D$14)/100,"")))) | AP21: =IF($B21="","",$AQ$6&CHOOSE(MONTH($C21),"F","G","H","J","K","M","N","Q","U","V","X","Z")&RIGHT(YEAR($C21),1)&" Index") | AR21: =IF($AP21="","",BDP($AP21,"LAST_PRICE")) | AV21: =IF($L21="","",$O21-$C$49) | AW21: =IF($L21="","",$H21-$K21-$C$50-$C$45/10000*$C$9*$D21/365) | AX21: =IF($L21="","",IF($AV21>0,"SELL FUT / BUY CASH +"&TEXT($AV21,"0.0")&" pts net",IF($AW21>0,"BUY FUT / SHORT CASH +"&TEXT($AW21,"0.0")&" pts net","no edge after costs")))
B22: =IF('Div by Expiry'!$B16="","",'Div by Expiry'!$B16) | C22: =IF($B22="","",'Div by Expiry'!$C16) | D22: =IF($B22="","",'Div by Expiry'!$D16) | E22: =IF($B22="","",IF($AI22="","",$C$9*$AI22/100*$D22/$C$11)) | F22: =IF($B22="","",IF($C$13="N",'Div by Expiry'!$G16-IF($C$16="Y",0,'Div by Expiry'!$U39),IF($AI22="","",SUMPRODUCT('Div by Expiry'!$E$13:$E16,1+$AI22/100*($C22-(Expiries!$J$16:$J19+Expiries!$F$16:$F19)/2)/$C$11)-IF($C$16="Y",0,SUMPRODUCT('Div by Expiry'!$T$36:$T39,1+$AI22/100*($C22-(Expiries!$J$16:$J19+Expiries!$F$16:$F19)/2)/$C$11))))) | G22: =IF($B22="","",IF($C$13="N",'Div by Expiry'!$E39-IF($C$16="Y",0,'Div by Expiry'!$W39),IF($AI22="","",SUMPRODUCT('Div by Expiry'!$D$36:$D39,1+$AI22/100*($C22-(Expiries!$J$16:$J19+Expiries!$F$16:$F19)/2)/$C$11)-IF($C$16="Y",0,SUMPRODUCT('Div by Expiry'!$V$36:$V39,1+$AI22/100*($C22-(Expiries!$J$16:$J19+Expiries!$F$16:$F19)/2)/$C$11))))) | H22: =IF($B22="","",IF($E22="","",$C$9+$E22-$F22)) | I22: =IF($B22="","",IF($H22="","",$H22-$G22)) | J22: =IF($B22="","",IF($H22="","",$H22-$C$12/100*$G22)) | K22: =IF($B22="","",IF(ISNUMBER($AQ22),$AQ22,IF(ISNUMBER($AR22),$AR22,""))) | L22: =IF($B22="","",IF(N($K22)=0,"",IF($E22="","",$C$9+$E22-$K22))) | M22: =IF($L22="","",$L22-$F22) | N22: =IF($L22="","",IF($G22=0,"",$M22/$G22)) | O22: =IF($L22="","",$K22-$J22) | P22: =IF($L22="","",$O22/$C$9*10000) | R22: =IF($B22="","",'Div by Expiry'!$J16) | S22: =IF($B22="","",$R22-'Div by Expiry'!$C$7) | T22: =IF($B22="","",IF($AJ22="","",$D$9*$AJ22/100*$S22/$D$11)) | U22: =IF($B22="","",IF($C$13="N",'Div by Expiry'!$M16-IF($D$16="Y",0,'Div by Expiry'!$Y39),IF($AJ22="","",SUMPRODUCT('Div by Expiry'!$K$13:$K16,1+$AJ22/100*($R22-(Expiries!$K$16:$K19+Expiries!$I$16:$I19)/2)/$D$11)-IF($D$16="Y",0,SUMPRODUCT('Div by Expiry'!$X$36:$X39,1+$AJ22/100*($R22-(Expiries!$K$16:$K19+Expiries!$I$16:$I19)/2)/$D$11))))) | V22: =IF($B22="","",IF($C$13="N",'Div by Expiry'!$J39-IF($D$16="Y",0,'Div by Expiry'!$AA39),IF($AJ22="","",SUMPRODUCT('Div by Expiry'!$I$36:$I39,1+$AJ22/100*($R22-(Expiries!$K$16:$K19+Expiries!$I$16:$I19)/2)/$D$11)-IF($D$16="Y",0,SUMPRODUCT('Div by Expiry'!$Z$36:$Z39,1+$AJ22/100*($R22-(Expiries!$K$16:$K19+Expiries!$I$16:$I19)/2)/$D$11))))) | W22: =IF($B22="","",IF($T22="","",$D$9+$T22-$U22)) | X22: =IF($B22="","",IF($W22="","",$W22-$V22)) | Y22: =IF($B22="","",IF($W22="","",$W22-$D$12/100*$V22)) | AA22: =IF($B22="","",IF(N($Z22)=0,"",IF($T22="","",$D$9+$T22-$Z22))) | AB22: =IF($AA22="","",$AA22-$U22) | AC22: =IF($AA22="","",IF($V22=0,"",$AB22/$V22)) | AD22: =IF($AA22="","",$Z22-$Y22) | AE22: =IF($AA22="","",$AD22/$D$9*10000) | AG22: =IF($N22="","",IF($AC22="","",($N22-$AC22)*100)) | AI22: =IF($B22="","",IF(ISNUMBER($AS22),$AS22,IF(ISNUMBER($C$10),$C$10,IFERROR(IF(COUNTIF($AL$8:$AL$17,"<="&$D22)=0,$AO$8,IF(COUNTIF($AL$8:$AL$17,"<="&$D22)>=COUNT($AL$8:$AL$17),INDEX($AO$8:$AO$17,COUNT($AL$8:$AL$17)),INDEX($AO$8:$AO$17,COUNTIF($AL$8:$AL$17,"<="&$D22))+(INDEX($AO$8:$AO$17,COUNTIF($AL$8:$AL$17,"<="&$D22)+1)-INDEX($AO$8:$AO$17,COUNTIF($AL$8:$AL$17,"<="&$D22)))*($D22-INDEX($AL$8:$AL$17,COUNTIF($AL$8:$AL$17,"<="&$D22)))/(INDEX($AL$8:$AL$17,COUNTIF($AL$8:$AL$17,"<="&$D22)+1)-INDEX($AL$8:$AL$17,COUNTIF($AL$8:$AL$17,"<="&$D22)))))+N($C$14)/100,"")))) | AJ22: =IF($B22="","",IF(ISNUMBER($AT22),$AT22,IF(ISNUMBER($D$10),$D$10,IFERROR(IF(COUNTIF($AL$8:$AL$17,"<="&$S22)=0,$AO$8,IF(COUNTIF($AL$8:$AL$17,"<="&$S22)>=COUNT($AL$8:$AL$17),INDEX($AO$8:$AO$17,COUNT($AL$8:$AL$17)),INDEX($AO$8:$AO$17,COUNTIF($AL$8:$AL$17,"<="&$S22))+(INDEX($AO$8:$AO$17,COUNTIF($AL$8:$AL$17,"<="&$S22)+1)-INDEX($AO$8:$AO$17,COUNTIF($AL$8:$AL$17,"<="&$S22)))*($S22-INDEX($AL$8:$AL$17,COUNTIF($AL$8:$AL$17,"<="&$S22)))/(INDEX($AL$8:$AL$17,COUNTIF($AL$8:$AL$17,"<="&$S22)+1)-INDEX($AL$8:$AL$17,COUNTIF($AL$8:$AL$17,"<="&$S22)))))+N($D$14)/100,"")))) | AP22: =IF($B22="","",$AQ$6&CHOOSE(MONTH($C22),"F","G","H","J","K","M","N","Q","U","V","X","Z")&RIGHT(YEAR($C22),1)&" Index") | AR22: =IF($AP22="","",BDP($AP22,"LAST_PRICE")) | AV22: =IF($L22="","",$O22-$C$49) | AW22: =IF($L22="","",$H22-$K22-$C$50-$C$45/10000*$C$9*$D22/365) | AX22: =IF($L22="","",IF($AV22>0,"SELL FUT / BUY CASH +"&TEXT($AV22,"0.0")&" pts net",IF($AW22>0,"BUY FUT / SHORT CASH +"&TEXT($AW22,"0.0")&" pts net","no edge after costs")))
B23: =IF('Div by Expiry'!$B17="","",'Div by Expiry'!$B17) | C23: =IF($B23="","",'Div by Expiry'!$C17) | D23: =IF($B23="","",'Div by Expiry'!$D17) | E23: =IF($B23="","",IF($AI23="","",$C$9*$AI23/100*$D23/$C$11)) | F23: =IF($B23="","",IF($C$13="N",'Div by Expiry'!$G17-IF($C$16="Y",0,'Div by Expiry'!$U40),IF($AI23="","",SUMPRODUCT('Div by Expiry'!$E$13:$E17,1+$AI23/100*($C23-(Expiries!$J$16:$J20+Expiries!$F$16:$F20)/2)/$C$11)-IF($C$16="Y",0,SUMPRODUCT('Div by Expiry'!$T$36:$T40,1+$AI23/100*($C23-(Expiries!$J$16:$J20+Expiries!$F$16:$F20)/2)/$C$11))))) | G23: =IF($B23="","",IF($C$13="N",'Div by Expiry'!$E40-IF($C$16="Y",0,'Div by Expiry'!$W40),IF($AI23="","",SUMPRODUCT('Div by Expiry'!$D$36:$D40,1+$AI23/100*($C23-(Expiries!$J$16:$J20+Expiries!$F$16:$F20)/2)/$C$11)-IF($C$16="Y",0,SUMPRODUCT('Div by Expiry'!$V$36:$V40,1+$AI23/100*($C23-(Expiries!$J$16:$J20+Expiries!$F$16:$F20)/2)/$C$11))))) | H23: =IF($B23="","",IF($E23="","",$C$9+$E23-$F23)) | I23: =IF($B23="","",IF($H23="","",$H23-$G23)) | J23: =IF($B23="","",IF($H23="","",$H23-$C$12/100*$G23)) | K23: =IF($B23="","",IF(ISNUMBER($AQ23),$AQ23,IF(ISNUMBER($AR23),$AR23,""))) | L23: =IF($B23="","",IF(N($K23)=0,"",IF($E23="","",$C$9+$E23-$K23))) | M23: =IF($L23="","",$L23-$F23) | N23: =IF($L23="","",IF($G23=0,"",$M23/$G23)) | O23: =IF($L23="","",$K23-$J23) | P23: =IF($L23="","",$O23/$C$9*10000) | R23: =IF($B23="","",'Div by Expiry'!$J17) | S23: =IF($B23="","",$R23-'Div by Expiry'!$C$7) | T23: =IF($B23="","",IF($AJ23="","",$D$9*$AJ23/100*$S23/$D$11)) | U23: =IF($B23="","",IF($C$13="N",'Div by Expiry'!$M17-IF($D$16="Y",0,'Div by Expiry'!$Y40),IF($AJ23="","",SUMPRODUCT('Div by Expiry'!$K$13:$K17,1+$AJ23/100*($R23-(Expiries!$K$16:$K20+Expiries!$I$16:$I20)/2)/$D$11)-IF($D$16="Y",0,SUMPRODUCT('Div by Expiry'!$X$36:$X40,1+$AJ23/100*($R23-(Expiries!$K$16:$K20+Expiries!$I$16:$I20)/2)/$D$11))))) | V23: =IF($B23="","",IF($C$13="N",'Div by Expiry'!$J40-IF($D$16="Y",0,'Div by Expiry'!$AA40),IF($AJ23="","",SUMPRODUCT('Div by Expiry'!$I$36:$I40,1+$AJ23/100*($R23-(Expiries!$K$16:$K20+Expiries!$I$16:$I20)/2)/$D$11)-IF($D$16="Y",0,SUMPRODUCT('Div by Expiry'!$Z$36:$Z40,1+$AJ23/100*($R23-(Expiries!$K$16:$K20+Expiries!$I$16:$I20)/2)/$D$11))))) | W23: =IF($B23="","",IF($T23="","",$D$9+$T23-$U23)) | X23: =IF($B23="","",IF($W23="","",$W23-$V23)) | Y23: =IF($B23="","",IF($W23="","",$W23-$D$12/100*$V23)) | AA23: =IF($B23="","",IF(N($Z23)=0,"",IF($T23="","",$D$9+$T23-$Z23))) | AB23: =IF($AA23="","",$AA23-$U23) | AC23: =IF($AA23="","",IF($V23=0,"",$AB23/$V23)) | AD23: =IF($AA23="","",$Z23-$Y23) | AE23: =IF($AA23="","",$AD23/$D$9*10000) | AG23: =IF($N23="","",IF($AC23="","",($N23-$AC23)*100)) | AI23: =IF($B23="","",IF(ISNUMBER($AS23),$AS23,IF(ISNUMBER($C$10),$C$10,IFERROR(IF(COUNTIF($AL$8:$AL$17,"<="&$D23)=0,$AO$8,IF(COUNTIF($AL$8:$AL$17,"<="&$D23)>=COUNT($AL$8:$AL$17),INDEX($AO$8:$AO$17,COUNT($AL$8:$AL$17)),INDEX($AO$8:$AO$17,COUNTIF($AL$8:$AL$17,"<="&$D23))+(INDEX($AO$8:$AO$17,COUNTIF($AL$8:$AL$17,"<="&$D23)+1)-INDEX($AO$8:$AO$17,COUNTIF($AL$8:$AL$17,"<="&$D23)))*($D23-INDEX($AL$8:$AL$17,COUNTIF($AL$8:$AL$17,"<="&$D23)))/(INDEX($AL$8:$AL$17,COUNTIF($AL$8:$AL$17,"<="&$D23)+1)-INDEX($AL$8:$AL$17,COUNTIF($AL$8:$AL$17,"<="&$D23)))))+N($C$14)/100,"")))) | AJ23: =IF($B23="","",IF(ISNUMBER($AT23),$AT23,IF(ISNUMBER($D$10),$D$10,IFERROR(IF(COUNTIF($AL$8:$AL$17,"<="&$S23)=0,$AO$8,IF(COUNTIF($AL$8:$AL$17,"<="&$S23)>=COUNT($AL$8:$AL$17),INDEX($AO$8:$AO$17,COUNT($AL$8:$AL$17)),INDEX($AO$8:$AO$17,COUNTIF($AL$8:$AL$17,"<="&$S23))+(INDEX($AO$8:$AO$17,COUNTIF($AL$8:$AL$17,"<="&$S23)+1)-INDEX($AO$8:$AO$17,COUNTIF($AL$8:$AL$17,"<="&$S23)))*($S23-INDEX($AL$8:$AL$17,COUNTIF($AL$8:$AL$17,"<="&$S23)))/(INDEX($AL$8:$AL$17,COUNTIF($AL$8:$AL$17,"<="&$S23)+1)-INDEX($AL$8:$AL$17,COUNTIF($AL$8:$AL$17,"<="&$S23)))))+N($D$14)/100,"")))) | AP23: =IF($B23="","",$AQ$6&CHOOSE(MONTH($C23),"F","G","H","J","K","M","N","Q","U","V","X","Z")&RIGHT(YEAR($C23),1)&" Index") | AR23: =IF($AP23="","",BDP($AP23,"LAST_PRICE")) | AV23: =IF($L23="","",$O23-$C$49) | AW23: =IF($L23="","",$H23-$K23-$C$50-$C$45/10000*$C$9*$D23/365) | AX23: =IF($L23="","",IF($AV23>0,"SELL FUT / BUY CASH +"&TEXT($AV23,"0.0")&" pts net",IF($AW23>0,"BUY FUT / SHORT CASH +"&TEXT($AW23,"0.0")&" pts net","no edge after costs")))
B24: =IF('Div by Expiry'!$B18="","",'Div by Expiry'!$B18) | C24: =IF($B24="","",'Div by Expiry'!$C18) | D24: =IF($B24="","",'Div by Expiry'!$D18) | E24: =IF($B24="","",IF($AI24="","",$C$9*$AI24/100*$D24/$C$11)) | F24: =IF($B24="","",IF($C$13="N",'Div by Expiry'!$G18-IF($C$16="Y",0,'Div by Expiry'!$U41),IF($AI24="","",SUMPRODUCT('Div by Expiry'!$E$13:$E18,1+$AI24/100*($C24-(Expiries!$J$16:$J21+Expiries!$F$16:$F21)/2)/$C$11)-IF($C$16="Y",0,SUMPRODUCT('Div by Expiry'!$T$36:$T41,1+$AI24/100*($C24-(Expiries!$J$16:$J21+Expiries!$F$16:$F21)/2)/$C$11))))) | G24: =IF($B24="","",IF($C$13="N",'Div by Expiry'!$E41-IF($C$16="Y",0,'Div by Expiry'!$W41),IF($AI24="","",SUMPRODUCT('Div by Expiry'!$D$36:$D41,1+$AI24/100*($C24-(Expiries!$J$16:$J21+Expiries!$F$16:$F21)/2)/$C$11)-IF($C$16="Y",0,SUMPRODUCT('Div by Expiry'!$V$36:$V41,1+$AI24/100*($C24-(Expiries!$J$16:$J21+Expiries!$F$16:$F21)/2)/$C$11))))) | H24: =IF($B24="","",IF($E24="","",$C$9+$E24-$F24)) | I24: =IF($B24="","",IF($H24="","",$H24-$G24)) | J24: =IF($B24="","",IF($H24="","",$H24-$C$12/100*$G24)) | K24: =IF($B24="","",IF(ISNUMBER($AQ24),$AQ24,IF(ISNUMBER($AR24),$AR24,""))) | L24: =IF($B24="","",IF(N($K24)=0,"",IF($E24="","",$C$9+$E24-$K24))) | M24: =IF($L24="","",$L24-$F24) | N24: =IF($L24="","",IF($G24=0,"",$M24/$G24)) | O24: =IF($L24="","",$K24-$J24) | P24: =IF($L24="","",$O24/$C$9*10000) | R24: =IF($B24="","",'Div by Expiry'!$J18) | S24: =IF($B24="","",$R24-'Div by Expiry'!$C$7) | T24: =IF($B24="","",IF($AJ24="","",$D$9*$AJ24/100*$S24/$D$11)) | U24: =IF($B24="","",IF($C$13="N",'Div by Expiry'!$M18-IF($D$16="Y",0,'Div by Expiry'!$Y41),IF($AJ24="","",SUMPRODUCT('Div by Expiry'!$K$13:$K18,1+$AJ24/100*($R24-(Expiries!$K$16:$K21+Expiries!$I$16:$I21)/2)/$D$11)-IF($D$16="Y",0,SUMPRODUCT('Div by Expiry'!$X$36:$X41,1+$AJ24/100*($R24-(Expiries!$K$16:$K21+Expiries!$I$16:$I21)/2)/$D$11))))) | V24: =IF($B24="","",IF($C$13="N",'Div by Expiry'!$J41-IF($D$16="Y",0,'Div by Expiry'!$AA41),IF($AJ24="","",SUMPRODUCT('Div by Expiry'!$I$36:$I41,1+$AJ24/100*($R24-(Expiries!$K$16:$K21+Expiries!$I$16:$I21)/2)/$D$11)-IF($D$16="Y",0,SUMPRODUCT('Div by Expiry'!$Z$36:$Z41,1+$AJ24/100*($R24-(Expiries!$K$16:$K21+Expiries!$I$16:$I21)/2)/$D$11))))) | W24: =IF($B24="","",IF($T24="","",$D$9+$T24-$U24)) | X24: =IF($B24="","",IF($W24="","",$W24-$V24)) | Y24: =IF($B24="","",IF($W24="","",$W24-$D$12/100*$V24)) | AA24: =IF($B24="","",IF(N($Z24)=0,"",IF($T24="","",$D$9+$T24-$Z24))) | AB24: =IF($AA24="","",$AA24-$U24) | AC24: =IF($AA24="","",IF($V24=0,"",$AB24/$V24)) | AD24: =IF($AA24="","",$Z24-$Y24) | AE24: =IF($AA24="","",$AD24/$D$9*10000) | AG24: =IF($N24="","",IF($AC24="","",($N24-$AC24)*100)) | AI24: =IF($B24="","",IF(ISNUMBER($AS24),$AS24,IF(ISNUMBER($C$10),$C$10,IFERROR(IF(COUNTIF($AL$8:$AL$17,"<="&$D24)=0,$AO$8,IF(COUNTIF($AL$8:$AL$17,"<="&$D24)>=COUNT($AL$8:$AL$17),INDEX($AO$8:$AO$17,COUNT($AL$8:$AL$17)),INDEX($AO$8:$AO$17,COUNTIF($AL$8:$AL$17,"<="&$D24))+(INDEX($AO$8:$AO$17,COUNTIF($AL$8:$AL$17,"<="&$D24)+1)-INDEX($AO$8:$AO$17,COUNTIF($AL$8:$AL$17,"<="&$D24)))*($D24-INDEX($AL$8:$AL$17,COUNTIF($AL$8:$AL$17,"<="&$D24)))/(INDEX($AL$8:$AL$17,COUNTIF($AL$8:$AL$17,"<="&$D24)+1)-INDEX($AL$8:$AL$17,COUNTIF($AL$8:$AL$17,"<="&$D24)))))+N($C$14)/100,"")))) | AJ24: =IF($B24="","",IF(ISNUMBER($AT24),$AT24,IF(ISNUMBER($D$10),$D$10,IFERROR(IF(COUNTIF($AL$8:$AL$17,"<="&$S24)=0,$AO$8,IF(COUNTIF($AL$8:$AL$17,"<="&$S24)>=COUNT($AL$8:$AL$17),INDEX($AO$8:$AO$17,COUNT($AL$8:$AL$17)),INDEX($AO$8:$AO$17,COUNTIF($AL$8:$AL$17,"<="&$S24))+(INDEX($AO$8:$AO$17,COUNTIF($AL$8:$AL$17,"<="&$S24)+1)-INDEX($AO$8:$AO$17,COUNTIF($AL$8:$AL$17,"<="&$S24)))*($S24-INDEX($AL$8:$AL$17,COUNTIF($AL$8:$AL$17,"<="&$S24)))/(INDEX($AL$8:$AL$17,COUNTIF($AL$8:$AL$17,"<="&$S24)+1)-INDEX($AL$8:$AL$17,COUNTIF($AL$8:$AL$17,"<="&$S24)))))+N($D$14)/100,"")))) | AP24: =IF($B24="","",$AQ$6&CHOOSE(MONTH($C24),"F","G","H","J","K","M","N","Q","U","V","X","Z")&RIGHT(YEAR($C24),1)&" Index") | AR24: =IF($AP24="","",BDP($AP24,"LAST_PRICE")) | AV24: =IF($L24="","",$O24-$C$49) | AW24: =IF($L24="","",$H24-$K24-$C$50-$C$45/10000*$C$9*$D24/365) | AX24: =IF($L24="","",IF($AV24>0,"SELL FUT / BUY CASH +"&TEXT($AV24,"0.0")&" pts net",IF($AW24>0,"BUY FUT / SHORT CASH +"&TEXT($AW24,"0.0")&" pts net","no edge after costs")))
B25: =IF('Div by Expiry'!$B19="","",'Div by Expiry'!$B19) | C25: =IF($B25="","",'Div by Expiry'!$C19) | D25: =IF($B25="","",'Div by Expiry'!$D19) | E25: =IF($B25="","",IF($AI25="","",$C$9*$AI25/100*$D25/$C$11)) | F25: =IF($B25="","",IF($C$13="N",'Div by Expiry'!$G19-IF($C$16="Y",0,'Div by Expiry'!$U42),IF($AI25="","",SUMPRODUCT('Div by Expiry'!$E$13:$E19,1+$AI25/100*($C25-(Expiries!$J$16:$J22+Expiries!$F$16:$F22)/2)/$C$11)-IF($C$16="Y",0,SUMPRODUCT('Div by Expiry'!$T$36:$T42,1+$AI25/100*($C25-(Expiries!$J$16:$J22+Expiries!$F$16:$F22)/2)/$C$11))))) | G25: =IF($B25="","",IF($C$13="N",'Div by Expiry'!$E42-IF($C$16="Y",0,'Div by Expiry'!$W42),IF($AI25="","",SUMPRODUCT('Div by Expiry'!$D$36:$D42,1+$AI25/100*($C25-(Expiries!$J$16:$J22+Expiries!$F$16:$F22)/2)/$C$11)-IF($C$16="Y",0,SUMPRODUCT('Div by Expiry'!$V$36:$V42,1+$AI25/100*($C25-(Expiries!$J$16:$J22+Expiries!$F$16:$F22)/2)/$C$11))))) | H25: =IF($B25="","",IF($E25="","",$C$9+$E25-$F25)) | I25: =IF($B25="","",IF($H25="","",$H25-$G25)) | J25: =IF($B25="","",IF($H25="","",$H25-$C$12/100*$G25)) | K25: =IF($B25="","",IF(ISNUMBER($AQ25),$AQ25,IF(ISNUMBER($AR25),$AR25,""))) | L25: =IF($B25="","",IF(N($K25)=0,"",IF($E25="","",$C$9+$E25-$K25))) | M25: =IF($L25="","",$L25-$F25) | N25: =IF($L25="","",IF($G25=0,"",$M25/$G25)) | O25: =IF($L25="","",$K25-$J25) | P25: =IF($L25="","",$O25/$C$9*10000) | R25: =IF($B25="","",'Div by Expiry'!$J19) | S25: =IF($B25="","",$R25-'Div by Expiry'!$C$7) | T25: =IF($B25="","",IF($AJ25="","",$D$9*$AJ25/100*$S25/$D$11)) | U25: =IF($B25="","",IF($C$13="N",'Div by Expiry'!$M19-IF($D$16="Y",0,'Div by Expiry'!$Y42),IF($AJ25="","",SUMPRODUCT('Div by Expiry'!$K$13:$K19,1+$AJ25/100*($R25-(Expiries!$K$16:$K22+Expiries!$I$16:$I22)/2)/$D$11)-IF($D$16="Y",0,SUMPRODUCT('Div by Expiry'!$X$36:$X42,1+$AJ25/100*($R25-(Expiries!$K$16:$K22+Expiries!$I$16:$I22)/2)/$D$11))))) | V25: =IF($B25="","",IF($C$13="N",'Div by Expiry'!$J42-IF($D$16="Y",0,'Div by Expiry'!$AA42),IF($AJ25="","",SUMPRODUCT('Div by Expiry'!$I$36:$I42,1+$AJ25/100*($R25-(Expiries!$K$16:$K22+Expiries!$I$16:$I22)/2)/$D$11)-IF($D$16="Y",0,SUMPRODUCT('Div by Expiry'!$Z$36:$Z42,1+$AJ25/100*($R25-(Expiries!$K$16:$K22+Expiries!$I$16:$I22)/2)/$D$11))))) | W25: =IF($B25="","",IF($T25="","",$D$9+$T25-$U25)) | X25: =IF($B25="","",IF($W25="","",$W25-$V25)) | Y25: =IF($B25="","",IF($W25="","",$W25-$D$12/100*$V25)) | AA25: =IF($B25="","",IF(N($Z25)=0,"",IF($T25="","",$D$9+$T25-$Z25))) | AB25: =IF($AA25="","",$AA25-$U25) | AC25: =IF($AA25="","",IF($V25=0,"",$AB25/$V25)) | AD25: =IF($AA25="","",$Z25-$Y25) | AE25: =IF($AA25="","",$AD25/$D$9*10000) | AG25: =IF($N25="","",IF($AC25="","",($N25-$AC25)*100)) | AI25: =IF($B25="","",IF(ISNUMBER($AS25),$AS25,IF(ISNUMBER($C$10),$C$10,IFERROR(IF(COUNTIF($AL$8:$AL$17,"<="&$D25)=0,$AO$8,IF(COUNTIF($AL$8:$AL$17,"<="&$D25)>=COUNT($AL$8:$AL$17),INDEX($AO$8:$AO$17,COUNT($AL$8:$AL$17)),INDEX($AO$8:$AO$17,COUNTIF($AL$8:$AL$17,"<="&$D25))+(INDEX($AO$8:$AO$17,COUNTIF($AL$8:$AL$17,"<="&$D25)+1)-INDEX($AO$8:$AO$17,COUNTIF($AL$8:$AL$17,"<="&$D25)))*($D25-INDEX($AL$8:$AL$17,COUNTIF($AL$8:$AL$17,"<="&$D25)))/(INDEX($AL$8:$AL$17,COUNTIF($AL$8:$AL$17,"<="&$D25)+1)-INDEX($AL$8:$AL$17,COUNTIF($AL$8:$AL$17,"<="&$D25)))))+N($C$14)/100,"")))) | AJ25: =IF($B25="","",IF(ISNUMBER($AT25),$AT25,IF(ISNUMBER($D$10),$D$10,IFERROR(IF(COUNTIF($AL$8:$AL$17,"<="&$S25)=0,$AO$8,IF(COUNTIF($AL$8:$AL$17,"<="&$S25)>=COUNT($AL$8:$AL$17),INDEX($AO$8:$AO$17,COUNT($AL$8:$AL$17)),INDEX($AO$8:$AO$17,COUNTIF($AL$8:$AL$17,"<="&$S25))+(INDEX($AO$8:$AO$17,COUNTIF($AL$8:$AL$17,"<="&$S25)+1)-INDEX($AO$8:$AO$17,COUNTIF($AL$8:$AL$17,"<="&$S25)))*($S25-INDEX($AL$8:$AL$17,COUNTIF($AL$8:$AL$17,"<="&$S25)))/(INDEX($AL$8:$AL$17,COUNTIF($AL$8:$AL$17,"<="&$S25)+1)-INDEX($AL$8:$AL$17,COUNTIF($AL$8:$AL$17,"<="&$S25)))))+N($D$14)/100,"")))) | AP25: =IF($B25="","",$AQ$6&CHOOSE(MONTH($C25),"F","G","H","J","K","M","N","Q","U","V","X","Z")&RIGHT(YEAR($C25),1)&" Index") | AR25: =IF($AP25="","",BDP($AP25,"LAST_PRICE")) | AV25: =IF($L25="","",$O25-$C$49) | AW25: =IF($L25="","",$H25-$K25-$C$50-$C$45/10000*$C$9*$D25/365) | AX25: =IF($L25="","",IF($AV25>0,"SELL FUT / BUY CASH +"&TEXT($AV25,"0.0")&" pts net",IF($AW25>0,"BUY FUT / SHORT CASH +"&TEXT($AW25,"0.0")&" pts net","no edge after costs")))
B26: =IF('Div by Expiry'!$B20="","",'Div by Expiry'!$B20) | C26: =IF($B26="","",'Div by Expiry'!$C20) | D26: =IF($B26="","",'Div by Expiry'!$D20) | E26: =IF($B26="","",IF($AI26="","",$C$9*$AI26/100*$D26/$C$11)) | F26: =IF($B26="","",IF($C$13="N",'Div by Expiry'!$G20-IF($C$16="Y",0,'Div by Expiry'!$U43),IF($AI26="","",SUMPRODUCT('Div by Expiry'!$E$13:$E20,1+$AI26/100*($C26-(Expiries!$J$16:$J23+Expiries!$F$16:$F23)/2)/$C$11)-IF($C$16="Y",0,SUMPRODUCT('Div by Expiry'!$T$36:$T43,1+$AI26/100*($C26-(Expiries!$J$16:$J23+Expiries!$F$16:$F23)/2)/$C$11))))) | G26: =IF($B26="","",IF($C$13="N",'Div by Expiry'!$E43-IF($C$16="Y",0,'Div by Expiry'!$W43),IF($AI26="","",SUMPRODUCT('Div by Expiry'!$D$36:$D43,1+$AI26/100*($C26-(Expiries!$J$16:$J23+Expiries!$F$16:$F23)/2)/$C$11)-IF($C$16="Y",0,SUMPRODUCT('Div by Expiry'!$V$36:$V43,1+$AI26/100*($C26-(Expiries!$J$16:$J23+Expiries!$F$16:$F23)/2)/$C$11))))) | H26: =IF($B26="","",IF($E26="","",$C$9+$E26-$F26)) | I26: =IF($B26="","",IF($H26="","",$H26-$G26)) | J26: =IF($B26="","",IF($H26="","",$H26-$C$12/100*$G26)) | K26: =IF($B26="","",IF(ISNUMBER($AQ26),$AQ26,IF(ISNUMBER($AR26),$AR26,""))) | L26: =IF($B26="","",IF(N($K26)=0,"",IF($E26="","",$C$9+$E26-$K26))) | M26: =IF($L26="","",$L26-$F26) | N26: =IF($L26="","",IF($G26=0,"",$M26/$G26)) | O26: =IF($L26="","",$K26-$J26) | P26: =IF($L26="","",$O26/$C$9*10000) | R26: =IF($B26="","",'Div by Expiry'!$J20) | S26: =IF($B26="","",$R26-'Div by Expiry'!$C$7) | T26: =IF($B26="","",IF($AJ26="","",$D$9*$AJ26/100*$S26/$D$11)) | U26: =IF($B26="","",IF($C$13="N",'Div by Expiry'!$M20-IF($D$16="Y",0,'Div by Expiry'!$Y43),IF($AJ26="","",SUMPRODUCT('Div by Expiry'!$K$13:$K20,1+$AJ26/100*($R26-(Expiries!$K$16:$K23+Expiries!$I$16:$I23)/2)/$D$11)-IF($D$16="Y",0,SUMPRODUCT('Div by Expiry'!$X$36:$X43,1+$AJ26/100*($R26-(Expiries!$K$16:$K23+Expiries!$I$16:$I23)/2)/$D$11))))) | V26: =IF($B26="","",IF($C$13="N",'Div by Expiry'!$J43-IF($D$16="Y",0,'Div by Expiry'!$AA43),IF($AJ26="","",SUMPRODUCT('Div by Expiry'!$I$36:$I43,1+$AJ26/100*($R26-(Expiries!$K$16:$K23+Expiries!$I$16:$I23)/2)/$D$11)-IF($D$16="Y",0,SUMPRODUCT('Div by Expiry'!$Z$36:$Z43,1+$AJ26/100*($R26-(Expiries!$K$16:$K23+Expiries!$I$16:$I23)/2)/$D$11))))) | W26: =IF($B26="","",IF($T26="","",$D$9+$T26-$U26)) | X26: =IF($B26="","",IF($W26="","",$W26-$V26)) | Y26: =IF($B26="","",IF($W26="","",$W26-$D$12/100*$V26)) | AA26: =IF($B26="","",IF(N($Z26)=0,"",IF($T26="","",$D$9+$T26-$Z26))) | AB26: =IF($AA26="","",$AA26-$U26) | AC26: =IF($AA26="","",IF($V26=0,"",$AB26/$V26)) | AD26: =IF($AA26="","",$Z26-$Y26) | AE26: =IF($AA26="","",$AD26/$D$9*10000) | AG26: =IF($N26="","",IF($AC26="","",($N26-$AC26)*100)) | AI26: =IF($B26="","",IF(ISNUMBER($AS26),$AS26,IF(ISNUMBER($C$10),$C$10,IFERROR(IF(COUNTIF($AL$8:$AL$17,"<="&$D26)=0,$AO$8,IF(COUNTIF($AL$8:$AL$17,"<="&$D26)>=COUNT($AL$8:$AL$17),INDEX($AO$8:$AO$17,COUNT($AL$8:$AL$17)),INDEX($AO$8:$AO$17,COUNTIF($AL$8:$AL$17,"<="&$D26))+(INDEX($AO$8:$AO$17,COUNTIF($AL$8:$AL$17,"<="&$D26)+1)-INDEX($AO$8:$AO$17,COUNTIF($AL$8:$AL$17,"<="&$D26)))*($D26-INDEX($AL$8:$AL$17,COUNTIF($AL$8:$AL$17,"<="&$D26)))/(INDEX($AL$8:$AL$17,COUNTIF($AL$8:$AL$17,"<="&$D26)+1)-INDEX($AL$8:$AL$17,COUNTIF($AL$8:$AL$17,"<="&$D26)))))+N($C$14)/100,"")))) | AJ26: =IF($B26="","",IF(ISNUMBER($AT26),$AT26,IF(ISNUMBER($D$10),$D$10,IFERROR(IF(COUNTIF($AL$8:$AL$17,"<="&$S26)=0,$AO$8,IF(COUNTIF($AL$8:$AL$17,"<="&$S26)>=COUNT($AL$8:$AL$17),INDEX($AO$8:$AO$17,COUNT($AL$8:$AL$17)),INDEX($AO$8:$AO$17,COUNTIF($AL$8:$AL$17,"<="&$S26))+(INDEX($AO$8:$AO$17,COUNTIF($AL$8:$AL$17,"<="&$S26)+1)-INDEX($AO$8:$AO$17,COUNTIF($AL$8:$AL$17,"<="&$S26)))*($S26-INDEX($AL$8:$AL$17,COUNTIF($AL$8:$AL$17,"<="&$S26)))/(INDEX($AL$8:$AL$17,COUNTIF($AL$8:$AL$17,"<="&$S26)+1)-INDEX($AL$8:$AL$17,COUNTIF($AL$8:$AL$17,"<="&$S26)))))+N($D$14)/100,"")))) | AP26: =IF($B26="","",$AQ$6&CHOOSE(MONTH($C26),"F","G","H","J","K","M","N","Q","U","V","X","Z")&RIGHT(YEAR($C26),1)&" Index") | AR26: =IF($AP26="","",BDP($AP26,"LAST_PRICE")) | AV26: =IF($L26="","",$O26-$C$49) | AW26: =IF($L26="","",$H26-$K26-$C$50-$C$45/10000*$C$9*$D26/365) | AX26: =IF($L26="","",IF($AV26>0,"SELL FUT / BUY CASH +"&TEXT($AV26,"0.0")&" pts net",IF($AW26>0,"BUY FUT / SHORT CASH +"&TEXT($AW26,"0.0")&" pts net","no edge after costs")))
B27: =IF('Div by Expiry'!$B21="","",'Div by Expiry'!$B21) | C27: =IF($B27="","",'Div by Expiry'!$C21) | D27: =IF($B27="","",'Div by Expiry'!$D21) | E27: =IF($B27="","",IF($AI27="","",$C$9*$AI27/100*$D27/$C$11)) | F27: =IF($B27="","",IF($C$13="N",'Div by Expiry'!$G21-IF($C$16="Y",0,'Div by Expiry'!$U44),IF($AI27="","",SUMPRODUCT('Div by Expiry'!$E$13:$E21,1+$AI27/100*($C27-(Expiries!$J$16:$J24+Expiries!$F$16:$F24)/2)/$C$11)-IF($C$16="Y",0,SUMPRODUCT('Div by Expiry'!$T$36:$T44,1+$AI27/100*($C27-(Expiries!$J$16:$J24+Expiries!$F$16:$F24)/2)/$C$11))))) | G27: =IF($B27="","",IF($C$13="N",'Div by Expiry'!$E44-IF($C$16="Y",0,'Div by Expiry'!$W44),IF($AI27="","",SUMPRODUCT('Div by Expiry'!$D$36:$D44,1+$AI27/100*($C27-(Expiries!$J$16:$J24+Expiries!$F$16:$F24)/2)/$C$11)-IF($C$16="Y",0,SUMPRODUCT('Div by Expiry'!$V$36:$V44,1+$AI27/100*($C27-(Expiries!$J$16:$J24+Expiries!$F$16:$F24)/2)/$C$11))))) | H27: =IF($B27="","",IF($E27="","",$C$9+$E27-$F27)) | I27: =IF($B27="","",IF($H27="","",$H27-$G27)) | J27: =IF($B27="","",IF($H27="","",$H27-$C$12/100*$G27)) | K27: =IF($B27="","",IF(ISNUMBER($AQ27),$AQ27,IF(ISNUMBER($AR27),$AR27,""))) | L27: =IF($B27="","",IF(N($K27)=0,"",IF($E27="","",$C$9+$E27-$K27))) | M27: =IF($L27="","",$L27-$F27) | N27: =IF($L27="","",IF($G27=0,"",$M27/$G27)) | O27: =IF($L27="","",$K27-$J27) | P27: =IF($L27="","",$O27/$C$9*10000) | R27: =IF($B27="","",'Div by Expiry'!$J21) | S27: =IF($B27="","",$R27-'Div by Expiry'!$C$7) | T27: =IF($B27="","",IF($AJ27="","",$D$9*$AJ27/100*$S27/$D$11)) | U27: =IF($B27="","",IF($C$13="N",'Div by Expiry'!$M21-IF($D$16="Y",0,'Div by Expiry'!$Y44),IF($AJ27="","",SUMPRODUCT('Div by Expiry'!$K$13:$K21,1+$AJ27/100*($R27-(Expiries!$K$16:$K24+Expiries!$I$16:$I24)/2)/$D$11)-IF($D$16="Y",0,SUMPRODUCT('Div by Expiry'!$X$36:$X44,1+$AJ27/100*($R27-(Expiries!$K$16:$K24+Expiries!$I$16:$I24)/2)/$D$11))))) | V27: =IF($B27="","",IF($C$13="N",'Div by Expiry'!$J44-IF($D$16="Y",0,'Div by Expiry'!$AA44),IF($AJ27="","",SUMPRODUCT('Div by Expiry'!$I$36:$I44,1+$AJ27/100*($R27-(Expiries!$K$16:$K24+Expiries!$I$16:$I24)/2)/$D$11)-IF($D$16="Y",0,SUMPRODUCT('Div by Expiry'!$Z$36:$Z44,1+$AJ27/100*($R27-(Expiries!$K$16:$K24+Expiries!$I$16:$I24)/2)/$D$11))))) | W27: =IF($B27="","",IF($T27="","",$D$9+$T27-$U27)) | X27: =IF($B27="","",IF($W27="","",$W27-$V27)) | Y27: =IF($B27="","",IF($W27="","",$W27-$D$12/100*$V27)) | AA27: =IF($B27="","",IF(N($Z27)=0,"",IF($T27="","",$D$9+$T27-$Z27))) | AB27: =IF($AA27="","",$AA27-$U27) | AC27: =IF($AA27="","",IF($V27=0,"",$AB27/$V27)) | AD27: =IF($AA27="","",$Z27-$Y27) | AE27: =IF($AA27="","",$AD27/$D$9*10000) | AG27: =IF($N27="","",IF($AC27="","",($N27-$AC27)*100)) | AI27: =IF($B27="","",IF(ISNUMBER($AS27),$AS27,IF(ISNUMBER($C$10),$C$10,IFERROR(IF(COUNTIF($AL$8:$AL$17,"<="&$D27)=0,$AO$8,IF(COUNTIF($AL$8:$AL$17,"<="&$D27)>=COUNT($AL$8:$AL$17),INDEX($AO$8:$AO$17,COUNT($AL$8:$AL$17)),INDEX($AO$8:$AO$17,COUNTIF($AL$8:$AL$17,"<="&$D27))+(INDEX($AO$8:$AO$17,COUNTIF($AL$8:$AL$17,"<="&$D27)+1)-INDEX($AO$8:$AO$17,COUNTIF($AL$8:$AL$17,"<="&$D27)))*($D27-INDEX($AL$8:$AL$17,COUNTIF($AL$8:$AL$17,"<="&$D27)))/(INDEX($AL$8:$AL$17,COUNTIF($AL$8:$AL$17,"<="&$D27)+1)-INDEX($AL$8:$AL$17,COUNTIF($AL$8:$AL$17,"<="&$D27)))))+N($C$14)/100,"")))) | AJ27: =IF($B27="","",IF(ISNUMBER($AT27),$AT27,IF(ISNUMBER($D$10),$D$10,IFERROR(IF(COUNTIF($AL$8:$AL$17,"<="&$S27)=0,$AO$8,IF(COUNTIF($AL$8:$AL$17,"<="&$S27)>=COUNT($AL$8:$AL$17),INDEX($AO$8:$AO$17,COUNT($AL$8:$AL$17)),INDEX($AO$8:$AO$17,COUNTIF($AL$8:$AL$17,"<="&$S27))+(INDEX($AO$8:$AO$17,COUNTIF($AL$8:$AL$17,"<="&$S27)+1)-INDEX($AO$8:$AO$17,COUNTIF($AL$8:$AL$17,"<="&$S27)))*($S27-INDEX($AL$8:$AL$17,COUNTIF($AL$8:$AL$17,"<="&$S27)))/(INDEX($AL$8:$AL$17,COUNTIF($AL$8:$AL$17,"<="&$S27)+1)-INDEX($AL$8:$AL$17,COUNTIF($AL$8:$AL$17,"<="&$S27)))))+N($D$14)/100,"")))) | AP27: =IF($B27="","",$AQ$6&CHOOSE(MONTH($C27),"F","G","H","J","K","M","N","Q","U","V","X","Z")&RIGHT(YEAR($C27),1)&" Index") | AR27: =IF($AP27="","",BDP($AP27,"LAST_PRICE")) | AV27: =IF($L27="","",$O27-$C$49) | AW27: =IF($L27="","",$H27-$K27-$C$50-$C$45/10000*$C$9*$D27/365) | AX27: =IF($L27="","",IF($AV27>0,"SELL FUT / BUY CASH +"&TEXT($AV27,"0.0")&" pts net",IF($AW27>0,"BUY FUT / SHORT CASH +"&TEXT($AW27,"0.0")&" pts net","no edge after costs")))
B28: =IF('Div by Expiry'!$B22="","",'Div by Expiry'!$B22) | C28: =IF($B28="","",'Div by Expiry'!$C22) | D28: =IF($B28="","",'Div by Expiry'!$D22) | E28: =IF($B28="","",IF($AI28="","",$C$9*$AI28/100*$D28/$C$11)) | F28: =IF($B28="","",IF($C$13="N",'Div by Expiry'!$G22-IF($C$16="Y",0,'Div by Expiry'!$U45),IF($AI28="","",SUMPRODUCT('Div by Expiry'!$E$13:$E22,1+$AI28/100*($C28-(Expiries!$J$16:$J25+Expiries!$F$16:$F25)/2)/$C$11)-IF($C$16="Y",0,SUMPRODUCT('Div by Expiry'!$T$36:$T45,1+$AI28/100*($C28-(Expiries!$J$16:$J25+Expiries!$F$16:$F25)/2)/$C$11))))) | G28: =IF($B28="","",IF($C$13="N",'Div by Expiry'!$E45-IF($C$16="Y",0,'Div by Expiry'!$W45),IF($AI28="","",SUMPRODUCT('Div by Expiry'!$D$36:$D45,1+$AI28/100*($C28-(Expiries!$J$16:$J25+Expiries!$F$16:$F25)/2)/$C$11)-IF($C$16="Y",0,SUMPRODUCT('Div by Expiry'!$V$36:$V45,1+$AI28/100*($C28-(Expiries!$J$16:$J25+Expiries!$F$16:$F25)/2)/$C$11))))) | H28: =IF($B28="","",IF($E28="","",$C$9+$E28-$F28)) | I28: =IF($B28="","",IF($H28="","",$H28-$G28)) | J28: =IF($B28="","",IF($H28="","",$H28-$C$12/100*$G28)) | K28: =IF($B28="","",IF(ISNUMBER($AQ28),$AQ28,IF(ISNUMBER($AR28),$AR28,""))) | L28: =IF($B28="","",IF(N($K28)=0,"",IF($E28="","",$C$9+$E28-$K28))) | M28: =IF($L28="","",$L28-$F28) | N28: =IF($L28="","",IF($G28=0,"",$M28/$G28)) | O28: =IF($L28="","",$K28-$J28) | P28: =IF($L28="","",$O28/$C$9*10000) | R28: =IF($B28="","",'Div by Expiry'!$J22) | S28: =IF($B28="","",$R28-'Div by Expiry'!$C$7) | T28: =IF($B28="","",IF($AJ28="","",$D$9*$AJ28/100*$S28/$D$11)) | U28: =IF($B28="","",IF($C$13="N",'Div by Expiry'!$M22-IF($D$16="Y",0,'Div by Expiry'!$Y45),IF($AJ28="","",SUMPRODUCT('Div by Expiry'!$K$13:$K22,1+$AJ28/100*($R28-(Expiries!$K$16:$K25+Expiries!$I$16:$I25)/2)/$D$11)-IF($D$16="Y",0,SUMPRODUCT('Div by Expiry'!$X$36:$X45,1+$AJ28/100*($R28-(Expiries!$K$16:$K25+Expiries!$I$16:$I25)/2)/$D$11))))) | V28: =IF($B28="","",IF($C$13="N",'Div by Expiry'!$J45-IF($D$16="Y",0,'Div by Expiry'!$AA45),IF($AJ28="","",SUMPRODUCT('Div by Expiry'!$I$36:$I45,1+$AJ28/100*($R28-(Expiries!$K$16:$K25+Expiries!$I$16:$I25)/2)/$D$11)-IF($D$16="Y",0,SUMPRODUCT('Div by Expiry'!$Z$36:$Z45,1+$AJ28/100*($R28-(Expiries!$K$16:$K25+Expiries!$I$16:$I25)/2)/$D$11))))) | W28: =IF($B28="","",IF($T28="","",$D$9+$T28-$U28)) | X28: =IF($B28="","",IF($W28="","",$W28-$V28)) | Y28: =IF($B28="","",IF($W28="","",$W28-$D$12/100*$V28)) | AA28: =IF($B28="","",IF(N($Z28)=0,"",IF($T28="","",$D$9+$T28-$Z28))) | AB28: =IF($AA28="","",$AA28-$U28) | AC28: =IF($AA28="","",IF($V28=0,"",$AB28/$V28)) | AD28: =IF($AA28="","",$Z28-$Y28) | AE28: =IF($AA28="","",$AD28/$D$9*10000) | AG28: =IF($N28="","",IF($AC28="","",($N28-$AC28)*100)) | AI28: =IF($B28="","",IF(ISNUMBER($AS28),$AS28,IF(ISNUMBER($C$10),$C$10,IFERROR(IF(COUNTIF($AL$8:$AL$17,"<="&$D28)=0,$AO$8,IF(COUNTIF($AL$8:$AL$17,"<="&$D28)>=COUNT($AL$8:$AL$17),INDEX($AO$8:$AO$17,COUNT($AL$8:$AL$17)),INDEX($AO$8:$AO$17,COUNTIF($AL$8:$AL$17,"<="&$D28))+(INDEX($AO$8:$AO$17,COUNTIF($AL$8:$AL$17,"<="&$D28)+1)-INDEX($AO$8:$AO$17,COUNTIF($AL$8:$AL$17,"<="&$D28)))*($D28-INDEX($AL$8:$AL$17,COUNTIF($AL$8:$AL$17,"<="&$D28)))/(INDEX($AL$8:$AL$17,COUNTIF($AL$8:$AL$17,"<="&$D28)+1)-INDEX($AL$8:$AL$17,COUNTIF($AL$8:$AL$17,"<="&$D28)))))+N($C$14)/100,"")))) | AJ28: =IF($B28="","",IF(ISNUMBER($AT28),$AT28,IF(ISNUMBER($D$10),$D$10,IFERROR(IF(COUNTIF($AL$8:$AL$17,"<="&$S28)=0,$AO$8,IF(COUNTIF($AL$8:$AL$17,"<="&$S28)>=COUNT($AL$8:$AL$17),INDEX($AO$8:$AO$17,COUNT($AL$8:$AL$17)),INDEX($AO$8:$AO$17,COUNTIF($AL$8:$AL$17,"<="&$S28))+(INDEX($AO$8:$AO$17,COUNTIF($AL$8:$AL$17,"<="&$S28)+1)-INDEX($AO$8:$AO$17,COUNTIF($AL$8:$AL$17,"<="&$S28)))*($S28-INDEX($AL$8:$AL$17,COUNTIF($AL$8:$AL$17,"<="&$S28)))/(INDEX($AL$8:$AL$17,COUNTIF($AL$8:$AL$17,"<="&$S28)+1)-INDEX($AL$8:$AL$17,COUNTIF($AL$8:$AL$17,"<="&$S28)))))+N($D$14)/100,"")))) | AP28: =IF($B28="","",$AQ$6&CHOOSE(MONTH($C28),"F","G","H","J","K","M","N","Q","U","V","X","Z")&RIGHT(YEAR($C28),1)&" Index") | AR28: =IF($AP28="","",BDP($AP28,"LAST_PRICE")) | AV28: =IF($L28="","",$O28-$C$49) | AW28: =IF($L28="","",$H28-$K28-$C$50-$C$45/10000*$C$9*$D28/365) | AX28: =IF($L28="","",IF($AV28>0,"SELL FUT / BUY CASH +"&TEXT($AV28,"0.0")&" pts net",IF($AW28>0,"BUY FUT / SHORT CASH +"&TEXT($AW28,"0.0")&" pts net","no edge after costs")))
B29: =IF('Div by Expiry'!$B23="","",'Div by Expiry'!$B23) | C29: =IF($B29="","",'Div by Expiry'!$C23) | D29: =IF($B29="","",'Div by Expiry'!$D23) | E29: =IF($B29="","",IF($AI29="","",$C$9*$AI29/100*$D29/$C$11)) | F29: =IF($B29="","",IF($C$13="N",'Div by Expiry'!$G23-IF($C$16="Y",0,'Div by Expiry'!$U46),IF($AI29="","",SUMPRODUCT('Div by Expiry'!$E$13:$E23,1+$AI29/100*($C29-(Expiries!$J$16:$J26+Expiries!$F$16:$F26)/2)/$C$11)-IF($C$16="Y",0,SUMPRODUCT('Div by Expiry'!$T$36:$T46,1+$AI29/100*($C29-(Expiries!$J$16:$J26+Expiries!$F$16:$F26)/2)/$C$11))))) | G29: =IF($B29="","",IF($C$13="N",'Div by Expiry'!$E46-IF($C$16="Y",0,'Div by Expiry'!$W46),IF($AI29="","",SUMPRODUCT('Div by Expiry'!$D$36:$D46,1+$AI29/100*($C29-(Expiries!$J$16:$J26+Expiries!$F$16:$F26)/2)/$C$11)-IF($C$16="Y",0,SUMPRODUCT('Div by Expiry'!$V$36:$V46,1+$AI29/100*($C29-(Expiries!$J$16:$J26+Expiries!$F$16:$F26)/2)/$C$11))))) | H29: =IF($B29="","",IF($E29="","",$C$9+$E29-$F29)) | I29: =IF($B29="","",IF($H29="","",$H29-$G29)) | J29: =IF($B29="","",IF($H29="","",$H29-$C$12/100*$G29)) | K29: =IF($B29="","",IF(ISNUMBER($AQ29),$AQ29,IF(ISNUMBER($AR29),$AR29,""))) | L29: =IF($B29="","",IF(N($K29)=0,"",IF($E29="","",$C$9+$E29-$K29))) | M29: =IF($L29="","",$L29-$F29) | N29: =IF($L29="","",IF($G29=0,"",$M29/$G29)) | O29: =IF($L29="","",$K29-$J29) | P29: =IF($L29="","",$O29/$C$9*10000) | R29: =IF($B29="","",'Div by Expiry'!$J23) | S29: =IF($B29="","",$R29-'Div by Expiry'!$C$7) | T29: =IF($B29="","",IF($AJ29="","",$D$9*$AJ29/100*$S29/$D$11)) | U29: =IF($B29="","",IF($C$13="N",'Div by Expiry'!$M23-IF($D$16="Y",0,'Div by Expiry'!$Y46),IF($AJ29="","",SUMPRODUCT('Div by Expiry'!$K$13:$K23,1+$AJ29/100*($R29-(Expiries!$K$16:$K26+Expiries!$I$16:$I26)/2)/$D$11)-IF($D$16="Y",0,SUMPRODUCT('Div by Expiry'!$X$36:$X46,1+$AJ29/100*($R29-(Expiries!$K$16:$K26+Expiries!$I$16:$I26)/2)/$D$11))))) | V29: =IF($B29="","",IF($C$13="N",'Div by Expiry'!$J46-IF($D$16="Y",0,'Div by Expiry'!$AA46),IF($AJ29="","",SUMPRODUCT('Div by Expiry'!$I$36:$I46,1+$AJ29/100*($R29-(Expiries!$K$16:$K26+Expiries!$I$16:$I26)/2)/$D$11)-IF($D$16="Y",0,SUMPRODUCT('Div by Expiry'!$Z$36:$Z46,1+$AJ29/100*($R29-(Expiries!$K$16:$K26+Expiries!$I$16:$I26)/2)/$D$11))))) | W29: =IF($B29="","",IF($T29="","",$D$9+$T29-$U29)) | X29: =IF($B29="","",IF($W29="","",$W29-$V29)) | Y29: =IF($B29="","",IF($W29="","",$W29-$D$12/100*$V29)) | AA29: =IF($B29="","",IF(N($Z29)=0,"",IF($T29="","",$D$9+$T29-$Z29))) | AB29: =IF($AA29="","",$AA29-$U29) | AC29: =IF($AA29="","",IF($V29=0,"",$AB29/$V29)) | AD29: =IF($AA29="","",$Z29-$Y29) | AE29: =IF($AA29="","",$AD29/$D$9*10000) | AG29: =IF($N29="","",IF($AC29="","",($N29-$AC29)*100)) | AI29: =IF($B29="","",IF(ISNUMBER($AS29),$AS29,IF(ISNUMBER($C$10),$C$10,IFERROR(IF(COUNTIF($AL$8:$AL$17,"<="&$D29)=0,$AO$8,IF(COUNTIF($AL$8:$AL$17,"<="&$D29)>=COUNT($AL$8:$AL$17),INDEX($AO$8:$AO$17,COUNT($AL$8:$AL$17)),INDEX($AO$8:$AO$17,COUNTIF($AL$8:$AL$17,"<="&$D29))+(INDEX($AO$8:$AO$17,COUNTIF($AL$8:$AL$17,"<="&$D29)+1)-INDEX($AO$8:$AO$17,COUNTIF($AL$8:$AL$17,"<="&$D29)))*($D29-INDEX($AL$8:$AL$17,COUNTIF($AL$8:$AL$17,"<="&$D29)))/(INDEX($AL$8:$AL$17,COUNTIF($AL$8:$AL$17,"<="&$D29)+1)-INDEX($AL$8:$AL$17,COUNTIF($AL$8:$AL$17,"<="&$D29)))))+N($C$14)/100,"")))) | AJ29: =IF($B29="","",IF(ISNUMBER($AT29),$AT29,IF(ISNUMBER($D$10),$D$10,IFERROR(IF(COUNTIF($AL$8:$AL$17,"<="&$S29)=0,$AO$8,IF(COUNTIF($AL$8:$AL$17,"<="&$S29)>=COUNT($AL$8:$AL$17),INDEX($AO$8:$AO$17,COUNT($AL$8:$AL$17)),INDEX($AO$8:$AO$17,COUNTIF($AL$8:$AL$17,"<="&$S29))+(INDEX($AO$8:$AO$17,COUNTIF($AL$8:$AL$17,"<="&$S29)+1)-INDEX($AO$8:$AO$17,COUNTIF($AL$8:$AL$17,"<="&$S29)))*($S29-INDEX($AL$8:$AL$17,COUNTIF($AL$8:$AL$17,"<="&$S29)))/(INDEX($AL$8:$AL$17,COUNTIF($AL$8:$AL$17,"<="&$S29)+1)-INDEX($AL$8:$AL$17,COUNTIF($AL$8:$AL$17,"<="&$S29)))))+N($D$14)/100,"")))) | AP29: =IF($B29="","",$AQ$6&CHOOSE(MONTH($C29),"F","G","H","J","K","M","N","Q","U","V","X","Z")&RIGHT(YEAR($C29),1)&" Index") | AR29: =IF($AP29="","",BDP($AP29,"LAST_PRICE")) | AV29: =IF($L29="","",$O29-$C$49) | AW29: =IF($L29="","",$H29-$K29-$C$50-$C$45/10000*$C$9*$D29/365) | AX29: =IF($L29="","",IF($AV29>0,"SELL FUT / BUY CASH +"&TEXT($AV29,"0.0")&" pts net",IF($AW29>0,"BUY FUT / SHORT CASH +"&TEXT($AW29,"0.0")&" pts net","no edge after costs")))
B30: =IF('Div by Expiry'!$B24="","",'Div by Expiry'!$B24) | C30: =IF($B30="","",'Div by Expiry'!$C24) | D30: =IF($B30="","",'Div by Expiry'!$D24) | E30: =IF($B30="","",IF($AI30="","",$C$9*$AI30/100*$D30/$C$11)) | F30: =IF($B30="","",IF($C$13="N",'Div by Expiry'!$G24-IF($C$16="Y",0,'Div by Expiry'!$U47),IF($AI30="","",SUMPRODUCT('Div by Expiry'!$E$13:$E24,1+$AI30/100*($C30-(Expiries!$J$16:$J27+Expiries!$F$16:$F27)/2)/$C$11)-IF($C$16="Y",0,SUMPRODUCT('Div by Expiry'!$T$36:$T47,1+$AI30/100*($C30-(Expiries!$J$16:$J27+Expiries!$F$16:$F27)/2)/$C$11))))) | G30: =IF($B30="","",IF($C$13="N",'Div by Expiry'!$E47-IF($C$16="Y",0,'Div by Expiry'!$W47),IF($AI30="","",SUMPRODUCT('Div by Expiry'!$D$36:$D47,1+$AI30/100*($C30-(Expiries!$J$16:$J27+Expiries!$F$16:$F27)/2)/$C$11)-IF($C$16="Y",0,SUMPRODUCT('Div by Expiry'!$V$36:$V47,1+$AI30/100*($C30-(Expiries!$J$16:$J27+Expiries!$F$16:$F27)/2)/$C$11))))) | H30: =IF($B30="","",IF($E30="","",$C$9+$E30-$F30)) | I30: =IF($B30="","",IF($H30="","",$H30-$G30)) | J30: =IF($B30="","",IF($H30="","",$H30-$C$12/100*$G30)) | K30: =IF($B30="","",IF(ISNUMBER($AQ30),$AQ30,IF(ISNUMBER($AR30),$AR30,""))) | L30: =IF($B30="","",IF(N($K30)=0,"",IF($E30="","",$C$9+$E30-$K30))) | M30: =IF($L30="","",$L30-$F30) | N30: =IF($L30="","",IF($G30=0,"",$M30/$G30)) | O30: =IF($L30="","",$K30-$J30) | P30: =IF($L30="","",$O30/$C$9*10000) | R30: =IF($B30="","",'Div by Expiry'!$J24) | S30: =IF($B30="","",$R30-'Div by Expiry'!$C$7) | T30: =IF($B30="","",IF($AJ30="","",$D$9*$AJ30/100*$S30/$D$11)) | U30: =IF($B30="","",IF($C$13="N",'Div by Expiry'!$M24-IF($D$16="Y",0,'Div by Expiry'!$Y47),IF($AJ30="","",SUMPRODUCT('Div by Expiry'!$K$13:$K24,1+$AJ30/100*($R30-(Expiries!$K$16:$K27+Expiries!$I$16:$I27)/2)/$D$11)-IF($D$16="Y",0,SUMPRODUCT('Div by Expiry'!$X$36:$X47,1+$AJ30/100*($R30-(Expiries!$K$16:$K27+Expiries!$I$16:$I27)/2)/$D$11))))) | V30: =IF($B30="","",IF($C$13="N",'Div by Expiry'!$J47-IF($D$16="Y",0,'Div by Expiry'!$AA47),IF($AJ30="","",SUMPRODUCT('Div by Expiry'!$I$36:$I47,1+$AJ30/100*($R30-(Expiries!$K$16:$K27+Expiries!$I$16:$I27)/2)/$D$11)-IF($D$16="Y",0,SUMPRODUCT('Div by Expiry'!$Z$36:$Z47,1+$AJ30/100*($R30-(Expiries!$K$16:$K27+Expiries!$I$16:$I27)/2)/$D$11))))) | W30: =IF($B30="","",IF($T30="","",$D$9+$T30-$U30)) | X30: =IF($B30="","",IF($W30="","",$W30-$V30)) | Y30: =IF($B30="","",IF($W30="","",$W30-$D$12/100*$V30)) | AA30: =IF($B30="","",IF(N($Z30)=0,"",IF($T30="","",$D$9+$T30-$Z30))) | AB30: =IF($AA30="","",$AA30-$U30) | AC30: =IF($AA30="","",IF($V30=0,"",$AB30/$V30)) | AD30: =IF($AA30="","",$Z30-$Y30) | AE30: =IF($AA30="","",$AD30/$D$9*10000) | AG30: =IF($N30="","",IF($AC30="","",($N30-$AC30)*100)) | AI30: =IF($B30="","",IF(ISNUMBER($AS30),$AS30,IF(ISNUMBER($C$10),$C$10,IFERROR(IF(COUNTIF($AL$8:$AL$17,"<="&$D30)=0,$AO$8,IF(COUNTIF($AL$8:$AL$17,"<="&$D30)>=COUNT($AL$8:$AL$17),INDEX($AO$8:$AO$17,COUNT($AL$8:$AL$17)),INDEX($AO$8:$AO$17,COUNTIF($AL$8:$AL$17,"<="&$D30))+(INDEX($AO$8:$AO$17,COUNTIF($AL$8:$AL$17,"<="&$D30)+1)-INDEX($AO$8:$AO$17,COUNTIF($AL$8:$AL$17,"<="&$D30)))*($D30-INDEX($AL$8:$AL$17,COUNTIF($AL$8:$AL$17,"<="&$D30)))/(INDEX($AL$8:$AL$17,COUNTIF($AL$8:$AL$17,"<="&$D30)+1)-INDEX($AL$8:$AL$17,COUNTIF($AL$8:$AL$17,"<="&$D30)))))+N($C$14)/100,"")))) | AJ30: =IF($B30="","",IF(ISNUMBER($AT30),$AT30,IF(ISNUMBER($D$10),$D$10,IFERROR(IF(COUNTIF($AL$8:$AL$17,"<="&$S30)=0,$AO$8,IF(COUNTIF($AL$8:$AL$17,"<="&$S30)>=COUNT($AL$8:$AL$17),INDEX($AO$8:$AO$17,COUNT($AL$8:$AL$17)),INDEX($AO$8:$AO$17,COUNTIF($AL$8:$AL$17,"<="&$S30))+(INDEX($AO$8:$AO$17,COUNTIF($AL$8:$AL$17,"<="&$S30)+1)-INDEX($AO$8:$AO$17,COUNTIF($AL$8:$AL$17,"<="&$S30)))*($S30-INDEX($AL$8:$AL$17,COUNTIF($AL$8:$AL$17,"<="&$S30)))/(INDEX($AL$8:$AL$17,COUNTIF($AL$8:$AL$17,"<="&$S30)+1)-INDEX($AL$8:$AL$17,COUNTIF($AL$8:$AL$17,"<="&$S30)))))+N($D$14)/100,"")))) | AP30: =IF($B30="","",$AQ$6&CHOOSE(MONTH($C30),"F","G","H","J","K","M","N","Q","U","V","X","Z")&RIGHT(YEAR($C30),1)&" Index") | AR30: =IF($AP30="","",BDP($AP30,"LAST_PRICE")) | AV30: =IF($L30="","",$O30-$C$49) | AW30: =IF($L30="","",$H30-$K30-$C$50-$C$45/10000*$C$9*$D30/365) | AX30: =IF($L30="","",IF($AV30>0,"SELL FUT / BUY CASH +"&TEXT($AV30,"0.0")&" pts net",IF($AW30>0,"BUY FUT / SHORT CASH +"&TEXT($AW30,"0.0")&" pts net","no edge after costs")))
... B34: =IF('Div by Expiry'!$B28="","",'Div by Expiry'!$B28) | C34: =IF($B34="","",'Div by Expiry'!$C28) | D34: =IF($B34="","",'Div by Expiry'!$D28) | E34: =IF($B34="","",IF($AI34="","",$C$9*$AI34/100*$D34/$C$11)) | F34: =IF($B34="","",IF($C$13="N",'Div by Expiry'!$G28-IF($C$16="Y",0,'Div by Expiry'!$U51),IF($AI34="","",SUMPRODUCT('Div by Expiry'!$E$13:$E28,1+$AI34/100*($C34-(Expiries!$J$16:$J31+Expiries!$F$16:$F31)/2)/$C$11)-IF($C$16="Y",0,SUMPRODUCT('Div by Expiry'!$T$36:$T51,1+$AI34/100*($C34-(Expiries!$J$16:$J31+Expiries!$F$16:$F31)/2)/$C$11))))) | G34: =IF($B34="","",IF($C$13="N",'Div by Expiry'!$E51-IF($C$16="Y",0,'Div by Expiry'!$W51),IF($AI34="","",SUMPRODUCT('Div by Expiry'!$D$36:$D51,1+$AI34/100*($C34-(Expiries!$J$16:$J31+Expiries!$F$16:$F31)/2)/$C$11)-IF($C$16="Y",0,SUMPRODUCT('Div by Expiry'!$V$36:$V51,1+$AI34/100*($C34-(Expiries!$J$16:$J31+Expiries!$F$16:$F31)/2)/$C$11))))) | H34: =IF($B34="","",IF($E34="","",$C$9+$E34-$F34)) | I34: =IF($B34="","",IF($H34="","",$H34-$G34)) | J34: =IF($B34="","",IF($H34="","",$H34-$C$12/100*$G34)) | K34: =IF($B34="","",IF(ISNUMBER($AQ34),$AQ34,IF(ISNUMBER($AR34),$AR34,""))) | L34: =IF($B34="","",IF(N($K34)=0,"",IF($E34="","",$C$9+$E34-$K34))) | M34: =IF($L34="","",$L34-$F34) | N34: =IF($L34="","",IF($G34=0,"",$M34/$G34)) | O34: =IF($L34="","",$K34-$J34) | P34: =IF($L34="","",$O34/$C$9*10000) | R34: =IF($B34="","",'Div by Expiry'!$J28) | S34: =IF($B34="","",$R34-'Div by Expiry'!$C$7) | T34: =IF($B34="","",IF($AJ34="","",$D$9*$AJ34/100*$S34/$D$11)) | U34: =IF($B34="","",IF($C$13="N",'Div by Expiry'!$M28-IF($D$16="Y",0,'Div by Expiry'!$Y51),IF($AJ34="","",SUMPRODUCT('Div by Expiry'!$K$13:$K28,1+$AJ34/100*($R34-(Expiries!$K$16:$K31+Expiries!$I$16:$I31)/2)/$D$11)-IF($D$16="Y",0,SUMPRODUCT('Div by Expiry'!$X$36:$X51,1+$AJ34/100*($R34-(Expiries!$K$16:$K31+Expiries!$I$16:$I31)/2)/$D$11))))) | V34: =IF($B34="","",IF($C$13="N",'Div by Expiry'!$J51-IF($D$16="Y",0,'Div by Expiry'!$AA51),IF($AJ34="","",SUMPRODUCT('Div by Expiry'!$I$36:$I51,1+$AJ34/100*($R34-(Expiries!$K$16:$K31+Expiries!$I$16:$I31)/2)/$D$11)-IF($D$16="Y",0,SUMPRODUCT('Div by Expiry'!$Z$36:$Z51,1+$AJ34/100*($R34-(Expiries!$K$16:$K31+Expiries!$I$16:$I31)/2)/$D$11))))) | W34: =IF($B34="","",IF($T34="","",$D$9+$T34-$U34)) | X34: =IF($B34="","",IF($W34="","",$W34-$V34)) | Y34: =IF($B34="","",IF($W34="","",$W34-$D$12/100*$V34)) | AA34: =IF($B34="","",IF(N($Z34)=0,"",IF($T34="","",$D$9+$T34-$Z34))) | AB34: =IF($AA34="","",$AA34-$U34) | AC34: =IF($AA34="","",IF($V34=0,"",$AB34/$V34)) | AD34: =IF($AA34="","",$Z34-$Y34) | AE34: =IF($AA34="","",$AD34/$D$9*10000) | AG34: =IF($N34="","",IF($AC34="","",($N34-$AC34)*100)) | AI34: =IF($B34="","",IF(ISNUMBER($AS34),$AS34,IF(ISNUMBER($C$10),$C$10,IFERROR(IF(COUNTIF($AL$8:$AL$17,"<="&$D34)=0,$AO$8,IF(COUNTIF($AL$8:$AL$17,"<="&$D34)>=COUNT($AL$8:$AL$17),INDEX($AO$8:$AO$17,COUNT($AL$8:$AL$17)),INDEX($AO$8:$AO$17,COUNTIF($AL$8:$AL$17,"<="&$D34))+(INDEX($AO$8:$AO$17,COUNTIF($AL$8:$AL$17,"<="&$D34)+1)-INDEX($AO$8:$AO$17,COUNTIF($AL$8:$AL$17,"<="&$D34)))*($D34-INDEX($AL$8:$AL$17,COUNTIF($AL$8:$AL$17,"<="&$D34)))/(INDEX($AL$8:$AL$17,COUNTIF($AL$8:$AL$17,"<="&$D34)+1)-INDEX($AL$8:$AL$17,COUNTIF($AL$8:$AL$17,"<="&$D34)))))+N($C$14)/100,"")))) | AJ34: =IF($B34="","",IF(ISNUMBER($AT34),$AT34,IF(ISNUMBER($D$10),$D$10,IFERROR(IF(COUNTIF($AL$8:$AL$17,"<="&$S34)=0,$AO$8,IF(COUNTIF($AL$8:$AL$17,"<="&$S34)>=COUNT($AL$8:$AL$17),INDEX($AO$8:$AO$17,COUNT($AL$8:$AL$17)),INDEX($AO$8:$AO$17,COUNTIF($AL$8:$AL$17,"<="&$S34))+(INDEX($AO$8:$AO$17,COUNTIF($AL$8:$AL$17,"<="&$S34)+1)-INDEX($AO$8:$AO$17,COUNTIF($AL$8:$AL$17,"<="&$S34)))*($S34-INDEX($AL$8:$AL$17,COUNTIF($AL$8:$AL$17,"<="&$S34)))/(INDEX($AL$8:$AL$17,COUNTIF($AL$8:$AL$17,"<="&$S34)+1)-INDEX($AL$8:$AL$17,COUNTIF($AL$8:$AL$17,"<="&$S34)))))+N($D$14)/100,"")))) | AP34: =IF($B34="","",$AQ$6&CHOOSE(MONTH($C34),"F","G","H","J","K","M","N","Q","U","V","X","Z")&RIGHT(YEAR($C34),1)&" Index") | AR34: =IF($AP34="","",BDP($AP34,"LAST_PRICE")) | AV34: =IF($L34="","",$O34-$C$49) | AW34: =IF($L34="","",$H34-$K34-$C$50-$C$45/10000*$C$9*$D34/365) | AX34: =IF($L34="","",IF($AV34>0,"SELL FUT / BUY CASH +"&TEXT($AV34,"0.0")&" pts net",IF($AW34>0,"BUY FUT / SHORT CASH +"&TEXT($AW34,"0.0")&" pts net","no edge after costs")))
B36: READ BEFORE TRADING
B37: - | C37: FRANKING PRICED is a residual - it also absorbs any gap between your dividend forecast and the market's, so a negative number means the market sees FEWER dividends than you, not negative franking.
B38: - | C38: Even a domestic holder values credits below face (tax timing, 45-day rule) - do not expect 100%.
B41: TRANSACTION COSTS - INDEX POINTS (SPI leg) | G41: Same panel as Bloomberg FAIR, entered in INDEX POINTS (the bp-of-spot equivalent shows beside each). Everything starts at zero - until you type your desk's numbers the ACTION column just reflects raw mispricing. FAIR's panel values port straight in. MXAU gets no cost columns: there is no listed price-index future to execute against. | AK41: Full curve pull - reference and ticker check. Add "CURVE_DATE=YYYY-MM-DD" inside the BDS for a historical snapshot.
C42: pts (type) | D42: =bp of spot | AK42: =BDS($AL$6,"CURVE_TENOR_RATES","headers=y")
B43: Stk bid/ask sprd | C43: 0 | D43: =IF(N($C43)=0,"",$C43/$C$9*10000)
B44: Stk commission | C44: 0 | D44: =IF(N($C44)=0,"",$C44/$C$9*10000)
B45: Stk borrowing cost (ANNUAL bp) | C45: 0 | D45: accrues by days into the reverse edge
B46: Fut bid/ask sprd | C46: 0 | D46: =IF(N($C46)=0,"",$C46/$C$9*10000)
B47: Fut commission | C47: 0 | D47: =IF(N($C47)=0,"",$C47/$C$9*10000)
B48: Other | C48: 0 | D48: =IF(N($C48)=0,"",$C48/$C$9*10000)
B49: BUY CASH / SELL FUTURES (pts) | C49: =$C$43+$C$44+$C$46+$C$47+$C$48 | D49: =IF(N($C49)=0,"",$C49/$C$9*10000)
B50: SELL CASH / BUY FUTURES (pts, ex-borrow) | C50: =$C$49 | G50: The reverse trade pays the same spreads/commissions PLUS the borrow, which grows with days to expiry - so the borrow is added per contract inside the 'net edge reverse' column, not here.
B51: TOTAL ROLL FUTURES (pts) | C51: =2*($C$46+$C$47) | G51: Out of the front + into the back = futures spread and commission twice. Type a number over this to hardcode your roll cost.
B52: - | C52: Net edges and the ACTION verdict sit per contract at the far right of the table (cols AV / AW / AX).
B55: CALENDAR SPREAD - futures vs futures | G55: Both legs are futures, so no basket, no borrow, no franking monetization - the only dividend risk is the window BETWEEN the two expiries, and funding cancels except its slope (the carry differential). EDGE > 0 means the market spread is too wide: SELL the back / BUY the front. Costs = one roll.
B56: Front contract # | C56: 1 | E56: Back contract # | F56: 2
B57: Contract / expiry | C57: =IFERROR(INDEX($B$19:$B$34,$C$56),"") | D57: =IFERROR(INDEX($C$19:$C$34,$C$56),"") | E57: =IFERROR(INDEX($B$19:$B$34,$F$56),"") | F57: =IFERROR(INDEX($C$19:$C$34,$F$56),"")
B58: Market spread, back - front (pts) | C58: =IF(OR(NOT(ISNUMBER(INDEX($K$19:$K$34,$C$56))),NOT(ISNUMBER(INDEX($K$19:$K$34,$F$56)))),"",INDEX($K$19:$K$34,$F$56)-INDEX($K$19:$K$34,$C$56)) | G58: Needs a market price on BOTH rows (manual or live).
B59: Model spread at YOUR % (pts) | C59: =IF(OR(NOT(ISNUMBER(INDEX($J$19:$J$34,$C$56))),NOT(ISNUMBER(INDEX($J$19:$J$34,$F$56)))),"",INDEX($J$19:$J$34,$F$56)-INDEX($J$19:$J$34,$C$56))
B60: EDGE market - model (pts) | C60: =IF(OR($C58="",$C59=""),"",$C58-$C59)
B61: carry differential (pts) | C61: =IF(OR(NOT(ISNUMBER(INDEX($E$19:$E$34,$C$56))),NOT(ISNUMBER(INDEX($E$19:$E$34,$F$56)))),"",INDEX($E$19:$E$34,$F$56)-INDEX($E$19:$E$34,$C$56))
B62: dividends in the window (pts) | C62: =IF(OR(NOT(ISNUMBER(INDEX($F$19:$F$34,$C$56))),NOT(ISNUMBER(INDEX($F$19:$F$34,$F$56)))),"",INDEX($F$19:$F$34,$F$56)-INDEX($F$19:$F$34,$C$56)) | G62: The dividend exposure of the spread is ONLY this between-expiries window - usually far better known than a full year.
B63: credits in the window (pts) | C63: =IF(OR(NOT(ISNUMBER(INDEX($G$19:$G$34,$C$56))),NOT(ISNUMBER(INDEX($G$19:$G$34,$F$56)))),"",INDEX($G$19:$G$34,$F$56)-INDEX($G$19:$G$34,$C$56))
B64: Franking priced, front / back | C64: =IF(NOT(ISNUMBER(INDEX($N$19:$N$34,$C$56))),"",INDEX($N$19:$N$34,$C$56)) | D64: =IF(NOT(ISNUMBER(INDEX($N$19:$N$34,$F$56))),"",INDEX($N$19:$N$34,$F$56))
B65: Total roll cost (pts) | C65: =$C$51
B66: NET EDGE after roll (pts) | C66: =IF($C60="","",ABS($C60)-$C65) | D66: =IF($C66="","",IF($C66<=0,"costs exceed the edge",IF($C60>0,"SELL back / BUY front","BUY back / SELL front")))

Sheet Field Check
B2: FIELD MNEMONIC TESTER
B3: Test ticker | C3: BHP AU Equity | E3: BHP pays fully franked dividends, so a working franking field should return 100 here.
B4: FRANKING FIELD (CONFIRMED) | C4: EQY_DVD_PCT_FRANKED | E4: Confirmed working on terminal. Both data tabs read their franking mnemonic from this cell - change it here and it flows everywhere.
B7: Field | C7: Result | D7: Status | E7: Notes
B8: --- IN USE (all confirmed working) ---
B9: EQY_DVD_PCT_FRANKED | C9: =_xll.BDP($C$3,$B9) | D9: =IF(ISNUMBER(C9),"OK - numeric",IF(C9="","blank / no data",IF(ISTEXT(C9),"OK - text","INVALID or error"))) | E9: Franked %. Returns 100 for fully franked. Confirmed.
B10: EQY_DVD_SH_12M | C10: =_xll.BDP($C$3,$B10) | D10: =IF(ISNUMBER(C10),"OK - numeric",IF(C10="","blank / no data",IF(ISTEXT(C10),"OK - text","INVALID or error"))) | E10: Gross DPS paid over trailing 12 months, in trading currency.
B11: EQY_DVD_YLD_12M | C11: =_xll.BDP($C$3,$B11) | D11: =IF(ISNUMBER(C11),"OK - numeric",IF(C11="","blank / no data",IF(ISTEXT(C11),"OK - text","INVALID or error"))) | E11: Trailing 12-month gross dividend yield, %.
B12: EQY_DVD_YLD_IND | C12: =_xll.BDP($C$3,$B12) | D12: =IF(ISNUMBER(C12),"OK - numeric",IF(C12="","blank / no data",IF(ISTEXT(C12),"OK - text","INVALID or error"))) | E12: Indicated gross dividend yield, %. Primary bottom-up input.
B13: NAME | C13: =_xll.BDP($C$3,$B13) | D13: =IF(ISNUMBER(C13),"OK - numeric",IF(C13="","blank / no data",IF(ISTEXT(C13),"OK - text","INVALID or error"))) | E13: Company name. If this fails, the ticker or the add-in is the problem, not the field.
B14: --- NEXT / UPCOMING DIVIDEND: RESOLVED - see the v4 block below ---
B15: BDVD_PROJ_DIV_AMT | C15: =_xll.BDP($C$3,$B15) | D15: =IF(ISNUMBER(C15),"OK - numeric",IF(C15="","blank / no data",IF(ISTEXT(C15),"OK - text","INVALID or error"))) | E15: Single next projected amount. Superseded by BDVD_ALL_PROJECTIONS, which returns the full schedule.
B16: BDVD_PROJ_DIV_EX_DT | C16: =_xll.BDP($C$3,$B16) | D16: =IF(ISNUMBER(C16),"OK - numeric",IF(C16="","blank / no data",IF(ISTEXT(C16),"OK - text","INVALID or error"))) | E16: Projected ex-date to go with the above.
B17: EQY_DVD_SH_LAST | C17: =_xll.BDP($C$3,$B17) | D17: =IF(ISNUMBER(C17),"OK - numeric",IF(C17="","blank / no data",IF(ISTEXT(C17),"OK - text","INVALID or error"))) | E17: Most recent declared gross DPS. Not forward-looking, but it always works and is often close enough.
B18: DVD_SH_LAST | C18: =_xll.BDP($C$3,$B18) | D18: =IF(ISNUMBER(C18),"OK - numeric",IF(C18="","blank / no data",IF(ISTEXT(C18),"OK - text","INVALID or error"))) | E18: Shorter variant of the above - test which one your terminal takes.
B19: EQY_DVD_SH_NEXT | C19: =_xll.BDP($C$3,$B19) | D19: =IF(ISNUMBER(C19),"OK - numeric",IF(C19="","blank / no data",IF(ISTEXT(C19),"OK - text","INVALID or error"))) | E19: YOUR ATTEMPT - returns Invalid Field. Kept here only so nobody retries it.
B20: --- CONTEXT FROM V2 ---
B21: GICS_SECTOR_NAME | D21: not pulled | E21: Pulled on the data tabs (column E) and rolled up on the Sector tab.
B22: CUR_MKT_CAP / PX_LAST / CRNCY | D22: not pulled | E22: Not used by any calculation. Weights now come from your pasted index shares and divisor (v4).
B23: BEST_DIV_YLD / DVD_PAYOUT_RATIO | D23: not pulled | E23: Forward and context metrics. Not part of steps 1-4.
B25: FORWARD DIVIDENDS - RESOLVED
B26: - | C26: BDVD_ALL_PROJECTIONS (v4 block below) returns the full projected schedule - ex-dates and amounts running years out. Needs the BDVD entitlement; the single-value candidates above are superseded.
B31: OTHER SYNTAX
B32: Purpose | C32: Formula | D32: Notes
B33: Members (names only) | C33: '=BDS("AS51 Index","INDX_MEMBERS") | E33: What the data tabs use - no weight entitlement needed. Weights come from your pasted shares.
B34: Dividend history | C34: '=BDS($C$3,"DVD_HIST_ALL","DVD_START_DT","20250801","DVD_END_DT","20260803") | E34: Dividend history. The calendar pulls this per stock (7 rows, horizontal) alongside the projections - see the confirmed field and live sample below.
B35: Index yield now (12M) | C35: '=BDP("AS51 Index","EQY_DVD_YLD_12M") | E35: EQY_DVD_YLD_IND returns N/A at index level - 12M is the field that works.
B36: Suppress errors at source | C36: '=IFERROR(BDP($C$3,"EQY_DVD_YLD_IND"),0) | E36: Excel-side, always works. Preferred over Bloomberg's own fill parameters, which vary by add-in version.
B37: Index yield, point-in-time | C37: '=BDH("AS51 Index","EQY_DVD_YLD_12M","20260630","20260630")
B38: Index yield, monthly history | C38: '=BDH("AS51 Index","EQY_DVD_YLD_12M","20150101","20260804","per=m") | E38: Spills down - park it on a scratch sheet, not here.
B39: Formulas shown as text - copy and drop the leading apostrophe.
B41: FIELDS THE BOOK USES
B42: Projected dividends (BDS) | C42: BDVD_ALL_PROJECTIONS | E42: Confirmed working. Full projected schedule; Dvd Calendar reads this cell - a wrong mnemonic is a one-cell fix.
B43: Dividend currency (BDP) | C43: EQY_DVD_CRNCY | E43: Confirmed working. Feeds the Dvd FX column on the data tabs.
B44: Dividend history (BDS) | C44: DVD_HIST_ALL | E44: Confirmed working, incl. DVD_START_DT / DVD_END_DT overrides (YYYYMMDD). The Override workbench pulls it for the picked stock.
B45: Next earnings date (BDP) | C45: EXPECTED_REPORT_DT | D45: =_xll.BDP($C$3,$C$45) | E45: =IF(ISNUMBER($D$45),"OK","check field") | F45: Candidate - feeds the Next earnings column on the data tabs. Alternates: NEXT_ANN_DT, EXPECTED_REPORT_DATE.
B47: LIVE SAMPLE 1 - the projections pull (3 rows: Projected Declared / Ex / Amount)
C48: =_xll.BDS($C$3,$C$42,"headers=y","startcol=1","endcol=3","dir=h")
B52: DIVIDEND TYPES THAT COUNT AS CASH (history rows carry a type; anything not listed is ignored) | F52: Excluded by omission: Spinoff, Bonus, Stock Split, Rights Issue, Entitlement, Omitted, Discontinued. Specials stay IN for index points - blank a cell to drop that type.
B53: Cash type 1 | C53: Final
B54: Cash type 2 | C54: Interim
B55: Cash type 3 | C55: Regular Cash
B56: Cash type 4 | C56: Special Cash
B57: Cash type 5 | C57: Return of Capital
B59: History pull window (auto) | C59: =TEXT(Expiries!$C$6-90,"yyyymmdd") | D59: =TEXT(Expiries!$C$6+560,"yyyymmdd") | F59: ~3 months back and 18 months forward - past the last contract even at the 16-contract maximum, so a declared dividend cannot fall outside the pull whichever date Bloomberg filters it on.
B61: LIVE SAMPLE 2 - the history pull (7 rows: the AMOUNT is the 5th)
C62: =_xll.BDS($C$3,$C$44,"headers=y","startcol=1","endcol=7","dir=h","DVD_START_DT",$C$59,"DVD_END_DT",$D$59)
B70: Keep the rows to the right of both samples clear - they spill as far as they need.

Sheet AS51
A1: S&P/ASX 200 (AS51) - MEMBERS, DIVIDENDS & FRANKING
A2: Index ticker | B2: AS51 Index | C2: Index ccy | D2: AUD | E2: Members returned | H2: =SUMPRODUCT(($A$6:$A$275<>"")*1) | J2: No dividend | L2: =COUNTIF($N$6:$N$275,"No dividend") | M2: =IF($H$2=$H$3+$L$2,"reconciles","CHECK: status counts do not sum to members") | O2: Paste INDEX SHARES in column B and the official INDEX DIVISOR in B3 (blue). A refresh can reshuffle members - your pasted shares do NOT move with them.
A3: Index divisor | B3: 3.0303208e+08 | C3: AUD -> index ccy | D3: =IF($D$2="AUD",1,_xll.BDP("AUD"&$D$2&" Curncy","PX_LAST")) | E3: Dividend payers | H3: =COUNTIF($N$6:$N$275,"OK")+COUNTIF($N$6:$N$275,"Frank assumed") | J3: Frank assumed | L3: =COUNTIF($N$6:$N$275,"Frank assumed") | M3: <- no franking value returned, taken as 100% franked. | O3: D3 converts the reference DPS column (AUD) into the index currency for the points maths.
A4: TOTALS | J4: =IFERROR(SUM($J$6:$J$275),"") | K4: =IFERROR(SUM($K$6:$K$275),"") | L4: =IFERROR(SUM($L$6:$L$275),"") | N4: =IFERROR(SUMIF($N$6:$N$275,"OK",$J$6:$J$275)/$J$4,"") | O4: <- FRANKING REPORTED: share of 12M dividend points where Bloomberg returned a franking value. The rest are assumed fully franked.
A5: Member Ticker | B5: Index Shares | C5: Bloomberg Ticker | D5: Company Name | E5: GICS Sector | F5: DPS 12M | G5: Div Yld 12M (%) | H5: Div Yld Ind (%) | I5: Franked (%) | J5: Dvd 12M (pts) | K5: Franked (pts) | L5: Unfranked (pts) | N5: Status | P5: Dvd CCY | Q5: Dvd FX | S5: Next earnings
A6: =_xll.BDS($B$2,"INDX_MEMBERS","cols=1;rows=200") | B6: 170700811 | C6: =IF($A6="","",$A6&" Equity") | D6: =IF($A6="","",_xll.BDP($C6,"NAME")) | E6: =IF($A6="","",_xll.BDP($C6,"GICS_SECTOR_NAME")) | F6: =IF($A6="","",_xll.BDP($C6,"EQY_DVD_SH_12M")) | G6: =IF($A6="","",_xll.BDP($C6,"EQY_DVD_YLD_12M")) | H6: =IF($A6="","",_xll.BDP($C6,"EQY_DVD_YLD_IND")) | I6: =IF($A6="","",_xll.BDP($C6,'Field Check'!$C$4)) | J6: =IFERROR(IF($B6="","",IF(ISNUMBER($F6),$B6*$F6*$D$3/$B$3,0)),"") | K6: =IFERROR(IF($J6="","",$J6*IF(ISNUMBER($I6),$I6,'Index Summary'!$C$7)/100),"") | L6: =IFERROR(IF($K6="","",$J6-$K6),"") | N6: =IF($C6="","",IF(NOT(ISNUMBER($F6)),"No dividend",IF($F6=0,"No dividend",IF(ISNUMBER($I6),"OK","Frank assumed")))) | P6: =IF($N6="No dividend","",IF($C6="","",_xll.BDP($C6,'Field Check'!$C$43))) | Q6: =IFERROR(IF(LEN($P6)<>3,1,IF($P6=$D$2,1,_xll.BDP($P6&$D$2&" Curncy","PX_LAST"))),1) | S6: =IF($C6="","",_xll.BDP($C6,'Field Check'!$C$45))
A7: 4DX AT | B7: 505754250 | C7: =IF($A7="","",$A7&" Equity") | D7: =IF($A7="","",_xll.BDP($C7,"NAME")) | E7: =IF($A7="","",_xll.BDP($C7,"GICS_SECTOR_NAME")) | F7: =IF($A7="","",_xll.BDP($C7,"EQY_DVD_SH_12M")) | G7: =IF($A7="","",_xll.BDP($C7,"EQY_DVD_YLD_12M")) | H7: =IF($A7="","",_xll.BDP($C7,"EQY_DVD_YLD_IND")) | I7: =IF($A7="","",_xll.BDP($C7,'Field Check'!$C$4)) | J7: =IFERROR(IF($B7="","",IF(ISNUMBER($F7),$B7*$F7*$D$3/$B$3,0)),"") | K7: =IFERROR(IF($J7="","",$J7*IF(ISNUMBER($I7),$I7,'Index Summary'!$C$7)/100),"") | L7: =IFERROR(IF($K7="","",$J7-$K7),"") | N7: =IF($C7="","",IF(NOT(ISNUMBER($F7)),"No dividend",IF($F7=0,"No dividend",IF(ISNUMBER($I7),"OK","Frank assumed")))) | P7: =IF($N7="No dividend","",IF($C7="","",_xll.BDP($C7,'Field Check'!$C$43))) | Q7: =IFERROR(IF(LEN($P7)<>3,1,IF($P7=$D$2,1,_xll.BDP($P7&$D$2&" Curncy","PX_LAST"))),1) | S7: =IF($C7="","",_xll.BDP($C7,'Field Check'!$C$45))
A8: A2M AT | B8: 725376000 | C8: =IF($A8="","",$A8&" Equity") | D8: =IF($A8="","",_xll.BDP($C8,"NAME")) | E8: =IF($A8="","",_xll.BDP($C8,"GICS_SECTOR_NAME")) | F8: =IF($A8="","",_xll.BDP($C8,"EQY_DVD_SH_12M")) | G8: =IF($A8="","",_xll.BDP($C8,"EQY_DVD_YLD_12M")) | H8: =IF($A8="","",_xll.BDP($C8,"EQY_DVD_YLD_IND")) | I8: =IF($A8="","",_xll.BDP($C8,'Field Check'!$C$4)) | J8: =IFERROR(IF($B8="","",IF(ISNUMBER($F8),$B8*$F8*$D$3/$B$3,0)),"") | K8: =IFERROR(IF($J8="","",$J8*IF(ISNUMBER($I8),$I8,'Index Summary'!$C$7)/100),"") | L8: =IFERROR(IF($K8="","",$J8-$K8),"") | N8: =IF($C8="","",IF(NOT(ISNUMBER($F8)),"No dividend",IF($F8=0,"No dividend",IF(ISNUMBER($I8),"OK","Frank assumed")))) | P8: =IF($N8="No dividend","",IF($C8="","",_xll.BDP($C8,'Field Check'!$C$43))) | Q8: =IFERROR(IF(LEN($P8)<>3,1,IF($P8=$D$2,1,_xll.BDP($P8&$D$2&" Curncy","PX_LAST"))),1) | S8: =IF($C8="","",_xll.BDP($C8,'Field Check'!$C$45))
A9: AAI AT | B9: 37378206 | C9: =IF($A9="","",$A9&" Equity") | D9: =IF($A9="","",_xll.BDP($C9,"NAME")) | E9: =IF($A9="","",_xll.BDP($C9,"GICS_SECTOR_NAME")) | F9: =IF($A9="","",_xll.BDP($C9,"EQY_DVD_SH_12M")) | G9: =IF($A9="","",_xll.BDP($C9,"EQY_DVD_YLD_12M")) | H9: =IF($A9="","",_xll.BDP($C9,"EQY_DVD_YLD_IND")) | I9: =IF($A9="","",_xll.BDP($C9,'Field Check'!$C$4)) | J9: =IFERROR(IF($B9="","",IF(ISNUMBER($F9),$B9*$F9*$D$3/$B$3,0)),"") | K9: =IFERROR(IF($J9="","",$J9*IF(ISNUMBER($I9),$I9,'Index Summary'!$C$7)/100),"") | L9: =IFERROR(IF($K9="","",$J9-$K9),"") | N9: =IF($C9="","",IF(NOT(ISNUMBER($F9)),"No dividend",IF($F9=0,"No dividend",IF(ISNUMBER($I9),"OK","Frank assumed")))) | P9: =IF($N9="No dividend","",IF($C9="","",_xll.BDP($C9,'Field Check'!$C$43))) | Q9: =IFERROR(IF(LEN($P9)<>3,1,IF($P9=$D$2,1,_xll.BDP($P9&$D$2&" Curncy","PX_LAST"))),1) | S9: =IF($C9="","",_xll.BDP($C9,'Field Check'!$C$45))
A10: ABB AT | B10: 278724300 | C10: =IF($A10="","",$A10&" Equity") | D10: =IF($A10="","",_xll.BDP($C10,"NAME")) | E10: =IF($A10="","",_xll.BDP($C10,"GICS_SECTOR_NAME")) | F10: =IF($A10="","",_xll.BDP($C10,"EQY_DVD_SH_12M")) | G10: =IF($A10="","",_xll.BDP($C10,"EQY_DVD_YLD_12M")) | H10: =IF($A10="","",_xll.BDP($C10,"EQY_DVD_YLD_IND")) | I10: =IF($A10="","",_xll.BDP($C10,'Field Check'!$C$4)) | J10: =IFERROR(IF($B10="","",IF(ISNUMBER($F10),$B10*$F10*$D$3/$B$3,0)),"") | K10: =IFERROR(IF($J10="","",$J10*IF(ISNUMBER($I10),$I10,'Index Summary'!$C$7)/100),"") | L10: =IFERROR(IF($K10="","",$J10-$K10),"") | N10: =IF($C10="","",IF(NOT(ISNUMBER($F10)),"No dividend",IF($F10=0,"No dividend",IF(ISNUMBER($I10),"OK","Frank assumed")))) | P10: =IF($N10="No dividend","",IF($C10="","",_xll.BDP($C10,'Field Check'!$C$43))) | Q10: =IFERROR(IF(LEN($P10)<>3,1,IF($P10=$D$2,1,_xll.BDP($P10&$D$2&" Curncy","PX_LAST"))),1) | S10: =IF($C10="","",_xll.BDP($C10,'Field Check'!$C$45))
A11: AGL AT | B11: 598744830 | C11: =IF($A11="","",$A11&" Equity") | D11: =IF($A11="","",_xll.BDP($C11,"NAME")) | E11: =IF($A11="","",_xll.BDP($C11,"GICS_SECTOR_NAME")) | F11: =IF($A11="","",_xll.BDP($C11,"EQY_DVD_SH_12M")) | G11: =IF($A11="","",_xll.BDP($C11,"EQY_DVD_YLD_12M")) | H11: =IF($A11="","",_xll.BDP($C11,"EQY_DVD_YLD_IND")) | I11: =IF($A11="","",_xll.BDP($C11,'Field Check'!$C$4)) | J11: =IFERROR(IF($B11="","",IF(ISNUMBER($F11),$B11*$F11*$D$3/$B$3,0)),"") | K11: =IFERROR(IF($J11="","",$J11*IF(ISNUMBER($I11),$I11,'Index Summary'!$C$7)/100),"") | L11: =IFERROR(IF($K11="","",$J11-$K11),"") | N11: =IF($C11="","",IF(NOT(ISNUMBER($F11)),"No dividend",IF($F11=0,"No dividend",IF(ISNUMBER($I11),"OK","Frank assumed")))) | P11: =IF($N11="No dividend","",IF($C11="","",_xll.BDP($C11,'Field Check'!$C$43))) | Q11: =IFERROR(IF(LEN($P11)<>3,1,IF($P11=$D$2,1,_xll.BDP($P11&$D$2&" Curncy","PX_LAST"))),1) | S11: =IF($C11="","",_xll.BDP($C11,'Field Check'!$C$45))
A12: AIA AT | B12: 393740000 | C12: =IF($A12="","",$A12&" Equity") | D12: =IF($A12="","",_xll.BDP($C12,"NAME")) | E12: =IF($A12="","",_xll.BDP($C12,"GICS_SECTOR_NAME")) | F12: =IF($A12="","",_xll.BDP($C12,"EQY_DVD_SH_12M")) | G12: =IF($A12="","",_xll.BDP($C12,"EQY_DVD_YLD_12M")) | H12: =IF($A12="","",_xll.BDP($C12,"EQY_DVD_YLD_IND")) | I12: =IF($A12="","",_xll.BDP($C12,'Field Check'!$C$4)) | J12: =IFERROR(IF($B12="","",IF(ISNUMBER($F12),$B12*$F12*$D$3/$B$3,0)),"") | K12: =IFERROR(IF($J12="","",$J12*IF(ISNUMBER($I12),$I12,'Index Summary'!$C$7)/100),"") | L12: =IFERROR(IF($K12="","",$J12-$K12),"") | N12: =IF($C12="","",IF(NOT(ISNUMBER($F12)),"No dividend",IF($F12=0,"No dividend",IF(ISNUMBER($I12),"OK","Frank assumed")))) | P12: =IF($N12="No dividend","",IF($C12="","",_xll.BDP($C12,'Field Check'!$C$43))) | Q12: =IFERROR(IF(LEN($P12)<>3,1,IF($P12=$D$2,1,_xll.BDP($P12&$D$2&" Curncy","PX_LAST"))),1) | S12: =IF($C12="","",_xll.BDP($C12,'Field Check'!$C$45))
A13: ALD AT | B13: 238302000 | C13: =IF($A13="","",$A13&" Equity") | D13: =IF($A13="","",_xll.BDP($C13,"NAME")) | E13: =IF($A13="","",_xll.BDP($C13,"GICS_SECTOR_NAME")) | F13: =IF($A13="","",_xll.BDP($C13,"EQY_DVD_SH_12M")) | G13: =IF($A13="","",_xll.BDP($C13,"EQY_DVD_YLD_12M")) | H13: =IF($A13="","",_xll.BDP($C13,"EQY_DVD_YLD_IND")) | I13: =IF($A13="","",_xll.BDP($C13,'Field Check'!$C$4)) | J13: =IFERROR(IF($B13="","",IF(ISNUMBER($F13),$B13*$F13*$D$3/$B$3,0)),"") | K13: =IFERROR(IF($J13="","",$J13*IF(ISNUMBER($I13),$I13,'Index Summary'!$C$7)/100),"") | L13: =IFERROR(IF($K13="","",$J13-$K13),"") | N13: =IF($C13="","",IF(NOT(ISNUMBER($F13)),"No dividend",IF($F13=0,"No dividend",IF(ISNUMBER($I13),"OK","Frank assumed")))) | P13: =IF($N13="No dividend","",IF($C13="","",_xll.BDP($C13,'Field Check'!$C$43))) | Q13: =IFERROR(IF(LEN($P13)<>3,1,IF($P13=$D$2,1,_xll.BDP($P13&$D$2&" Curncy","PX_LAST"))),1) | S13: =IF($C13="","",_xll.BDP($C13,'Field Check'!$C$45))
A14: ALK AT | B14: 1079301950 | C14: =IF($A14="","",$A14&" Equity") | D14: =IF($A14="","",_xll.BDP($C14,"NAME")) | E14: =IF($A14="","",_xll.BDP($C14,"GICS_SECTOR_NAME")) | F14: =IF($A14="","",_xll.BDP($C14,"EQY_DVD_SH_12M")) | G14: =IF($A14="","",_xll.BDP($C14,"EQY_DVD_YLD_12M")) | H14: =IF($A14="","",_xll.BDP($C14,"EQY_DVD_YLD_IND")) | I14: =IF($A14="","",_xll.BDP($C14,'Field Check'!$C$4)) | J14: =IFERROR(IF($B14="","",IF(ISNUMBER($F14),$B14*$F14*$D$3/$B$3,0)),"") | K14: =IFERROR(IF($J14="","",$J14*IF(ISNUMBER($I14),$I14,'Index Summary'!$C$7)/100),"") | L14: =IFERROR(IF($K14="","",$J14-$K14),"") | N14: =IF($C14="","",IF(NOT(ISNUMBER($F14)),"No dividend",IF($F14=0,"No dividend",IF(ISNUMBER($I14),"OK","Frank assumed")))) | P14: =IF($N14="No dividend","",IF($C14="","",_xll.BDP($C14,'Field Check'!$C$43))) | Q14: =IFERROR(IF(LEN($P14)<>3,1,IF($P14=$D$2,1,_xll.BDP($P14&$D$2&" Curncy","PX_LAST"))),1) | S14: =IF($C14="","",_xll.BDP($C14,'Field Check'!$C$45))
A15: ALL AT | B15: 603067000 | C15: =IF($A15="","",$A15&" Equity") | D15: =IF($A15="","",_xll.BDP($C15,"NAME")) | E15: =IF($A15="","",_xll.BDP($C15,"GICS_SECTOR_NAME")) | F15: =IF($A15="","",_xll.BDP($C15,"EQY_DVD_SH_12M")) | G15: =IF($A15="","",_xll.BDP($C15,"EQY_DVD_YLD_12M")) | H15: =IF($A15="","",_xll.BDP($C15,"EQY_DVD_YLD_IND")) | I15: =IF($A15="","",_xll.BDP($C15,'Field Check'!$C$4)) | J15: =IFERROR(IF($B15="","",IF(ISNUMBER($F15),$B15*$F15*$D$3/$B$3,0)),"") | K15: =IFERROR(IF($J15="","",$J15*IF(ISNUMBER($I15),$I15,'Index Summary'!$C$7)/100),"") | L15: =IFERROR(IF($K15="","",$J15-$K15),"") | N15: =IF($C15="","",IF(NOT(ISNUMBER($F15)),"No dividend",IF($F15=0,"No dividend",IF(ISNUMBER($I15),"OK","Frank assumed")))) | P15: =IF($N15="No dividend","",IF($C15="","",_xll.BDP($C15,'Field Check'!$C$43))) | Q15: =IFERROR(IF(LEN($P15)<>3,1,IF($P15=$D$2,1,_xll.BDP($P15&$D$2&" Curncy","PX_LAST"))),1) | S15: =IF($C15="","",_xll.BDP($C15,'Field Check'!$C$45))
A16: ALQ AT | B16: 507543000 | C16: =IF($A16="","",$A16&" Equity") | D16: =IF($A16="","",_xll.BDP($C16,"NAME")) | E16: =IF($A16="","",_xll.BDP($C16,"GICS_SECTOR_NAME")) | F16: =IF($A16="","",_xll.BDP($C16,"EQY_DVD_SH_12M")) | G16: =IF($A16="","",_xll.BDP($C16,"EQY_DVD_YLD_12M")) | H16: =IF($A16="","",_xll.BDP($C16,"EQY_DVD_YLD_IND")) | I16: =IF($A16="","",_xll.BDP($C16,'Field Check'!$C$4)) | J16: =IFERROR(IF($B16="","",IF(ISNUMBER($F16),$B16*$F16*$D$3/$B$3,0)),"") | K16: =IFERROR(IF($J16="","",$J16*IF(ISNUMBER($I16),$I16,'Index Summary'!$C$7)/100),"") | L16: =IFERROR(IF($K16="","",$J16-$K16),"") | N16: =IF($C16="","",IF(NOT(ISNUMBER($F16)),"No dividend",IF($F16=0,"No dividend",IF(ISNUMBER($I16),"OK","Frank assumed")))) | P16: =IF($N16="No dividend","",IF($C16="","",_xll.BDP($C16,'Field Check'!$C$43))) | Q16: =IFERROR(IF(LEN($P16)<>3,1,IF($P16=$D$2,1,_xll.BDP($P16&$D$2&" Curncy","PX_LAST"))),1) | S16: =IF($C16="","",_xll.BDP($C16,'Field Check'!$C$45))
A17: ALX AT | B17: 464329280 | C17: =IF($A17="","",$A17&" Equity") | D17: =IF($A17="","",_xll.BDP($C17,"NAME")) | E17: =IF($A17="","",_xll.BDP($C17,"GICS_SECTOR_NAME")) | F17: =IF($A17="","",_xll.BDP($C17,"EQY_DVD_SH_12M")) | G17: =IF($A17="","",_xll.BDP($C17,"EQY_DVD_YLD_12M")) | H17: =IF($A17="","",_xll.BDP($C17,"EQY_DVD_YLD_IND")) | I17: =IF($A17="","",_xll.BDP($C17,'Field Check'!$C$4)) | J17: =IFERROR(IF($B17="","",IF(ISNUMBER($F17),$B17*$F17*$D$3/$B$3,0)),"") | K17: =IFERROR(IF($J17="","",$J17*IF(ISNUMBER($I17),$I17,'Index Summary'!$C$7)/100),"") | L17: =IFERROR(IF($K17="","",$J17-$K17),"") | N17: =IF($C17="","",IF(NOT(ISNUMBER($F17)),"No dividend",IF($F17=0,"No dividend",IF(ISNUMBER($I17),"OK","Frank assumed")))) | P17: =IF($N17="No dividend","",IF($C17="","",_xll.BDP($C17,'Field Check'!$C$43))) | Q17: =IFERROR(IF(LEN($P17)<>3,1,IF($P17=$D$2,1,_xll.BDP($P17&$D$2&" Curncy","PX_LAST"))),1) | S17: =IF($C17="","",_xll.BDP($C17,'Field Check'!$C$45))
A18: AMC AT | B18: 129179400 | C18: =IF($A18="","",$A18&" Equity") | D18: =IF($A18="","",_xll.BDP($C18,"NAME")) | E18: =IF($A18="","",_xll.BDP($C18,"GICS_SECTOR_NAME")) | F18: =IF($A18="","",_xll.BDP($C18,"EQY_DVD_SH_12M")) | G18: =IF($A18="","",_xll.BDP($C18,"EQY_DVD_YLD_12M")) | H18: =IF($A18="","",_xll.BDP($C18,"EQY_DVD_YLD_IND")) | I18: =IF($A18="","",_xll.BDP($C18,'Field Check'!$C$4)) | J18: =IFERROR(IF($B18="","",IF(ISNUMBER($F18),$B18*$F18*$D$3/$B$3,0)),"") | K18: =IFERROR(IF($J18="","",$J18*IF(ISNUMBER($I18),$I18,'Index Summary'!$C$7)/100),"") | L18: =IFERROR(IF($K18="","",$J18-$K18),"") | N18: =IF($C18="","",IF(NOT(ISNUMBER($F18)),"No dividend",IF($F18=0,"No dividend",IF(ISNUMBER($I18),"OK","Frank assumed")))) | P18: =IF($N18="No dividend","",IF($C18="","",_xll.BDP($C18,'Field Check'!$C$43))) | Q18: =IFERROR(IF(LEN($P18)<>3,1,IF($P18=$D$2,1,_xll.BDP($P18&$D$2&" Curncy","PX_LAST"))),1) | S18: =IF($C18="","",_xll.BDP($C18,'Field Check'!$C$45))
... A205: ZIP AT | B205: 1256897000 | C205: =IF($A205="","",$A205&" Equity") | D205: =IF($A205="","",_xll.BDP($C205,"NAME")) | E205: =IF($A205="","",_xll.BDP($C205,"GICS_SECTOR_NAME")) | F205: =IF($A205="","",_xll.BDP($C205,"EQY_DVD_SH_12M")) | G205: =IF($A205="","",_xll.BDP($C205,"EQY_DVD_YLD_12M")) | H205: =IF($A205="","",_xll.BDP($C205,"EQY_DVD_YLD_IND")) | I205: =IF($A205="","",_xll.BDP($C205,'Field Check'!$C$4)) | J205: =IFERROR(IF($B205="","",IF(ISNUMBER($F205),$B205*$F205*$D$3/$B$3,0)),"") | K205: =IFERROR(IF($J205="","",$J205*IF(ISNUMBER($I205),$I205,'Index Summary'!$C$7)/100),"") | L205: =IFERROR(IF($K205="","",$J205-$K205),"") | N205: =IF($C205="","",IF(NOT(ISNUMBER($F205)),"No dividend",IF($F205=0,"No dividend",IF(ISNUMBER($I205),"OK","Frank assumed")))) | P205: =IF($N205="No dividend","",IF($C205="","",_xll.BDP($C205,'Field Check'!$C$43))) | Q205: =IFERROR(IF(LEN($P205)<>3,1,IF($P205=$D$2,1,_xll.BDP($P205&$D$2&" Curncy","PX_LAST"))),1) | S205: =IF($C205="","",_xll.BDP($C205,'Field Check'!$C$45))
C206: =IF($A206="","",$A206&" Equity") | D206: =IF($A206="","",_xll.BDP($C206,"NAME")) | E206: =IF($A206="","",_xll.BDP($C206,"GICS_SECTOR_NAME")) | F206: =IF($A206="","",_xll.BDP($C206,"EQY_DVD_SH_12M")) | G206: =IF($A206="","",_xll.BDP($C206,"EQY_DVD_YLD_12M")) | H206: =IF($A206="","",_xll.BDP($C206,"EQY_DVD_YLD_IND")) | I206: =IF($A206="","",_xll.BDP($C206,'Field Check'!$C$4)) | J206: =IFERROR(IF($B206="","",IF(ISNUMBER($F206),$B206*$F206*$D$3/$B$3,0)),"") | K206: =IFERROR(IF($J206="","",$J206*IF(ISNUMBER($I206),$I206,'Index Summary'!$C$7)/100),"") | L206: =IFERROR(IF($K206="","",$J206-$K206),"") | N206: =IF($C206="","",IF(NOT(ISNUMBER($F206)),"No dividend",IF($F206=0,"No dividend",IF(ISNUMBER($I206),"OK","Frank assumed")))) | P206: =IF($N206="No dividend","",IF($C206="","",_xll.BDP($C206,'Field Check'!$C$43))) | Q206: =IFERROR(IF(LEN($P206)<>3,1,IF($P206=$D$2,1,_xll.BDP($P206&$D$2&" Curncy","PX_LAST"))),1) | S206: =IF($C206="","",_xll.BDP($C206,'Field Check'!$C$45))
C207: =IF($A207="","",$A207&" Equity") | D207: =IF($A207="","",_xll.BDP($C207,"NAME")) | E207: =IF($A207="","",_xll.BDP($C207,"GICS_SECTOR_NAME")) | F207: =IF($A207="","",_xll.BDP($C207,"EQY_DVD_SH_12M")) | G207: =IF($A207="","",_xll.BDP($C207,"EQY_DVD_YLD_12M")) | H207: =IF($A207="","",_xll.BDP($C207,"EQY_DVD_YLD_IND")) | I207: =IF($A207="","",_xll.BDP($C207,'Field Check'!$C$4)) | J207: =IFERROR(IF($B207="","",IF(ISNUMBER($F207),$B207*$F207*$D$3/$B$3,0)),"") | K207: =IFERROR(IF($J207="","",$J207*IF(ISNUMBER($I207),$I207,'Index Summary'!$C$7)/100),"") | L207: =IFERROR(IF($K207="","",$J207-$K207),"") | N207: =IF($C207="","",IF(NOT(ISNUMBER($F207)),"No dividend",IF($F207=0,"No dividend",IF(ISNUMBER($I207),"OK","Frank assumed")))) | P207: =IF($N207="No dividend","",IF($C207="","",_xll.BDP($C207,'Field Check'!$C$43))) | Q207: =IFERROR(IF(LEN($P207)<>3,1,IF($P207=$D$2,1,_xll.BDP($P207&$D$2&" Curncy","PX_LAST"))),1) | S207: =IF($C207="","",_xll.BDP($C207,'Field Check'!$C$45))
C208: =IF($A208="","",$A208&" Equity") | D208: =IF($A208="","",_xll.BDP($C208,"NAME")) | E208: =IF($A208="","",_xll.BDP($C208,"GICS_SECTOR_NAME")) | F208: =IF($A208="","",_xll.BDP($C208,"EQY_DVD_SH_12M")) | G208: =IF($A208="","",_xll.BDP($C208,"EQY_DVD_YLD_12M")) | H208: =IF($A208="","",_xll.BDP($C208,"EQY_DVD_YLD_IND")) | I208: =IF($A208="","",_xll.BDP($C208,'Field Check'!$C$4)) | J208: =IFERROR(IF($B208="","",IF(ISNUMBER($F208),$B208*$F208*$D$3/$B$3,0)),"") | K208: =IFERROR(IF($J208="","",$J208*IF(ISNUMBER($I208),$I208,'Index Summary'!$C$7)/100),"") | L208: =IFERROR(IF($K208="","",$J208-$K208),"") | N208: =IF($C208="","",IF(NOT(ISNUMBER($F208)),"No dividend",IF($F208=0,"No dividend",IF(ISNUMBER($I208),"OK","Frank assumed")))) | P208: =IF($N208="No dividend","",IF($C208="","",_xll.BDP($C208,'Field Check'!$C$43))) | Q208: =IFERROR(IF(LEN($P208)<>3,1,IF($P208=$D$2,1,_xll.BDP($P208&$D$2&" Curncy","PX_LAST"))),1) | S208: =IF($C208="","",_xll.BDP($C208,'Field Check'!$C$45))
C209: =IF($A209="","",$A209&" Equity") | D209: =IF($A209="","",_xll.BDP($C209,"NAME")) | E209: =IF($A209="","",_xll.BDP($C209,"GICS_SECTOR_NAME")) | F209: =IF($A209="","",_xll.BDP($C209,"EQY_DVD_SH_12M")) | G209: =IF($A209="","",_xll.BDP($C209,"EQY_DVD_YLD_12M")) | H209: =IF($A209="","",_xll.BDP($C209,"EQY_DVD_YLD_IND")) | I209: =IF($A209="","",_xll.BDP($C209,'Field Check'!$C$4)) | J209: =IFERROR(IF($B209="","",IF(ISNUMBER($F209),$B209*$F209*$D$3/$B$3,0)),"") | K209: =IFERROR(IF($J209="","",$J209*IF(ISNUMBER($I209),$I209,'Index Summary'!$C$7)/100),"") | L209: =IFERROR(IF($K209="","",$J209-$K209),"") | N209: =IF($C209="","",IF(NOT(ISNUMBER($F209)),"No dividend",IF($F209=0,"No dividend",IF(ISNUMBER($I209),"OK","Frank assumed")))) | P209: =IF($N209="No dividend","",IF($C209="","",_xll.BDP($C209,'Field Check'!$C$43))) | Q209: =IFERROR(IF(LEN($P209)<>3,1,IF($P209=$D$2,1,_xll.BDP($P209&$D$2&" Curncy","PX_LAST"))),1) | S209: =IF($C209="","",_xll.BDP($C209,'Field Check'!$C$45))
C210: =IF($A210="","",$A210&" Equity") | D210: =IF($A210="","",_xll.BDP($C210,"NAME")) | E210: =IF($A210="","",_xll.BDP($C210,"GICS_SECTOR_NAME")) | F210: =IF($A210="","",_xll.BDP($C210,"EQY_DVD_SH_12M")) | G210: =IF($A210="","",_xll.BDP($C210,"EQY_DVD_YLD_12M")) | H210: =IF($A210="","",_xll.BDP($C210,"EQY_DVD_YLD_IND")) | I210: =IF($A210="","",_xll.BDP($C210,'Field Check'!$C$4)) | J210: =IFERROR(IF($B210="","",IF(ISNUMBER($F210),$B210*$F210*$D$3/$B$3,0)),"") | K210: =IFERROR(IF($J210="","",$J210*IF(ISNUMBER($I210),$I210,'Index Summary'!$C$7)/100),"") | L210: =IFERROR(IF($K210="","",$J210-$K210),"") | N210: =IF($C210="","",IF(NOT(ISNUMBER($F210)),"No dividend",IF($F210=0,"No dividend",IF(ISNUMBER($I210),"OK","Frank assumed")))) | P210: =IF($N210="No dividend","",IF($C210="","",_xll.BDP($C210,'Field Check'!$C$43))) | Q210: =IFERROR(IF(LEN($P210)<>3,1,IF($P210=$D$2,1,_xll.BDP($P210&$D$2&" Curncy","PX_LAST"))),1) | S210: =IF($C210="","",_xll.BDP($C210,'Field Check'!$C$45))
C211: =IF($A211="","",$A211&" Equity") | D211: =IF($A211="","",_xll.BDP($C211,"NAME")) | E211: =IF($A211="","",_xll.BDP($C211,"GICS_SECTOR_NAME")) | F211: =IF($A211="","",_xll.BDP($C211,"EQY_DVD_SH_12M")) | G211: =IF($A211="","",_xll.BDP($C211,"EQY_DVD_YLD_12M")) | H211: =IF($A211="","",_xll.BDP($C211,"EQY_DVD_YLD_IND")) | I211: =IF($A211="","",_xll.BDP($C211,'Field Check'!$C$4)) | J211: =IFERROR(IF($B211="","",IF(ISNUMBER($F211),$B211*$F211*$D$3/$B$3,0)),"") | K211: =IFERROR(IF($J211="","",$J211*IF(ISNUMBER($I211),$I211,'Index Summary'!$C$7)/100),"") | L211: =IFERROR(IF($K211="","",$J211-$K211),"") | N211: =IF($C211="","",IF(NOT(ISNUMBER($F211)),"No dividend",IF($F211=0,"No dividend",IF(ISNUMBER($I211),"OK","Frank assumed")))) | P211: =IF($N211="No dividend","",IF($C211="","",_xll.BDP($C211,'Field Check'!$C$43))) | Q211: =IFERROR(IF(LEN($P211)<>3,1,IF($P211=$D$2,1,_xll.BDP($P211&$D$2&" Curncy","PX_LAST"))),1) | S211: =IF($C211="","",_xll.BDP($C211,'Field Check'!$C$45))
C212: =IF($A212="","",$A212&" Equity") | D212: =IF($A212="","",_xll.BDP($C212,"NAME")) | E212: =IF($A212="","",_xll.BDP($C212,"GICS_SECTOR_NAME")) | F212: =IF($A212="","",_xll.BDP($C212,"EQY_DVD_SH_12M")) | G212: =IF($A212="","",_xll.BDP($C212,"EQY_DVD_YLD_12M")) | H212: =IF($A212="","",_xll.BDP($C212,"EQY_DVD_YLD_IND")) | I212: =IF($A212="","",_xll.BDP($C212,'Field Check'!$C$4)) | J212: =IFERROR(IF($B212="","",IF(ISNUMBER($F212),$B212*$F212*$D$3/$B$3,0)),"") | K212: =IFERROR(IF($J212="","",$J212*IF(ISNUMBER($I212),$I212,'Index Summary'!$C$7)/100),"") | L212: =IFERROR(IF($K212="","",$J212-$K212),"") | N212: =IF($C212="","",IF(NOT(ISNUMBER($F212)),"No dividend",IF($F212=0,"No dividend",IF(ISNUMBER($I212),"OK","Frank assumed")))) | P212: =IF($N212="No dividend","",IF($C212="","",_xll.BDP($C212,'Field Check'!$C$43))) | Q212: =IFERROR(IF(LEN($P212)<>3,1,IF($P212=$D$2,1,_xll.BDP($P212&$D$2&" Curncy","PX_LAST"))),1) | S212: =IF($C212="","",_xll.BDP($C212,'Field Check'!$C$45))
C213: =IF($A213="","",$A213&" Equity") | D213: =IF($A213="","",_xll.BDP($C213,"NAME")) | E213: =IF($A213="","",_xll.BDP($C213,"GICS_SECTOR_NAME")) | F213: =IF($A213="","",_xll.BDP($C213,"EQY_DVD_SH_12M")) | G213: =IF($A213="","",_xll.BDP($C213,"EQY_DVD_YLD_12M")) | H213: =IF($A213="","",_xll.BDP($C213,"EQY_DVD_YLD_IND")) | I213: =IF($A213="","",_xll.BDP($C213,'Field Check'!$C$4)) | J213: =IFERROR(IF($B213="","",IF(ISNUMBER($F213),$B213*$F213*$D$3/$B$3,0)),"") | K213: =IFERROR(IF($J213="","",$J213*IF(ISNUMBER($I213),$I213,'Index Summary'!$C$7)/100),"") | L213: =IFERROR(IF($K213="","",$J213-$K213),"") | N213: =IF($C213="","",IF(NOT(ISNUMBER($F213)),"No dividend",IF($F213=0,"No dividend",IF(ISNUMBER($I213),"OK","Frank assumed")))) | P213: =IF($N213="No dividend","",IF($C213="","",_xll.BDP($C213,'Field Check'!$C$43))) | Q213: =IFERROR(IF(LEN($P213)<>3,1,IF($P213=$D$2,1,_xll.BDP($P213&$D$2&" Curncy","PX_LAST"))),1) | S213: =IF($C213="","",_xll.BDP($C213,'Field Check'!$C$45))
C214: =IF($A214="","",$A214&" Equity") | D214: =IF($A214="","",_xll.BDP($C214,"NAME")) | E214: =IF($A214="","",_xll.BDP($C214,"GICS_SECTOR_NAME")) | F214: =IF($A214="","",_xll.BDP($C214,"EQY_DVD_SH_12M")) | G214: =IF($A214="","",_xll.BDP($C214,"EQY_DVD_YLD_12M")) | H214: =IF($A214="","",_xll.BDP($C214,"EQY_DVD_YLD_IND")) | I214: =IF($A214="","",_xll.BDP($C214,'Field Check'!$C$4)) | J214: =IFERROR(IF($B214="","",IF(ISNUMBER($F214),$B214*$F214*$D$3/$B$3,0)),"") | K214: =IFERROR(IF($J214="","",$J214*IF(ISNUMBER($I214),$I214,'Index Summary'!$C$7)/100),"") | L214: =IFERROR(IF($K214="","",$J214-$K214),"") | N214: =IF($C214="","",IF(NOT(ISNUMBER($F214)),"No dividend",IF($F214=0,"No dividend",IF(ISNUMBER($I214),"OK","Frank assumed")))) | P214: =IF($N214="No dividend","",IF($C214="","",_xll.BDP($C214,'Field Check'!$C$43))) | Q214: =IFERROR(IF(LEN($P214)<>3,1,IF($P214=$D$2,1,_xll.BDP($P214&$D$2&" Curncy","PX_LAST"))),1) | S214: =IF($C214="","",_xll.BDP($C214,'Field Check'!$C$45))
C215: =IF($A215="","",$A215&" Equity") | D215: =IF($A215="","",_xll.BDP($C215,"NAME")) | E215: =IF($A215="","",_xll.BDP($C215,"GICS_SECTOR_NAME")) | F215: =IF($A215="","",_xll.BDP($C215,"EQY_DVD_SH_12M")) | G215: =IF($A215="","",_xll.BDP($C215,"EQY_DVD_YLD_12M")) | H215: =IF($A215="","",_xll.BDP($C215,"EQY_DVD_YLD_IND")) | I215: =IF($A215="","",_xll.BDP($C215,'Field Check'!$C$4)) | J215: =IFERROR(IF($B215="","",IF(ISNUMBER($F215),$B215*$F215*$D$3/$B$3,0)),"") | K215: =IFERROR(IF($J215="","",$J215*IF(ISNUMBER($I215),$I215,'Index Summary'!$C$7)/100),"") | L215: =IFERROR(IF($K215="","",$J215-$K215),"") | N215: =IF($C215="","",IF(NOT(ISNUMBER($F215)),"No dividend",IF($F215=0,"No dividend",IF(ISNUMBER($I215),"OK","Frank assumed")))) | P215: =IF($N215="No dividend","",IF($C215="","",_xll.BDP($C215,'Field Check'!$C$43))) | Q215: =IFERROR(IF(LEN($P215)<>3,1,IF($P215=$D$2,1,_xll.BDP($P215&$D$2&" Curncy","PX_LAST"))),1) | S215: =IF($C215="","",_xll.BDP($C215,'Field Check'!$C$45))
C216: =IF($A216="","",$A216&" Equity") | D216: =IF($A216="","",_xll.BDP($C216,"NAME")) | E216: =IF($A216="","",_xll.BDP($C216,"GICS_SECTOR_NAME")) | F216: =IF($A216="","",_xll.BDP($C216,"EQY_DVD_SH_12M")) | G216: =IF($A216="","",_xll.BDP($C216,"EQY_DVD_YLD_12M")) | H216: =IF($A216="","",_xll.BDP($C216,"EQY_DVD_YLD_IND")) | I216: =IF($A216="","",_xll.BDP($C216,'Field Check'!$C$4)) | J216: =IFERROR(IF($B216="","",IF(ISNUMBER($F216),$B216*$F216*$D$3/$B$3,0)),"") | K216: =IFERROR(IF($J216="","",$J216*IF(ISNUMBER($I216),$I216,'Index Summary'!$C$7)/100),"") | L216: =IFERROR(IF($K216="","",$J216-$K216),"") | N216: =IF($C216="","",IF(NOT(ISNUMBER($F216)),"No dividend",IF($F216=0,"No dividend",IF(ISNUMBER($I216),"OK","Frank assumed")))) | P216: =IF($N216="No dividend","",IF($C216="","",_xll.BDP($C216,'Field Check'!$C$43))) | Q216: =IFERROR(IF(LEN($P216)<>3,1,IF($P216=$D$2,1,_xll.BDP($P216&$D$2&" Curncy","PX_LAST"))),1) | S216: =IF($C216="","",_xll.BDP($C216,'Field Check'!$C$45))
C217: =IF($A217="","",$A217&" Equity") | D217: =IF($A217="","",_xll.BDP($C217,"NAME")) | E217: =IF($A217="","",_xll.BDP($C217,"GICS_SECTOR_NAME")) | F217: =IF($A217="","",_xll.BDP($C217,"EQY_DVD_SH_12M")) | G217: =IF($A217="","",_xll.BDP($C217,"EQY_DVD_YLD_12M")) | H217: =IF($A217="","",_xll.BDP($C217,"EQY_DVD_YLD_IND")) | I217: =IF($A217="","",_xll.BDP($C217,'Field Check'!$C$4)) | J217: =IFERROR(IF($B217="","",IF(ISNUMBER($F217),$B217*$F217*$D$3/$B$3,0)),"") | K217: =IFERROR(IF($J217="","",$J217*IF(ISNUMBER($I217),$I217,'Index Summary'!$C$7)/100),"") | L217: =IFERROR(IF($K217="","",$J217-$K217),"") | N217: =IF($C217="","",IF(NOT(ISNUMBER($F217)),"No dividend",IF($F217=0,"No dividend",IF(ISNUMBER($I217),"OK","Frank assumed")))) | P217: =IF($N217="No dividend","",IF($C217="","",_xll.BDP($C217,'Field Check'!$C$43))) | Q217: =IFERROR(IF(LEN($P217)<>3,1,IF($P217=$D$2,1,_xll.BDP($P217&$D$2&" Curncy","PX_LAST"))),1) | S217: =IF($C217="","",_xll.BDP($C217,'Field Check'!$C$45))
... C275: =IF($A275="","",$A275&" Equity") | D275: =IF($A275="","",_xll.BDP($C275,"NAME")) | E275: =IF($A275="","",_xll.BDP($C275,"GICS_SECTOR_NAME")) | F275: =IF($A275="","",_xll.BDP($C275,"EQY_DVD_SH_12M")) | G275: =IF($A275="","",_xll.BDP($C275,"EQY_DVD_YLD_12M")) | H275: =IF($A275="","",_xll.BDP($C275,"EQY_DVD_YLD_IND")) | I275: =IF($A275="","",_xll.BDP($C275,'Field Check'!$C$4)) | J275: =IFERROR(IF($B275="","",IF(ISNUMBER($F275),$B275*$F275*$D$3/$B$3,0)),"") | K275: =IFERROR(IF($J275="","",$J275*IF(ISNUMBER($I275),$I275,'Index Summary'!$C$7)/100),"") | L275: =IFERROR(IF($K275="","",$J275-$K275),"") | N275: =IF($C275="","",IF(NOT(ISNUMBER($F275)),"No dividend",IF($F275=0,"No dividend",IF(ISNUMBER($I275),"OK","Frank assumed")))) | P275: =IF($N275="No dividend","",IF($C275="","",_xll.BDP($C275,'Field Check'!$C$43))) | Q275: =IFERROR(IF(LEN($P275)<>3,1,IF($P275=$D$2,1,_xll.BDP($P275&$D$2&" Curncy","PX_LAST"))),1) | S275: =IF($C275="","",_xll.BDP($C275,'Field Check'!$C$45))

Sheet MXAU
A1: MSCI Australia (MXAU) - MEMBERS, DIVIDENDS & FRANKING
A2: Index ticker | B2: MXAU Index | C2: Index ccy | D2: AUD | E2: Members returned | H2: =SUMPRODUCT(($A$6:$A$175<>"")*1) | J2: No dividend | L2: =COUNTIF($N$6:$N$175,"No dividend") | M2: =IF($H$2=$H$3+$L$2,"reconciles","CHECK: status counts do not sum to members") | O2: No shares data needed: paste WEIGHT % (T) and snapshot PRICE (U) per stock, the index level at that snapshot (U2), and the price-ccy -> USD cross (U3; leave blank if prices are already USD). Shares derive automatically - the divisor cancels out of the maths. | T2: Level @ snapshot | U2: 1826.12
A3: Index divisor | B3: 1 | C3: AUD -> index ccy | D3: =IF($D$2="AUD",1,_xll.BDP("AUD"&$D$2&" Curncy","PX_LAST")) | E3: Dividend payers | H3: =COUNTIF($N$6:$N$175,"OK")+COUNTIF($N$6:$N$175,"Frank assumed") | J3: Frank assumed | L3: =COUNTIF($N$6:$N$175,"Frank assumed") | M3: <- no franking value returned, taken as 100% franked. | O3: D3 converts the reference DPS column (AUD) into the index currency for the points maths. | T3: price ccy -> USD
A4: TOTALS | J4: =IFERROR(SUM($J$6:$J$175),"") | K4: =IFERROR(SUM($K$6:$K$175),"") | L4: =IFERROR(SUM($L$6:$L$175),"") | N4: =IFERROR(SUMIF($N$6:$N$175,"OK",$J$6:$J$175)/$J$4,"") | O4: <- FRANKING REPORTED: share of 12M dividend points where Bloomberg returned a franking value. The rest are assumed fully franked.
A5: Member Ticker | B5: Eff. shares (auto) | C5: Bloomberg Ticker | D5: Company Name | E5: GICS Sector | F5: DPS 12M | G5: Div Yld 12M (%) | H5: Div Yld Ind (%) | I5: Franked (%) | J5: Dvd 12M (pts) | K5: Franked (pts) | L5: Unfranked (pts) | N5: Status | P5: Dvd CCY | Q5: Dvd FX | S5: Next earnings | T5: Weight (%) | U5: Price @ snapshot
A6: N/A | B6: =IF(COUNT($T6,$U6)=2,$U$2*$T6/100/($U6*IF($U$3="",1,$U$3)),"") | C6: FMG AT Equity | D6: =IF($A6="","",_xll.BDP($C6,"NAME")) | E6: =IF($A6="","",_xll.BDP($C6,"GICS_SECTOR_NAME")) | F6: =IF($A6="","",_xll.BDP($C6,"EQY_DVD_SH_12M")) | G6: =IF($A6="","",_xll.BDP($C6,"EQY_DVD_YLD_12M")) | H6: =IF($A6="","",_xll.BDP($C6,"EQY_DVD_YLD_IND")) | I6: =IF($A6="","",_xll.BDP($C6,'Field Check'!$C$4)) | J6: =IFERROR(IF($B6="","",IF(ISNUMBER($F6),$B6*$F6*$D$3/$B$3,0)),"") | K6: =IFERROR(IF($J6="","",$J6*IF(ISNUMBER($I6),$I6,'Index Summary'!$C$7)/100),"") | L6: =IFERROR(IF($K6="","",$J6-$K6),"") | N6: =IF($C6="","",IF(NOT(ISNUMBER($F6)),"No dividend",IF($F6=0,"No dividend",IF(ISNUMBER($I6),"OK","Frank assumed")))) | P6: =IF($N6="No dividend","",IF($C6="","",_xll.BDP($C6,'Field Check'!$C$43))) | Q6: =IFERROR(IF(LEN($P6)<>3,1,IF($P6=$D$2,1,_xll.BDP($P6&$D$2&" Curncy","PX_LAST"))),1) | S6: =IF($C6="","",_xll.BDP($C6,'Field Check'!$C$45)) | T6: 1.3613892 | U6: 18.02
A7: N/A | B7: =IF(COUNT($T7,$U7)=2,$U$2*$T7/100/($U7*IF($U$3="",1,$U$3)),"") | C7: IAG AT Equity | D7: =IF($A7="","",_xll.BDP($C7,"NAME")) | E7: =IF($A7="","",_xll.BDP($C7,"GICS_SECTOR_NAME")) | F7: =IF($A7="","",_xll.BDP($C7,"EQY_DVD_SH_12M")) | G7: =IF($A7="","",_xll.BDP($C7,"EQY_DVD_YLD_12M")) | H7: =IF($A7="","",_xll.BDP($C7,"EQY_DVD_YLD_IND")) | I7: =IF($A7="","",_xll.BDP($C7,'Field Check'!$C$4)) | J7: =IFERROR(IF($B7="","",IF(ISNUMBER($F7),$B7*$F7*$D$3/$B$3,0)),"") | K7: =IFERROR(IF($J7="","",$J7*IF(ISNUMBER($I7),$I7,'Index Summary'!$C$7)/100),"") | L7: =IFERROR(IF($K7="","",$J7-$K7),"") | N7: =IF($C7="","",IF(NOT(ISNUMBER($F7)),"No dividend",IF($F7=0,"No dividend",IF(ISNUMBER($I7),"OK","Frank assumed")))) | P7: =IF($N7="No dividend","",IF($C7="","",_xll.BDP($C7,'Field Check'!$C$43))) | Q7: =IFERROR(IF(LEN($P7)<>3,1,IF($P7=$D$2,1,_xll.BDP($P7&$D$2&" Curncy","PX_LAST"))),1) | S7: =IF($C7="","",_xll.BDP($C7,'Field Check'!$C$45)) | T7: 0.90053688 | U7: 8.63
A8: N/A | B8: =IF(COUNT($T8,$U8)=2,$U$2*$T8/100/($U8*IF($U$3="",1,$U$3)),"") | C8: SUN AT Equity | D8: =IF($A8="","",_xll.BDP($C8,"NAME")) | E8: =IF($A8="","",_xll.BDP($C8,"GICS_SECTOR_NAME")) | F8: =IF($A8="","",_xll.BDP($C8,"EQY_DVD_SH_12M")) | G8: =IF($A8="","",_xll.BDP($C8,"EQY_DVD_YLD_12M")) | H8: =IF($A8="","",_xll.BDP($C8,"EQY_DVD_YLD_IND")) | I8: =IF($A8="","",_xll.BDP($C8,'Field Check'!$C$4)) | J8: =IFERROR(IF($B8="","",IF(ISNUMBER($F8),$B8*$F8*$D$3/$B$3,0)),"") | K8: =IFERROR(IF($J8="","",$J8*IF(ISNUMBER($I8),$I8,'Index Summary'!$C$7)/100),"") | L8: =IFERROR(IF($K8="","",$J8-$K8),"") | N8: =IF($C8="","",IF(NOT(ISNUMBER($F8)),"No dividend",IF($F8=0,"No dividend",IF(ISNUMBER($I8),"OK","Frank assumed")))) | P8: =IF($N8="No dividend","",IF($C8="","",_xll.BDP($C8,'Field Check'!$C$43))) | Q8: =IFERROR(IF(LEN($P8)<>3,1,IF($P8=$D$2,1,_xll.BDP($P8&$D$2&" Curncy","PX_LAST"))),1) | S8: =IF($C8="","",_xll.BDP($C8,'Field Check'!$C$45)) | T8: 0.97880359 | U8: 19.34
A9: N/A | B9: =IF(COUNT($T9,$U9)=2,$U$2*$T9/100/($U9*IF($U$3="",1,$U$3)),"") | C9: ASX AT Equity | D9: =IF($A9="","",_xll.BDP($C9,"NAME")) | E9: =IF($A9="","",_xll.BDP($C9,"GICS_SECTOR_NAME")) | F9: =IF($A9="","",_xll.BDP($C9,"EQY_DVD_SH_12M")) | G9: =IF($A9="","",_xll.BDP($C9,"EQY_DVD_YLD_12M")) | H9: =IF($A9="","",_xll.BDP($C9,"EQY_DVD_YLD_IND")) | I9: =IF($A9="","",_xll.BDP($C9,'Field Check'!$C$4)) | J9: =IFERROR(IF($B9="","",IF(ISNUMBER($F9),$B9*$F9*$D$3/$B$3,0)),"") | K9: =IFERROR(IF($J9="","",$J9*IF(ISNUMBER($I9),$I9,'Index Summary'!$C$7)/100),"") | L9: =IFERROR(IF($K9="","",$J9-$K9),"") | N9: =IF($C9="","",IF(NOT(ISNUMBER($F9)),"No dividend",IF($F9=0,"No dividend",IF(ISNUMBER($I9),"OK","Frank assumed")))) | P9: =IF($N9="No dividend","",IF($C9="","",_xll.BDP($C9,'Field Check'!$C$43))) | Q9: =IFERROR(IF(LEN($P9)<>3,1,IF($P9=$D$2,1,_xll.BDP($P9&$D$2&" Curncy","PX_LAST"))),1) | S9: =IF($C9="","",_xll.BDP($C9,'Field Check'!$C$45)) | T9: 0.52605652 | U9: 57.6
A10: N/A | B10: =IF(COUNT($T10,$U10)=2,$U$2*$T10/100/($U10*IF($U$3="",1,$U$3)),"") | C10: BHP AT Equity | D10: =IF($A10="","",_xll.BDP($C10,"NAME")) | E10: =IF($A10="","",_xll.BDP($C10,"GICS_SECTOR_NAME")) | F10: =IF($A10="","",_xll.BDP($C10,"EQY_DVD_SH_12M")) | G10: =IF($A10="","",_xll.BDP($C10,"EQY_DVD_YLD_12M")) | H10: =IF($A10="","",_xll.BDP($C10,"EQY_DVD_YLD_IND")) | I10: =IF($A10="","",_xll.BDP($C10,'Field Check'!$C$4)) | J10: =IFERROR(IF($B10="","",IF(ISNUMBER($F10),$B10*$F10*$D$3/$B$3,0)),"") | K10: =IFERROR(IF($J10="","",$J10*IF(ISNUMBER($I10),$I10,'Index Summary'!$C$7)/100),"") | L10: =IFERROR(IF($K10="","",$J10-$K10),"") | N10: =IF($C10="","",IF(NOT(ISNUMBER($F10)),"No dividend",IF($F10=0,"No dividend",IF(ISNUMBER($I10),"OK","Frank assumed")))) | P10: =IF($N10="No dividend","",IF($C10="","",_xll.BDP($C10,'Field Check'!$C$43))) | Q10: =IFERROR(IF(LEN($P10)<>3,1,IF($P10=$D$2,1,_xll.BDP($P10&$D$2&" Curncy","PX_LAST"))),1) | S10: =IF($C10="","",_xll.BDP($C10,'Field Check'!$C$45)) | T10: 14.954773 | U10: 62.97
A11: N/A | B11: =IF(COUNT($T11,$U11)=2,$U$2*$T11/100/($U11*IF($U$3="",1,$U$3)),"") | C11: ANZ AT Equity | D11: =IF($A11="","",_xll.BDP($C11,"NAME")) | E11: =IF($A11="","",_xll.BDP($C11,"GICS_SECTOR_NAME")) | F11: =IF($A11="","",_xll.BDP($C11,"EQY_DVD_SH_12M")) | G11: =IF($A11="","",_xll.BDP($C11,"EQY_DVD_YLD_12M")) | H11: =IF($A11="","",_xll.BDP($C11,"EQY_DVD_YLD_IND")) | I11: =IF($A11="","",_xll.BDP($C11,'Field Check'!$C$4)) | J11: =IFERROR(IF($B11="","",IF(ISNUMBER($F11),$B11*$F11*$D$3/$B$3,0)),"") | K11: =IFERROR(IF($J11="","",$J11*IF(ISNUMBER($I11),$I11,'Index Summary'!$C$7)/100),"") | L11: =IFERROR(IF($K11="","",$J11-$K11),"") | N11: =IF($C11="","",IF(NOT(ISNUMBER($F11)),"No dividend",IF($F11=0,"No dividend",IF(ISNUMBER($I11),"OK","Frank assumed")))) | P11: =IF($N11="No dividend","",IF($C11="","",_xll.BDP($C11,'Field Check'!$C$43))) | Q11: =IFERROR(IF(LEN($P11)<>3,1,IF($P11=$D$2,1,_xll.BDP($P11&$D$2&" Curncy","PX_LAST"))),1) | S11: =IF($C11="","",_xll.BDP($C11,'Field Check'!$C$45)) | T11: 5.3152314 | U11: 37.73
A12: N/A | B12: =IF(COUNT($T12,$U12)=2,$U$2*$T12/100/($U12*IF($U$3="",1,$U$3)),"") | C12: BXB AT Equity | D12: =IF($A12="","",_xll.BDP($C12,"NAME")) | E12: =IF($A12="","",_xll.BDP($C12,"GICS_SECTOR_NAME")) | F12: =IF($A12="","",_xll.BDP($C12,"EQY_DVD_SH_12M")) | G12: =IF($A12="","",_xll.BDP($C12,"EQY_DVD_YLD_12M")) | H12: =IF($A12="","",_xll.BDP($C12,"EQY_DVD_YLD_IND")) | I12: =IF($A12="","",_xll.BDP($C12,'Field Check'!$C$4)) | J12: =IFERROR(IF($B12="","",IF(ISNUMBER($F12),$B12*$F12*$D$3/$B$3,0)),"") | K12: =IFERROR(IF($J12="","",$J12*IF(ISNUMBER($I12),$I12,'Index Summary'!$C$7)/100),"") | L12: =IFERROR(IF($K12="","",$J12-$K12),"") | N12: =IF($C12="","",IF(NOT(ISNUMBER($F12)),"No dividend",IF($F12=0,"No dividend",IF(ISNUMBER($I12),"OK","Frank assumed")))) | P12: =IF($N12="No dividend","",IF($C12="","",_xll.BDP($C12,'Field Check'!$C$43))) | Q12: =IFERROR(IF(LEN($P12)<>3,1,IF($P12=$D$2,1,_xll.BDP($P12&$D$2&" Curncy","PX_LAST"))),1) | S12: =IF($C12="","",_xll.BDP($C12,'Field Check'!$C$45)) | T12: 1.2841309 | U12: 20.35
A13: N/A | B13: =IF(COUNT($T13,$U13)=2,$U$2*$T13/100/($U13*IF($U$3="",1,$U$3)),"") | C13: CBA AT Equity | D13: =IF($A13="","",_xll.BDP($C13,"NAME")) | E13: =IF($A13="","",_xll.BDP($C13,"GICS_SECTOR_NAME")) | F13: =IF($A13="","",_xll.BDP($C13,"EQY_DVD_SH_12M")) | G13: =IF($A13="","",_xll.BDP($C13,"EQY_DVD_YLD_12M")) | H13: =IF($A13="","",_xll.BDP($C13,"EQY_DVD_YLD_IND")) | I13: =IF($A13="","",_xll.BDP($C13,'Field Check'!$C$4)) | J13: =IFERROR(IF($B13="","",IF(ISNUMBER($F13),$B13*$F13*$D$3/$B$3,0)),"") | K13: =IFERROR(IF($J13="","",$J13*IF(ISNUMBER($I13),$I13,'Index Summary'!$C$7)/100),"") | L13: =IFERROR(IF($K13="","",$J13-$K13),"") | N13: =IF($C13="","",IF(NOT(ISNUMBER($F13)),"No dividend",IF($F13=0,"No dividend",IF(ISNUMBER($I13),"OK","Frank assumed")))) | P13: =IF($N13="No dividend","",IF($C13="","",_xll.BDP($C13,'Field Check'!$C$43))) | Q13: =IFERROR(IF(LEN($P13)<>3,1,IF($P13=$D$2,1,_xll.BDP($P13&$D$2&" Curncy","PX_LAST"))),1) | S13: =IF($C13="","",_xll.BDP($C13,'Field Check'!$C$45)) | T13: 13.922711 | U13: 178.01
A14: N/A | B14: =IF(COUNT($T14,$U14)=2,$U$2*$T14/100/($U14*IF($U$3="",1,$U$3)),"") | C14: COH AT Equity | D14: =IF($A14="","",_xll.BDP($C14,"NAME")) | E14: =IF($A14="","",_xll.BDP($C14,"GICS_SECTOR_NAME")) | F14: =IF($A14="","",_xll.BDP($C14,"EQY_DVD_SH_12M")) | G14: =IF($A14="","",_xll.BDP($C14,"EQY_DVD_YLD_12M")) | H14: =IF($A14="","",_xll.BDP($C14,"EQY_DVD_YLD_IND")) | I14: =IF($A14="","",_xll.BDP($C14,'Field Check'!$C$4)) | J14: =IFERROR(IF($B14="","",IF(ISNUMBER($F14),$B14*$F14*$D$3/$B$3,0)),"") | K14: =IFERROR(IF($J14="","",$J14*IF(ISNUMBER($I14),$I14,'Index Summary'!$C$7)/100),"") | L14: =IFERROR(IF($K14="","",$J14-$K14),"") | N14: =IF($C14="","",IF(NOT(ISNUMBER($F14)),"No dividend",IF($F14=0,"No dividend",IF(ISNUMBER($I14),"OK","Frank assumed")))) | P14: =IF($N14="No dividend","",IF($C14="","",_xll.BDP($C14,'Field Check'!$C$43))) | Q14: =IFERROR(IF(LEN($P14)<>3,1,IF($P14=$D$2,1,_xll.BDP($P14&$D$2&" Curncy","PX_LAST"))),1) | S14: =IF($C14="","",_xll.BDP($C14,'Field Check'!$C$45)) | T14: 0.38164286 | U14: 124.86
A15: N/A | B15: =IF(COUNT($T15,$U15)=2,$U$2*$T15/100/($U15*IF($U$3="",1,$U$3)),"") | C15: VCX AT Equity | D15: =IF($A15="","",_xll.BDP($C15,"NAME")) | E15: =IF($A15="","",_xll.BDP($C15,"GICS_SECTOR_NAME")) | F15: =IF($A15="","",_xll.BDP($C15,"EQY_DVD_SH_12M")) | G15: =IF($A15="","",_xll.BDP($C15,"EQY_DVD_YLD_12M")) | H15: =IF($A15="","",_xll.BDP($C15,"EQY_DVD_YLD_IND")) | I15: =IF($A15="","",_xll.BDP($C15,'Field Check'!$C$4)) | J15: =IFERROR(IF($B15="","",IF(ISNUMBER($F15),$B15*$F15*$D$3/$B$3,0)),"") | K15: =IFERROR(IF($J15="","",$J15*IF(ISNUMBER($I15),$I15,'Index Summary'!$C$7)/100),"") | L15: =IFERROR(IF($K15="","",$J15-$K15),"") | N15: =IF($C15="","",IF(NOT(ISNUMBER($F15)),"No dividend",IF($F15=0,"No dividend",IF(ISNUMBER($I15),"OK","Frank assumed")))) | P15: =IF($N15="No dividend","",IF($C15="","",_xll.BDP($C15,'Field Check'!$C$43))) | Q15: =IFERROR(IF(LEN($P15)<>3,1,IF($P15=$D$2,1,_xll.BDP($P15&$D$2&" Curncy","PX_LAST"))),1) | S15: =IF($C15="","",_xll.BDP($C15,'Field Check'!$C$45)) | T15: 0.49957551 | U15: 2.71
A16: N/A | B16: =IF(COUNT($T16,$U16)=2,$U$2*$T16/100/($U16*IF($U$3="",1,$U$3)),"") | C16: CAR AT Equity | D16: =IF($A16="","",_xll.BDP($C16,"NAME")) | E16: =IF($A16="","",_xll.BDP($C16,"GICS_SECTOR_NAME")) | F16: =IF($A16="","",_xll.BDP($C16,"EQY_DVD_SH_12M")) | G16: =IF($A16="","",_xll.BDP($C16,"EQY_DVD_YLD_12M")) | H16: =IF($A16="","",_xll.BDP($C16,"EQY_DVD_YLD_IND")) | I16: =IF($A16="","",_xll.BDP($C16,'Field Check'!$C$4)) | J16: =IFERROR(IF($B16="","",IF(ISNUMBER($F16),$B16*$F16*$D$3/$B$3,0)),"") | K16: =IFERROR(IF($J16="","",$J16*IF(ISNUMBER($I16),$I16,'Index Summary'!$C$7)/100),"") | L16: =IFERROR(IF($K16="","",$J16-$K16),"") | N16: =IF($C16="","",IF(NOT(ISNUMBER($F16)),"No dividend",IF($F16=0,"No dividend",IF(ISNUMBER($I16),"OK","Frank assumed")))) | P16: =IF($N16="No dividend","",IF($C16="","",_xll.BDP($C16,'Field Check'!$C$43))) | Q16: =IFERROR(IF(LEN($P16)<>3,1,IF($P16=$D$2,1,_xll.BDP($P16&$D$2&" Curncy","PX_LAST"))),1) | S16: =IF($C16="","",_xll.BDP($C16,'Field Check'!$C$45)) | T16: 0.45450316 | U16: 27.02
A17: N/A | B17: =IF(COUNT($T17,$U17)=2,$U$2*$T17/100/($U17*IF($U$3="",1,$U$3)),"") | C17: GMG AT Equity | D17: =IF($A17="","",_xll.BDP($C17,"NAME")) | E17: =IF($A17="","",_xll.BDP($C17,"GICS_SECTOR_NAME")) | F17: =IF($A17="","",_xll.BDP($C17,"EQY_DVD_SH_12M")) | G17: =IF($A17="","",_xll.BDP($C17,"EQY_DVD_YLD_12M")) | H17: =IF($A17="","",_xll.BDP($C17,"EQY_DVD_YLD_IND")) | I17: =IF($A17="","",_xll.BDP($C17,'Field Check'!$C$4)) | J17: =IFERROR(IF($B17="","",IF(ISNUMBER($F17),$B17*$F17*$D$3/$B$3,0)),"") | K17: =IFERROR(IF($J17="","",$J17*IF(ISNUMBER($I17),$I17,'Index Summary'!$C$7)/100),"") | L17: =IFERROR(IF($K17="","",$J17-$K17),"") | N17: =IF($C17="","",IF(NOT(ISNUMBER($F17)),"No dividend",IF($F17=0,"No dividend",IF(ISNUMBER($I17),"OK","Frank assumed")))) | P17: =IF($N17="No dividend","",IF($C17="","",_xll.BDP($C17,'Field Check'!$C$43))) | Q17: =IFERROR(IF(LEN($P17)<>3,1,IF($P17=$D$2,1,_xll.BDP($P17&$D$2&" Curncy","PX_LAST"))),1) | S17: =IF($C17="","",_xll.BDP($C17,'Field Check'!$C$45)) | T17: 2.7907072 | U17: 29.95
... A52: N/A | B52: =IF(COUNT($T52,$U52)=2,$U$2*$T52/100/($U52*IF($U$3="",1,$U$3)),"") | C52: TLC AT Equity | D52: =IF($A52="","",_xll.BDP($C52,"NAME")) | E52: =IF($A52="","",_xll.BDP($C52,"GICS_SECTOR_NAME")) | F52: =IF($A52="","",_xll.BDP($C52,"EQY_DVD_SH_12M")) | G52: =IF($A52="","",_xll.BDP($C52,"EQY_DVD_YLD_12M")) | H52: =IF($A52="","",_xll.BDP($C52,"EQY_DVD_YLD_IND")) | I52: =IF($A52="","",_xll.BDP($C52,'Field Check'!$C$4)) | J52: =IFERROR(IF($B52="","",IF(ISNUMBER($F52),$B52*$F52*$D$3/$B$3,0)),"") | K52: =IFERROR(IF($J52="","",$J52*IF(ISNUMBER($I52),$I52,'Index Summary'!$C$7)/100),"") | L52: =IFERROR(IF($K52="","",$J52-$K52),"") | N52: =IF($C52="","",IF(NOT(ISNUMBER($F52)),"No dividend",IF($F52=0,"No dividend",IF(ISNUMBER($I52),"OK","Frank assumed")))) | P52: =IF($N52="No dividend","",IF($C52="","",_xll.BDP($C52,'Field Check'!$C$43))) | Q52: =IFERROR(IF(LEN($P52)<>3,1,IF($P52=$D$2,1,_xll.BDP($P52&$D$2&" Curncy","PX_LAST"))),1) | S52: =IF($C52="","",_xll.BDP($C52,'Field Check'!$C$45)) | T52: 0.56798482 | U52: 5.46
B53: =IF(COUNT($T53,$U53)=2,$U$2*$T53/($U53*IF($U$3="",1,$U$3)),"") | C53: =IF($A53="","",$A53&" Equity") | D53: =IF($A53="","",_xll.BDP($C53,"NAME")) | E53: =IF($A53="","",_xll.BDP($C53,"GICS_SECTOR_NAME")) | F53: =IF($A53="","",_xll.BDP($C53,"EQY_DVD_SH_12M")) | G53: =IF($A53="","",_xll.BDP($C53,"EQY_DVD_YLD_12M")) | H53: =IF($A53="","",_xll.BDP($C53,"EQY_DVD_YLD_IND")) | I53: =IF($A53="","",_xll.BDP($C53,'Field Check'!$C$4)) | J53: =IFERROR(IF($B53="","",IF(ISNUMBER($F53),$B53*$F53*$D$3/$B$3,0)),"") | K53: =IFERROR(IF($J53="","",$J53*IF(ISNUMBER($I53),$I53,'Index Summary'!$C$7)/100),"") | L53: =IFERROR(IF($K53="","",$J53-$K53),"") | N53: =IF($C53="","",IF(NOT(ISNUMBER($F53)),"No dividend",IF($F53=0,"No dividend",IF(ISNUMBER($I53),"OK","Frank assumed")))) | P53: =IF($N53="No dividend","",IF($C53="","",_xll.BDP($C53,'Field Check'!$C$43))) | Q53: =IFERROR(IF(LEN($P53)<>3,1,IF($P53=$D$2,1,_xll.BDP($P53&$D$2&" Curncy","PX_LAST"))),1) | S53: =IF($C53="","",_xll.BDP($C53,'Field Check'!$C$45))
B54: =IF(COUNT($T54,$U54)=2,$U$2*$T54/($U54*IF($U$3="",1,$U$3)),"") | C54: =IF($A54="","",$A54&" Equity") | D54: =IF($A54="","",_xll.BDP($C54,"NAME")) | E54: =IF($A54="","",_xll.BDP($C54,"GICS_SECTOR_NAME")) | F54: =IF($A54="","",_xll.BDP($C54,"EQY_DVD_SH_12M")) | G54: =IF($A54="","",_xll.BDP($C54,"EQY_DVD_YLD_12M")) | H54: =IF($A54="","",_xll.BDP($C54,"EQY_DVD_YLD_IND")) | I54: =IF($A54="","",_xll.BDP($C54,'Field Check'!$C$4)) | J54: =IFERROR(IF($B54="","",IF(ISNUMBER($F54),$B54*$F54*$D$3/$B$3,0)),"") | K54: =IFERROR(IF($J54="","",$J54*IF(ISNUMBER($I54),$I54,'Index Summary'!$C$7)/100),"") | L54: =IFERROR(IF($K54="","",$J54-$K54),"") | N54: =IF($C54="","",IF(NOT(ISNUMBER($F54)),"No dividend",IF($F54=0,"No dividend",IF(ISNUMBER($I54),"OK","Frank assumed")))) | P54: =IF($N54="No dividend","",IF($C54="","",_xll.BDP($C54,'Field Check'!$C$43))) | Q54: =IFERROR(IF(LEN($P54)<>3,1,IF($P54=$D$2,1,_xll.BDP($P54&$D$2&" Curncy","PX_LAST"))),1) | S54: =IF($C54="","",_xll.BDP($C54,'Field Check'!$C$45))
B55: =IF(COUNT($T55,$U55)=2,$U$2*$T55/($U55*IF($U$3="",1,$U$3)),"") | C55: =IF($A55="","",$A55&" Equity") | D55: =IF($A55="","",_xll.BDP($C55,"NAME")) | E55: =IF($A55="","",_xll.BDP($C55,"GICS_SECTOR_NAME")) | F55: =IF($A55="","",_xll.BDP($C55,"EQY_DVD_SH_12M")) | G55: =IF($A55="","",_xll.BDP($C55,"EQY_DVD_YLD_12M")) | H55: =IF($A55="","",_xll.BDP($C55,"EQY_DVD_YLD_IND")) | I55: =IF($A55="","",_xll.BDP($C55,'Field Check'!$C$4)) | J55: =IFERROR(IF($B55="","",IF(ISNUMBER($F55),$B55*$F55*$D$3/$B$3,0)),"") | K55: =IFERROR(IF($J55="","",$J55*IF(ISNUMBER($I55),$I55,'Index Summary'!$C$7)/100),"") | L55: =IFERROR(IF($K55="","",$J55-$K55),"") | N55: =IF($C55="","",IF(NOT(ISNUMBER($F55)),"No dividend",IF($F55=0,"No dividend",IF(ISNUMBER($I55),"OK","Frank assumed")))) | P55: =IF($N55="No dividend","",IF($C55="","",_xll.BDP($C55,'Field Check'!$C$43))) | Q55: =IFERROR(IF(LEN($P55)<>3,1,IF($P55=$D$2,1,_xll.BDP($P55&$D$2&" Curncy","PX_LAST"))),1) | S55: =IF($C55="","",_xll.BDP($C55,'Field Check'!$C$45))
B56: =IF(COUNT($T56,$U56)=2,$U$2*$T56/($U56*IF($U$3="",1,$U$3)),"") | C56: =IF($A56="","",$A56&" Equity") | D56: =IF($A56="","",_xll.BDP($C56,"NAME")) | E56: =IF($A56="","",_xll.BDP($C56,"GICS_SECTOR_NAME")) | F56: =IF($A56="","",_xll.BDP($C56,"EQY_DVD_SH_12M")) | G56: =IF($A56="","",_xll.BDP($C56,"EQY_DVD_YLD_12M")) | H56: =IF($A56="","",_xll.BDP($C56,"EQY_DVD_YLD_IND")) | I56: =IF($A56="","",_xll.BDP($C56,'Field Check'!$C$4)) | J56: =IFERROR(IF($B56="","",IF(ISNUMBER($F56),$B56*$F56*$D$3/$B$3,0)),"") | K56: =IFERROR(IF($J56="","",$J56*IF(ISNUMBER($I56),$I56,'Index Summary'!$C$7)/100),"") | L56: =IFERROR(IF($K56="","",$J56-$K56),"") | N56: =IF($C56="","",IF(NOT(ISNUMBER($F56)),"No dividend",IF($F56=0,"No dividend",IF(ISNUMBER($I56),"OK","Frank assumed")))) | P56: =IF($N56="No dividend","",IF($C56="","",_xll.BDP($C56,'Field Check'!$C$43))) | Q56: =IFERROR(IF(LEN($P56)<>3,1,IF($P56=$D$2,1,_xll.BDP($P56&$D$2&" Curncy","PX_LAST"))),1) | S56: =IF($C56="","",_xll.BDP($C56,'Field Check'!$C$45))
B57: =IF(COUNT($T57,$U57)=2,$U$2*$T57/($U57*IF($U$3="",1,$U$3)),"") | C57: =IF($A57="","",$A57&" Equity") | D57: =IF($A57="","",_xll.BDP($C57,"NAME")) | E57: =IF($A57="","",_xll.BDP($C57,"GICS_SECTOR_NAME")) | F57: =IF($A57="","",_xll.BDP($C57,"EQY_DVD_SH_12M")) | G57: =IF($A57="","",_xll.BDP($C57,"EQY_DVD_YLD_12M")) | H57: =IF($A57="","",_xll.BDP($C57,"EQY_DVD_YLD_IND")) | I57: =IF($A57="","",_xll.BDP($C57,'Field Check'!$C$4)) | J57: =IFERROR(IF($B57="","",IF(ISNUMBER($F57),$B57*$F57*$D$3/$B$3,0)),"") | K57: =IFERROR(IF($J57="","",$J57*IF(ISNUMBER($I57),$I57,'Index Summary'!$C$7)/100),"") | L57: =IFERROR(IF($K57="","",$J57-$K57),"") | N57: =IF($C57="","",IF(NOT(ISNUMBER($F57)),"No dividend",IF($F57=0,"No dividend",IF(ISNUMBER($I57),"OK","Frank assumed")))) | P57: =IF($N57="No dividend","",IF($C57="","",_xll.BDP($C57,'Field Check'!$C$43))) | Q57: =IFERROR(IF(LEN($P57)<>3,1,IF($P57=$D$2,1,_xll.BDP($P57&$D$2&" Curncy","PX_LAST"))),1) | S57: =IF($C57="","",_xll.BDP($C57,'Field Check'!$C$45))
B58: =IF(COUNT($T58,$U58)=2,$U$2*$T58/($U58*IF($U$3="",1,$U$3)),"") | C58: =IF($A58="","",$A58&" Equity") | D58: =IF($A58="","",_xll.BDP($C58,"NAME")) | E58: =IF($A58="","",_xll.BDP($C58,"GICS_SECTOR_NAME")) | F58: =IF($A58="","",_xll.BDP($C58,"EQY_DVD_SH_12M")) | G58: =IF($A58="","",_xll.BDP($C58,"EQY_DVD_YLD_12M")) | H58: =IF($A58="","",_xll.BDP($C58,"EQY_DVD_YLD_IND")) | I58: =IF($A58="","",_xll.BDP($C58,'Field Check'!$C$4)) | J58: =IFERROR(IF($B58="","",IF(ISNUMBER($F58),$B58*$F58*$D$3/$B$3,0)),"") | K58: =IFERROR(IF($J58="","",$J58*IF(ISNUMBER($I58),$I58,'Index Summary'!$C$7)/100),"") | L58: =IFERROR(IF($K58="","",$J58-$K58),"") | N58: =IF($C58="","",IF(NOT(ISNUMBER($F58)),"No dividend",IF($F58=0,"No dividend",IF(ISNUMBER($I58),"OK","Frank assumed")))) | P58: =IF($N58="No dividend","",IF($C58="","",_xll.BDP($C58,'Field Check'!$C$43))) | Q58: =IFERROR(IF(LEN($P58)<>3,1,IF($P58=$D$2,1,_xll.BDP($P58&$D$2&" Curncy","PX_LAST"))),1) | S58: =IF($C58="","",_xll.BDP($C58,'Field Check'!$C$45))
B59: =IF(COUNT($T59,$U59)=2,$U$2*$T59/($U59*IF($U$3="",1,$U$3)),"") | C59: =IF($A59="","",$A59&" Equity") | D59: =IF($A59="","",_xll.BDP($C59,"NAME")) | E59: =IF($A59="","",_xll.BDP($C59,"GICS_SECTOR_NAME")) | F59: =IF($A59="","",_xll.BDP($C59,"EQY_DVD_SH_12M")) | G59: =IF($A59="","",_xll.BDP($C59,"EQY_DVD_YLD_12M")) | H59: =IF($A59="","",_xll.BDP($C59,"EQY_DVD_YLD_IND")) | I59: =IF($A59="","",_xll.BDP($C59,'Field Check'!$C$4)) | J59: =IFERROR(IF($B59="","",IF(ISNUMBER($F59),$B59*$F59*$D$3/$B$3,0)),"") | K59: =IFERROR(IF($J59="","",$J59*IF(ISNUMBER($I59),$I59,'Index Summary'!$C$7)/100),"") | L59: =IFERROR(IF($K59="","",$J59-$K59),"") | N59: =IF($C59="","",IF(NOT(ISNUMBER($F59)),"No dividend",IF($F59=0,"No dividend",IF(ISNUMBER($I59),"OK","Frank assumed")))) | P59: =IF($N59="No dividend","",IF($C59="","",_xll.BDP($C59,'Field Check'!$C$43))) | Q59: =IFERROR(IF(LEN($P59)<>3,1,IF($P59=$D$2,1,_xll.BDP($P59&$D$2&" Curncy","PX_LAST"))),1) | S59: =IF($C59="","",_xll.BDP($C59,'Field Check'!$C$45))
B60: =IF(COUNT($T60,$U60)=2,$U$2*$T60/($U60*IF($U$3="",1,$U$3)),"") | C60: =IF($A60="","",$A60&" Equity") | D60: =IF($A60="","",_xll.BDP($C60,"NAME")) | E60: =IF($A60="","",_xll.BDP($C60,"GICS_SECTOR_NAME")) | F60: =IF($A60="","",_xll.BDP($C60,"EQY_DVD_SH_12M")) | G60: =IF($A60="","",_xll.BDP($C60,"EQY_DVD_YLD_12M")) | H60: =IF($A60="","",_xll.BDP($C60,"EQY_DVD_YLD_IND")) | I60: =IF($A60="","",_xll.BDP($C60,'Field Check'!$C$4)) | J60: =IFERROR(IF($B60="","",IF(ISNUMBER($F60),$B60*$F60*$D$3/$B$3,0)),"") | K60: =IFERROR(IF($J60="","",$J60*IF(ISNUMBER($I60),$I60,'Index Summary'!$C$7)/100),"") | L60: =IFERROR(IF($K60="","",$J60-$K60),"") | N60: =IF($C60="","",IF(NOT(ISNUMBER($F60)),"No dividend",IF($F60=0,"No dividend",IF(ISNUMBER($I60),"OK","Frank assumed")))) | P60: =IF($N60="No dividend","",IF($C60="","",_xll.BDP($C60,'Field Check'!$C$43))) | Q60: =IFERROR(IF(LEN($P60)<>3,1,IF($P60=$D$2,1,_xll.BDP($P60&$D$2&" Curncy","PX_LAST"))),1) | S60: =IF($C60="","",_xll.BDP($C60,'Field Check'!$C$45))
B61: =IF(COUNT($T61,$U61)=2,$U$2*$T61/($U61*IF($U$3="",1,$U$3)),"") | C61: =IF($A61="","",$A61&" Equity") | D61: =IF($A61="","",_xll.BDP($C61,"NAME")) | E61: =IF($A61="","",_xll.BDP($C61,"GICS_SECTOR_NAME")) | F61: =IF($A61="","",_xll.BDP($C61,"EQY_DVD_SH_12M")) | G61: =IF($A61="","",_xll.BDP($C61,"EQY_DVD_YLD_12M")) | H61: =IF($A61="","",_xll.BDP($C61,"EQY_DVD_YLD_IND")) | I61: =IF($A61="","",_xll.BDP($C61,'Field Check'!$C$4)) | J61: =IFERROR(IF($B61="","",IF(ISNUMBER($F61),$B61*$F61*$D$3/$B$3,0)),"") | K61: =IFERROR(IF($J61="","",$J61*IF(ISNUMBER($I61),$I61,'Index Summary'!$C$7)/100),"") | L61: =IFERROR(IF($K61="","",$J61-$K61),"") | N61: =IF($C61="","",IF(NOT(ISNUMBER($F61)),"No dividend",IF($F61=0,"No dividend",IF(ISNUMBER($I61),"OK","Frank assumed")))) | P61: =IF($N61="No dividend","",IF($C61="","",_xll.BDP($C61,'Field Check'!$C$43))) | Q61: =IFERROR(IF(LEN($P61)<>3,1,IF($P61=$D$2,1,_xll.BDP($P61&$D$2&" Curncy","PX_LAST"))),1) | S61: =IF($C61="","",_xll.BDP($C61,'Field Check'!$C$45))
B62: =IF(COUNT($T62,$U62)=2,$U$2*$T62/($U62*IF($U$3="",1,$U$3)),"") | C62: =IF($A62="","",$A62&" Equity") | D62: =IF($A62="","",_xll.BDP($C62,"NAME")) | E62: =IF($A62="","",_xll.BDP($C62,"GICS_SECTOR_NAME")) | F62: =IF($A62="","",_xll.BDP($C62,"EQY_DVD_SH_12M")) | G62: =IF($A62="","",_xll.BDP($C62,"EQY_DVD_YLD_12M")) | H62: =IF($A62="","",_xll.BDP($C62,"EQY_DVD_YLD_IND")) | I62: =IF($A62="","",_xll.BDP($C62,'Field Check'!$C$4)) | J62: =IFERROR(IF($B62="","",IF(ISNUMBER($F62),$B62*$F62*$D$3/$B$3,0)),"") | K62: =IFERROR(IF($J62="","",$J62*IF(ISNUMBER($I62),$I62,'Index Summary'!$C$7)/100),"") | L62: =IFERROR(IF($K62="","",$J62-$K62),"") | N62: =IF($C62="","",IF(NOT(ISNUMBER($F62)),"No dividend",IF($F62=0,"No dividend",IF(ISNUMBER($I62),"OK","Frank assumed")))) | P62: =IF($N62="No dividend","",IF($C62="","",_xll.BDP($C62,'Field Check'!$C$43))) | Q62: =IFERROR(IF(LEN($P62)<>3,1,IF($P62=$D$2,1,_xll.BDP($P62&$D$2&" Curncy","PX_LAST"))),1) | S62: =IF($C62="","",_xll.BDP($C62,'Field Check'!$C$45))
B63: =IF(COUNT($T63,$U63)=2,$U$2*$T63/($U63*IF($U$3="",1,$U$3)),"") | C63: =IF($A63="","",$A63&" Equity") | D63: =IF($A63="","",_xll.BDP($C63,"NAME")) | E63: =IF($A63="","",_xll.BDP($C63,"GICS_SECTOR_NAME")) | F63: =IF($A63="","",_xll.BDP($C63,"EQY_DVD_SH_12M")) | G63: =IF($A63="","",_xll.BDP($C63,"EQY_DVD_YLD_12M")) | H63: =IF($A63="","",_xll.BDP($C63,"EQY_DVD_YLD_IND")) | I63: =IF($A63="","",_xll.BDP($C63,'Field Check'!$C$4)) | J63: =IFERROR(IF($B63="","",IF(ISNUMBER($F63),$B63*$F63*$D$3/$B$3,0)),"") | K63: =IFERROR(IF($J63="","",$J63*IF(ISNUMBER($I63),$I63,'Index Summary'!$C$7)/100),"") | L63: =IFERROR(IF($K63="","",$J63-$K63),"") | N63: =IF($C63="","",IF(NOT(ISNUMBER($F63)),"No dividend",IF($F63=0,"No dividend",IF(ISNUMBER($I63),"OK","Frank assumed")))) | P63: =IF($N63="No dividend","",IF($C63="","",_xll.BDP($C63,'Field Check'!$C$43))) | Q63: =IFERROR(IF(LEN($P63)<>3,1,IF($P63=$D$2,1,_xll.BDP($P63&$D$2&" Curncy","PX_LAST"))),1) | S63: =IF($C63="","",_xll.BDP($C63,'Field Check'!$C$45))
B64: =IF(COUNT($T64,$U64)=2,$U$2*$T64/($U64*IF($U$3="",1,$U$3)),"") | C64: =IF($A64="","",$A64&" Equity") | D64: =IF($A64="","",_xll.BDP($C64,"NAME")) | E64: =IF($A64="","",_xll.BDP($C64,"GICS_SECTOR_NAME")) | F64: =IF($A64="","",_xll.BDP($C64,"EQY_DVD_SH_12M")) | G64: =IF($A64="","",_xll.BDP($C64,"EQY_DVD_YLD_12M")) | H64: =IF($A64="","",_xll.BDP($C64,"EQY_DVD_YLD_IND")) | I64: =IF($A64="","",_xll.BDP($C64,'Field Check'!$C$4)) | J64: =IFERROR(IF($B64="","",IF(ISNUMBER($F64),$B64*$F64*$D$3/$B$3,0)),"") | K64: =IFERROR(IF($J64="","",$J64*IF(ISNUMBER($I64),$I64,'Index Summary'!$C$7)/100),"") | L64: =IFERROR(IF($K64="","",$J64-$K64),"") | N64: =IF($C64="","",IF(NOT(ISNUMBER($F64)),"No dividend",IF($F64=0,"No dividend",IF(ISNUMBER($I64),"OK","Frank assumed")))) | P64: =IF($N64="No dividend","",IF($C64="","",_xll.BDP($C64,'Field Check'!$C$43))) | Q64: =IFERROR(IF(LEN($P64)<>3,1,IF($P64=$D$2,1,_xll.BDP($P64&$D$2&" Curncy","PX_LAST"))),1) | S64: =IF($C64="","",_xll.BDP($C64,'Field Check'!$C$45))
... B175: =IF(COUNT($T175,$U175)=2,$U$2*$T175/($U175*IF($U$3="",1,$U$3)),"") | C175: =IF($A175="","",$A175&" Equity") | D175: =IF($A175="","",_xll.BDP($C175,"NAME")) | E175: =IF($A175="","",_xll.BDP($C175,"GICS_SECTOR_NAME")) | F175: =IF($A175="","",_xll.BDP($C175,"EQY_DVD_SH_12M")) | G175: =IF($A175="","",_xll.BDP($C175,"EQY_DVD_YLD_12M")) | H175: =IF($A175="","",_xll.BDP($C175,"EQY_DVD_YLD_IND")) | I175: =IF($A175="","",_xll.BDP($C175,'Field Check'!$C$4)) | J175: =IFERROR(IF($B175="","",IF(ISNUMBER($F175),$B175*$F175*$D$3/$B$3,0)),"") | K175: =IFERROR(IF($J175="","",$J175*IF(ISNUMBER($I175),$I175,'Index Summary'!$C$7)/100),"") | L175: =IFERROR(IF($K175="","",$J175-$K175),"") | N175: =IF($C175="","",IF(NOT(ISNUMBER($F175)),"No dividend",IF($F175=0,"No dividend",IF(ISNUMBER($I175),"OK","Frank assumed")))) | P175: =IF($N175="No dividend","",IF($C175="","",_xll.BDP($C175,'Field Check'!$C$43))) | Q175: =IFERROR(IF(LEN($P175)<>3,1,IF($P175=$D$2,1,_xll.BDP($P175&$D$2&" Curncy","PX_LAST"))),1) | S175: =IF($C175="","",_xll.BDP($C175,'Field Check'!$C$45))

Sheet Dvd Calendar
A1: DIVIDEND CALENDAR - TWO BLOOMBERG PULLS PER STOCK. NEVER EDIT, NEVER SORT.
A2: Per stock: HISTORY (7 rows) then PROJECTIONS (3 rows). Windows take the union of the two, each ex-date once, cash types only.
B3: CHECKS | C3: events read | D3: =SUM($B$7:$B$2261)+SUM($B$2265:$B$3144) | G3: stocks with 0 projections | I3: =COUNTIFS($A$7:$A$2261," projections",$B$7:$B$2261,0)+COUNTIFS($A$2265:$A$3144," projections",$B$2265:$B$3144,0) | J3: last projected ex-date | K3: =IFERROR(IF(MAX($C$7:$C$2261,$C$2265:$C$3144)=0,"",MAX($C$7:$C$2261,$C$2265:$C$3144)),"")
A5: S&P/ASX 200 (AS51)
A6: Ticker | B6: Events | C6: Last ex | D6: Bloomberg spill ->
A7: =IF('AS51'!$C$6="","",'AS51'!$C$6) | B7: =IF($A7="",0,COUNT($E8:$CZ8)) | C7: =IF($B7=0,0,MAX($E8:$CZ8)) | D7: =_xll.BDS($A7,'Field Check'!$C$44,"headers=y","startcol=1","endcol=7","dir=h","DVD_START_DT",'Field Check'!$C$59,"DVD_END_DT",'Field Check'!$D$59)
A14: =IF($A7="",""," projections") | B14: =IF($A7="",0,COUNT($E15:$CZ15)) | C14: =IF($B14=0,0,MAX($E15:$CZ15)) | D14: =_xll.BDS($A7,'Field Check'!$C$42,"headers=y","startcol=1","endcol=3","dir=h")
A18: =IF('AS51'!$C$7="","",'AS51'!$C$7) | B18: =IF($A18="",0,COUNT($E19:$CZ19)) | C18: =IF($B18=0,0,MAX($E19:$CZ19)) | D18: =_xll.BDS($A18,'Field Check'!$C$44,"headers=y","startcol=1","endcol=7","dir=h","DVD_START_DT",'Field Check'!$C$59,"DVD_END_DT",'Field Check'!$D$59)
A25: =IF($A18="",""," projections") | B25: =IF($A18="",0,COUNT($E26:$CZ26)) | C25: =IF($B25=0,0,MAX($E26:$CZ26)) | D25: =_xll.BDS($A18,'Field Check'!$C$42,"headers=y","startcol=1","endcol=3","dir=h")
A29: =IF('AS51'!$C$8="","",'AS51'!$C$8) | B29: =IF($A29="",0,COUNT($E30:$CZ30)) | C29: =IF($B29=0,0,MAX($E30:$CZ30)) | D29: =_xll.BDS($A29,'Field Check'!$C$44,"headers=y","startcol=1","endcol=7","dir=h","DVD_START_DT",'Field Check'!$C$59,"DVD_END_DT",'Field Check'!$D$59,"cols=2;rows=7") | E29: 46198
D30: Ex-Date | E30: 46211
D31: Record Date | E31: 46212
D32: Payable Date | E32: 46227
D33: Dividend Amount | E33: 0.41355
D34: Dividend Frequency | E34: None
D35: Dividend Type | E35: Special Cash
A36: =IF($A29="",""," projections") | B36: =IF($A29="",0,COUNT($E37:$CZ37)) | C36: =IF($B36=0,0,MAX($E37:$CZ37)) | D36: =_xll.BDS($A29,'Field Check'!$C$42,"headers=y","startcol=1","endcol=3","dir=h","cols=20;rows=3") | E36: 46251 | F36: 46434 | G36: 46615 | H36: 46798 | I36: 46979 | J36: 47169 | K36: 47350 | L36: 47533 | M36: 47714 | N36: 47897 | O36: 48078 | P36: 48261 | Q36: 48442 | R36: 48625 | S36: 48806 | T36: 48989 | U36: 49170 | V36: 49360 | W36: 49541
D37: Ex-Date | E37: 46283 | F37: 46465 | G37: 46647 | H37: 46829 | I37: 47011 | J37: 47200 | K37: 47382 | L37: 47564 | M37: 47746 | N37: 47928 | O37: 48110 | P37: 48292 | Q37: 48474 | R37: 48656 | S37: 48838 | T37: 49020 | U37: 49202 | V37: 49390 | W37: 49573
D38: Amount Per Share | E38: 0.12 | F38: 0.12 | G38: 0.12 | H38: 0.12 | I38: 0.15 | J38: 0.15 | K38: 0.15 | L38: 0.15 | M38: 0.15 | N38: 0.17 | O38: 0.17 | P38: 0.17 | Q38: 0.17 | R38: 0.17 | S38: 0.17 | T38: 0.2 | U38: 0.2 | V38: 0.2 | W38: 0.2
A40: =IF('AS51'!$C$9="","",'AS51'!$C$9) | B40: =IF($A40="",0,COUNT($E41:$CZ41)) | C40: =IF($B40=0,0,MAX($E41:$CZ41)) | D40: =_xll.BDS($A40,'Field Check'!$C$44,"headers=y","startcol=1","endcol=7","dir=h","DVD_START_DT",'Field Check'!$C$59,"DVD_END_DT",'Field Check'!$D$59,"cols=3;rows=7") | E40: 46234 | F40: 46150
D41: Ex-Date | E41: 46244 | F41: 46160
D42: Record Date | E42: 46245 | F42: 46161
D43: Payable Date | E43: 46261 | F43: 46178
D44: Dividend Amount | E44: 0.1 | F44: 0.1
D45: Dividend Frequency | E45: Quarter | F45: Quarter
D46: Dividend Type | E46: Regular Cash | F46: Regular Cash
A47: =IF($A40="",""," projections") | B47: =IF($A40="",0,COUNT($E48:$CZ48)) | C47: =IF($B47=0,0,MAX($E48:$CZ48)) | D47: =_xll.BDS($A40,'Field Check'!$C$42,"headers=y","startcol=1","endcol=3","dir=h","cols=38;rows=3") | E47: 46316 | F47: 46443 | G47: 46513 | H47: 46597 | I47: 46673 | J47: 46807 | K47: 46884 | L47: 46961 | M47: 47044 | N47: 47171 | O47: 47248 | P47: 47325 | Q47: 47408 | R47: 47535 | S47: 47612 | T47: 47696 | U47: 47772 | V47: 47899 | W47: 47976 | X47: 48060 | Y47: 48137 | Z47: 48263 | AA47: 48340 | AB47: 48424 | AC47: 48500 | AD47: 48627 | AE47: 48704 | AF47: 48788 | AG47: 48871 | AH47: 48998 | AI47: 49075 | AJ47: 49152 | AK47: 49235 | AL47: 49369 | AM47: 49446 | AN47: 49523 | AO47: 49606
D48: Ex-Date | E48: 46328 | F48: 46454 | G48: 46524 | H48: 46605 | I48: 46685 | J48: 46818 | K48: 46895 | L48: 46969 | M48: 47056 | N48: 47182 | O48: 47259 | P48: 47333 | Q48: 47420 | R48: 47546 | S48: 47623 | T48: 47704 | U48: 47784 | V48: 47910 | W48: 47987 | X48: 48068 | Y48: 48148 | Z48: 48274 | AA48: 48351 | AB48: 48432 | AC48: 48512 | AD48: 48638 | AE48: 48715 | AF48: 48796 | AG48: 48883 | AH48: 49009 | AI48: 49086 | AJ48: 49160 | AK48: 49247 | AL48: 49380 | AM48: 49457 | AN48: 49531 | AO48: 49618
D49: Amount Per Share | E49: 0.1 | F49: 0.1 | G49: 0.1 | H49: 0.1 | I49: 0.1 | J49: 0.1 | K49: 0.1 | L49: 0.1 | M49: 0.11 | N49: 0.11 | O49: 0.11 | P49: 0.11 | Q49: 0.11 | R49: 0.11 | S49: 0.11 | T49: 0.11 | U49: 0.11 | V49: 0.11 | W49: 0.11 | X49: 0.11 | Y49: 0.12 | Z49: 0.12 | AA49: 0.12 | AB49: 0.12 | AC49: 0.12 | AD49: 0.12 | AE49: 0.12 | AF49: 0.12 | AG49: 0.12 | AH49: 0.12 | AI49: 0.12 | AJ49: 0.12 | AK49: 0.12 | AL49: 0.12 | AM49: 0.12 | AN49: 0.12 | AO49: 0.12
A51: =IF('AS51'!$C$10="","",'AS51'!$C$10) | B51: =IF($A51="",0,COUNT($E52:$CZ52)) | C51: =IF($B51=0,0,MAX($E52:$CZ52)) | D51: =_xll.BDS($A51,'Field Check'!$C$44,"headers=y","startcol=1","endcol=7","dir=h","DVD_START_DT",'Field Check'!$C$59,"DVD_END_DT",'Field Check'!$D$59)
A58: =IF($A51="",""," projections") | B58: =IF($A51="",0,COUNT($E59:$CZ59)) | C58: =IF($B58=0,0,MAX($E59:$CZ59)) | D58: =_xll.BDS($A51,'Field Check'!$C$42,"headers=y","startcol=1","endcol=3","dir=h","cols=21;rows=3") | E58: 46258 | F58: 46441 | G58: 46622 | H58: 46804 | I58: 46986 | J58: 47168 | K58: 47357 | L58: 47539 | M58: 47721 | N58: 47903 | O58: 48085 | P58: 48267 | Q58: 48449 | R58: 48631 | S58: 48813 | T58: 48995 | U58: 49177 | V58: 49359 | W58: 49548 | X58: 49730
D59: Ex-Date | E59: 46269 | F59: 46454 | G59: 46633 | H59: 46815 | I59: 46997 | J59: 47179 | K59: 47368 | L59: 47550 | M59: 47732 | N59: 47914 | O59: 48096 | P59: 48278 | Q59: 48460 | R59: 48642 | S59: 48824 | T59: 49006 | U59: 49188 | V59: 49370 | W59: 49559 | X59: 49741
D60: Amount Per Share | E60: 0.024 | F60: 0.024 | G60: 0.024 | H60: 0.024 | I60: 0.024 | J60: 0.024 | K60: 0.024 | L60: 0.024 | M60: 0.024 | N60: 0.024 | O60: 0.024 | P60: 0.024 | Q60: 0.024 | R60: 0.024 | S60: 0.024 | T60: 0.024 | U60: 0.024 | V60: 0.024 | W60: 0.024 | X60: 0.024
A62: =IF('AS51'!$C$11="","",'AS51'!$C$11) | B62: =IF($A62="",0,COUNT($E63:$CZ63)) | C62: =IF($B62=0,0,MAX($E63:$CZ63)) | D62: =_xll.BDS($A62,'Field Check'!$C$44,"headers=y","startcol=1","endcol=7","dir=h","DVD_START_DT",'Field Check'!$C$59,"DVD_END_DT",'Field Check'!$D$59,"cols=2;rows=7") | E62: 46246
D63: Ex-Date | E63: 46259
D64: Record Date | E64: 46260
D65: Payable Date | E65: 46289
D66: Dividend Amount | E66: 0.26
D67: Dividend Frequency | E67: Semi-Anl
D68: Dividend Type | E68: Final
A69: =IF($A62="",""," projections") | B69: =IF($A62="",0,COUNT($E70:$CZ70)) | C69: =IF($B69=0,0,MAX($E70:$CZ70)) | D69: =_xll.BDS($A62,'Field Check'!$C$42,"headers=y","startcol=1","endcol=3","dir=h","cols=21;rows=3") | E69: 46428 | F69: 46610 | G69: 46792 | H69: 46974 | I69: 47163 | J69: 47345 | K69: 47527 | L69: 47709 | M69: 47891 | N69: 48073 | O69: 48255 | P69: 48437 | Q69: 48619 | R69: 48801 | S69: 48983 | T69: 49165 | U69: 49354 | V69: 49536 | W69: 49718 | X69: 49900
D70: Ex-Date | E70: 46441 | F70: 46623 | G70: 46805 | H70: 46987 | I70: 47176 | J70: 47358 | K70: 47540 | L70: 47722 | M70: 47904 | N70: 48086 | O70: 48268 | P70: 48450 | Q70: 48632 | R70: 48814 | S70: 48996 | T70: 49178 | U70: 49367 | V70: 49549 | W70: 49731 | X70: 49913
D71: Amount Per Share | E71: 0.23 | F71: 0.27 | G71: 0.23 | H71: 0.28 | I71: 0.23 | J71: 0.29 | K71: 0.23 | L71: 0.3 | M71: 0.23 | N71: 0.31 | O71: 0.23 | P71: 0.32 | Q71: 0.23 | R71: 0.33 | S71: 0.23 | T71: 0.34 | U71: 0.23 | V71: 0.35 | W71: 0.23 | X71: 0.35
A73: =IF('AS51'!$C$12="","",'AS51'!$C$12) | B73: =IF($A73="",0,COUNT($E74:$CZ74)) | C73: =IF($B73=0,0,MAX($E74:$CZ74)) | D73: =_xll.BDS($A73,'Field Check'!$C$44,"headers=y","startcol=1","endcol=7","dir=h","DVD_START_DT",'Field Check'!$C$59,"DVD_END_DT",'Field Check'!$D$59)
A80: =IF($A73="",""," projections") | B80: =IF($A73="",0,COUNT($E81:$CZ81)) | C80: =IF($B80=0,0,MAX($E81:$CZ81)) | D80: =_xll.BDS($A73,'Field Check'!$C$42,"headers=y","startcol=1","endcol=3","dir=h","cols=21;rows=3") | E80: 46254 | F80: 46437 | G80: 46618 | H80: 46800 | I80: 46982 | J80: 47164 | K80: 47353 | L80: 47535 | M80: 47717 | N80: 47899 | O80: 48081 | P80: 48263 | Q80: 48445 | R80: 48627 | S80: 48809 | T80: 48991 | U80: 49173 | V80: 49362 | W80: 49544 | X80: 49726
D81: Ex-Date | E81: 46281 | F81: 46463 | G81: 46645 | H81: 46827 | I81: 47009 | J81: 47191 | K81: 47380 | L81: 47562 | M81: 47744 | N81: 47926 | O81: 48108 | P81: 48290 | Q81: 48472 | R81: 48654 | S81: 48836 | T81: 49018 | U81: 49200 | V81: 49389 | W81: 49571 | X81: 49753
D82: Amount Per Share | E82: 0.065 | F82: 0.065 | G82: 0.07 | H82: 0.0725 | I82: 0.0825 | J82: 0.0875 | K82: 0.0975 | L82: 0.0875 | M82: 0.0975 | N82: 0.09 | O82: 0.1 | P82: 0.0925 | Q82: 0.1025 | R82: 0.095 | S82: 0.105 | T82: 0.0975 | U82: 0.1075 | V82: 0.1 | W82: 0.11 | X82: 0.1025
A84: =IF('AS51'!$C$13="","",'AS51'!$C$13) | B84: =IF($A84="",0,COUNT($E85:$CZ85)) | C84: =IF($B84=0,0,MAX($E85:$CZ85)) | D84: =_xll.BDS($A84,'Field Check'!$C$44,"headers=y","startcol=1","endcol=7","dir=h","DVD_START_DT",'Field Check'!$C$59,"DVD_END_DT",'Field Check'!$D$59)
A91: =IF($A84="",""," projections") | B91: =IF($A84="",0,COUNT($E92:$CZ92)) | C91: =IF($B91=0,0,MAX($E92:$CZ92)) | D91: =_xll.BDS($A84,'Field Check'!$C$42,"headers=y","startcol=1","endcol=3","dir=h","cols=21;rows=3") | E91: 46258 | F91: 46440 | G91: 46622 | H91: 46804 | I91: 46986 | J91: 47168 | K91: 47350 | L91: 47532 | M91: 47714 | N91: 47903 | O91: 48078 | P91: 48267 | Q91: 48449 | R91: 48631 | S91: 48813 | T91: 48995 | U91: 49177 | V91: 49359 | W91: 49541 | X91: 49730
D92: Ex-Date | E92: 46269 | F92: 46451 | G92: 46633 | H92: 46815 | I92: 46997 | J92: 47179 | K92: 47361 | L92: 47543 | M92: 47725 | N92: 47914 | O92: 48089 | P92: 48278 | Q92: 48460 | R92: 48642 | S92: 48824 | T92: 49006 | U92: 49188 | V92: 49370 | W92: 49552 | X92: 49741
D93: Amount Per Share | E93: 1 | F93: 1 | G93: 0.8 | H93: 0.8 | I93: 0.8 | J93: 0.85 | K93: 0.85 | L93: 0.9 | M93: 0.9 | N93: 0.9 | O93: 0.9 | P93: 0.9 | Q93: 0.9 | R93: 0.9 | S93: 0.93 | T93: 0.93 | U93: 0.95 | V93: 0.95 | W93: 0.95 | X93: 0.95
A95: =IF('AS51'!$C$14="","",'AS51'!$C$14) | B95: =IF($A95="",0,COUNT($E96:$CZ96)) | C95: =IF($B95=0,0,MAX($E96:$CZ96)) | D95: =_xll.BDS($A95,'Field Check'!$C$44,"headers=y","startcol=1","endcol=7","dir=h","DVD_START_DT",'Field Check'!$C$59,"DVD_END_DT",'Field Check'!$D$59,"cols=2;rows=7") | E95: 46224
D96: Ex-Date | E96: #N/A N/A
D97: Record Date | E97: #N/A N/A
D98: Payable Date | E98: #N/A N/A
D99: Dividend Amount | E99: 0.02
D100: Dividend Frequency | E100: Irreg
D101: Dividend Type | E101: Regular Cash
A102: =IF($A95="",""," projections") | B102: =IF($A95="",0,COUNT($E103:$CZ103)) | C102: =IF($B102=0,0,MAX($E103:$CZ103)) | D102: =_xll.BDS($A95,'Field Check'!$C$42,"headers=y","startcol=1","endcol=3","dir=h")
A106: =IF('AS51'!$C$15="","",'AS51'!$C$15) | B106: =IF($A106="",0,COUNT($E107:$CZ107)) | C106: =IF($B106=0,0,MAX($E107:$CZ107)) | D106: =_xll.BDS($A106,'Field Check'!$C$44,"headers=y","startcol=1","endcol=7","dir=h","DVD_START_DT",'Field Check'!$C$59,"DVD_END_DT",'Field Check'!$D$59,"cols=2;rows=7") | E106: 46155
D107: Ex-Date | E107: 46167
D108: Record Date | E108: 46168
D109: Payable Date | E109: 46204
D110: Dividend Amount | E110: 0.5
D111: Dividend Frequency | E111: Semi-Anl
D112: Dividend Type | E112: Interim
A113: =IF($A106="",""," projections") | B113: =IF($A106="",0,COUNT($E114:$CZ114)) | C113: =IF($B113=0,0,MAX($E114:$CZ114)) | D113: =_xll.BDS($A106,'Field Check'!$C$42,"headers=y","startcol=1","endcol=3","dir=h","cols=20;rows=3") | E113: 46344 | F113: 46519 | G113: 46708 | H113: 46883 | I113: 47073 | J113: 47247 | K113: 47437 | L113: 47611 | M113: 47801 | N113: 47975 | O113: 48165 | P113: 48339 | Q113: 48529 | R113: 48710 | S113: 48893 | T113: 49074 | U113: 49257 | V113: 49445 | W113: 49628
D114: Ex-Date | E114: 46352 | F114: 46524 | G114: 46721 | H114: 46888 | I114: 47087 | J114: 47252 | K114: 47452 | L114: 47616 | M114: 47816 | N114: 47980 | O114: 48180 | P114: 48344 | Q114: 48548 | R114: 48715 | S114: 48912 | T114: 49079 | U114: 49276 | V114: 49450 | W114: 49640
D115: Amount Per Share | E115: 0.52 | F115: 0.51 | G115: 0.55 | H115: 0.55 | I115: 0.55 | J115: 0.55 | K115: 0.55 | L115: 0.55 | M115: 0.55 | N115: 0.55 | O115: 0.55 | P115: 0.55 | Q115: 0.55 | R115: 0.55 | S115: 0.55 | T115: 0.55 | U115: 0.55 | V115: 0.55 | W115: 0.55
A117: =IF('AS51'!$C$16="","",'AS51'!$C$16) | B117: =IF($A117="",0,COUNT($E118:$CZ118)) | C117: =IF($B117=0,0,MAX($E118:$CZ118)) | D117: =_xll.BDS($A117,'Field Check'!$C$44,"headers=y","startcol=1","endcol=7","dir=h","DVD_START_DT",'Field Check'!$C$59,"DVD_END_DT",'Field Check'!$D$59,"cols=2;rows=7") | E117: 46160
D118: Ex-Date | E118: 46185
D119: Record Date | E119: 46188
D120: Payable Date | E120: 46206
D121: Dividend Amount | E121: 0.231
D122: Dividend Frequency | E122: Semi-Anl
D123: Dividend Type | E123: Final
A124: =IF($A117="",""," projections") | B124: =IF($A117="",0,COUNT($E125:$CZ125)) | C124: =IF($B124=0,0,MAX($E125:$CZ125)) | D124: =_xll.BDS($A117,'Field Check'!$C$42,"headers=y","startcol=1","endcol=3","dir=h","cols=21;rows=3") | E124: 46349 | F124: 46524 | G124: 46707 | H124: 46896 | I124: 47078 | J124: 47267 | K124: 47442 | L124: 47631 | M124: 47806 | N124: 47995 | O124: 48170 | P124: 48359 | Q124: 48534 | R124: 48723 | S124: 48898 | T124: 49094 | U124: 49269 | V124: 49458 | W124: 49633 | X124: 49822
D125: Ex-Date | E125: 46357 | F125: 46549 | G125: 46715 | H125: 46933 | I125: 47086 | J125: 47304 | K125: 47450 | L125: 47668 | M125: 47814 | N125: 48032 | O125: 48178 | P125: 48396 | Q125: 48542 | R125: 48760 | S125: 48906 | T125: 49131 | U125: 49277 | V125: 49495 | W125: 49641 | X125: 49859
D126: Amount Per Share | E126: 0.241 | F126: 0.251 | G126: 0.262 | H126: 0.273 | I126: 0.283 | J126: 0.295 | K126: 0.3 | L126: 0.313 | M126: 0.318 | N126: 0.332 | O126: 0.318 | P126: 0.332 | Q126: 0.318 | R126: 0.332 | S126: 0.318 | T126: 0.332 | U126: 0.318 | V126: 0.332 | W126: 0.318 | X126: 0.332
A128: =IF('AS51'!$C$17="","",'AS51'!$C$17) | B128: =IF($A128="",0,COUNT($E129:$CZ129)) | C128: =IF($B128=0,0,MAX($E129:$CZ129)) | D128: =_xll.BDS($A128,'Field Check'!$C$44,"headers=y","startcol=1","endcol=7","dir=h","DVD_START_DT",'Field Check'!$C$59,"DVD_END_DT",'Field Check'!$D$59)
A135: =IF($A128="",""," projections") | B135: =IF($A128="",0,COUNT($E136:$CZ136)) | C135: =IF($B135=0,0,MAX($E136:$CZ136)) | D135: =_xll.BDS($A128,'Field Check'!$C$42,"headers=y","startcol=1","endcol=3","dir=h","cols=20;rows=3") | E135: 46283 | F135: 46471 | G135: 46647 | H135: 46835 | I135: 47018 | J135: 47199 | K135: 47382 | L135: 47563 | M135: 47746 | N135: 47927 | O135: 48110 | P135: 48298 | Q135: 48474 | R135: 48662 | S135: 48838 | T135: 49026 | U135: 49209 | V135: 49390 | W135: 49573
D136: Ex-Date | E136: 46288 | F136: 46476 | G136: 46652 | H136: 46840 | I136: 47023 | J136: 47204 | K136: 47387 | L136: 47568 | M136: 47751 | N136: 47932 | O136: 48115 | P136: 48303 | Q136: 48479 | R136: 48667 | S136: 48843 | T136: 49031 | U136: 49214 | V136: 49395 | W136: 49578
D137: Amount Per Share | E137: 0.2 | F137: 0.2 | G137: 0.2 | H137: 0.22 | I137: 0.22 | J137: 0.22 | K137: 0.22 | L137: 0.22 | M137: 0.22 | N137: 0.22 | O137: 0.22 | P137: 0.22 | Q137: 0.22 | R137: 0.22 | S137: 0.22 | T137: 0.22 | U137: 0.22 | V137: 0.22 | W137: 0.22
A139: =IF('AS51'!$C$18="","",'AS51'!$C$18) | B139: =IF($A139="",0,COUNT($E140:$CZ140)) | C139: =IF($B139=0,0,MAX($E140:$CZ140)) | D139: =_xll.BDS($A139,'Field Check'!$C$44,"headers=y","startcol=1","endcol=7","dir=h","DVD_START_DT",'Field Check'!$C$59,"DVD_END_DT",'Field Check'!$D$59,"cols=3;rows=7") | E139: 46246 | F139: 46149
D140: Ex-Date | E140: 46268 | F140: 46169
D141: Record Date | E141: 46269 | F141: 46170
D142: Payable Date | E142: 46289 | F142: 46190
D143: Dividend Amount | E143: 0.65 | F143: 0.65
D144: Dividend Frequency | E144: Quarter | F144: Quarter
D145: Dividend Type | E145: Final | F145: Interim
A146: =IF($A139="",""," projections") | B146: =IF($A139="",0,COUNT($E147:$CZ147)) | C146: =IF($B146=0,0,MAX($E147:$CZ147)) | D146: =_xll.BDS($A139,'Field Check'!$C$42,"headers=y","startcol=1","endcol=3","dir=h","cols=41;rows=3") | E146: 46330 | F146: 46420 | G146: 46510 | H146: 46604 | I146: 46686 | J146: 46791 | K146: 46875 | L146: 46975 | M146: 47057 | N146: 47155 | O146: 47240 | P146: 47339 | Q146: 47421 | R146: 47519 | S146: 47605 | T146: 47703 | U146: 47785 | V146: 47883 | W146: 47970 | X146: 48067 | Y146: 48149 | Z146: 48247 | AA146: 48337 | AB146: 48431 | AC146: 48513 | AD146: 48618 | AE146: 48701 | AF146: 48802 | AG146: 48877 | AH146: 48982 | AI146: 49065 | AJ146: 49166 | AK146: 49241 | AL146: 49353 | AM146: 49436 | AN146: 49537 | AO146: 49612 | AP146: 49717 | AQ146: 49800 | AR146: 49901
D147: Ex-Date | E147: 46352 | F147: 46441 | G147: 46531 | H147: 46636 | I147: 46707 | J147: 46812 | K147: 46896 | L147: 47002 | M147: 47078 | N147: 47176 | O147: 47261 | P147: 47367 | Q147: 47442 | R147: 47540 | S147: 47626 | T147: 47731 | U147: 47806 | V147: 47904 | W147: 47990 | X147: 48095 | Y147: 48170 | Z147: 48268 | AA147: 48358 | AB147: 48463 | AC147: 48534 | AD147: 48639 | AE147: 48722 | AF147: 48828 | AG147: 48898 | AH147: 49003 | AI147: 49086 | AJ147: 49192 | AK147: 49262 | AL147: 49374 | AM147: 49457 | AN147: 49563 | AO147: 49633 | AP147: 49738 | AQ147: 49821 | AR147: 49927
D148: Amount Per Share | E148: 0.6625 | F148: 0.6625 | G148: 0.6625 | H148: 0.6625 | I148: 0.675 | J148: 0.675 | K148: 0.675 | L148: 0.675 | M148: 0.6875 | N148: 0.6875 | O148: 0.6875 | P148: 0.6875 | Q148: 0.7 | R148: 0.7 | S148: 0.7 | T148: 0.7 | U148: 0.7125 | V148: 0.7125 | W148: 0.7125 | X148: 0.7125 | Y148: 0.725 | Z148: 0.725 | AA148: 0.725 | AB148: 0.725 | AC148: 0.7375 | AD148: 0.7375 | AE148: 0.7375 | AF148: 0.7375 | AG148: 0.75 | AH148: 0.75 | AI148: 0.75 | AJ148: 0.75 | AK148: 0.7625 | AL148: 0.7625 | AM148: 0.7625 | AN148: 0.7625 | AO148: 0.7625 | AP148: 0.7625 | AQ148: 0.7625 | AR148: 0.7625
A150: =IF('AS51'!$C$19="","",'AS51'!$C$19) | B150: =IF($A150="",0,COUNT($E151:$CZ151)) | C150: =IF($B150=0,0,MAX($E151:$CZ151)) | D150: =_xll.BDS($A150,'Field Check'!$C$44,"headers=y","startcol=1","endcol=7","dir=h","DVD_START_DT",'Field Check'!$C$59,"DVD_END_DT",'Field Check'!$D$59,"cols=2;rows=7") | E150: 46240
D151: Ex-Date | E151: 46254
D152: Record Date | E152: 46255
D153: Payable Date | E153: 46290
D154: Dividend Amount | E154: 0.03
D155: Dividend Frequency | E155: Semi-Anl
D156: Dividend Type | E156: Interim
...

Sheet Accrual
B2: DIVIDEND ACCRUAL PER STOCK, PER CONTRACT
B3: shares x FX x window DPS / divisor. Franked band = gross x the stock's franked %.
B5: CHECKS
B6: AS51 members missing shares | C6: =SUMPRODUCT(('AS51'!$A$6:$A$275<>"")*('AS51'!$B$6:$B$275="")) | F6: Paste index shares into column B of the data tab. Anything counted here contributes nothing.
B7: MXAU members missing shares | C7: =SUMPRODUCT((MXAU!$A$6:$A$175<>"")*(MXAU!$B$6:$B$175=""))
B8: Divisors entered (AS51 / MXAU) | C8: =IF(ISNUMBER('AS51'!$B$3),"OK","MISSING") | D8: =IF(ISNUMBER(MXAU!$B$3),"OK","MISSING") | F8: B3 on each data tab. Without it every cell below is blank.
B9: Payers declaring in another currency | C9: =SUMPRODUCT(('AS51'!$C$6:$C$275<>"")*(LEN('AS51'!$P$6:$P$275)=3)*('AS51'!$P$6:$P$275<>'AS51'!$D$2))+SUMPRODUCT((MXAU!$C$6:$C$175<>"")*(LEN(MXAU!$P$6:$P$175)=3)*(MXAU!$P$6:$P$175<>MXAU!$D$2)) | F9: Converted by the Dvd FX column - typically BHP and RIO (declare in USD).
B10: Overrides | C10: =IF(Override!$C$4="ON","ON - "&Override!$E$4&" active","OFF")
B11: S&P/ASX 200 (AS51) | F11: GROSS DIVIDEND (index pts) | W11: FRANKED PORTION (index pts) | AN11: SECTOR PICK | AQ11: o/w SPECIAL + RETURN OF CAPITAL (index pts) - Bloomberg history only, no override interaction; futures FV excludes these by default | BH11: FRANKED PORTION of specials (index pts)
B12: window start | F12: =IF(Expiries!$B16="","",Expiries!$J16) | G12: =IF(Expiries!$B17="","",Expiries!$J17) | H12: =IF(Expiries!$B18="","",Expiries!$J18) | I12: =IF(Expiries!$B19="","",Expiries!$J19) | J12: =IF(Expiries!$B20="","",Expiries!$J20) | K12: =IF(Expiries!$B21="","",Expiries!$J21) | L12: =IF(Expiries!$B22="","",Expiries!$J22) | M12: =IF(Expiries!$B23="","",Expiries!$J23) | N12: =IF(Expiries!$B24="","",Expiries!$J24) | O12: =IF(Expiries!$B25="","",Expiries!$J25) | P12: =IF(Expiries!$B26="","",Expiries!$J26) | Q12: =IF(Expiries!$B27="","",Expiries!$J27) | R12: =IF(Expiries!$B28="","",Expiries!$J28) | S12: =IF(Expiries!$B29="","",Expiries!$J29) | T12: =IF(Expiries!$B30="","",Expiries!$J30) | U12: =IF(Expiries!$B31="","",Expiries!$J31) | W12: =IF(Expiries!$B16="","",Expiries!$J16) | X12: =IF(Expiries!$B17="","",Expiries!$J17) | Y12: =IF(Expiries!$B18="","",Expiries!$J18) | Z12: =IF(Expiries!$B19="","",Expiries!$J19) | AA12: =IF(Expiries!$B20="","",Expiries!$J20) | AB12: =IF(Expiries!$B21="","",Expiries!$J21) | AC12: =IF(Expiries!$B22="","",Expiries!$J22) | AD12: =IF(Expiries!$B23="","",Expiries!$J23) | AE12: =IF(Expiries!$B24="","",Expiries!$J24) | AF12: =IF(Expiries!$B25="","",Expiries!$J25) | AG12: =IF(Expiries!$B26="","",Expiries!$J26) | AH12: =IF(Expiries!$B27="","",Expiries!$J27) | AI12: =IF(Expiries!$B28="","",Expiries!$J28) | AJ12: =IF(Expiries!$B29="","",Expiries!$J29) | AK12: =IF(Expiries!$B30="","",Expiries!$J30) | AL12: =IF(Expiries!$B31="","",Expiries!$J31) | AQ12: =IF(Expiries!$B16="","",Expiries!$J16) | AR12: =IF(Expiries!$B17="","",Expiries!$J17) | AS12: =IF(Expiries!$B18="","",Expiries!$J18) | AT12: =IF(Expiries!$B19="","",Expiries!$J19) | AU12: =IF(Expiries!$B20="","",Expiries!$J20) | AV12: =IF(Expiries!$B21="","",Expiries!$J21) | AW12: =IF(Expiries!$B22="","",Expiries!$J22) | AX12: =IF(Expiries!$B23="","",Expiries!$J23) | AY12: =IF(Expiries!$B24="","",Expiries!$J24) | AZ12: =IF(Expiries!$B25="","",Expiries!$J25) | BA12: =IF(Expiries!$B26="","",Expiries!$J26) | BB12: =IF(Expiries!$B27="","",Expiries!$J27) | BC12: =IF(Expiries!$B28="","",Expiries!$J28) | BD12: =IF(Expiries!$B29="","",Expiries!$J29) | BE12: =IF(Expiries!$B30="","",Expiries!$J30) | BF12: =IF(Expiries!$B31="","",Expiries!$J31) | BH12: =IF(Expiries!$B16="","",Expiries!$J16) | BI12: =IF(Expiries!$B17="","",Expiries!$J17) | BJ12: =IF(Expiries!$B18="","",Expiries!$J18) | BK12: =IF(Expiries!$B19="","",Expiries!$J19) | BL12: =IF(Expiries!$B20="","",Expiries!$J20) | BM12: =IF(Expiries!$B21="","",Expiries!$J21) | BN12: =IF(Expiries!$B22="","",Expiries!$J22) | BO12: =IF(Expiries!$B23="","",Expiries!$J23) | BP12: =IF(Expiries!$B24="","",Expiries!$J24) | BQ12: =IF(Expiries!$B25="","",Expiries!$J25) | BR12: =IF(Expiries!$B26="","",Expiries!$J26) | BS12: =IF(Expiries!$B27="","",Expiries!$J27) | BT12: =IF(Expiries!$B28="","",Expiries!$J28) | BU12: =IF(Expiries!$B29="","",Expiries!$J29) | BV12: =IF(Expiries!$B30="","",Expiries!$J30) | BW12: =IF(Expiries!$B31="","",Expiries!$J31)
