Workbook
Name VAL_DATE: Summary!$C$11
Name YEAR_Y: Summary!$C$12
Name INC_SPECIALS: Summary!$C$13
Name RMB_CROSS: Summary!$C$14
Name HORIZON_DT: Summary!$C$15
Name PULL_FUND: Summary!$C$16
Name HIST_FROM: Summary!$C$18
Name HIST_TO: Summary!$D$18
Name OV_SWITCH: Override!$C$4
Name GRID_FROM: Grids!$D$5
Name GRID_TO: Grids!$D$6
Name VAL_SERIAL: Grids!$D$7
Name REALIZED_TO: Grids!$D$8
Name PROJ_FROM: Grids!$D$9
Name PEND_FROM: Pending!$F$4
Name PEND_TO: Pending!$H$4
Name FLD_PROJ: 'Field Check'!$C$6
Name FLD_HIST: 'Field Check'!$C$7
Name FLD_CCY: 'Field Check'!$C$8
Name FLD_DPS12M: 'Field Check'!$C$9
Name FLD_YLD12M: 'Field Check'!$C$10
Name EPS_FIELD: 'Field Check'!$C$15
Name YR_OVERRIDE: 'Field Check'!$C$16
Name PAYOUT_FIELD: 'Field Check'!$C$17
Name NDEBITDA_FIELD: 'Field Check'!$C$18
Name EBINT_FIELD: 'Field Check'!$C$19
Name NDE_FIELD: 'Field Check'!$C$20
Name BUYBACK_QUERY: 'Field Check'!$C$21
Name FCF_FIELD: 'Field Check'!$C$24
Name BESTEPS_FIELD: 'Field Check'!$C$25
Name BESTDPS_FIELD: 'Field Check'!$C$26
Name FWD_OVERRIDE: 'Field Check'!$C$27
Name TYPE1: 'Field Check'!$C$30
Name TYPE2: 'Field Check'!$C$31
Name TYPE3: 'Field Check'!$C$32
Name TYPE4: 'Field Check'!$C$33
Name SPECIAL_LBL: 'Field Check'!$C$34
Name OVR_TICKERS: Override!$B$12:$B$71
Name OVR_BASE: Override!$D$12:$D$71
Name OVR_LOW: Override!$E$12:$E$71
Name OVR_HIGH: Override!$F$12:$F$71

Sheet Field Check
B1: FIELD MNEMONIC TESTER & CONFIG
B2: Every mnemonic, query and type label lives on this tab - fix one here and the whole book follows. Green = verified on YOUR terminal. Amber = candidate.
B3: Test ticker | C3: 700 HK Equity
B4: WHEN SOMETHING BREAKS: 1) the HEALTH strip on Summary 2) the status column E below 3) the two live samples at the bottom - a changed spill shape shows there instantly.
B5: CONFIRMED - dividends & members
B6: Projected dividends (BDS) | C6: BDVD_ALL_PROJECTIONS | F6: Columns: Projected Declared / Ex-Date / Amount (the calendar pulls just these three). The declared date is filled even for far forecasts - ANNOUNCED means it has already passed.
B7: Dividend history (BDS) | C7: DVD_HIST_ALL | F7: Columns: Declared / Ex / Record / Payable / AMOUNT (5th) / Frequency / Type.
B8: Dividend currency (BDP) | C8: EQY_DVD_CRNCY | F8: Feeds the FX-to-HKD column.
B9: DPS 12M (BDP) | C9: EQY_DVD_SH_12M | F9: Reference + the divisor check on Summary.
B10: Yield 12M (BDP) | C10: EQY_DVD_YLD_12M | F10: Reference; also read at index level on Summary.
B11: GICS sector (BDP) | C11: GICS_SECTOR_NAME | F11: Drives every sector rollup and the Override view.
B12: Name (BDP) | C12: NAME
B14: CONFIRMED - fundamentals (verified on your terminal run)
B15: EPS by fiscal year (BDP) | C15: IS_EPS | F15: With the year override below. Tested OK.
B16: fiscal-year override name | C16: EQY_FUND_YEAR
B17: Payout by fiscal year (BDP) | C17: DVD_PAYOUT_RATIO | F17: Fiscal basis - DPS and EPS on the same clock. Tested OK.
B18: Net debt / EBITDA (BDP) | C18: NET_DEBT_TO_EBITDA | F18: Tested OK.
B19: EBITDA / interest (BDP) | C19: EBITDA_TO_INTEREST_EXPN | F19: Tested OK.
B20: Net debt / equity (BDH, 5Y) | C20: NET_DEBT_TO_SHRHLDR_EQTY | F20: Your working BDH pull (note _EQTY): five rows of date + value per stock on Fund History.
B21: Buyback yield by year (BQL) | C21: dropna((bs_tot_val_of_shares_repurchased(fpt=ltm)/cur_mkt_cap())*100, true) | F21: Your working BQL query: LTM buybacks / market cap, yearly, per stock on Fund History.
B23: CANDIDATES - check column E after a refresh | D23: live result | E23: status
B24: FCF yield (BDP) | C24: FREE_CASH_FLOW_YIELD | D24: =BDP($C$3,$C$24) | E24: =IF(ISNUMBER($D$24),"OK","check field") | F24: Came back N/A on the test name - the field exists but may need a different basis. Alternates: CF_FREE_CASH_FLOW_YIELD, FCF_YIELD.
B25: Forward EPS (BDP) | C25: BEST_EPS | D25: =BDP($C$3,$C$25,$C$27,TEXT(MOD(Summary!$C$12,100),"00")&"Y") | E25: =IF(ISNUMBER($D$25),"OK","check field") | F25: Consensus EPS for year Y via the period override below.
B26: Forward DPS (BDP) | C26: BEST_DPS | D26: =BDP($C$3,$C$26,$C$27,TEXT(MOD(Summary!$C$12,100),"00")&"Y") | E26: =IF(ISNUMBER($D$26),"OK","check field") | F26: Consensus DPS for year Y - sits beside the model's own number on Fundamentals.
B27: forward period override name | C27: BEST_FPERIOD_OVERRIDE | F27: e.g. 26Y = fiscal 2026. Alternate: BEST_FPERIOD_OVR.
B29: DIVIDEND TYPES THAT COUNT AS CASH (anything not listed is ignored) | F29: Seen in your data and EXCLUDED by omission: Spinoff, Bonus, Stock Split, Rights Issue, Entitlement, Omitted, Discontinued - none are cash dividends.
B30: Cash type 1 | C30: Final
B31: Cash type 2 | C31: Interim
B32: Cash type 3 | C32: Regular Cash
B33: Cash type 4 | C33: Return of Capital | F33: Cash to holders - blank this cell to exclude it.
B34: Special label | C34: Special Cash | F34: Counted only when the specials switch on Summary is Y.
B36: LIVE SAMPLE 1 - projections, FULL width (the calendar itself pulls only columns 1-3)
C37: =BDS($C$3,$C$6,"headers=y","startcol=1","endcol=7","dir=h")
B45: LIVE SAMPLE 2 - dividend history (7 rows: the amount is the 5th)
C46: =BDS($C$3,$C$7,"headers=y","startcol=1","endcol=7","dir=h","DVD_START_DT",Summary!$C$18,"DVD_END_DT",Summary!$D$18)
B55: YOUR BQL QUERY - reference
C56: '=@BQL.QUERY(AC16&AC17,"showallcols=t, showheaders=f, xlfill=b","cols=10;rows=1")
C57: let(#div=dividends(offset=1, status=TBA);#hastba=count(#div().status);) get(groupsort(#div,sortby=#div().ex_date,order=asc)) for(filter(members('HSI Index'),#hastba>0))
B59: Leave the space right of both samples clear - they spill as far as they need.

Sheet Summary
B1: HK DIVIDEND FUTURES MODEL - HSI / HSTECH / HSCEI
B2: Full-year index dividend points (what has gone ex + what is still to come) against the dividend futures. The year is the contract - there is no monthly ladder.
B3: HEALTH | C3: =IF(N(HSI!$L$2)=0,"paste quantities + divisor on the HSI tab",IF(ISNUMBER(HSI!$B$3)=FALSE,"divisor missing (HSI B3)",IF(N(HSI!$Y$5)=0,"waiting for prices - refresh on the terminal",IF(ABS(C48-1)>0.02,"UNITS OFF - multiply quantities by ~"&TEXT(C48,"#,##0"),IF(C55>0,"calendar window overflow - widen it",IF(C53>0,C53&" amount(s) TBA - consider overriding","OK")))))) | D3: =IF(N(HSTECH!$L$2)=0,"paste quantities + divisor on the HSTECH tab",IF(ISNUMBER(HSTECH!$B$3)=FALSE,"divisor missing (HSTECH B3)",IF(N(HSTECH!$Y$5)=0,"waiting for prices - refresh on the terminal",IF(ABS(D48-1)>0.02,"UNITS OFF - multiply quantities by ~"&TEXT(D48,"#,##0"),IF(D55>0,"calendar window overflow - widen it",IF(D53>0,D53&" amount(s) TBA - consider overriding","OK")))))) | E3: =IF(N(HSCEI!$L$2)=0,"paste quantities + divisor on the HSCEI tab",IF(ISNUMBER(HSCEI!$B$3)=FALSE,"divisor missing (HSCEI B3)",IF(N(HSCEI!$Y$5)=0,"waiting for prices - refresh on the terminal",IF(ABS(E48-1)>0.02,"UNITS OFF - multiply quantities by ~"&TEXT(E48,"#,##0"),IF(E55>0,"calendar window overflow - widen it",IF(E53>0,E53&" amount(s) TBA - consider overriding","OK")))))) | G3: <- these three cells always name the next thing to fix. When all three say OK, the model is trustworthy.
B4: START HERE
B5: 1 | C5: Paste BASKET QUANTITY into column B and the INDEX DIVISOR into B3 on the HSI, HSTECH and HSCEI tabs (blue cells). Quantity and divisor must be in CONSISTENT units - the SCALE FACTOR row in CHECKS below tells you instantly if they are not, and by how much.
B6: 2 | C6: Set the control block below, then enter your futures tickers in the MODEL block (or just type the quote you see).
B7: 3 | C7: On a Bloomberg terminal press Ctrl+Alt+F9 and wait - the first refresh is a few thousand requests. Set 'Pull fundamentals' to N for a fast dividends-only refresh.
B8: 4 | C8: Read the CHECKS block at the bottom before you quote a gap.
B10: CONTROL
B11: Valuation date | C11: =TODAY() | G11: Today by default. Type a date to freeze the study.
B12: Year (Y) - the futures year | C12: =YEAR($C$11) | G12: 2026 prices the Dec26 contract. 2027 models next year (realized empties, projections fill it). A past year gives the realized outcome.
B13: Include special dividends? | C13: Y | G13: Applies to REALIZED dividends (history carries a type). Bloomberg projections carry no type, so projected specials cannot be split out - they are always included.
B14: RMB cross for CNY dividends | C14: CNY | G14: CNY or CNH - which cross converts RMB-declared dividends into HKD.
B15: Pending list horizon | C15: =DATE($C$12,12,31) | G15: Pending shows every event with an ex-date after the valuation date up to here.
B16: Pull fundamentals? (Y/N) | C16: Y | G16: N blanks the EPS / payout / forward / buyback / leverage requests (~3,500 of them). The dividend model itself never needs them.
B17: Overrides | C17: =IF(Override!$C$4="ON","ON - "&Override!$E$4&" stock(s) set - the model uses YOUR numbers there.","OFF - pure Bloomberg projections.")
B18: History pull window (auto) | C18: =TEXT(DATE($C$12-5,1,1),"yyyymmdd") | D18: =TEXT(MAX($C$11,DATE($C$12,12,31)),"yyyymmdd") | G18: Five full years before Y plus the year itself - feeds the model and the 5-year fundamentals.
B20: MODEL vs FUTURES (index dividend points for year Y)
C21: HSI | D21: HSTECH | E21: HSCEI | G21: Points are index points: basket qty x FX-to-HKD x DPS / divisor.
B22: Index ticker | C22: HSI Index | D22: HSTECH Index | E22: HSCEI Index
B23: Index level | C23: =IF($C$22="","",BDP($C$22,"PX_LAST")) | D23: =IF($D$22="","",BDP($D$22,"PX_LAST")) | E23: =IF($E$22="","",BDP($E$22,"PX_LAST"))
B25: Realized so far (pts) | C25: =HSI!$O$5 | D25: =HSTECH!$O$5 | E25: =HSCEI!$O$5 | G25: Ex-dates from 1 Jan of Y to the valuation date - fact, never overridden. Cash dividend types only (no spinoffs / scrip - see the type list on Field Check).
B26: Still to come - Bloomberg (pts) | C26: =HSI!$W$5 | D26: =HSTECH!$W$5 | E26: =HSCEI!$W$5
B27: Still to come - EFFECTIVE (pts) | C27: =HSI!$P$5 | D27: =HSTECH!$P$5 | E27: =HSCEI!$P$5
B28: YEAR TOTAL - base (pts) | C28: =HSI!$Q$5 | D28: =HSTECH!$Q$5 | E28: =HSCEI!$Q$5
B29: your LOW case (pts) | C29: =HSI!$R$5 | D29: =HSTECH!$R$5 | E29: =HSCEI!$R$5
B30: your HIGH case (pts) | C30: =HSI!$S$5 | D30: =HSTECH!$S$5 | E30: =HSCEI!$S$5
B31: Implied index dividend yield | C31: =IFERROR(C28/C23,"") | D31: =IFERROR(D28/D23,"") | E31: =IFERROR(E28/E23,"")
B33: Futures ticker
B34: Futures price (Bloomberg) | C34: =IF($C$33="","",BDP($C$33,"PX_LAST")) | D34: =IF($D$33="","",BDP($D$33,"PX_LAST")) | E34: =IF($E$33="","",BDP($E$33,"PX_LAST"))
B35: Futures quote - type it yourself
B36: FUTURES USED | C36: =IF(ISNUMBER(C35),C35,IF(ISNUMBER(C34),C34,"")) | D36: =IF(ISNUMBER(D35),D35,IF(ISNUMBER(D34),D34,"")) | E36: =IF(ISNUMBER(E35),E35,IF(ISNUMBER(E34),E34,""))
B37: GAP model - futures (pts) | C37: =IF(C36="","",C28-C36) | D37: =IF(D36="","",D28-D36) | E37: =IF(E36="","",E28-E36) | G37: Positive = your model sees MORE dividends than the futures pay for. Read the TBA line in CHECKS before quoting it.
B38: Gap (% of futures) | C38: =IF(C36="","",IFERROR(C37/C36,"")) | D38: =IF(D36="","",IFERROR(D37/D36,"")) | E38: =IF(E36="","",IFERROR(E37/E36,""))
B39: Where the futures sit | C39: =IF(C36="","",IF((C36>=C29)*(C36<=C30)>0,"inside your low-high range",IF(C36<C29,"BELOW your low - cheap vs you","ABOVE your high - rich vs you"))) | D39: =IF(D36="","",IF((D36>=D29)*(D36<=D30)>0,"inside your low-high range",IF(D36<D29,"BELOW your low - cheap vs you","ABOVE your high - rich vs you"))) | E39: =IF(E36="","",IF((E36>=E29)*(E36<=E30)>0,"inside your low-high range",IF(E36<E29,"BELOW your low - cheap vs you","ABOVE your high - rich vs you")))
B41: CHECKS (read these before trusting the gap)
B42: Members returned | C42: =HSI!$H$2 | D42: =HSTECH!$H$2 | E42: =HSCEI!$H$2 | G42: Short of the real membership means the BDS pull was cut off.
B43: Basket quantities pasted | C43: =HSI!$L$2 | D43: =HSTECH!$L$2 | E43: =HSCEI!$L$2 | G43: Should equal members.
B44: Members with NO quantity | C44: =HSI!$P$2 | D44: =HSTECH!$P$2 | E44: =HSCEI!$P$2 | G44: Each one contributes zero points.
B45: Divisor entered | C45: =IF(ISNUMBER(HSI!$B$3),"OK","MISSING") | D45: =IF(ISNUMBER(HSTECH!$B$3),"OK","MISSING") | E45: =IF(ISNUMBER(HSCEI!$B$3),"OK","MISSING") | G45: Without it every points column is blank.
B46: Basket value (index pts) | C46: =HSI!$Y$5 | D46: =HSTECH!$Y$5 | E46: =HSCEI!$Y$5 | G46: SUM of quantity x price / divisor. If your quantities and divisor are the real index ones, this IS the index level.
B47: Index level (the comparison) | C47: =C23 | D47: =D23 | E47: =E23
B48: SCALE CHECK - level / basket value | C48: =IF(N(HSI!$Y$5)=0,"",C23/HSI!$Y$5) | D48: =IF(N(HSTECH!$Y$5)=0,"",D23/HSTECH!$Y$5) | E48: =IF(N(HSCEI!$Y$5)=0,"",E23/HSCEI!$Y$5) | G48: MUST BE 1.00. If it reads 100,000 your quantities are that much too small - multiply them by exactly this number. Fix before reading anything else.
B49: Bottom-up 12M yield | C49: =IFERROR(HSI!$V$5/C23,"") | D49: =IFERROR(HSTECH!$V$5/D23,"") | E49: =IFERROR(HSCEI!$V$5/E23,"") | G49: Trailing 12M dividends of your basket over the index level.
B50: Bloomberg index 12M yield | C50: =IF($C$22="","",IFERROR(BDP($C$22,"EQY_DVD_YLD_12M")/100,"")) | D50: =IF($D$22="","",IFERROR(BDP($D$22,"EQY_DVD_YLD_12M")/100,"")) | E50: =IF($E$22="","",IFERROR(BDP($E$22,"EQY_DVD_YLD_12M")/100,""))
B51: THE DIVISOR CHECK - gap (bp) | C51: =IF(N(C50)*N(C49)=0,"",(C49-C50)*10000) | D51: =IF(N(D50)*N(D49)=0,"",(D49-D50)*10000) | E51: =IF(N(E50)*N(E49)=0,"",(E49-E50)*10000) | G51: Bottom-up minus Bloomberg, once the SCALE CHECK is 1.00.
B52: Dividend ratio (BBG / bottom-up) | C52: =IF(N(C49)=0,"",C50/C49) | D52: =IF(N(D49)=0,"",D50/D49) | E52: =IF(N(E49)=0,"",E50/E49) | G52: Only meaningful once the SCALE CHECK reads 1.00. Then it is a REAL dividend difference - a different member list, specials, or free-float factors - not units.
B53: Stocks with an amount still TBA | C53: =COUNTIF(HSI!$U$7:$U$106,"TBA amount - override me") | D53: =COUNTIF(HSTECH!$U$7:$U$46,"TBA amount - override me") | E53: =COUNTIF(HSCEI!$U$7:$U$66,"TBA amount - override me") | G53: Announced with no amount yet: they add ZERO until you override them.
B54: Stocks you have overridden | C54: =COUNTIF(HSI!$U$7:$U$106,"overridden") | D54: =COUNTIF(HSTECH!$U$7:$U$46,"overridden") | E54: =COUNTIF(HSCEI!$U$7:$U$66,"overridden")
B55: Events beyond the data window | C55: =COUNTA('Dvd Calendar'!$AS$10:$CF$1109) | D55: =COUNTA('Dvd Calendar'!$AS$1115:$CF$1554) | E55: =COUNTA('Dvd Calendar'!$AS$1560:$CF$2219) | G55: Must be 0 - otherwise a stock has more events than the calendar window holds (one parameter to widen).
B56: Pending list - shown / total | C56: =COUNT(Pending!$B$10:$B$309)&" / "&COUNTIFS(Grids!$EE$12:$GQ$111,">="&PEND_FROM,Grids!$EE$12:$GQ$111,"<"&PEND_TO) | D56: =COUNT(Pending!$B$316:$B$435)&" / "&COUNTIFS(Grids!$EE$116:$GQ$155,">="&PEND_FROM,Grids!$EE$116:$GQ$155,"<"&PEND_TO) | E56: =COUNT(Pending!$B$442:$B$621)&" / "&COUNTIFS(Grids!$EE$160:$GQ$219,">="&PEND_FROM,Grids!$EE$160:$GQ$219,"<"&PEND_TO) | G56: If these differ the list is truncated; the model still counts them.

Sheet Pending
B1: PENDING DIVIDENDS - EVERYTHING STILL TO GO EX, SORTED BY DATE
B2: Ex-dates after the valuation date, up to the horizon. Amount TBA counts as ZERO until you override that stock.
B4: Horizon | C4: =HORIZON_DT | E4: thresholds -> | F4: =(VAL_DATE+1)*1000000000 | H4: =(HORIZON_DT+1)*1000000000 | I4: =Summary!$C$17
B6: Hang Seng Index (HSI)
B7: Events pending | C7: =COUNTIFS(Grids!$EE$12:$GQ$111,">="&PEND_FROM,Grids!$EE$12:$GQ$111,"<"&PEND_TO) | D7: =IF($C$7>300,"LIST TRUNCATED - showing the first 300; the model still counts all of them.","all listed below") | L7: offset | M7: =COUNTIF(Grids!$EE$12:$GQ$111,"<"&PEND_FROM)
B9: Ex-date | C9: Ticker | D9: Name | E9: DPS (declared ccy) | F9: CCY | G9: Index pts | H9: Cumulative pts | I9: Status | J9: Your override? | L9: engine
B10: =IF($L10="","",$M10) | C10: =IF($L10="","",INDEX(HSI!$C$7:$C$106,$N10)) | D10: =IF($L10="","",INDEX(HSI!$D$7:$D$106,$N10)) | E10: =IF($L10="","",IF($P10=0,"TBA",IFERROR(INDEX(Grids!$C$12:$BO$111,$N10,$O10),"-"))) | F10: =IF($L10="","",INDEX(HSI!$F$7:$F$106,$N10)) | G10: =IF($L10="","",IF($P10=0,"TBA",IFERROR(INDEX(Grids!$BQ$12:$EC$111,$N10,$O10),"-"))) | H10: =IF($L10="","",SUM($G$10:$G10)) | I10: =IF($L10="","",IF(INT(($L10-INT($L10/10000000)*10000000)/1000000)=0,"Bloomberg projection",IF($P10=1,"ANNOUNCED","ANNOUNCED - amount TBA"))) | J10: =IF($L10="","",IF((OV_SWITCH="ON")*(COUNTIFS(OVR_TICKERS,INDEX(HSI!$C$7:$C$106,$N10),OVR_BASE,">=0")>0)>0,"stock overridden","")) | L10: =IFERROR(IF(SMALL(Grids!$EE$12:$GQ$111,$M$7+1)>=PEND_TO,"",SMALL(Grids!$EE$12:$GQ$111,$M$7+1)),"") | M10: =IF($L10="","",INT($L10/1000000000)) | N10: =IF($L10="","",INT(($L10-INT($L10/1000000)*1000000)/1000)) | O10: =IF($L10="","",$L10-INT($L10/1000)*1000) | P10: =IF($L10="","",INT(($L10-INT($L10/1000000000)*1000000000)/100000000))
B11: =IF($L11="","",$M11) | C11: =IF($L11="","",INDEX(HSI!$C$7:$C$106,$N11)) | D11: =IF($L11="","",INDEX(HSI!$D$7:$D$106,$N11)) | E11: =IF($L11="","",IF($P11=0,"TBA",IFERROR(INDEX(Grids!$C$12:$BO$111,$N11,$O11),"-"))) | F11: =IF($L11="","",INDEX(HSI!$F$7:$F$106,$N11)) | G11: =IF($L11="","",IF($P11=0,"TBA",IFERROR(INDEX(Grids!$BQ$12:$EC$111,$N11,$O11),"-"))) | H11: =IF($L11="","",SUM($G$10:$G11)) | I11: =IF($L11="","",IF(INT(($L11-INT($L11/10000000)*10000000)/1000000)=0,"Bloomberg projection",IF($P11=1,"ANNOUNCED","ANNOUNCED - amount TBA"))) | J11: =IF($L11="","",IF((OV_SWITCH="ON")*(COUNTIFS(OVR_TICKERS,INDEX(HSI!$C$7:$C$106,$N11),OVR_BASE,">=0")>0)>0,"stock overridden","")) | L11: =IFERROR(IF(SMALL(Grids!$EE$12:$GQ$111,$M$7+2)>=PEND_TO,"",SMALL(Grids!$EE$12:$GQ$111,$M$7+2)),"") | M11: =IF($L11="","",INT($L11/1000000000)) | N11: =IF($L11="","",INT(($L11-INT($L11/1000000)*1000000)/1000)) | O11: =IF($L11="","",$L11-INT($L11/1000)*1000) | P11: =IF($L11="","",INT(($L11-INT($L11/1000000000)*1000000000)/100000000))
B12: =IF($L12="","",$M12) | C12: =IF($L12="","",INDEX(HSI!$C$7:$C$106,$N12)) | D12: =IF($L12="","",INDEX(HSI!$D$7:$D$106,$N12)) | E12: =IF($L12="","",IF($P12=0,"TBA",IFERROR(INDEX(Grids!$C$12:$BO$111,$N12,$O12),"-"))) | F12: =IF($L12="","",INDEX(HSI!$F$7:$F$106,$N12)) | G12: =IF($L12="","",IF($P12=0,"TBA",IFERROR(INDEX(Grids!$BQ$12:$EC$111,$N12,$O12),"-"))) | H12: =IF($L12="","",SUM($G$10:$G12)) | I12: =IF($L12="","",IF(INT(($L12-INT($L12/10000000)*10000000)/1000000)=0,"Bloomberg projection",IF($P12=1,"ANNOUNCED","ANNOUNCED - amount TBA"))) | J12: =IF($L12="","",IF((OV_SWITCH="ON")*(COUNTIFS(OVR_TICKERS,INDEX(HSI!$C$7:$C$106,$N12),OVR_BASE,">=0")>0)>0,"stock overridden","")) | L12: =IFERROR(IF(SMALL(Grids!$EE$12:$GQ$111,$M$7+3)>=PEND_TO,"",SMALL(Grids!$EE$12:$GQ$111,$M$7+3)),"") | M12: =IF($L12="","",INT($L12/1000000000)) | N12: =IF($L12="","",INT(($L12-INT($L12/1000000)*1000000)/1000)) | O12: =IF($L12="","",$L12-INT($L12/1000)*1000) | P12: =IF($L12="","",INT(($L12-INT($L12/1000000000)*1000000000)/100000000))
B13: =IF($L13="","",$M13) | C13: =IF($L13="","",INDEX(HSI!$C$7:$C$106,$N13)) | D13: =IF($L13="","",INDEX(HSI!$D$7:$D$106,$N13)) | E13: =IF($L13="","",IF($P13=0,"TBA",IFERROR(INDEX(Grids!$C$12:$BO$111,$N13,$O13),"-"))) | F13: =IF($L13="","",INDEX(HSI!$F$7:$F$106,$N13)) | G13: =IF($L13="","",IF($P13=0,"TBA",IFERROR(INDEX(Grids!$BQ$12:$EC$111,$N13,$O13),"-"))) | H13: =IF($L13="","",SUM($G$10:$G13)) | I13: =IF($L13="","",IF(INT(($L13-INT($L13/10000000)*10000000)/1000000)=0,"Bloomberg projection",IF($P13=1,"ANNOUNCED","ANNOUNCED - amount TBA"))) | J13: =IF($L13="","",IF((OV_SWITCH="ON")*(COUNTIFS(OVR_TICKERS,INDEX(HSI!$C$7:$C$106,$N13),OVR_BASE,">=0")>0)>0,"stock overridden","")) | L13: =IFERROR(IF(SMALL(Grids!$EE$12:$GQ$111,$M$7+4)>=PEND_TO,"",SMALL(Grids!$EE$12:$GQ$111,$M$7+4)),"") | M13: =IF($L13="","",INT($L13/1000000000)) | N13: =IF($L13="","",INT(($L13-INT($L13/1000000)*1000000)/1000)) | O13: =IF($L13="","",$L13-INT($L13/1000)*1000) | P13: =IF($L13="","",INT(($L13-INT($L13/1000000000)*1000000000)/100000000))
B14: =IF($L14="","",$M14) | C14: =IF($L14="","",INDEX(HSI!$C$7:$C$106,$N14)) | D14: =IF($L14="","",INDEX(HSI!$D$7:$D$106,$N14)) | E14: =IF($L14="","",IF($P14=0,"TBA",IFERROR(INDEX(Grids!$C$12:$BO$111,$N14,$O14),"-"))) | F14: =IF($L14="","",INDEX(HSI!$F$7:$F$106,$N14)) | G14: =IF($L14="","",IF($P14=0,"TBA",IFERROR(INDEX(Grids!$BQ$12:$EC$111,$N14,$O14),"-"))) | H14: =IF($L14="","",SUM($G$10:$G14)) | I14: =IF($L14="","",IF(INT(($L14-INT($L14/10000000)*10000000)/1000000)=0,"Bloomberg projection",IF($P14=1,"ANNOUNCED","ANNOUNCED - amount TBA"))) | J14: =IF($L14="","",IF((OV_SWITCH="ON")*(COUNTIFS(OVR_TICKERS,INDEX(HSI!$C$7:$C$106,$N14),OVR_BASE,">=0")>0)>0,"stock overridden","")) | L14: =IFERROR(IF(SMALL(Grids!$EE$12:$GQ$111,$M$7+5)>=PEND_TO,"",SMALL(Grids!$EE$12:$GQ$111,$M$7+5)),"") | M14: =IF($L14="","",INT($L14/1000000000)) | N14: =IF($L14="","",INT(($L14-INT($L14/1000000)*1000000)/1000)) | O14: =IF($L14="","",$L14-INT($L14/1000)*1000) | P14: =IF($L14="","",INT(($L14-INT($L14/1000000000)*1000000000)/100000000))
B15: =IF($L15="","",$M15) | C15: =IF($L15="","",INDEX(HSI!$C$7:$C$106,$N15)) | D15: =IF($L15="","",INDEX(HSI!$D$7:$D$106,$N15)) | E15: =IF($L15="","",IF($P15=0,"TBA",IFERROR(INDEX(Grids!$C$12:$BO$111,$N15,$O15),"-"))) | F15: =IF($L15="","",INDEX(HSI!$F$7:$F$106,$N15)) | G15: =IF($L15="","",IF($P15=0,"TBA",IFERROR(INDEX(Grids!$BQ$12:$EC$111,$N15,$O15),"-"))) | H15: =IF($L15="","",SUM($G$10:$G15)) | I15: =IF($L15="","",IF(INT(($L15-INT($L15/10000000)*10000000)/1000000)=0,"Bloomberg projection",IF($P15=1,"ANNOUNCED","ANNOUNCED - amount TBA"))) | J15: =IF($L15="","",IF((OV_SWITCH="ON")*(COUNTIFS(OVR_TICKERS,INDEX(HSI!$C$7:$C$106,$N15),OVR_BASE,">=0")>0)>0,"stock overridden","")) | L15: =IFERROR(IF(SMALL(Grids!$EE$12:$GQ$111,$M$7+6)>=PEND_TO,"",SMALL(Grids!$EE$12:$GQ$111,$M$7+6)),"") | M15: =IF($L15="","",INT($L15/1000000000)) | N15: =IF($L15="","",INT(($L15-INT($L15/1000000)*1000000)/1000)) | O15: =IF($L15="","",$L15-INT($L15/1000)*1000) | P15: =IF($L15="","",INT(($L15-INT($L15/1000000000)*1000000000)/100000000))
B16: =IF($L16="","",$M16) | C16: =IF($L16="","",INDEX(HSI!$C$7:$C$106,$N16)) | D16: =IF($L16="","",INDEX(HSI!$D$7:$D$106,$N16)) | E16: =IF($L16="","",IF($P16=0,"TBA",IFERROR(INDEX(Grids!$C$12:$BO$111,$N16,$O16),"-"))) | F16: =IF($L16="","",INDEX(HSI!$F$7:$F$106,$N16)) | G16: =IF($L16="","",IF($P16=0,"TBA",IFERROR(INDEX(Grids!$BQ$12:$EC$111,$N16,$O16),"-"))) | H16: =IF($L16="","",SUM($G$10:$G16)) | I16: =IF($L16="","",IF(INT(($L16-INT($L16/10000000)*10000000)/1000000)=0,"Bloomberg projection",IF($P16=1,"ANNOUNCED","ANNOUNCED - amount TBA"))) | J16: =IF($L16="","",IF((OV_SWITCH="ON")*(COUNTIFS(OVR_TICKERS,INDEX(HSI!$C$7:$C$106,$N16),OVR_BASE,">=0")>0)>0,"stock overridden","")) | L16: =IFERROR(IF(SMALL(Grids!$EE$12:$GQ$111,$M$7+7)>=PEND_TO,"",SMALL(Grids!$EE$12:$GQ$111,$M$7+7)),"") | M16: =IF($L16="","",INT($L16/1000000000)) | N16: =IF($L16="","",INT(($L16-INT($L16/1000000)*1000000)/1000)) | O16: =IF($L16="","",$L16-INT($L16/1000)*1000) | P16: =IF($L16="","",INT(($L16-INT($L16/1000000000)*1000000000)/100000000))
B17: =IF($L17="","",$M17) | C17: =IF($L17="","",INDEX(HSI!$C$7:$C$106,$N17)) | D17: =IF($L17="","",INDEX(HSI!$D$7:$D$106,$N17)) | E17: =IF($L17="","",IF($P17=0,"TBA",IFERROR(INDEX(Grids!$C$12:$BO$111,$N17,$O17),"-"))) | F17: =IF($L17="","",INDEX(HSI!$F$7:$F$106,$N17)) | G17: =IF($L17="","",IF($P17=0,"TBA",IFERROR(INDEX(Grids!$BQ$12:$EC$111,$N17,$O17),"-"))) | H17: =IF($L17="","",SUM($G$10:$G17)) | I17: =IF($L17="","",IF(INT(($L17-INT($L17/10000000)*10000000)/1000000)=0,"Bloomberg projection",IF($P17=1,"ANNOUNCED","ANNOUNCED - amount TBA"))) | J17: =IF($L17="","",IF((OV_SWITCH="ON")*(COUNTIFS(OVR_TICKERS,INDEX(HSI!$C$7:$C$106,$N17),OVR_BASE,">=0")>0)>0,"stock overridden","")) | L17: =IFERROR(IF(SMALL(Grids!$EE$12:$GQ$111,$M$7+8)>=PEND_TO,"",SMALL(Grids!$EE$12:$GQ$111,$M$7+8)),"") | M17: =IF($L17="","",INT($L17/1000000000)) | N17: =IF($L17="","",INT(($L17-INT($L17/1000000)*1000000)/1000)) | O17: =IF($L17="","",$L17-INT($L17/1000)*1000) | P17: =IF($L17="","",INT(($L17-INT($L17/1000000000)*1000000000)/100000000))
B18: =IF($L18="","",$M18) | C18: =IF($L18="","",INDEX(HSI!$C$7:$C$106,$N18)) | D18: =IF($L18="","",INDEX(HSI!$D$7:$D$106,$N18)) | E18: =IF($L18="","",IF($P18=0,"TBA",IFERROR(INDEX(Grids!$C$12:$BO$111,$N18,$O18),"-"))) | F18: =IF($L18="","",INDEX(HSI!$F$7:$F$106,$N18)) | G18: =IF($L18="","",IF($P18=0,"TBA",IFERROR(INDEX(Grids!$BQ$12:$EC$111,$N18,$O18),"-"))) | H18: =IF($L18="","",SUM($G$10:$G18)) | I18: =IF($L18="","",IF(INT(($L18-INT($L18/10000000)*10000000)/1000000)=0,"Bloomberg projection",IF($P18=1,"ANNOUNCED","ANNOUNCED - amount TBA"))) | J18: =IF($L18="","",IF((OV_SWITCH="ON")*(COUNTIFS(OVR_TICKERS,INDEX(HSI!$C$7:$C$106,$N18),OVR_BASE,">=0")>0)>0,"stock overridden","")) | L18: =IFERROR(IF(SMALL(Grids!$EE$12:$GQ$111,$M$7+9)>=PEND_TO,"",SMALL(Grids!$EE$12:$GQ$111,$M$7+9)),"") | M18: =IF($L18="","",INT($L18/1000000000)) | N18: =IF($L18="","",INT(($L18-INT($L18/1000000)*1000000)/1000)) | O18: =IF($L18="","",$L18-INT($L18/1000)*1000) | P18: =IF($L18="","",INT(($L18-INT($L18/1000000000)*1000000000)/100000000))
B19: =IF($L19="","",$M19) | C19: =IF($L19="","",INDEX(HSI!$C$7:$C$106,$N19)) | D19: =IF($L19="","",INDEX(HSI!$D$7:$D$106,$N19)) | E19: =IF($L19="","",IF($P19=0,"TBA",IFERROR(INDEX(Grids!$C$12:$BO$111,$N19,$O19),"-"))) | F19: =IF($L19="","",INDEX(HSI!$F$7:$F$106,$N19)) | G19: =IF($L19="","",IF($P19=0,"TBA",IFERROR(INDEX(Grids!$BQ$12:$EC$111,$N19,$O19),"-"))) | H19: =IF($L19="","",SUM($G$10:$G19)) | I19: =IF($L19="","",IF(INT(($L19-INT($L19/10000000)*10000000)/1000000)=0,"Bloomberg projection",IF($P19=1,"ANNOUNCED","ANNOUNCED - amount TBA"))) | J19: =IF($L19="","",IF((OV_SWITCH="ON")*(COUNTIFS(OVR_TICKERS,INDEX(HSI!$C$7:$C$106,$N19),OVR_BASE,">=0")>0)>0,"stock overridden","")) | L19: =IFERROR(IF(SMALL(Grids!$EE$12:$GQ$111,$M$7+10)>=PEND_TO,"",SMALL(Grids!$EE$12:$GQ$111,$M$7+10)),"") | M19: =IF($L19="","",INT($L19/1000000000)) | N19: =IF($L19="","",INT(($L19-INT($L19/1000000)*1000000)/1000)) | O19: =IF($L19="","",$L19-INT($L19/1000)*1000) | P19: =IF($L19="","",INT(($L19-INT($L19/1000000000)*1000000000)/100000000))
B20: =IF($L20="","",$M20) | C20: =IF($L20="","",INDEX(HSI!$C$7:$C$106,$N20)) | D20: =IF($L20="","",INDEX(HSI!$D$7:$D$106,$N20)) | E20: =IF($L20="","",IF($P20=0,"TBA",IFERROR(INDEX(Grids!$C$12:$BO$111,$N20,$O20),"-"))) | F20: =IF($L20="","",INDEX(HSI!$F$7:$F$106,$N20)) | G20: =IF($L20="","",IF($P20=0,"TBA",IFERROR(INDEX(Grids!$BQ$12:$EC$111,$N20,$O20),"-"))) | H20: =IF($L20="","",SUM($G$10:$G20)) | I20: =IF($L20="","",IF(INT(($L20-INT($L20/10000000)*10000000)/1000000)=0,"Bloomberg projection",IF($P20=1,"ANNOUNCED","ANNOUNCED - amount TBA"))) | J20: =IF($L20="","",IF((OV_SWITCH="ON")*(COUNTIFS(OVR_TICKERS,INDEX(HSI!$C$7:$C$106,$N20),OVR_BASE,">=0")>0)>0,"stock overridden","")) | L20: =IFERROR(IF(SMALL(Grids!$EE$12:$GQ$111,$M$7+11)>=PEND_TO,"",SMALL(Grids!$EE$12:$GQ$111,$M$7+11)),"") | M20: =IF($L20="","",INT($L20/1000000000)) | N20: =IF($L20="","",INT(($L20-INT($L20/1000000)*1000000)/1000)) | O20: =IF($L20="","",$L20-INT($L20/1000)*1000) | P20: =IF($L20="","",INT(($L20-INT($L20/1000000000)*1000000000)/100000000))
B21: =IF($L21="","",$M21) | C21: =IF($L21="","",INDEX(HSI!$C$7:$C$106,$N21)) | D21: =IF($L21="","",INDEX(HSI!$D$7:$D$106,$N21)) | E21: =IF($L21="","",IF($P21=0,"TBA",IFERROR(INDEX(Grids!$C$12:$BO$111,$N21,$O21),"-"))) | F21: =IF($L21="","",INDEX(HSI!$F$7:$F$106,$N21)) | G21: =IF($L21="","",IF($P21=0,"TBA",IFERROR(INDEX(Grids!$BQ$12:$EC$111,$N21,$O21),"-"))) | H21: =IF($L21="","",SUM($G$10:$G21)) | I21: =IF($L21="","",IF(INT(($L21-INT($L21/10000000)*10000000)/1000000)=0,"Bloomberg projection",IF($P21=1,"ANNOUNCED","ANNOUNCED - amount TBA"))) | J21: =IF($L21="","",IF((OV_SWITCH="ON")*(COUNTIFS(OVR_TICKERS,INDEX(HSI!$C$7:$C$106,$N21),OVR_BASE,">=0")>0)>0,"stock overridden","")) | L21: =IFERROR(IF(SMALL(Grids!$EE$12:$GQ$111,$M$7+12)>=PEND_TO,"",SMALL(Grids!$EE$12:$GQ$111,$M$7+12)),"") | M21: =IF($L21="","",INT($L21/1000000000)) | N21: =IF($L21="","",INT(($L21-INT($L21/1000000)*1000000)/1000)) | O21: =IF($L21="","",$L21-INT($L21/1000)*1000) | P21: =IF($L21="","",INT(($L21-INT($L21/1000000000)*1000000000)/100000000))
B22: =IF($L22="","",$M22) | C22: =IF($L22="","",INDEX(HSI!$C$7:$C$106,$N22)) | D22: =IF($L22="","",INDEX(HSI!$D$7:$D$106,$N22)) | E22: =IF($L22="","",IF($P22=0,"TBA",IFERROR(INDEX(Grids!$C$12:$BO$111,$N22,$O22),"-"))) | F22: =IF($L22="","",INDEX(HSI!$F$7:$F$106,$N22)) | G22: =IF($L22="","",IF($P22=0,"TBA",IFERROR(INDEX(Grids!$BQ$12:$EC$111,$N22,$O22),"-"))) | H22: =IF($L22="","",SUM($G$10:$G22)) | I22: =IF($L22="","",IF(INT(($L22-INT($L22/10000000)*10000000)/1000000)=0,"Bloomberg projection",IF($P22=1,"ANNOUNCED","ANNOUNCED - amount TBA"))) | J22: =IF($L22="","",IF((OV_SWITCH="ON")*(COUNTIFS(OVR_TICKERS,INDEX(HSI!$C$7:$C$106,$N22),OVR_BASE,">=0")>0)>0,"stock overridden","")) | L22: =IFERROR(IF(SMALL(Grids!$EE$12:$GQ$111,$M$7+13)>=PEND_TO,"",SMALL(Grids!$EE$12:$GQ$111,$M$7+13)),"") | M22: =IF($L22="","",INT($L22/1000000000)) | N22: =IF($L22="","",INT(($L22-INT($L22/1000000)*1000000)/1000)) | O22: =IF($L22="","",$L22-INT($L22/1000)*1000) | P22: =IF($L22="","",INT(($L22-INT($L22/1000000000)*1000000000)/100000000))
B23: =IF($L23="","",$M23) | C23: =IF($L23="","",INDEX(HSI!$C$7:$C$106,$N23)) | D23: =IF($L23="","",INDEX(HSI!$D$7:$D$106,$N23)) | E23: =IF($L23="","",IF($P23=0,"TBA",IFERROR(INDEX(Grids!$C$12:$BO$111,$N23,$O23),"-"))) | F23: =IF($L23="","",INDEX(HSI!$F$7:$F$106,$N23)) | G23: =IF($L23="","",IF($P23=0,"TBA",IFERROR(INDEX(Grids!$BQ$12:$EC$111,$N23,$O23),"-"))) | H23: =IF($L23="","",SUM($G$10:$G23)) | I23: =IF($L23="","",IF(INT(($L23-INT($L23/10000000)*10000000)/1000000)=0,"Bloomberg projection",IF($P23=1,"ANNOUNCED","ANNOUNCED - amount TBA"))) | J23: =IF($L23="","",IF((OV_SWITCH="ON")*(COUNTIFS(OVR_TICKERS,INDEX(HSI!$C$7:$C$106,$N23),OVR_BASE,">=0")>0)>0,"stock overridden","")) | L23: =IFERROR(IF(SMALL(Grids!$EE$12:$GQ$111,$M$7+14)>=PEND_TO,"",SMALL(Grids!$EE$12:$GQ$111,$M$7+14)),"") | M23: =IF($L23="","",INT($L23/1000000000)) | N23: =IF($L23="","",INT(($L23-INT($L23/1000000)*1000000)/1000)) | O23: =IF($L23="","",$L23-INT($L23/1000)*1000) | P23: =IF($L23="","",INT(($L23-INT($L23/1000000000)*1000000000)/100000000))
B24: =IF($L24="","",$M24) | C24: =IF($L24="","",INDEX(HSI!$C$7:$C$106,$N24)) | D24: =IF($L24="","",INDEX(HSI!$D$7:$D$106,$N24)) | E24: =IF($L24="","",IF($P24=0,"TBA",IFERROR(INDEX(Grids!$C$12:$BO$111,$N24,$O24),"-"))) | F24: =IF($L24="","",INDEX(HSI!$F$7:$F$106,$N24)) | G24: =IF($L24="","",IF($P24=0,"TBA",IFERROR(INDEX(Grids!$BQ$12:$EC$111,$N24,$O24),"-"))) | H24: =IF($L24="","",SUM($G$10:$G24)) | I24: =IF($L24="","",IF(INT(($L24-INT($L24/10000000)*10000000)/1000000)=0,"Bloomberg projection",IF($P24=1,"ANNOUNCED","ANNOUNCED - amount TBA"))) | J24: =IF($L24="","",IF((OV_SWITCH="ON")*(COUNTIFS(OVR_TICKERS,INDEX(HSI!$C$7:$C$106,$N24),OVR_BASE,">=0")>0)>0,"stock overridden","")) | L24: =IFERROR(IF(SMALL(Grids!$EE$12:$GQ$111,$M$7+15)>=PEND_TO,"",SMALL(Grids!$EE$12:$GQ$111,$M$7+15)),"") | M24: =IF($L24="","",INT($L24/1000000000)) | N24: =IF($L24="","",INT(($L24-INT($L24/1000000)*1000000)/1000)) | O24: =IF($L24="","",$L24-INT($L24/1000)*1000) | P24: =IF($L24="","",INT(($L24-INT($L24/1000000000)*1000000000)/100000000))
B25: =IF($L25="","",$M25) | C25: =IF($L25="","",INDEX(HSI!$C$7:$C$106,$N25)) | D25: =IF($L25="","",INDEX(HSI!$D$7:$D$106,$N25)) | E25: =IF($L25="","",IF($P25=0,"TBA",IFERROR(INDEX(Grids!$C$12:$BO$111,$N25,$O25),"-"))) | F25: =IF($L25="","",INDEX(HSI!$F$7:$F$106,$N25)) | G25: =IF($L25="","",IF($P25=0,"TBA",IFERROR(INDEX(Grids!$BQ$12:$EC$111,$N25,$O25),"-"))) | H25: =IF($L25="","",SUM($G$10:$G25)) | I25: =IF($L25="","",IF(INT(($L25-INT($L25/10000000)*10000000)/1000000)=0,"Bloomberg projection",IF($P25=1,"ANNOUNCED","ANNOUNCED - amount TBA"))) | J25: =IF($L25="","",IF((OV_SWITCH="ON")*(COUNTIFS(OVR_TICKERS,INDEX(HSI!$C$7:$C$106,$N25),OVR_BASE,">=0")>0)>0,"stock overridden","")) | L25: =IFERROR(IF(SMALL(Grids!$EE$12:$GQ$111,$M$7+16)>=PEND_TO,"",SMALL(Grids!$EE$12:$GQ$111,$M$7+16)),"") | M25: =IF($L25="","",INT($L25/1000000000)) | N25: =IF($L25="","",INT(($L25-INT($L25/1000000)*1000000)/1000)) | O25: =IF($L25="","",$L25-INT($L25/1000)*1000) | P25: =IF($L25="","",INT(($L25-INT($L25/1000000000)*1000000000)/100000000))
B26: =IF($L26="","",$M26) | C26: =IF($L26="","",INDEX(HSI!$C$7:$C$106,$N26)) | D26: =IF($L26="","",INDEX(HSI!$D$7:$D$106,$N26)) | E26: =IF($L26="","",IF($P26=0,"TBA",IFERROR(INDEX(Grids!$C$12:$BO$111,$N26,$O26),"-"))) | F26: =IF($L26="","",INDEX(HSI!$F$7:$F$106,$N26)) | G26: =IF($L26="","",IF($P26=0,"TBA",IFERROR(INDEX(Grids!$BQ$12:$EC$111,$N26,$O26),"-"))) | H26: =IF($L26="","",SUM($G$10:$G26)) | I26: =IF($L26="","",IF(INT(($L26-INT($L26/10000000)*10000000)/1000000)=0,"Bloomberg projection",IF($P26=1,"ANNOUNCED","ANNOUNCED - amount TBA"))) | J26: =IF($L26="","",IF((OV_SWITCH="ON")*(COUNTIFS(OVR_TICKERS,INDEX(HSI!$C$7:$C$106,$N26),OVR_BASE,">=0")>0)>0,"stock overridden","")) | L26: =IFERROR(IF(SMALL(Grids!$EE$12:$GQ$111,$M$7+17)>=PEND_TO,"",SMALL(Grids!$EE$12:$GQ$111,$M$7+17)),"") | M26: =IF($L26="","",INT($L26/1000000000)) | N26: =IF($L26="","",INT(($L26-INT($L26/1000000)*1000000)/1000)) | O26: =IF($L26="","",$L26-INT($L26/1000)*1000) | P26: =IF($L26="","",INT(($L26-INT($L26/1000000000)*1000000000)/100000000))
B27: =IF($L27="","",$M27) | C27: =IF($L27="","",INDEX(HSI!$C$7:$C$106,$N27)) | D27: =IF($L27="","",INDEX(HSI!$D$7:$D$106,$N27)) | E27: =IF($L27="","",IF($P27=0,"TBA",IFERROR(INDEX(Grids!$C$12:$BO$111,$N27,$O27),"-"))) | F27: =IF($L27="","",INDEX(HSI!$F$7:$F$106,$N27)) | G27: =IF($L27="","",IF($P27=0,"TBA",IFERROR(INDEX(Grids!$BQ$12:$EC$111,$N27,$O27),"-"))) | H27: =IF($L27="","",SUM($G$10:$G27)) | I27: =IF($L27="","",IF(INT(($L27-INT($L27/10000000)*10000000)/1000000)=0,"Bloomberg projection",IF($P27=1,"ANNOUNCED","ANNOUNCED - amount TBA"))) | J27: =IF($L27="","",IF((OV_SWITCH="ON")*(COUNTIFS(OVR_TICKERS,INDEX(HSI!$C$7:$C$106,$N27),OVR_BASE,">=0")>0)>0,"stock overridden","")) | L27: =IFERROR(IF(SMALL(Grids!$EE$12:$GQ$111,$M$7+18)>=PEND_TO,"",SMALL(Grids!$EE$12:$GQ$111,$M$7+18)),"") | M27: =IF($L27="","",INT($L27/1000000000)) | N27: =IF($L27="","",INT(($L27-INT($L27/1000000)*1000000)/1000)) | O27: =IF($L27="","",$L27-INT($L27/1000)*1000) | P27: =IF($L27="","",INT(($L27-INT($L27/1000000000)*1000000000)/100000000))
B28: =IF($L28="","",$M28) | C28: =IF($L28="","",INDEX(HSI!$C$7:$C$106,$N28)) | D28: =IF($L28="","",INDEX(HSI!$D$7:$D$106,$N28)) | E28: =IF($L28="","",IF($P28=0,"TBA",IFERROR(INDEX(Grids!$C$12:$BO$111,$N28,$O28),"-"))) | F28: =IF($L28="","",INDEX(HSI!$F$7:$F$106,$N28)) | G28: =IF($L28="","",IF($P28=0,"TBA",IFERROR(INDEX(Grids!$BQ$12:$EC$111,$N28,$O28),"-"))) | H28: =IF($L28="","",SUM($G$10:$G28)) | I28: =IF($L28="","",IF(INT(($L28-INT($L28/10000000)*10000000)/1000000)=0,"Bloomberg projection",IF($P28=1,"ANNOUNCED","ANNOUNCED - amount TBA"))) | J28: =IF($L28="","",IF((OV_SWITCH="ON")*(COUNTIFS(OVR_TICKERS,INDEX(HSI!$C$7:$C$106,$N28),OVR_BASE,">=0")>0)>0,"stock overridden","")) | L28: =IFERROR(IF(SMALL(Grids!$EE$12:$GQ$111,$M$7+19)>=PEND_TO,"",SMALL(Grids!$EE$12:$GQ$111,$M$7+19)),"") | M28: =IF($L28="","",INT($L28/1000000000)) | N28: =IF($L28="","",INT(($L28-INT($L28/1000000)*1000000)/1000)) | O28: =IF($L28="","",$L28-INT($L28/1000)*1000) | P28: =IF($L28="","",INT(($L28-INT($L28/1000000000)*1000000000)/100000000))
B29: =IF($L29="","",$M29) | C29: =IF($L29="","",INDEX(HSI!$C$7:$C$106,$N29)) | D29: =IF($L29="","",INDEX(HSI!$D$7:$D$106,$N29)) | E29: =IF($L29="","",IF($P29=0,"TBA",IFERROR(INDEX(Grids!$C$12:$BO$111,$N29,$O29),"-"))) | F29: =IF($L29="","",INDEX(HSI!$F$7:$F$106,$N29)) | G29: =IF($L29="","",IF($P29=0,"TBA",IFERROR(INDEX(Grids!$BQ$12:$EC$111,$N29,$O29),"-"))) | H29: =IF($L29="","",SUM($G$10:$G29)) | I29: =IF($L29="","",IF(INT(($L29-INT($L29/10000000)*10000000)/1000000)=0,"Bloomberg projection",IF($P29=1,"ANNOUNCED","ANNOUNCED - amount TBA"))) | J29: =IF($L29="","",IF((OV_SWITCH="ON")*(COUNTIFS(OVR_TICKERS,INDEX(HSI!$C$7:$C$106,$N29),OVR_BASE,">=0")>0)>0,"stock overridden","")) | L29: =IFERROR(IF(SMALL(Grids!$EE$12:$GQ$111,$M$7+20)>=PEND_TO,"",SMALL(Grids!$EE$12:$GQ$111,$M$7+20)),"") | M29: =IF($L29="","",INT($L29/1000000000)) | N29: =IF($L29="","",INT(($L29-INT($L29/1000000)*1000000)/1000)) | O29: =IF($L29="","",$L29-INT($L29/1000)*1000) | P29: =IF($L29="","",INT(($L29-INT($L29/1000000000)*1000000000)/100000000))
B30: =IF($L30="","",$M30) | C30: =IF($L30="","",INDEX(HSI!$C$7:$C$106,$N30)) | D30: =IF($L30="","",INDEX(HSI!$D$7:$D$106,$N30)) | E30: =IF($L30="","",IF($P30=0,"TBA",IFERROR(INDEX(Grids!$C$12:$BO$111,$N30,$O30),"-"))) | F30: =IF($L30="","",INDEX(HSI!$F$7:$F$106,$N30)) | G30: =IF($L30="","",IF($P30=0,"TBA",IFERROR(INDEX(Grids!$BQ$12:$EC$111,$N30,$O30),"-"))) | H30: =IF($L30="","",SUM($G$10:$G30)) | I30: =IF($L30="","",IF(INT(($L30-INT($L30/10000000)*10000000)/1000000)=0,"Bloomberg projection",IF($P30=1,"ANNOUNCED","ANNOUNCED - amount TBA"))) | J30: =IF($L30="","",IF((OV_SWITCH="ON")*(COUNTIFS(OVR_TICKERS,INDEX(HSI!$C$7:$C$106,$N30),OVR_BASE,">=0")>0)>0,"stock overridden","")) | L30: =IFERROR(IF(SMALL(Grids!$EE$12:$GQ$111,$M$7+21)>=PEND_TO,"",SMALL(Grids!$EE$12:$GQ$111,$M$7+21)),"") | M30: =IF($L30="","",INT($L30/1000000000)) | N30: =IF($L30="","",INT(($L30-INT($L30/1000000)*1000000)/1000)) | O30: =IF($L30="","",$L30-INT($L30/1000)*1000) | P30: =IF($L30="","",INT(($L30-INT($L30/1000000000)*1000000000)/100000000))
B31: =IF($L31="","",$M31) | C31: =IF($L31="","",INDEX(HSI!$C$7:$C$106,$N31)) | D31: =IF($L31="","",INDEX(HSI!$D$7:$D$106,$N31)) | E31: =IF($L31="","",IF($P31=0,"TBA",IFERROR(INDEX(Grids!$C$12:$BO$111,$N31,$O31),"-"))) | F31: =IF($L31="","",INDEX(HSI!$F$7:$F$106,$N31)) | G31: =IF($L31="","",IF($P31=0,"TBA",IFERROR(INDEX(Grids!$BQ$12:$EC$111,$N31,$O31),"-"))) | H31: =IF($L31="","",SUM($G$10:$G31)) | I31: =IF($L31="","",IF(INT(($L31-INT($L31/10000000)*10000000)/1000000)=0,"Bloomberg projection",IF($P31=1,"ANNOUNCED","ANNOUNCED - amount TBA"))) | J31: =IF($L31="","",IF((OV_SWITCH="ON")*(COUNTIFS(OVR_TICKERS,INDEX(HSI!$C$7:$C$106,$N31),OVR_BASE,">=0")>0)>0,"stock overridden","")) | L31: =IFERROR(IF(SMALL(Grids!$EE$12:$GQ$111,$M$7+22)>=PEND_TO,"",SMALL(Grids!$EE$12:$GQ$111,$M$7+22)),"") | M31: =IF($L31="","",INT($L31/1000000000)) | N31: =IF($L31="","",INT(($L31-INT($L31/1000000)*1000000)/1000)) | O31: =IF($L31="","",$L31-INT($L31/1000)*1000) | P31: =IF($L31="","",INT(($L31-INT($L31/1000000000)*1000000000)/100000000))
B32: =IF($L32="","",$M32) | C32: =IF($L32="","",INDEX(HSI!$C$7:$C$106,$N32)) | D32: =IF($L32="","",INDEX(HSI!$D$7:$D$106,$N32)) | E32: =IF($L32="","",IF($P32=0,"TBA",IFERROR(INDEX(Grids!$C$12:$BO$111,$N32,$O32),"-"))) | F32: =IF($L32="","",INDEX(HSI!$F$7:$F$106,$N32)) | G32: =IF($L32="","",IF($P32=0,"TBA",IFERROR(INDEX(Grids!$BQ$12:$EC$111,$N32,$O32),"-"))) | H32: =IF($L32="","",SUM($G$10:$G32)) | I32: =IF($L32="","",IF(INT(($L32-INT($L32/10000000)*10000000)/1000000)=0,"Bloomberg projection",IF($P32=1,"ANNOUNCED","ANNOUNCED - amount TBA"))) | J32: =IF($L32="","",IF((OV_SWITCH="ON")*(COUNTIFS(OVR_TICKERS,INDEX(HSI!$C$7:$C$106,$N32),OVR_BASE,">=0")>0)>0,"stock overridden","")) | L32: =IFERROR(IF(SMALL(Grids!$EE$12:$GQ$111,$M$7+23)>=PEND_TO,"",SMALL(Grids!$EE$12:$GQ$111,$M$7+23)),"") | M32: =IF($L32="","",INT($L32/1000000000)) | N32: =IF($L32="","",INT(($L32-INT($L32/1000000)*1000000)/1000)) | O32: =IF($L32="","",$L32-INT($L32/1000)*1000) | P32: =IF($L32="","",INT(($L32-INT($L32/1000000000)*1000000000)/100000000))
B33: =IF($L33="","",$M33) | C33: =IF($L33="","",INDEX(HSI!$C$7:$C$106,$N33)) | D33: =IF($L33="","",INDEX(HSI!$D$7:$D$106,$N33)) | E33: =IF($L33="","",IF($P33=0,"TBA",IFERROR(INDEX(Grids!$C$12:$BO$111,$N33,$O33),"-"))) | F33: =IF($L33="","",INDEX(HSI!$F$7:$F$106,$N33)) | G33: =IF($L33="","",IF($P33=0,"TBA",IFERROR(INDEX(Grids!$BQ$12:$EC$111,$N33,$O33),"-"))) | H33: =IF($L33="","",SUM($G$10:$G33)) | I33: =IF($L33="","",IF(INT(($L33-INT($L33/10000000)*10000000)/1000000)=0,"Bloomberg projection",IF($P33=1,"ANNOUNCED","ANNOUNCED - amount TBA"))) | J33: =IF($L33="","",IF((OV_SWITCH="ON")*(COUNTIFS(OVR_TICKERS,INDEX(HSI!$C$7:$C$106,$N33),OVR_BASE,">=0")>0)>0,"stock overridden","")) | L33: =IFERROR(IF(SMALL(Grids!$EE$12:$GQ$111,$M$7+24)>=PEND_TO,"",SMALL(Grids!$EE$12:$GQ$111,$M$7+24)),"") | M33: =IF($L33="","",INT($L33/1000000000)) | N33: =IF($L33="","",INT(($L33-INT($L33/1000000)*1000000)/1000)) | O33: =IF($L33="","",$L33-INT($L33/1000)*1000) | P33: =IF($L33="","",INT(($L33-INT($L33/1000000000)*1000000000)/100000000))
B34: =IF($L34="","",$M34) | C34: =IF($L34="","",INDEX(HSI!$C$7:$C$106,$N34)) | D34: =IF($L34="","",INDEX(HSI!$D$7:$D$106,$N34)) | E34: =IF($L34="","",IF($P34=0,"TBA",IFERROR(INDEX(Grids!$C$12:$BO$111,$N34,$O34),"-"))) | F34: =IF($L34="","",INDEX(HSI!$F$7:$F$106,$N34)) | G34: =IF($L34="","",IF($P34=0,"TBA",IFERROR(INDEX(Grids!$BQ$12:$EC$111,$N34,$O34),"-"))) | H34: =IF($L34="","",SUM($G$10:$G34)) | I34: =IF($L34="","",IF(INT(($L34-INT($L34/10000000)*10000000)/1000000)=0,"Bloomberg projection",IF($P34=1,"ANNOUNCED","ANNOUNCED - amount TBA"))) | J34: =IF($L34="","",IF((OV_SWITCH="ON")*(COUNTIFS(OVR_TICKERS,INDEX(HSI!$C$7:$C$106,$N34),OVR_BASE,">=0")>0)>0,"stock overridden","")) | L34: =IFERROR(IF(SMALL(Grids!$EE$12:$GQ$111,$M$7+25)>=PEND_TO,"",SMALL(Grids!$EE$12:$GQ$111,$M$7+25)),"") | M34: =IF($L34="","",INT($L34/1000000000)) | N34: =IF($L34="","",INT(($L34-INT($L34/1000000)*1000000)/1000)) | O34: =IF($L34="","",$L34-INT($L34/1000)*1000) | P34: =IF($L34="","",INT(($L34-INT($L34/1000000000)*1000000000)/100000000))
B35: =IF($L35="","",$M35) | C35: =IF($L35="","",INDEX(HSI!$C$7:$C$106,$N35)) | D35: =IF($L35="","",INDEX(HSI!$D$7:$D$106,$N35)) | E35: =IF($L35="","",IF($P35=0,"TBA",IFERROR(INDEX(Grids!$C$12:$BO$111,$N35,$O35),"-"))) | F35: =IF($L35="","",INDEX(HSI!$F$7:$F$106,$N35)) | G35: =IF($L35="","",IF($P35=0,"TBA",IFERROR(INDEX(Grids!$BQ$12:$EC$111,$N35,$O35),"-"))) | H35: =IF($L35="","",SUM($G$10:$G35)) | I35: =IF($L35="","",IF(INT(($L35-INT($L35/10000000)*10000000)/1000000)=0,"Bloomberg projection",IF($P35=1,"ANNOUNCED","ANNOUNCED - amount TBA"))) | J35: =IF($L35="","",IF((OV_SWITCH="ON")*(COUNTIFS(OVR_TICKERS,INDEX(HSI!$C$7:$C$106,$N35),OVR_BASE,">=0")>0)>0,"stock overridden","")) | L35: =IFERROR(IF(SMALL(Grids!$EE$12:$GQ$111,$M$7+26)>=PEND_TO,"",SMALL(Grids!$EE$12:$GQ$111,$M$7+26)),"") | M35: =IF($L35="","",INT($L35/1000000000)) | N35: =IF($L35="","",INT(($L35-INT($L35/1000000)*1000000)/1000)) | O35: =IF($L35="","",$L35-INT($L35/1000)*1000) | P35: =IF($L35="","",INT(($L35-INT($L35/1000000000)*1000000000)/100000000))
B36: =IF($L36="","",$M36) | C36: =IF($L36="","",INDEX(HSI!$C$7:$C$106,$N36)) | D36: =IF($L36="","",INDEX(HSI!$D$7:$D$106,$N36)) | E36: =IF($L36="","",IF($P36=0,"TBA",IFERROR(INDEX(Grids!$C$12:$BO$111,$N36,$O36),"-"))) | F36: =IF($L36="","",INDEX(HSI!$F$7:$F$106,$N36)) | G36: =IF($L36="","",IF($P36=0,"TBA",IFERROR(INDEX(Grids!$BQ$12:$EC$111,$N36,$O36),"-"))) | H36: =IF($L36="","",SUM($G$10:$G36)) | I36: =IF($L36="","",IF(INT(($L36-INT($L36/10000000)*10000000)/1000000)=0,"Bloomberg projection",IF($P36=1,"ANNOUNCED","ANNOUNCED - amount TBA"))) | J36: =IF($L36="","",IF((OV_SWITCH="ON")*(COUNTIFS(OVR_TICKERS,INDEX(HSI!$C$7:$C$106,$N36),OVR_BASE,">=0")>0)>0,"stock overridden","")) | L36: =IFERROR(IF(SMALL(Grids!$EE$12:$GQ$111,$M$7+27)>=PEND_TO,"",SMALL(Grids!$EE$12:$GQ$111,$M$7+27)),"") | M36: =IF($L36="","",INT($L36/1000000000)) | N36: =IF($L36="","",INT(($L36-INT($L36/1000000)*1000000)/1000)) | O36: =IF($L36="","",$L36-INT($L36/1000)*1000) | P36: =IF($L36="","",INT(($L36-INT($L36/1000000000)*1000000000)/100000000))
B37: =IF($L37="","",$M37) | C37: =IF($L37="","",INDEX(HSI!$C$7:$C$106,$N37)) | D37: =IF($L37="","",INDEX(HSI!$D$7:$D$106,$N37)) | E37: =IF($L37="","",IF($P37=0,"TBA",IFERROR(INDEX(Grids!$C$12:$BO$111,$N37,$O37),"-"))) | F37: =IF($L37="","",INDEX(HSI!$F$7:$F$106,$N37)) | G37: =IF($L37="","",IF($P37=0,"TBA",IFERROR(INDEX(Grids!$BQ$12:$EC$111,$N37,$O37),"-"))) | H37: =IF($L37="","",SUM($G$10:$G37)) | I37: =IF($L37="","",IF(INT(($L37-INT($L37/10000000)*10000000)/1000000)=0,"Bloomberg projection",IF($P37=1,"ANNOUNCED","ANNOUNCED - amount TBA"))) | J37: =IF($L37="","",IF((OV_SWITCH="ON")*(COUNTIFS(OVR_TICKERS,INDEX(HSI!$C$7:$C$106,$N37),OVR_BASE,">=0")>0)>0,"stock overridden","")) | L37: =IFERROR(IF(SMALL(Grids!$EE$12:$GQ$111,$M$7+28)>=PEND_TO,"",SMALL(Grids!$EE$12:$GQ$111,$M$7+28)),"") | M37: =IF($L37="","",INT($L37/1000000000)) | N37: =IF($L37="","",INT(($L37-INT($L37/1000000)*1000000)/1000)) | O37: =IF($L37="","",$L37-INT($L37/1000)*1000) | P37: =IF($L37="","",INT(($L37-INT($L37/1000000000)*1000000000)/100000000))
B38: =IF($L38="","",$M38) | C38: =IF($L38="","",INDEX(HSI!$C$7:$C$106,$N38)) | D38: =IF($L38="","",INDEX(HSI!$D$7:$D$106,$N38)) | E38: =IF($L38="","",IF($P38=0,"TBA",IFERROR(INDEX(Grids!$C$12:$BO$111,$N38,$O38),"-"))) | F38: =IF($L38="","",INDEX(HSI!$F$7:$F$106,$N38)) | G38: =IF($L38="","",IF($P38=0,"TBA",IFERROR(INDEX(Grids!$BQ$12:$EC$111,$N38,$O38),"-"))) | H38: =IF($L38="","",SUM($G$10:$G38)) | I38: =IF($L38="","",IF(INT(($L38-INT($L38/10000000)*10000000)/1000000)=0,"Bloomberg projection",IF($P38=1,"ANNOUNCED","ANNOUNCED - amount TBA"))) | J38: =IF($L38="","",IF((OV_SWITCH="ON")*(COUNTIFS(OVR_TICKERS,INDEX(HSI!$C$7:$C$106,$N38),OVR_BASE,">=0")>0)>0,"stock overridden","")) | L38: =IFERROR(IF(SMALL(Grids!$EE$12:$GQ$111,$M$7+29)>=PEND_TO,"",SMALL(Grids!$EE$12:$GQ$111,$M$7+29)),"") | M38: =IF($L38="","",INT($L38/1000000000)) | N38: =IF($L38="","",INT(($L38-INT($L38/1000000)*1000000)/1000)) | O38: =IF($L38="","",$L38-INT($L38/1000)*1000) | P38: =IF($L38="","",INT(($L38-INT($L38/1000000000)*1000000000)/100000000))
B39: =IF($L39="","",$M39) | C39: =IF($L39="","",INDEX(HSI!$C$7:$C$106,$N39)) | D39: =IF($L39="","",INDEX(HSI!$D$7:$D$106,$N39)) | E39: =IF($L39="","",IF($P39=0,"TBA",IFERROR(INDEX(Grids!$C$12:$BO$111,$N39,$O39),"-"))) | F39: =IF($L39="","",INDEX(HSI!$F$7:$F$106,$N39)) | G39: =IF($L39="","",IF($P39=0,"TBA",IFERROR(INDEX(Grids!$BQ$12:$EC$111,$N39,$O39),"-"))) | H39: =IF($L39="","",SUM($G$10:$G39)) | I39: =IF($L39="","",IF(INT(($L39-INT($L39/10000000)*10000000)/1000000)=0,"Bloomberg projection",IF($P39=1,"ANNOUNCED","ANNOUNCED - amount TBA"))) | J39: =IF($L39="","",IF((OV_SWITCH="ON")*(COUNTIFS(OVR_TICKERS,INDEX(HSI!$C$7:$C$106,$N39),OVR_BASE,">=0")>0)>0,"stock overridden","")) | L39: =IFERROR(IF(SMALL(Grids!$EE$12:$GQ$111,$M$7+30)>=PEND_TO,"",SMALL(Grids!$EE$12:$GQ$111,$M$7+30)),"") | M39: =IF($L39="","",INT($L39/1000000000)) | N39: =IF($L39="","",INT(($L39-INT($L39/1000000)*1000000)/1000)) | O39: =IF($L39="","",$L39-INT($L39/1000)*1000) | P39: =IF($L39="","",INT(($L39-INT($L39/1000000000)*1000000000)/100000000))
B40: =IF($L40="","",$M40) | C40: =IF($L40="","",INDEX(HSI!$C$7:$C$106,$N40)) | D40: =IF($L40="","",INDEX(HSI!$D$7:$D$106,$N40)) | E40: =IF($L40="","",IF($P40=0,"TBA",IFERROR(INDEX(Grids!$C$12:$BO$111,$N40,$O40),"-"))) | F40: =IF($L40="","",INDEX(HSI!$F$7:$F$106,$N40)) | G40: =IF($L40="","",IF($P40=0,"TBA",IFERROR(INDEX(Grids!$BQ$12:$EC$111,$N40,$O40),"-"))) | H40: =IF($L40="","",SUM($G$10:$G40)) | I40: =IF($L40="","",IF(INT(($L40-INT($L40/10000000)*10000000)/1000000)=0,"Bloomberg projection",IF($P40=1,"ANNOUNCED","ANNOUNCED - amount TBA"))) | J40: =IF($L40="","",IF((OV_SWITCH="ON")*(COUNTIFS(OVR_TICKERS,INDEX(HSI!$C$7:$C$106,$N40),OVR_BASE,">=0")>0)>0,"stock overridden","")) | L40: =IFERROR(IF(SMALL(Grids!$EE$12:$GQ$111,$M$7+31)>=PEND_TO,"",SMALL(Grids!$EE$12:$GQ$111,$M$7+31)),"") | M40: =IF($L40="","",INT($L40/1000000000)) | N40: =IF($L40="","",INT(($L40-INT($L40/1000000)*1000000)/1000)) | O40: =IF($L40="","",$L40-INT($L40/1000)*1000) | P40: =IF($L40="","",INT(($L40-INT($L40/1000000000)*1000000000)/100000000))
B41: =IF($L41="","",$M41) | C41: =IF($L41="","",INDEX(HSI!$C$7:$C$106,$N41)) | D41: =IF($L41="","",INDEX(HSI!$D$7:$D$106,$N41)) | E41: =IF($L41="","",IF($P41=0,"TBA",IFERROR(INDEX(Grids!$C$12:$BO$111,$N41,$O41),"-"))) | F41: =IF($L41="","",INDEX(HSI!$F$7:$F$106,$N41)) | G41: =IF($L41="","",IF($P41=0,"TBA",IFERROR(INDEX(Grids!$BQ$12:$EC$111,$N41,$O41),"-"))) | H41: =IF($L41="","",SUM($G$10:$G41)) | I41: =IF($L41="","",IF(INT(($L41-INT($L41/10000000)*10000000)/1000000)=0,"Bloomberg projection",IF($P41=1,"ANNOUNCED","ANNOUNCED - amount TBA"))) | J41: =IF($L41="","",IF((OV_SWITCH="ON")*(COUNTIFS(OVR_TICKERS,INDEX(HSI!$C$7:$C$106,$N41),OVR_BASE,">=0")>0)>0,"stock overridden","")) | L41: =IFERROR(IF(SMALL(Grids!$EE$12:$GQ$111,$M$7+32)>=PEND_TO,"",SMALL(Grids!$EE$12:$GQ$111,$M$7+32)),"") | M41: =IF($L41="","",INT($L41/1000000000)) | N41: =IF($L41="","",INT(($L41-INT($L41/1000000)*1000000)/1000)) | O41: =IF($L41="","",$L41-INT($L41/1000)*1000) | P41: =IF($L41="","",INT(($L41-INT($L41/1000000000)*1000000000)/100000000))
B42: =IF($L42="","",$M42) | C42: =IF($L42="","",INDEX(HSI!$C$7:$C$106,$N42)) | D42: =IF($L42="","",INDEX(HSI!$D$7:$D$106,$N42)) | E42: =IF($L42="","",IF($P42=0,"TBA",IFERROR(INDEX(Grids!$C$12:$BO$111,$N42,$O42),"-"))) | F42: =IF($L42="","",INDEX(HSI!$F$7:$F$106,$N42)) | G42: =IF($L42="","",IF($P42=0,"TBA",IFERROR(INDEX(Grids!$BQ$12:$EC$111,$N42,$O42),"-"))) | H42: =IF($L42="","",SUM($G$10:$G42)) | I42: =IF($L42="","",IF(INT(($L42-INT($L42/10000000)*10000000)/1000000)=0,"Bloomberg projection",IF($P42=1,"ANNOUNCED","ANNOUNCED - amount TBA"))) | J42: =IF($L42="","",IF((OV_SWITCH="ON")*(COUNTIFS(OVR_TICKERS,INDEX(HSI!$C$7:$C$106,$N42),OVR_BASE,">=0")>0)>0,"stock overridden","")) | L42: =IFERROR(IF(SMALL(Grids!$EE$12:$GQ$111,$M$7+33)>=PEND_TO,"",SMALL(Grids!$EE$12:$GQ$111,$M$7+33)),"") | M42: =IF($L42="","",INT($L42/1000000000)) | N42: =IF($L42="","",INT(($L42-INT($L42/1000000)*1000000)/1000)) | O42: =IF($L42="","",$L42-INT($L42/1000)*1000) | P42: =IF($L42="","",INT(($L42-INT($L42/1000000000)*1000000000)/100000000))
B43: =IF($L43="","",$M43) | C43: =IF($L43="","",INDEX(HSI!$C$7:$C$106,$N43)) | D43: =IF($L43="","",INDEX(HSI!$D$7:$D$106,$N43)) | E43: =IF($L43="","",IF($P43=0,"TBA",IFERROR(INDEX(Grids!$C$12:$BO$111,$N43,$O43),"-"))) | F43: =IF($L43="","",INDEX(HSI!$F$7:$F$106,$N43)) | G43: =IF($L43="","",IF($P43=0,"TBA",IFERROR(INDEX(Grids!$BQ$12:$EC$111,$N43,$O43),"-"))) | H43: =IF($L43="","",SUM($G$10:$G43)) | I43: =IF($L43="","",IF(INT(($L43-INT($L43/10000000)*10000000)/1000000)=0,"Bloomberg projection",IF($P43=1,"ANNOUNCED","ANNOUNCED - amount TBA"))) | J43: =IF($L43="","",IF((OV_SWITCH="ON")*(COUNTIFS(OVR_TICKERS,INDEX(HSI!$C$7:$C$106,$N43),OVR_BASE,">=0")>0)>0,"stock overridden","")) | L43: =IFERROR(IF(SMALL(Grids!$EE$12:$GQ$111,$M$7+34)>=PEND_TO,"",SMALL(Grids!$EE$12:$GQ$111,$M$7+34)),"") | M43: =IF($L43="","",INT($L43/1000000000)) | N43: =IF($L43="","",INT(($L43-INT($L43/1000000)*1000000)/1000)) | O43: =IF($L43="","",$L43-INT($L43/1000)*1000) | P43: =IF($L43="","",INT(($L43-INT($L43/1000000000)*1000000000)/100000000))
B44: =IF($L44="","",$M44) | C44: =IF($L44="","",INDEX(HSI!$C$7:$C$106,$N44)) | D44: =IF($L44="","",INDEX(HSI!$D$7:$D$106,$N44)) | E44: =IF($L44="","",IF($P44=0,"TBA",IFERROR(INDEX(Grids!$C$12:$BO$111,$N44,$O44),"-"))) | F44: =IF($L44="","",INDEX(HSI!$F$7:$F$106,$N44)) | G44: =IF($L44="","",IF($P44=0,"TBA",IFERROR(INDEX(Grids!$BQ$12:$EC$111,$N44,$O44),"-"))) | H44: =IF($L44="","",SUM($G$10:$G44)) | I44: =IF($L44="","",IF(INT(($L44-INT($L44/10000000)*10000000)/1000000)=0,"Bloomberg projection",IF($P44=1,"ANNOUNCED","ANNOUNCED - amount TBA"))) | J44: =IF($L44="","",IF((OV_SWITCH="ON")*(COUNTIFS(OVR_TICKERS,INDEX(HSI!$C$7:$C$106,$N44),OVR_BASE,">=0")>0)>0,"stock overridden","")) | L44: =IFERROR(IF(SMALL(Grids!$EE$12:$GQ$111,$M$7+35)>=PEND_TO,"",SMALL(Grids!$EE$12:$GQ$111,$M$7+35)),"") | M44: =IF($L44="","",INT($L44/1000000000)) | N44: =IF($L44="","",INT(($L44-INT($L44/1000000)*1000000)/1000)) | O44: =IF($L44="","",$L44-INT($L44/1000)*1000) | P44: =IF($L44="","",INT(($L44-INT($L44/1000000000)*1000000000)/100000000))
B45: =IF($L45="","",$M45) | C45: =IF($L45="","",INDEX(HSI!$C$7:$C$106,$N45)) | D45: =IF($L45="","",INDEX(HSI!$D$7:$D$106,$N45)) | E45: =IF($L45="","",IF($P45=0,"TBA",IFERROR(INDEX(Grids!$C$12:$BO$111,$N45,$O45),"-"))) | F45: =IF($L45="","",INDEX(HSI!$F$7:$F$106,$N45)) | G45: =IF($L45="","",IF($P45=0,"TBA",IFERROR(INDEX(Grids!$BQ$12:$EC$111,$N45,$O45),"-"))) | H45: =IF($L45="","",SUM($G$10:$G45)) | I45: =IF($L45="","",IF(INT(($L45-INT($L45/10000000)*10000000)/1000000)=0,"Bloomberg projection",IF($P45=1,"ANNOUNCED","ANNOUNCED - amount TBA"))) | J45: =IF($L45="","",IF((OV_SWITCH="ON")*(COUNTIFS(OVR_TICKERS,INDEX(HSI!$C$7:$C$106,$N45),OVR_BASE,">=0")>0)>0,"stock overridden","")) | L45: =IFERROR(IF(SMALL(Grids!$EE$12:$GQ$111,$M$7+36)>=PEND_TO,"",SMALL(Grids!$EE$12:$GQ$111,$M$7+36)),"") | M45: =IF($L45="","",INT($L45/1000000000)) | N45: =IF($L45="","",INT(($L45-INT($L45/1000000)*1000000)/1000)) | O45: =IF($L45="","",$L45-INT($L45/1000)*1000) | P45: =IF($L45="","",INT(($L45-INT($L45/1000000000)*1000000000)/100000000))
B46: =IF($L46="","",$M46) | C46: =IF($L46="","",INDEX(HSI!$C$7:$C$106,$N46)) | D46: =IF($L46="","",INDEX(HSI!$D$7:$D$106,$N46)) | E46: =IF($L46="","",IF($P46=0,"TBA",IFERROR(INDEX(Grids!$C$12:$BO$111,$N46,$O46),"-"))) | F46: =IF($L46="","",INDEX(HSI!$F$7:$F$106,$N46)) | G46: =IF($L46="","",IF($P46=0,"TBA",IFERROR(INDEX(Grids!$BQ$12:$EC$111,$N46,$O46),"-"))) | H46: =IF($L46="","",SUM($G$10:$G46)) | I46: =IF($L46="","",IF(INT(($L46-INT($L46/10000000)*10000000)/1000000)=0,"Bloomberg projection",IF($P46=1,"ANNOUNCED","ANNOUNCED - amount TBA"))) | J46: =IF($L46="","",IF((OV_SWITCH="ON")*(COUNTIFS(OVR_TICKERS,INDEX(HSI!$C$7:$C$106,$N46),OVR_BASE,">=0")>0)>0,"stock overridden","")) | L46: =IFERROR(IF(SMALL(Grids!$EE$12:$GQ$111,$M$7+37)>=PEND_TO,"",SMALL(Grids!$EE$12:$GQ$111,$M$7+37)),"") | M46: =IF($L46="","",INT($L46/1000000000)) | N46: =IF($L46="","",INT(($L46-INT($L46/1000000)*1000000)/1000)) | O46: =IF($L46="","",$L46-INT($L46/1000)*1000) | P46: =IF($L46="","",INT(($L46-INT($L46/1000000000)*1000000000)/100000000))
B47: =IF($L47="","",$M47) | C47: =IF($L47="","",INDEX(HSI!$C$7:$C$106,$N47)) | D47: =IF($L47="","",INDEX(HSI!$D$7:$D$106,$N47)) | E47: =IF($L47="","",IF($P47=0,"TBA",IFERROR(INDEX(Grids!$C$12:$BO$111,$N47,$O47),"-"))) | F47: =IF($L47="","",INDEX(HSI!$F$7:$F$106,$N47)) | G47: =IF($L47="","",IF($P47=0,"TBA",IFERROR(INDEX(Grids!$BQ$12:$EC$111,$N47,$O47),"-"))) | H47: =IF($L47="","",SUM($G$10:$G47)) | I47: =IF($L47="","",IF(INT(($L47-INT($L47/10000000)*10000000)/1000000)=0,"Bloomberg projection",IF($P47=1,"ANNOUNCED","ANNOUNCED - amount TBA"))) | J47: =IF($L47="","",IF((OV_SWITCH="ON")*(COUNTIFS(OVR_TICKERS,INDEX(HSI!$C$7:$C$106,$N47),OVR_BASE,">=0")>0)>0,"stock overridden","")) | L47: =IFERROR(IF(SMALL(Grids!$EE$12:$GQ$111,$M$7+38)>=PEND_TO,"",SMALL(Grids!$EE$12:$GQ$111,$M$7+38)),"") | M47: =IF($L47="","",INT($L47/1000000000)) | N47: =IF($L47="","",INT(($L47-INT($L47/1000000)*1000000)/1000)) | O47: =IF($L47="","",$L47-INT($L47/1000)*1000) | P47: =IF($L47="","",INT(($L47-INT($L47/1000000000)*1000000000)/100000000))
B48: =IF($L48="","",$M48) | C48: =IF($L48="","",INDEX(HSI!$C$7:$C$106,$N48)) | D48: =IF($L48="","",INDEX(HSI!$D$7:$D$106,$N48)) | E48: =IF($L48="","",IF($P48=0,"TBA",IFERROR(INDEX(Grids!$C$12:$BO$111,$N48,$O48),"-"))) | F48: =IF($L48="","",INDEX(HSI!$F$7:$F$106,$N48)) | G48: =IF($L48="","",IF($P48=0,"TBA",IFERROR(INDEX(Grids!$BQ$12:$EC$111,$N48,$O48),"-"))) | H48: =IF($L48="","",SUM($G$10:$G48)) | I48: =IF($L48="","",IF(INT(($L48-INT($L48/10000000)*10000000)/1000000)=0,"Bloomberg projection",IF($P48=1,"ANNOUNCED","ANNOUNCED - amount TBA"))) | J48: =IF($L48="","",IF((OV_SWITCH="ON")*(COUNTIFS(OVR_TICKERS,INDEX(HSI!$C$7:$C$106,$N48),OVR_BASE,">=0")>0)>0,"stock overridden","")) | L48: =IFERROR(IF(SMALL(Grids!$EE$12:$GQ$111,$M$7+39)>=PEND_TO,"",SMALL(Grids!$EE$12:$GQ$111,$M$7+39)),"") | M48: =IF($L48="","",INT($L48/1000000000)) | N48: =IF($L48="","",INT(($L48-INT($L48/1000000)*1000000)/1000)) | O48: =IF($L48="","",$L48-INT($L48/1000)*1000) | P48: =IF($L48="","",INT(($L48-INT($L48/1000000000)*1000000000)/100000000))
B49: =IF($L49="","",$M49) | C49: =IF($L49="","",INDEX(HSI!$C$7:$C$106,$N49)) | D49: =IF($L49="","",INDEX(HSI!$D$7:$D$106,$N49)) | E49: =IF($L49="","",IF($P49=0,"TBA",IFERROR(INDEX(Grids!$C$12:$BO$111,$N49,$O49),"-"))) | F49: =IF($L49="","",INDEX(HSI!$F$7:$F$106,$N49)) | G49: =IF($L49="","",IF($P49=0,"TBA",IFERROR(INDEX(Grids!$BQ$12:$EC$111,$N49,$O49),"-"))) | H49: =IF($L49="","",SUM($G$10:$G49)) | I49: =IF($L49="","",IF(INT(($L49-INT($L49/10000000)*10000000)/1000000)=0,"Bloomberg projection",IF($P49=1,"ANNOUNCED","ANNOUNCED - amount TBA"))) | J49: =IF($L49="","",IF((OV_SWITCH="ON")*(COUNTIFS(OVR_TICKERS,INDEX(HSI!$C$7:$C$106,$N49),OVR_BASE,">=0")>0)>0,"stock overridden","")) | L49: =IFERROR(IF(SMALL(Grids!$EE$12:$GQ$111,$M$7+40)>=PEND_TO,"",SMALL(Grids!$EE$12:$GQ$111,$M$7+40)),"") | M49: =IF($L49="","",INT($L49/1000000000)) | N49: =IF($L49="","",INT(($L49-INT($L49/1000000)*1000000)/1000)) | O49: =IF($L49="","",$L49-INT($L49/1000)*1000) | P49: =IF($L49="","",INT(($L49-INT($L49/1000000000)*1000000000)/100000000))
B50: =IF($L50="","",$M50) | C50: =IF($L50="","",INDEX(HSI!$C$7:$C$106,$N50)) | D50: =IF($L50="","",INDEX(HSI!$D$7:$D$106,$N50)) | E50: =IF($L50="","",IF($P50=0,"TBA",IFERROR(INDEX(Grids!$C$12:$BO$111,$N50,$O50),"-"))) | F50: =IF($L50="","",INDEX(HSI!$F$7:$F$106,$N50)) | G50: =IF($L50="","",IF($P50=0,"TBA",IFERROR(INDEX(Grids!$BQ$12:$EC$111,$N50,$O50),"-"))) | H50: =IF($L50="","",SUM($G$10:$G50)) | I50: =IF($L50="","",IF(INT(($L50-INT($L50/10000000)*10000000)/1000000)=0,"Bloomberg projection",IF($P50=1,"ANNOUNCED","ANNOUNCED - amount TBA"))) | J50: =IF($L50="","",IF((OV_SWITCH="ON")*(COUNTIFS(OVR_TICKERS,INDEX(HSI!$C$7:$C$106,$N50),OVR_BASE,">=0")>0)>0,"stock overridden","")) | L50: =IFERROR(IF(SMALL(Grids!$EE$12:$GQ$111,$M$7+41)>=PEND_TO,"",SMALL(Grids!$EE$12:$GQ$111,$M$7+41)),"") | M50: =IF($L50="","",INT($L50/1000000000)) | N50: =IF($L50="","",INT(($L50-INT($L50/1000000)*1000000)/1000)) | O50: =IF($L50="","",$L50-INT($L50/1000)*1000) | P50: =IF($L50="","",INT(($L50-INT($L50/1000000000)*1000000000)/100000000))
B51: =IF($L51="","",$M51) | C51: =IF($L51="","",INDEX(HSI!$C$7:$C$106,$N51)) | D51: =IF($L51="","",INDEX(HSI!$D$7:$D$106,$N51)) | E51: =IF($L51="","",IF($P51=0,"TBA",IFERROR(INDEX(Grids!$C$12:$BO$111,$N51,$O51),"-"))) | F51: =IF($L51="","",INDEX(HSI!$F$7:$F$106,$N51)) | G51: =IF($L51="","",IF($P51=0,"TBA",IFERROR(INDEX(Grids!$BQ$12:$EC$111,$N51,$O51),"-"))) | H51: =IF($L51="","",SUM($G$10:$G51)) | I51: =IF($L51="","",IF(INT(($L51-INT($L51/10000000)*10000000)/1000000)=0,"Bloomberg projection",IF($P51=1,"ANNOUNCED","ANNOUNCED - amount TBA"))) | J51: =IF($L51="","",IF((OV_SWITCH="ON")*(COUNTIFS(OVR_TICKERS,INDEX(HSI!$C$7:$C$106,$N51),OVR_BASE,">=0")>0)>0,"stock overridden","")) | L51: =IFERROR(IF(SMALL(Grids!$EE$12:$GQ$111,$M$7+42)>=PEND_TO,"",SMALL(Grids!$EE$12:$GQ$111,$M$7+42)),"") | M51: =IF($L51="","",INT($L51/1000000000)) | N51: =IF($L51="","",INT(($L51-INT($L51/1000000)*1000000)/1000)) | O51: =IF($L51="","",$L51-INT($L51/1000)*1000) | P51: =IF($L51="","",INT(($L51-INT($L51/1000000000)*1000000000)/100000000))
B52: =IF($L52="","",$M52) | C52: =IF($L52="","",INDEX(HSI!$C$7:$C$106,$N52)) | D52: =IF($L52="","",INDEX(HSI!$D$7:$D$106,$N52)) | E52: =IF($L52="","",IF($P52=0,"TBA",IFERROR(INDEX(Grids!$C$12:$BO$111,$N52,$O52),"-"))) | F52: =IF($L52="","",INDEX(HSI!$F$7:$F$106,$N52)) | G52: =IF($L52="","",IF($P52=0,"TBA",IFERROR(INDEX(Grids!$BQ$12:$EC$111,$N52,$O52),"-"))) | H52: =IF($L52="","",SUM($G$10:$G52)) | I52: =IF($L52="","",IF(INT(($L52-INT($L52/10000000)*10000000)/1000000)=0,"Bloomberg projection",IF($P52=1,"ANNOUNCED","ANNOUNCED - amount TBA"))) | J52: =IF($L52="","",IF((OV_SWITCH="ON")*(COUNTIFS(OVR_TICKERS,INDEX(HSI!$C$7:$C$106,$N52),OVR_BASE,">=0")>0)>0,"stock overridden","")) | L52: =IFERROR(IF(SMALL(Grids!$EE$12:$GQ$111,$M$7+43)>=PEND_TO,"",SMALL(Grids!$EE$12:$GQ$111,$M$7+43)),"") | M52: =IF($L52="","",INT($L52/1000000000)) | N52: =IF($L52="","",INT(($L52-INT($L52/1000000)*1000000)/1000)) | O52: =IF($L52="","",$L52-INT($L52/1000)*1000) | P52: =IF($L52="","",INT(($L52-INT($L52/1000000000)*1000000000)/100000000))
B53: =IF($L53="","",$M53) | C53: =IF($L53="","",INDEX(HSI!$C$7:$C$106,$N53)) | D53: =IF($L53="","",INDEX(HSI!$D$7:$D$106,$N53)) | E53: =IF($L53="","",IF($P53=0,"TBA",IFERROR(INDEX(Grids!$C$12:$BO$111,$N53,$O53),"-"))) | F53: =IF($L53="","",INDEX(HSI!$F$7:$F$106,$N53)) | G53: =IF($L53="","",IF($P53=0,"TBA",IFERROR(INDEX(Grids!$BQ$12:$EC$111,$N53,$O53),"-"))) | H53: =IF($L53="","",SUM($G$10:$G53)) | I53: =IF($L53="","",IF(INT(($L53-INT($L53/10000000)*10000000)/1000000)=0,"Bloomberg projection",IF($P53=1,"ANNOUNCED","ANNOUNCED - amount TBA"))) | J53: =IF($L53="","",IF((OV_SWITCH="ON")*(COUNTIFS(OVR_TICKERS,INDEX(HSI!$C$7:$C$106,$N53),OVR_BASE,">=0")>0)>0,"stock overridden","")) | L53: =IFERROR(IF(SMALL(Grids!$EE$12:$GQ$111,$M$7+44)>=PEND_TO,"",SMALL(Grids!$EE$12:$GQ$111,$M$7+44)),"") | M53: =IF($L53="","",INT($L53/1000000000)) | N53: =IF($L53="","",INT(($L53-INT($L53/1000000)*1000000)/1000)) | O53: =IF($L53="","",$L53-INT($L53/1000)*1000) | P53: =IF($L53="","",INT(($L53-INT($L53/1000000000)*1000000000)/100000000))
B54: =IF($L54="","",$M54) | C54: =IF($L54="","",INDEX(HSI!$C$7:$C$106,$N54)) | D54: =IF($L54="","",INDEX(HSI!$D$7:$D$106,$N54)) | E54: =IF($L54="","",IF($P54=0,"TBA",IFERROR(INDEX(Grids!$C$12:$BO$111,$N54,$O54),"-"))) | F54: =IF($L54="","",INDEX(HSI!$F$7:$F$106,$N54)) | G54: =IF($L54="","",IF($P54=0,"TBA",IFERROR(INDEX(Grids!$BQ$12:$EC$111,$N54,$O54),"-"))) | H54: =IF($L54="","",SUM($G$10:$G54)) | I54: =IF($L54="","",IF(INT(($L54-INT($L54/10000000)*10000000)/1000000)=0,"Bloomberg projection",IF($P54=1,"ANNOUNCED","ANNOUNCED - amount TBA"))) | J54: =IF($L54="","",IF((OV_SWITCH="ON")*(COUNTIFS(OVR_TICKERS,INDEX(HSI!$C$7:$C$106,$N54),OVR_BASE,">=0")>0)>0,"stock overridden","")) | L54: =IFERROR(IF(SMALL(Grids!$EE$12:$GQ$111,$M$7+45)>=PEND_TO,"",SMALL(Grids!$EE$12:$GQ$111,$M$7+45)),"") | M54: =IF($L54="","",INT($L54/1000000000)) | N54: =IF($L54="","",INT(($L54-INT($L54/1000000)*1000000)/1000)) | O54: =IF($L54="","",$L54-INT($L54/1000)*1000) | P54: =IF($L54="","",INT(($L54-INT($L54/1000000000)*1000000000)/100000000))
B55: =IF($L55="","",$M55) | C55: =IF($L55="","",INDEX(HSI!$C$7:$C$106,$N55)) | D55: =IF($L55="","",INDEX(HSI!$D$7:$D$106,$N55)) | E55: =IF($L55="","",IF($P55=0,"TBA",IFERROR(INDEX(Grids!$C$12:$BO$111,$N55,$O55),"-"))) | F55: =IF($L55="","",INDEX(HSI!$F$7:$F$106,$N55)) | G55: =IF($L55="","",IF($P55=0,"TBA",IFERROR(INDEX(Grids!$BQ$12:$EC$111,$N55,$O55),"-"))) | H55: =IF($L55="","",SUM($G$10:$G55)) | I55: =IF($L55="","",IF(INT(($L55-INT($L55/10000000)*10000000)/1000000)=0,"Bloomberg projection",IF($P55=1,"ANNOUNCED","ANNOUNCED - amount TBA"))) | J55: =IF($L55="","",IF((OV_SWITCH="ON")*(COUNTIFS(OVR_TICKERS,INDEX(HSI!$C$7:$C$106,$N55),OVR_BASE,">=0")>0)>0,"stock overridden","")) | L55: =IFERROR(IF(SMALL(Grids!$EE$12:$GQ$111,$M$7+46)>=PEND_TO,"",SMALL(Grids!$EE$12:$GQ$111,$M$7+46)),"") | M55: =IF($L55="","",INT($L55/1000000000)) | N55: =IF($L55="","",INT(($L55-INT($L55/1000000)*1000000)/1000)) | O55: =IF($L55="","",$L55-INT($L55/1000)*1000) | P55: =IF($L55="","",INT(($L55-INT($L55/1000000000)*1000000000)/100000000))
B56: =IF($L56="","",$M56) | C56: =IF($L56="","",INDEX(HSI!$C$7:$C$106,$N56)) | D56: =IF($L56="","",INDEX(HSI!$D$7:$D$106,$N56)) | E56: =IF($L56="","",IF($P56=0,"TBA",IFERROR(INDEX(Grids!$C$12:$BO$111,$N56,$O56),"-"))) | F56: =IF($L56="","",INDEX(HSI!$F$7:$F$106,$N56)) | G56: =IF($L56="","",IF($P56=0,"TBA",IFERROR(INDEX(Grids!$BQ$12:$EC$111,$N56,$O56),"-"))) | H56: =IF($L56="","",SUM($G$10:$G56)) | I56: =IF($L56="","",IF(INT(($L56-INT($L56/10000000)*10000000)/1000000)=0,"Bloomberg projection",IF($P56=1,"ANNOUNCED","ANNOUNCED - amount TBA"))) | J56: =IF($L56="","",IF((OV_SWITCH="ON")*(COUNTIFS(OVR_TICKERS,INDEX(HSI!$C$7:$C$106,$N56),OVR_BASE,">=0")>0)>0,"stock overridden","")) | L56: =IFERROR(IF(SMALL(Grids!$EE$12:$GQ$111,$M$7+47)>=PEND_TO,"",SMALL(Grids!$EE$12:$GQ$111,$M$7+47)),"") | M56: =IF($L56="","",INT($L56/1000000000)) | N56: =IF($L56="","",INT(($L56-INT($L56/1000000)*1000000)/1000)) | O56: =IF($L56="","",$L56-INT($L56/1000)*1000) | P56: =IF($L56="","",INT(($L56-INT($L56/1000000000)*1000000000)/100000000))
B57: =IF($L57="","",$M57) | C57: =IF($L57="","",INDEX(HSI!$C$7:$C$106,$N57)) | D57: =IF($L57="","",INDEX(HSI!$D$7:$D$106,$N57)) | E57: =IF($L57="","",IF($P57=0,"TBA",IFERROR(INDEX(Grids!$C$12:$BO$111,$N57,$O57),"-"))) | F57: =IF($L57="","",INDEX(HSI!$F$7:$F$106,$N57)) | G57: =IF($L57="","",IF($P57=0,"TBA",IFERROR(INDEX(Grids!$BQ$12:$EC$111,$N57,$O57),"-"))) | H57: =IF($L57="","",SUM($G$10:$G57)) | I57: =IF($L57="","",IF(INT(($L57-INT($L57/10000000)*10000000)/1000000)=0,"Bloomberg projection",IF($P57=1,"ANNOUNCED","ANNOUNCED - amount TBA"))) | J57: =IF($L57="","",IF((OV_SWITCH="ON")*(COUNTIFS(OVR_TICKERS,INDEX(HSI!$C$7:$C$106,$N57),OVR_BASE,">=0")>0)>0,"stock overridden","")) | L57: =IFERROR(IF(SMALL(Grids!$EE$12:$GQ$111,$M$7+48)>=PEND_TO,"",SMALL(Grids!$EE$12:$GQ$111,$M$7+48)),"") | M57: =IF($L57="","",INT($L57/1000000000)) | N57: =IF($L57="","",INT(($L57-INT($L57/1000000)*1000000)/1000)) | O57: =IF($L57="","",$L57-INT($L57/1000)*1000) | P57: =IF($L57="","",INT(($L57-INT($L57/1000000000)*1000000000)/100000000))
B58: =IF($L58="","",$M58) | C58: =IF($L58="","",INDEX(HSI!$C$7:$C$106,$N58)) | D58: =IF($L58="","",INDEX(HSI!$D$7:$D$106,$N58)) | E58: =IF($L58="","",IF($P58=0,"TBA",IFERROR(INDEX(Grids!$C$12:$BO$111,$N58,$O58),"-"))) | F58: =IF($L58="","",INDEX(HSI!$F$7:$F$106,$N58)) | G58: =IF($L58="","",IF($P58=0,"TBA",IFERROR(INDEX(Grids!$BQ$12:$EC$111,$N58,$O58),"-"))) | H58: =IF($L58="","",SUM($G$10:$G58)) | I58: =IF($L58="","",IF(INT(($L58-INT($L58/10000000)*10000000)/1000000)=0,"Bloomberg projection",IF($P58=1,"ANNOUNCED","ANNOUNCED - amount TBA"))) | J58: =IF($L58="","",IF((OV_SWITCH="ON")*(COUNTIFS(OVR_TICKERS,INDEX(HSI!$C$7:$C$106,$N58),OVR_BASE,">=0")>0)>0,"stock overridden","")) | L58: =IFERROR(IF(SMALL(Grids!$EE$12:$GQ$111,$M$7+49)>=PEND_TO,"",SMALL(Grids!$EE$12:$GQ$111,$M$7+49)),"") | M58: =IF($L58="","",INT($L58/1000000000)) | N58: =IF($L58="","",INT(($L58-INT($L58/1000000)*1000000)/1000)) | O58: =IF($L58="","",$L58-INT($L58/1000)*1000) | P58: =IF($L58="","",INT(($L58-INT($L58/1000000000)*1000000000)/100000000))
B59: =IF($L59="","",$M59) | C59: =IF($L59="","",INDEX(HSI!$C$7:$C$106,$N59)) | D59: =IF($L59="","",INDEX(HSI!$D$7:$D$106,$N59)) | E59: =IF($L59="","",IF($P59=0,"TBA",IFERROR(INDEX(Grids!$C$12:$BO$111,$N59,$O59),"-"))) | F59: =IF($L59="","",INDEX(HSI!$F$7:$F$106,$N59)) | G59: =IF($L59="","",IF($P59=0,"TBA",IFERROR(INDEX(Grids!$BQ$12:$EC$111,$N59,$O59),"-"))) | H59: =IF($L59="","",SUM($G$10:$G59)) | I59: =IF($L59="","",IF(INT(($L59-INT($L59/10000000)*10000000)/1000000)=0,"Bloomberg projection",IF($P59=1,"ANNOUNCED","ANNOUNCED - amount TBA"))) | J59: =IF($L59="","",IF((OV_SWITCH="ON")*(COUNTIFS(OVR_TICKERS,INDEX(HSI!$C$7:$C$106,$N59),OVR_BASE,">=0")>0)>0,"stock overridden","")) | L59: =IFERROR(IF(SMALL(Grids!$EE$12:$GQ$111,$M$7+50)>=PEND_TO,"",SMALL(Grids!$EE$12:$GQ$111,$M$7+50)),"") | M59: =IF($L59="","",INT($L59/1000000000)) | N59: =IF($L59="","",INT(($L59-INT($L59/1000000)*1000000)/1000)) | O59: =IF($L59="","",$L59-INT($L59/1000)*1000) | P59: =IF($L59="","",INT(($L59-INT($L59/1000000000)*1000000000)/100000000))
B60: =IF($L60="","",$M60) | C60: =IF($L60="","",INDEX(HSI!$C$7:$C$106,$N60)) | D60: =IF($L60="","",INDEX(HSI!$D$7:$D$106,$N60)) | E60: =IF($L60="","",IF($P60=0,"TBA",IFERROR(INDEX(Grids!$C$12:$BO$111,$N60,$O60),"-"))) | F60: =IF($L60="","",INDEX(HSI!$F$7:$F$106,$N60)) | G60: =IF($L60="","",IF($P60=0,"TBA",IFERROR(INDEX(Grids!$BQ$12:$EC$111,$N60,$O60),"-"))) | H60: =IF($L60="","",SUM($G$10:$G60)) | I60: =IF($L60="","",IF(INT(($L60-INT($L60/10000000)*10000000)/1000000)=0,"Bloomberg projection",IF($P60=1,"ANNOUNCED","ANNOUNCED - amount TBA"))) | J60: =IF($L60="","",IF((OV_SWITCH="ON")*(COUNTIFS(OVR_TICKERS,INDEX(HSI!$C$7:$C$106,$N60),OVR_BASE,">=0")>0)>0,"stock overridden","")) | L60: =IFERROR(IF(SMALL(Grids!$EE$12:$GQ$111,$M$7+51)>=PEND_TO,"",SMALL(Grids!$EE$12:$GQ$111,$M$7+51)),"") | M60: =IF($L60="","",INT($L60/1000000000)) | N60: =IF($L60="","",INT(($L60-INT($L60/1000000)*1000000)/1000)) | O60: =IF($L60="","",$L60-INT($L60/1000)*1000) | P60: =IF($L60="","",INT(($L60-INT($L60/1000000000)*1000000000)/100000000))
B61: =IF($L61="","",$M61) | C61: =IF($L61="","",INDEX(HSI!$C$7:$C$106,$N61)) | D61: =IF($L61="","",INDEX(HSI!$D$7:$D$106,$N61)) | E61: =IF($L61="","",IF($P61=0,"TBA",IFERROR(INDEX(Grids!$C$12:$BO$111,$N61,$O61),"-"))) | F61: =IF($L61="","",INDEX(HSI!$F$7:$F$106,$N61)) | G61: =IF($L61="","",IF($P61=0,"TBA",IFERROR(INDEX(Grids!$BQ$12:$EC$111,$N61,$O61),"-"))) | H61: =IF($L61="","",SUM($G$10:$G61)) | I61: =IF($L61="","",IF(INT(($L61-INT($L61/10000000)*10000000)/1000000)=0,"Bloomberg projection",IF($P61=1,"ANNOUNCED","ANNOUNCED - amount TBA"))) | J61: =IF($L61="","",IF((OV_SWITCH="ON")*(COUNTIFS(OVR_TICKERS,INDEX(HSI!$C$7:$C$106,$N61),OVR_BASE,">=0")>0)>0,"stock overridden","")) | L61: =IFERROR(IF(SMALL(Grids!$EE$12:$GQ$111,$M$7+52)>=PEND_TO,"",SMALL(Grids!$EE$12:$GQ$111,$M$7+52)),"") | M61: =IF($L61="","",INT($L61/1000000000)) | N61: =IF($L61="","",INT(($L61-INT($L61/1000000)*1000000)/1000)) | O61: =IF($L61="","",$L61-INT($L61/1000)*1000) | P61: =IF($L61="","",INT(($L61-INT($L61/1000000000)*1000000000)/100000000))
B62: =IF($L62="","",$M62) | C62: =IF($L62="","",INDEX(HSI!$C$7:$C$106,$N62)) | D62: =IF($L62="","",INDEX(HSI!$D$7:$D$106,$N62)) | E62: =IF($L62="","",IF($P62=0,"TBA",IFERROR(INDEX(Grids!$C$12:$BO$111,$N62,$O62),"-"))) | F62: =IF($L62="","",INDEX(HSI!$F$7:$F$106,$N62)) | G62: =IF($L62="","",IF($P62=0,"TBA",IFERROR(INDEX(Grids!$BQ$12:$EC$111,$N62,$O62),"-"))) | H62: =IF($L62="","",SUM($G$10:$G62)) | I62: =IF($L62="","",IF(INT(($L62-INT($L62/10000000)*10000000)/1000000)=0,"Bloomberg projection",IF($P62=1,"ANNOUNCED","ANNOUNCED - amount TBA"))) | J62: =IF($L62="","",IF((OV_SWITCH="ON")*(COUNTIFS(OVR_TICKERS,INDEX(HSI!$C$7:$C$106,$N62),OVR_BASE,">=0")>0)>0,"stock overridden","")) | L62: =IFERROR(IF(SMALL(Grids!$EE$12:$GQ$111,$M$7+53)>=PEND_TO,"",SMALL(Grids!$EE$12:$GQ$111,$M$7+53)),"") | M62: =IF($L62="","",INT($L62/1000000000)) | N62: =IF($L62="","",INT(($L62-INT($L62/1000000)*1000000)/1000)) | O62: =IF($L62="","",$L62-INT($L62/1000)*1000) | P62: =IF($L62="","",INT(($L62-INT($L62/1000000000)*1000000000)/100000000))
B63: =IF($L63="","",$M63) | C63: =IF($L63="","",INDEX(HSI!$C$7:$C$106,$N63)) | D63: =IF($L63="","",INDEX(HSI!$D$7:$D$106,$N63)) | E63: =IF($L63="","",IF($P63=0,"TBA",IFERROR(INDEX(Grids!$C$12:$BO$111,$N63,$O63),"-"))) | F63: =IF($L63="","",INDEX(HSI!$F$7:$F$106,$N63)) | G63: =IF($L63="","",IF($P63=0,"TBA",IFERROR(INDEX(Grids!$BQ$12:$EC$111,$N63,$O63),"-"))) | H63: =IF($L63="","",SUM($G$10:$G63)) | I63: =IF($L63="","",IF(INT(($L63-INT($L63/10000000)*10000000)/1000000)=0,"Bloomberg projection",IF($P63=1,"ANNOUNCED","ANNOUNCED - amount TBA"))) | J63: =IF($L63="","",IF((OV_SWITCH="ON")*(COUNTIFS(OVR_TICKERS,INDEX(HSI!$C$7:$C$106,$N63),OVR_BASE,">=0")>0)>0,"stock overridden","")) | L63: =IFERROR(IF(SMALL(Grids!$EE$12:$GQ$111,$M$7+54)>=PEND_TO,"",SMALL(Grids!$EE$12:$GQ$111,$M$7+54)),"") | M63: =IF($L63="","",INT($L63/1000000000)) | N63: =IF($L63="","",INT(($L63-INT($L63/1000000)*1000000)/1000)) | O63: =IF($L63="","",$L63-INT($L63/1000)*1000) | P63: =IF($L63="","",INT(($L63-INT($L63/1000000000)*1000000000)/100000000))
B64: =IF($L64="","",$M64) | C64: =IF($L64="","",INDEX(HSI!$C$7:$C$106,$N64)) | D64: =IF($L64="","",INDEX(HSI!$D$7:$D$106,$N64)) | E64: =IF($L64="","",IF($P64=0,"TBA",IFERROR(INDEX(Grids!$C$12:$BO$111,$N64,$O64),"-"))) | F64: =IF($L64="","",INDEX(HSI!$F$7:$F$106,$N64)) | G64: =IF($L64="","",IF($P64=0,"TBA",IFERROR(INDEX(Grids!$BQ$12:$EC$111,$N64,$O64),"-"))) | H64: =IF($L64="","",SUM($G$10:$G64)) | I64: =IF($L64="","",IF(INT(($L64-INT($L64/10000000)*10000000)/1000000)=0,"Bloomberg projection",IF($P64=1,"ANNOUNCED","ANNOUNCED - amount TBA"))) | J64: =IF($L64="","",IF((OV_SWITCH="ON")*(COUNTIFS(OVR_TICKERS,INDEX(HSI!$C$7:$C$106,$N64),OVR_BASE,">=0")>0)>0,"stock overridden","")) | L64: =IFERROR(IF(SMALL(Grids!$EE$12:$GQ$111,$M$7+55)>=PEND_TO,"",SMALL(Grids!$EE$12:$GQ$111,$M$7+55)),"") | M64: =IF($L64="","",INT($L64/1000000000)) | N64: =IF($L64="","",INT(($L64-INT($L64/1000000)*1000000)/1000)) | O64: =IF($L64="","",$L64-INT($L64/1000)*1000) | P64: =IF($L64="","",INT(($L64-INT($L64/1000000000)*1000000000)/100000000))
B65: =IF($L65="","",$M65) | C65: =IF($L65="","",INDEX(HSI!$C$7:$C$106,$N65)) | D65: =IF($L65="","",INDEX(HSI!$D$7:$D$106,$N65)) | E65: =IF($L65="","",IF($P65=0,"TBA",IFERROR(INDEX(Grids!$C$12:$BO$111,$N65,$O65),"-"))) | F65: =IF($L65="","",INDEX(HSI!$F$7:$F$106,$N65)) | G65: =IF($L65="","",IF($P65=0,"TBA",IFERROR(INDEX(Grids!$BQ$12:$EC$111,$N65,$O65),"-"))) | H65: =IF($L65="","",SUM($G$10:$G65)) | I65: =IF($L65="","",IF(INT(($L65-INT($L65/10000000)*10000000)/1000000)=0,"Bloomberg projection",IF($P65=1,"ANNOUNCED","ANNOUNCED - amount TBA"))) | J65: =IF($L65="","",IF((OV_SWITCH="ON")*(COUNTIFS(OVR_TICKERS,INDEX(HSI!$C$7:$C$106,$N65),OVR_BASE,">=0")>0)>0,"stock overridden","")) | L65: =IFERROR(IF(SMALL(Grids!$EE$12:$GQ$111,$M$7+56)>=PEND_TO,"",SMALL(Grids!$EE$12:$GQ$111,$M$7+56)),"") | M65: =IF($L65="","",INT($L65/1000000000)) | N65: =IF($L65="","",INT(($L65-INT($L65/1000000)*1000000)/1000)) | O65: =IF($L65="","",$L65-INT($L65/1000)*1000) | P65: =IF($L65="","",INT(($L65-INT($L65/1000000000)*1000000000)/100000000))
B66: =IF($L66="","",$M66) | C66: =IF($L66="","",INDEX(HSI!$C$7:$C$106,$N66)) | D66: =IF($L66="","",INDEX(HSI!$D$7:$D$106,$N66)) | E66: =IF($L66="","",IF($P66=0,"TBA",IFERROR(INDEX(Grids!$C$12:$BO$111,$N66,$O66),"-"))) | F66: =IF($L66="","",INDEX(HSI!$F$7:$F$106,$N66)) | G66: =IF($L66="","",IF($P66=0,"TBA",IFERROR(INDEX(Grids!$BQ$12:$EC$111,$N66,$O66),"-"))) | H66: =IF($L66="","",SUM($G$10:$G66)) | I66: =IF($L66="","",IF(INT(($L66-INT($L66/10000000)*10000000)/1000000)=0,"Bloomberg projection",IF($P66=1,"ANNOUNCED","ANNOUNCED - amount TBA"))) | J66: =IF($L66="","",IF((OV_SWITCH="ON")*(COUNTIFS(OVR_TICKERS,INDEX(HSI!$C$7:$C$106,$N66),OVR_BASE,">=0")>0)>0,"stock overridden","")) | L66: =IFERROR(IF(SMALL(Grids!$EE$12:$GQ$111,$M$7+57)>=PEND_TO,"",SMALL(Grids!$EE$12:$GQ$111,$M$7+57)),"") | M66: =IF($L66="","",INT($L66/1000000000)) | N66: =IF($L66="","",INT(($L66-INT($L66/1000000)*1000000)/1000)) | O66: =IF($L66="","",$L66-INT($L66/1000)*1000) | P66: =IF($L66="","",INT(($L66-INT($L66/1000000000)*1000000000)/100000000))
B67: =IF($L67="","",$M67) | C67: =IF($L67="","",INDEX(HSI!$C$7:$C$106,$N67)) | D67: =IF($L67="","",INDEX(HSI!$D$7:$D$106,$N67)) | E67: =IF($L67="","",IF($P67=0,"TBA",IFERROR(INDEX(Grids!$C$12:$BO$111,$N67,$O67),"-"))) | F67: =IF($L67="","",INDEX(HSI!$F$7:$F$106,$N67)) | G67: =IF($L67="","",IF($P67=0,"TBA",IFERROR(INDEX(Grids!$BQ$12:$EC$111,$N67,$O67),"-"))) | H67: =IF($L67="","",SUM($G$10:$G67)) | I67: =IF($L67="","",IF(INT(($L67-INT($L67/10000000)*10000000)/1000000)=0,"Bloomberg projection",IF($P67=1,"ANNOUNCED","ANNOUNCED - amount TBA"))) | J67: =IF($L67="","",IF((OV_SWITCH="ON")*(COUNTIFS(OVR_TICKERS,INDEX(HSI!$C$7:$C$106,$N67),OVR_BASE,">=0")>0)>0,"stock overridden","")) | L67: =IFERROR(IF(SMALL(Grids!$EE$12:$GQ$111,$M$7+58)>=PEND_TO,"",SMALL(Grids!$EE$12:$GQ$111,$M$7+58)),"") | M67: =IF($L67="","",INT($L67/1000000000)) | N67: =IF($L67="","",INT(($L67-INT($L67/1000000)*1000000)/1000)) | O67: =IF($L67="","",$L67-INT($L67/1000)*1000) | P67: =IF($L67="","",INT(($L67-INT($L67/1000000000)*1000000000)/100000000))
B68: =IF($L68="","",$M68) | C68: =IF($L68="","",INDEX(HSI!$C$7:$C$106,$N68)) | D68: =IF($L68="","",INDEX(HSI!$D$7:$D$106,$N68)) | E68: =IF($L68="","",IF($P68=0,"TBA",IFERROR(INDEX(Grids!$C$12:$BO$111,$N68,$O68),"-"))) | F68: =IF($L68="","",INDEX(HSI!$F$7:$F$106,$N68)) | G68: =IF($L68="","",IF($P68=0,"TBA",IFERROR(INDEX(Grids!$BQ$12:$EC$111,$N68,$O68),"-"))) | H68: =IF($L68="","",SUM($G$10:$G68)) | I68: =IF($L68="","",IF(INT(($L68-INT($L68/10000000)*10000000)/1000000)=0,"Bloomberg projection",IF($P68=1,"ANNOUNCED","ANNOUNCED - amount TBA"))) | J68: =IF($L68="","",IF((OV_SWITCH="ON")*(COUNTIFS(OVR_TICKERS,INDEX(HSI!$C$7:$C$106,$N68),OVR_BASE,">=0")>0)>0,"stock overridden","")) | L68: =IFERROR(IF(SMALL(Grids!$EE$12:$GQ$111,$M$7+59)>=PEND_TO,"",SMALL(Grids!$EE$12:$GQ$111,$M$7+59)),"") | M68: =IF($L68="","",INT($L68/1000000000)) | N68: =IF($L68="","",INT(($L68-INT($L68/1000000)*1000000)/1000)) | O68: =IF($L68="","",$L68-INT($L68/1000)*1000) | P68: =IF($L68="","",INT(($L68-INT($L68/1000000000)*1000000000)/100000000))
B69: =IF($L69="","",$M69) | C69: =IF($L69="","",INDEX(HSI!$C$7:$C$106,$N69)) | D69: =IF($L69="","",INDEX(HSI!$D$7:$D$106,$N69)) | E69: =IF($L69="","",IF($P69=0,"TBA",IFERROR(INDEX(Grids!$C$12:$BO$111,$N69,$O69),"-"))) | F69: =IF($L69="","",INDEX(HSI!$F$7:$F$106,$N69)) | G69: =IF($L69="","",IF($P69=0,"TBA",IFERROR(INDEX(Grids!$BQ$12:$EC$111,$N69,$O69),"-"))) | H69: =IF($L69="","",SUM($G$10:$G69)) | I69: =IF($L69="","",IF(INT(($L69-INT($L69/10000000)*10000000)/1000000)=0,"Bloomberg projection",IF($P69=1,"ANNOUNCED","ANNOUNCED - amount TBA"))) | J69: =IF($L69="","",IF((OV_SWITCH="ON")*(COUNTIFS(OVR_TICKERS,INDEX(HSI!$C$7:$C$106,$N69),OVR_BASE,">=0")>0)>0,"stock overridden","")) | L69: =IFERROR(IF(SMALL(Grids!$EE$12:$GQ$111,$M$7+60)>=PEND_TO,"",SMALL(Grids!$EE$12:$GQ$111,$M$7+60)),"") | M69: =IF($L69="","",INT($L69/1000000000)) | N69: =IF($L69="","",INT(($L69-INT($L69/1000000)*1000000)/1000)) | O69: =IF($L69="","",$L69-INT($L69/1000)*1000) | P69: =IF($L69="","",INT(($L69-INT($L69/1000000000)*1000000000)/100000000))
B70: =IF($L70="","",$M70) | C70: =IF($L70="","",INDEX(HSI!$C$7:$C$106,$N70)) | D70: =IF($L70="","",INDEX(HSI!$D$7:$D$106,$N70)) | E70: =IF($L70="","",IF($P70=0,"TBA",IFERROR(INDEX(Grids!$C$12:$BO$111,$N70,$O70),"-"))) | F70: =IF($L70="","",INDEX(HSI!$F$7:$F$106,$N70)) | G70: =IF($L70="","",IF($P70=0,"TBA",IFERROR(INDEX(Grids!$BQ$12:$EC$111,$N70,$O70),"-"))) | H70: =IF($L70="","",SUM($G$10:$G70)) | I70: =IF($L70="","",IF(INT(($L70-INT($L70/10000000)*10000000)/1000000)=0,"Bloomberg projection",IF($P70=1,"ANNOUNCED","ANNOUNCED - amount TBA"))) | J70: =IF($L70="","",IF((OV_SWITCH="ON")*(COUNTIFS(OVR_TICKERS,INDEX(HSI!$C$7:$C$106,$N70),OVR_BASE,">=0")>0)>0,"stock overridden","")) | L70: =IFERROR(IF(SMALL(Grids!$EE$12:$GQ$111,$M$7+61)>=PEND_TO,"",SMALL(Grids!$EE$12:$GQ$111,$M$7+61)),"") | M70: =IF($L70="","",INT($L70/1000000000)) | N70: =IF($L70="","",INT(($L70-INT($L70/1000000)*1000000)/1000)) | O70: =IF($L70="","",$L70-INT($L70/1000)*1000) | P70: =IF($L70="","",INT(($L70-INT($L70/1000000000)*1000000000)/100000000))
B71: =IF($L71="","",$M71) | C71: =IF($L71="","",INDEX(HSI!$C$7:$C$106,$N71)) | D71: =IF($L71="","",INDEX(HSI!$D$7:$D$106,$N71)) | E71: =IF($L71="","",IF($P71=0,"TBA",IFERROR(INDEX(Grids!$C$12:$BO$111,$N71,$O71),"-"))) | F71: =IF($L71="","",INDEX(HSI!$F$7:$F$106,$N71)) | G71: =IF($L71="","",IF($P71=0,"TBA",IFERROR(INDEX(Grids!$BQ$12:$EC$111,$N71,$O71),"-"))) | H71: =IF($L71="","",SUM($G$10:$G71)) | I71: =IF($L71="","",IF(INT(($L71-INT($L71/10000000)*10000000)/1000000)=0,"Bloomberg projection",IF($P71=1,"ANNOUNCED","ANNOUNCED - amount TBA"))) | J71: =IF($L71="","",IF((OV_SWITCH="ON")*(COUNTIFS(OVR_TICKERS,INDEX(HSI!$C$7:$C$106,$N71),OVR_BASE,">=0")>0)>0,"stock overridden","")) | L71: =IFERROR(IF(SMALL(Grids!$EE$12:$GQ$111,$M$7+62)>=PEND_TO,"",SMALL(Grids!$EE$12:$GQ$111,$M$7+62)),"") | M71: =IF($L71="","",INT($L71/1000000000)) | N71: =IF($L71="","",INT(($L71-INT($L71/1000000)*1000000)/1000)) | O71: =IF($L71="","",$L71-INT($L71/1000)*1000) | P71: =IF($L71="","",INT(($L71-INT($L71/1000000000)*1000000000)/100000000))
B72: =IF($L72="","",$M72) | C72: =IF($L72="","",INDEX(HSI!$C$7:$C$106,$N72)) | D72: =IF($L72="","",INDEX(HSI!$D$7:$D$106,$N72)) | E72: =IF($L72="","",IF($P72=0,"TBA",IFERROR(INDEX(Grids!$C$12:$BO$111,$N72,$O72),"-"))) | F72: =IF($L72="","",INDEX(HSI!$F$7:$F$106,$N72)) | G72: =IF($L72="","",IF($P72=0,"TBA",IFERROR(INDEX(Grids!$BQ$12:$EC$111,$N72,$O72),"-"))) | H72: =IF($L72="","",SUM($G$10:$G72)) | I72: =IF($L72="","",IF(INT(($L72-INT($L72/10000000)*10000000)/1000000)=0,"Bloomberg projection",IF($P72=1,"ANNOUNCED","ANNOUNCED - amount TBA"))) | J72: =IF($L72="","",IF((OV_SWITCH="ON")*(COUNTIFS(OVR_TICKERS,INDEX(HSI!$C$7:$C$106,$N72),OVR_BASE,">=0")>0)>0,"stock overridden","")) | L72: =IFERROR(IF(SMALL(Grids!$EE$12:$GQ$111,$M$7+63)>=PEND_TO,"",SMALL(Grids!$EE$12:$GQ$111,$M$7+63)),"") | M72: =IF($L72="","",INT($L72/1000000000)) | N72: =IF($L72="","",INT(($L72-INT($L72/1000000)*1000000)/1000)) | O72: =IF($L72="","",$L72-INT($L72/1000)*1000) | P72: =IF($L72="","",INT(($L72-INT($L72/1000000000)*1000000000)/100000000))
B73: =IF($L73="","",$M73) | C73: =IF($L73="","",INDEX(HSI!$C$7:$C$106,$N73)) | D73: =IF($L73="","",INDEX(HSI!$D$7:$D$106,$N73)) | E73: =IF($L73="","",IF($P73=0,"TBA",IFERROR(INDEX(Grids!$C$12:$BO$111,$N73,$O73),"-"))) | F73: =IF($L73="","",INDEX(HSI!$F$7:$F$106,$N73)) | G73: =IF($L73="","",IF($P73=0,"TBA",IFERROR(INDEX(Grids!$BQ$12:$EC$111,$N73,$O73),"-"))) | H73: =IF($L73="","",SUM($G$10:$G73)) | I73: =IF($L73="","",IF(INT(($L73-INT($L73/10000000)*10000000)/1000000)=0,"Bloomberg projection",IF($P73=1,"ANNOUNCED","ANNOUNCED - amount TBA"))) | J73: =IF($L73="","",IF((OV_SWITCH="ON")*(COUNTIFS(OVR_TICKERS,INDEX(HSI!$C$7:$C$106,$N73),OVR_BASE,">=0")>0)>0,"stock overridden","")) | L73: =IFERROR(IF(SMALL(Grids!$EE$12:$GQ$111,$M$7+64)>=PEND_TO,"",SMALL(Grids!$EE$12:$GQ$111,$M$7+64)),"") | M73: =IF($L73="","",INT($L73/1000000000)) | N73: =IF($L73="","",INT(($L73-INT($L73/1000000)*1000000)/1000)) | O73: =IF($L73="","",$L73-INT($L73/1000)*1000) | P73: =IF($L73="","",INT(($L73-INT($L73/1000000000)*1000000000)/100000000))
B74: =IF($L74="","",$M74) | C74: =IF($L74="","",INDEX(HSI!$C$7:$C$106,$N74)) | D74: =IF($L74="","",INDEX(HSI!$D$7:$D$106,$N74)) | E74: =IF($L74="","",IF($P74=0,"TBA",IFERROR(INDEX(Grids!$C$12:$BO$111,$N74,$O74),"-"))) | F74: =IF($L74="","",INDEX(HSI!$F$7:$F$106,$N74)) | G74: =IF($L74="","",IF($P74=0,"TBA",IFERROR(INDEX(Grids!$BQ$12:$EC$111,$N74,$O74),"-"))) | H74: =IF($L74="","",SUM($G$10:$G74)) | I74: =IF($L74="","",IF(INT(($L74-INT($L74/10000000)*10000000)/1000000)=0,"Bloomberg projection",IF($P74=1,"ANNOUNCED","ANNOUNCED - amount TBA"))) | J74: =IF($L74="","",IF((OV_SWITCH="ON")*(COUNTIFS(OVR_TICKERS,INDEX(HSI!$C$7:$C$106,$N74),OVR_BASE,">=0")>0)>0,"stock overridden","")) | L74: =IFERROR(IF(SMALL(Grids!$EE$12:$GQ$111,$M$7+65)>=PEND_TO,"",SMALL(Grids!$EE$12:$GQ$111,$M$7+65)),"") | M74: =IF($L74="","",INT($L74/1000000000)) | N74: =IF($L74="","",INT(($L74-INT($L74/1000000)*1000000)/1000)) | O74: =IF($L74="","",$L74-INT($L74/1000)*1000) | P74: =IF($L74="","",INT(($L74-INT($L74/1000000000)*1000000000)/100000000))
B75: =IF($L75="","",$M75) | C75: =IF($L75="","",INDEX(HSI!$C$7:$C$106,$N75)) | D75: =IF($L75="","",INDEX(HSI!$D$7:$D$106,$N75)) | E75: =IF($L75="","",IF($P75=0,"TBA",IFERROR(INDEX(Grids!$C$12:$BO$111,$N75,$O75),"-"))) | F75: =IF($L75="","",INDEX(HSI!$F$7:$F$106,$N75)) | G75: =IF($L75="","",IF($P75=0,"TBA",IFERROR(INDEX(Grids!$BQ$12:$EC$111,$N75,$O75),"-"))) | H75: =IF($L75="","",SUM($G$10:$G75)) | I75: =IF($L75="","",IF(INT(($L75-INT($L75/10000000)*10000000)/1000000)=0,"Bloomberg projection",IF($P75=1,"ANNOUNCED","ANNOUNCED - amount TBA"))) | J75: =IF($L75="","",IF((OV_SWITCH="ON")*(COUNTIFS(OVR_TICKERS,INDEX(HSI!$C$7:$C$106,$N75),OVR_BASE,">=0")>0)>0,"stock overridden","")) | L75: =IFERROR(IF(SMALL(Grids!$EE$12:$GQ$111,$M$7+66)>=PEND_TO,"",SMALL(Grids!$EE$12:$GQ$111,$M$7+66)),"") | M75: =IF($L75="","",INT($L75/1000000000)) | N75: =IF($L75="","",INT(($L75-INT($L75/1000000)*1000000)/1000)) | O75: =IF($L75="","",$L75-INT($L75/1000)*1000) | P75: =IF($L75="","",INT(($L75-INT($L75/1000000000)*1000000000)/100000000))
B76: =IF($L76="","",$M76) | C76: =IF($L76="","",INDEX(HSI!$C$7:$C$106,$N76)) | D76: =IF($L76="","",INDEX(HSI!$D$7:$D$106,$N76)) | E76: =IF($L76="","",IF($P76=0,"TBA",IFERROR(INDEX(Grids!$C$12:$BO$111,$N76,$O76),"-"))) | F76: =IF($L76="","",INDEX(HSI!$F$7:$F$106,$N76)) | G76: =IF($L76="","",IF($P76=0,"TBA",IFERROR(INDEX(Grids!$BQ$12:$EC$111,$N76,$O76),"-"))) | H76: =IF($L76="","",SUM($G$10:$G76)) | I76: =IF($L76="","",IF(INT(($L76-INT($L76/10000000)*10000000)/1000000)=0,"Bloomberg projection",IF($P76=1,"ANNOUNCED","ANNOUNCED - amount TBA"))) | J76: =IF($L76="","",IF((OV_SWITCH="ON")*(COUNTIFS(OVR_TICKERS,INDEX(HSI!$C$7:$C$106,$N76),OVR_BASE,">=0")>0)>0,"stock overridden","")) | L76: =IFERROR(IF(SMALL(Grids!$EE$12:$GQ$111,$M$7+67)>=PEND_TO,"",SMALL(Grids!$EE$12:$GQ$111,$M$7+67)),"") | M76: =IF($L76="","",INT($L76/1000000000)) | N76: =IF($L76="","",INT(($L76-INT($L76/1000000)*1000000)/1000)) | O76: =IF($L76="","",$L76-INT($L76/1000)*1000) | P76: =IF($L76="","",INT(($L76-INT($L76/1000000000)*1000000000)/100000000))
B77: =IF($L77="","",$M77) | C77: =IF($L77="","",INDEX(HSI!$C$7:$C$106,$N77)) | D77: =IF($L77="","",INDEX(HSI!$D$7:$D$106,$N77)) | E77: =IF($L77="","",IF($P77=0,"TBA",IFERROR(INDEX(Grids!$C$12:$BO$111,$N77,$O77),"-"))) | F77: =IF($L77="","",INDEX(HSI!$F$7:$F$106,$N77)) | G77: =IF($L77="","",IF($P77=0,"TBA",IFERROR(INDEX(Grids!$BQ$12:$EC$111,$N77,$O77),"-"))) | H77: =IF($L77="","",SUM($G$10:$G77)) | I77: =IF($L77="","",IF(INT(($L77-INT($L77/10000000)*10000000)/1000000)=0,"Bloomberg projection",IF($P77=1,"ANNOUNCED","ANNOUNCED - amount TBA"))) | J77: =IF($L77="","",IF((OV_SWITCH="ON")*(COUNTIFS(OVR_TICKERS,INDEX(HSI!$C$7:$C$106,$N77),OVR_BASE,">=0")>0)>0,"stock overridden","")) | L77: =IFERROR(IF(SMALL(Grids!$EE$12:$GQ$111,$M$7+68)>=PEND_TO,"",SMALL(Grids!$EE$12:$GQ$111,$M$7+68)),"") | M77: =IF($L77="","",INT($L77/1000000000)) | N77: =IF($L77="","",INT(($L77-INT($L77/1000000)*1000000)/1000)) | O77: =IF($L77="","",$L77-INT($L77/1000)*1000) | P77: =IF($L77="","",INT(($L77-INT($L77/1000000000)*1000000000)/100000000))
B78: =IF($L78="","",$M78) | C78: =IF($L78="","",INDEX(HSI!$C$7:$C$106,$N78)) | D78: =IF($L78="","",INDEX(HSI!$D$7:$D$106,$N78)) | E78: =IF($L78="","",IF($P78=0,"TBA",IFERROR(INDEX(Grids!$C$12:$BO$111,$N78,$O78),"-"))) | F78: =IF($L78="","",INDEX(HSI!$F$7:$F$106,$N78)) | G78: =IF($L78="","",IF($P78=0,"TBA",IFERROR(INDEX(Grids!$BQ$12:$EC$111,$N78,$O78),"-"))) | H78: =IF($L78="","",SUM($G$10:$G78)) | I78: =IF($L78="","",IF(INT(($L78-INT($L78/10000000)*10000000)/1000000)=0,"Bloomberg projection",IF($P78=1,"ANNOUNCED","ANNOUNCED - amount TBA"))) | J78: =IF($L78="","",IF((OV_SWITCH="ON")*(COUNTIFS(OVR_TICKERS,INDEX(HSI!$C$7:$C$106,$N78),OVR_BASE,">=0")>0)>0,"stock overridden","")) | L78: =IFERROR(IF(SMALL(Grids!$EE$12:$GQ$111,$M$7+69)>=PEND_TO,"",SMALL(Grids!$EE$12:$GQ$111,$M$7+69)),"") | M78: =IF($L78="","",INT($L78/1000000000)) | N78: =IF($L78="","",INT(($L78-INT($L78/1000000)*1000000)/1000)) | O78: =IF($L78="","",$L78-INT($L78/1000)*1000) | P78: =IF($L78="","",INT(($L78-INT($L78/1000000000)*1000000000)/100000000))
B79: =IF($L79="","",$M79) | C79: =IF($L79="","",INDEX(HSI!$C$7:$C$106,$N79)) | D79: =IF($L79="","",INDEX(HSI!$D$7:$D$106,$N79)) | E79: =IF($L79="","",IF($P79=0,"TBA",IFERROR(INDEX(Grids!$C$12:$BO$111,$N79,$O79),"-"))) | F79: =IF($L79="","",INDEX(HSI!$F$7:$F$106,$N79)) | G79: =IF($L79="","",IF($P79=0,"TBA",IFERROR(INDEX(Grids!$BQ$12:$EC$111,$N79,$O79),"-"))) | H79: =IF($L79="","",SUM($G$10:$G79)) | I79: =IF($L79="","",IF(INT(($L79-INT($L79/10000000)*10000000)/1000000)=0,"Bloomberg projection",IF($P79=1,"ANNOUNCED","ANNOUNCED - amount TBA"))) | J79: =IF($L79="","",IF((OV_SWITCH="ON")*(COUNTIFS(OVR_TICKERS,INDEX(HSI!$C$7:$C$106,$N79),OVR_BASE,">=0")>0)>0,"stock overridden","")) | L79: =IFERROR(IF(SMALL(Grids!$EE$12:$GQ$111,$M$7+70)>=PEND_TO,"",SMALL(Grids!$EE$12:$GQ$111,$M$7+70)),"") | M79: =IF($L79="","",INT($L79/1000000000)) | N79: =IF($L79="","",INT(($L79-INT($L79/1000000)*1000000)/1000)) | O79: =IF($L79="","",$L79-INT($L79/1000)*1000) | P79: =IF($L79="","",INT(($L79-INT($L79/1000000000)*1000000000)/100000000))
B80: =IF($L80="","",$M80) | C80: =IF($L80="","",INDEX(HSI!$C$7:$C$106,$N80)) | D80: =IF($L80="","",INDEX(HSI!$D$7:$D$106,$N80)) | E80: =IF($L80="","",IF($P80=0,"TBA",IFERROR(INDEX(Grids!$C$12:$BO$111,$N80,$O80),"-"))) | F80: =IF($L80="","",INDEX(HSI!$F$7:$F$106,$N80)) | G80: =IF($L80="","",IF($P80=0,"TBA",IFERROR(INDEX(Grids!$BQ$12:$EC$111,$N80,$O80),"-"))) | H80: =IF($L80="","",SUM($G$10:$G80)) | I80: =IF($L80="","",IF(INT(($L80-INT($L80/10000000)*10000000)/1000000)=0,"Bloomberg projection",IF($P80=1,"ANNOUNCED","ANNOUNCED - amount TBA"))) | J80: =IF($L80="","",IF((OV_SWITCH="ON")*(COUNTIFS(OVR_TICKERS,INDEX(HSI!$C$7:$C$106,$N80),OVR_BASE,">=0")>0)>0,"stock overridden","")) | L80: =IFERROR(IF(SMALL(Grids!$EE$12:$GQ$111,$M$7+71)>=PEND_TO,"",SMALL(Grids!$EE$12:$GQ$111,$M$7+71)),"") | M80: =IF($L80="","",INT($L80/1000000000)) | N80: =IF($L80="","",INT(($L80-INT($L80/1000000)*1000000)/1000)) | O80: =IF($L80="","",$L80-INT($L80/1000)*1000) | P80: =IF($L80="","",INT(($L80-INT($L80/1000000000)*1000000000)/100000000))
B81: =IF($L81="","",$M81) | C81: =IF($L81="","",INDEX(HSI!$C$7:$C$106,$N81)) | D81: =IF($L81="","",INDEX(HSI!$D$7:$D$106,$N81)) | E81: =IF($L81="","",IF($P81=0,"TBA",IFERROR(INDEX(Grids!$C$12:$BO$111,$N81,$O81),"-"))) | F81: =IF($L81="","",INDEX(HSI!$F$7:$F$106,$N81)) | G81: =IF($L81="","",IF($P81=0,"TBA",IFERROR(INDEX(Grids!$BQ$12:$EC$111,$N81,$O81),"-"))) | H81: =IF($L81="","",SUM($G$10:$G81)) | I81: =IF($L81="","",IF(INT(($L81-INT($L81/10000000)*10000000)/1000000)=0,"Bloomberg projection",IF($P81=1,"ANNOUNCED","ANNOUNCED - amount TBA"))) | J81: =IF($L81="","",IF((OV_SWITCH="ON")*(COUNTIFS(OVR_TICKERS,INDEX(HSI!$C$7:$C$106,$N81),OVR_BASE,">=0")>0)>0,"stock overridden","")) | L81: =IFERROR(IF(SMALL(Grids!$EE$12:$GQ$111,$M$7+72)>=PEND_TO,"",SMALL(Grids!$EE$12:$GQ$111,$M$7+72)),"") | M81: =IF($L81="","",INT($L81/1000000000)) | N81: =IF($L81="","",INT(($L81-INT($L81/1000000)*1000000)/1000)) | O81: =IF($L81="","",$L81-INT($L81/1000)*1000) | P81: =IF($L81="","",INT(($L81-INT($L81/1000000000)*1000000000)/100000000))
B82: =IF($L82="","",$M82) | C82: =IF($L82="","",INDEX(HSI!$C$7:$C$106,$N82)) | D82: =IF($L82="","",INDEX(HSI!$D$7:$D$106,$N82)) | E82: =IF($L82="","",IF($P82=0,"TBA",IFERROR(INDEX(Grids!$C$12:$BO$111,$N82,$O82),"-"))) | F82: =IF($L82="","",INDEX(HSI!$F$7:$F$106,$N82)) | G82: =IF($L82="","",IF($P82=0,"TBA",IFERROR(INDEX(Grids!$BQ$12:$EC$111,$N82,$O82),"-"))) | H82: =IF($L82="","",SUM($G$10:$G82)) | I82: =IF($L82="","",IF(INT(($L82-INT($L82/10000000)*10000000)/1000000)=0,"Bloomberg projection",IF($P82=1,"ANNOUNCED","ANNOUNCED - amount TBA"))) | J82: =IF($L82="","",IF((OV_SWITCH="ON")*(COUNTIFS(OVR_TICKERS,INDEX(HSI!$C$7:$C$106,$N82),OVR_BASE,">=0")>0)>0,"stock overridden","")) | L82: =IFERROR(IF(SMALL(Grids!$EE$12:$GQ$111,$M$7+73)>=PEND_TO,"",SMALL(Grids!$EE$12:$GQ$111,$M$7+73)),"") | M82: =IF($L82="","",INT($L82/1000000000)) | N82: =IF($L82="","",INT(($L82-INT($L82/1000000)*1000000)/1000)) | O82: =IF($L82="","",$L82-INT($L82/1000)*1000) | P82: =IF($L82="","",INT(($L82-INT($L82/1000000000)*1000000000)/100000000))
B83: =IF($L83="","",$M83) | C83: =IF($L83="","",INDEX(HSI!$C$7:$C$106,$N83)) | D83: =IF($L83="","",INDEX(HSI!$D$7:$D$106,$N83)) | E83: =IF($L83="","",IF($P83=0,"TBA",IFERROR(INDEX(Grids!$C$12:$BO$111,$N83,$O83),"-"))) | F83: =IF($L83="","",INDEX(HSI!$F$7:$F$106,$N83)) | G83: =IF($L83="","",IF($P83=0,"TBA",IFERROR(INDEX(Grids!$BQ$12:$EC$111,$N83,$O83),"-"))) | H83: =IF($L83="","",SUM($G$10:$G83)) | I83: =IF($L83="","",IF(INT(($L83-INT($L83/10000000)*10000000)/1000000)=0,"Bloomberg projection",IF($P83=1,"ANNOUNCED","ANNOUNCED - amount TBA"))) | J83: =IF($L83="","",IF((OV_SWITCH="ON")*(COUNTIFS(OVR_TICKERS,INDEX(HSI!$C$7:$C$106,$N83),OVR_BASE,">=0")>0)>0,"stock overridden","")) | L83: =IFERROR(IF(SMALL(Grids!$EE$12:$GQ$111,$M$7+74)>=PEND_TO,"",SMALL(Grids!$EE$12:$GQ$111,$M$7+74)),"") | M83: =IF($L83="","",INT($L83/1000000000)) | N83: =IF($L83="","",INT(($L83-INT($L83/1000000)*1000000)/1000)) | O83: =IF($L83="","",$L83-INT($L83/1000)*1000) | P83: =IF($L83="","",INT(($L83-INT($L83/1000000000)*1000000000)/100000000))
B84: =IF($L84="","",$M84) | C84: =IF($L84="","",INDEX(HSI!$C$7:$C$106,$N84)) | D84: =IF($L84="","",INDEX(HSI!$D$7:$D$106,$N84)) | E84: =IF($L84="","",IF($P84=0,"TBA",IFERROR(INDEX(Grids!$C$12:$BO$111,$N84,$O84),"-"))) | F84: =IF($L84="","",INDEX(HSI!$F$7:$F$106,$N84)) | G84: =IF($L84="","",IF($P84=0,"TBA",IFERROR(INDEX(Grids!$BQ$12:$EC$111,$N84,$O84),"-"))) | H84: =IF($L84="","",SUM($G$10:$G84)) | I84: =IF($L84="","",IF(INT(($L84-INT($L84/10000000)*10000000)/1000000)=0,"Bloomberg projection",IF($P84=1,"ANNOUNCED","ANNOUNCED - amount TBA"))) | J84: =IF($L84="","",IF((OV_SWITCH="ON")*(COUNTIFS(OVR_TICKERS,INDEX(HSI!$C$7:$C$106,$N84),OVR_BASE,">=0")>0)>0,"stock overridden","")) | L84: =IFERROR(IF(SMALL(Grids!$EE$12:$GQ$111,$M$7+75)>=PEND_TO,"",SMALL(Grids!$EE$12:$GQ$111,$M$7+75)),"") | M84: =IF($L84="","",INT($L84/1000000000)) | N84: =IF($L84="","",INT(($L84-INT($L84/1000000)*1000000)/1000)) | O84: =IF($L84="","",$L84-INT($L84/1000)*1000) | P84: =IF($L84="","",INT(($L84-INT($L84/1000000000)*1000000000)/100000000))
B85: =IF($L85="","",$M85) | C85: =IF($L85="","",INDEX(HSI!$C$7:$C$106,$N85)) | D85: =IF($L85="","",INDEX(HSI!$D$7:$D$106,$N85)) | E85: =IF($L85="","",IF($P85=0,"TBA",IFERROR(INDEX(Grids!$C$12:$BO$111,$N85,$O85),"-"))) | F85: =IF($L85="","",INDEX(HSI!$F$7:$F$106,$N85)) | G85: =IF($L85="","",IF($P85=0,"TBA",IFERROR(INDEX(Grids!$BQ$12:$EC$111,$N85,$O85),"-"))) | H85: =IF($L85="","",SUM($G$10:$G85)) | I85: =IF($L85="","",IF(INT(($L85-INT($L85/10000000)*10000000)/1000000)=0,"Bloomberg projection",IF($P85=1,"ANNOUNCED","ANNOUNCED - amount TBA"))) | J85: =IF($L85="","",IF((OV_SWITCH="ON")*(COUNTIFS(OVR_TICKERS,INDEX(HSI!$C$7:$C$106,$N85),OVR_BASE,">=0")>0)>0,"stock overridden","")) | L85: =IFERROR(IF(SMALL(Grids!$EE$12:$GQ$111,$M$7+76)>=PEND_TO,"",SMALL(Grids!$EE$12:$GQ$111,$M$7+76)),"") | M85: =IF($L85="","",INT($L85/1000000000)) | N85: =IF($L85="","",INT(($L85-INT($L85/1000000)*1000000)/1000)) | O85: =IF($L85="","",$L85-INT($L85/1000)*1000) | P85: =IF($L85="","",INT(($L85-INT($L85/1000000000)*1000000000)/100000000))
B86: =IF($L86="","",$M86) | C86: =IF($L86="","",INDEX(HSI!$C$7:$C$106,$N86)) | D86: =IF($L86="","",INDEX(HSI!$D$7:$D$106,$N86)) | E86: =IF($L86="","",IF($P86=0,"TBA",IFERROR(INDEX(Grids!$C$12:$BO$111,$N86,$O86),"-"))) | F86: =IF($L86="","",INDEX(HSI!$F$7:$F$106,$N86)) | G86: =IF($L86="","",IF($P86=0,"TBA",IFERROR(INDEX(Grids!$BQ$12:$EC$111,$N86,$O86),"-"))) | H86: =IF($L86="","",SUM($G$10:$G86)) | I86: =IF($L86="","",IF(INT(($L86-INT($L86/10000000)*10000000)/1000000)=0,"Bloomberg projection",IF($P86=1,"ANNOUNCED","ANNOUNCED - amount TBA"))) | J86: =IF($L86="","",IF((OV_SWITCH="ON")*(COUNTIFS(OVR_TICKERS,INDEX(HSI!$C$7:$C$106,$N86),OVR_BASE,">=0")>0)>0,"stock overridden","")) | L86: =IFERROR(IF(SMALL(Grids!$EE$12:$GQ$111,$M$7+77)>=PEND_TO,"",SMALL(Grids!$EE$12:$GQ$111,$M$7+77)),"") | M86: =IF($L86="","",INT($L86/1000000000)) | N86: =IF($L86="","",INT(($L86-INT($L86/1000000)*1000000)/1000)) | O86: =IF($L86="","",$L86-INT($L86/1000)*1000) | P86: =IF($L86="","",INT(($L86-INT($L86/1000000000)*1000000000)/100000000))
B87: =IF($L87="","",$M87) | C87: =IF($L87="","",INDEX(HSI!$C$7:$C$106,$N87)) | D87: =IF($L87="","",INDEX(HSI!$D$7:$D$106,$N87)) | E87: =IF($L87="","",IF($P87=0,"TBA",IFERROR(INDEX(Grids!$C$12:$BO$111,$N87,$O87),"-"))) | F87: =IF($L87="","",INDEX(HSI!$F$7:$F$106,$N87)) | G87: =IF($L87="","",IF($P87=0,"TBA",IFERROR(INDEX(Grids!$BQ$12:$EC$111,$N87,$O87),"-"))) | H87: =IF($L87="","",SUM($G$10:$G87)) | I87: =IF($L87="","",IF(INT(($L87-INT($L87/10000000)*10000000)/1000000)=0,"Bloomberg projection",IF($P87=1,"ANNOUNCED","ANNOUNCED - amount TBA"))) | J87: =IF($L87="","",IF((OV_SWITCH="ON")*(COUNTIFS(OVR_TICKERS,INDEX(HSI!$C$7:$C$106,$N87),OVR_BASE,">=0")>0)>0,"stock overridden","")) | L87: =IFERROR(IF(SMALL(Grids!$EE$12:$GQ$111,$M$7+78)>=PEND_TO,"",SMALL(Grids!$EE$12:$GQ$111,$M$7+78)),"") | M87: =IF($L87="","",INT($L87/1000000000)) | N87: =IF($L87="","",INT(($L87-INT($L87/1000000)*1000000)/1000)) | O87: =IF($L87="","",$L87-INT($L87/1000)*1000) | P87: =IF($L87="","",INT(($L87-INT($L87/1000000000)*1000000000)/100000000))
B88: =IF($L88="","",$M88) | C88: =IF($L88="","",INDEX(HSI!$C$7:$C$106,$N88)) | D88: =IF($L88="","",INDEX(HSI!$D$7:$D$106,$N88)) | E88: =IF($L88="","",IF($P88=0,"TBA",IFERROR(INDEX(Grids!$C$12:$BO$111,$N88,$O88),"-"))) | F88: =IF($L88="","",INDEX(HSI!$F$7:$F$106,$N88)) | G88: =IF($L88="","",IF($P88=0,"TBA",IFERROR(INDEX(Grids!$BQ$12:$EC$111,$N88,$O88),"-"))) | H88: =IF($L88="","",SUM($G$10:$G88)) | I88: =IF($L88="","",IF(INT(($L88-INT($L88/10000000)*10000000)/1000000)=0,"Bloomberg projection",IF($P88=1,"ANNOUNCED","ANNOUNCED - amount TBA"))) | J88: =IF($L88="","",IF((OV_SWITCH="ON")*(COUNTIFS(OVR_TICKERS,INDEX(HSI!$C$7:$C$106,$N88),OVR_BASE,">=0")>0)>0,"stock overridden","")) | L88: =IFERROR(IF(SMALL(Grids!$EE$12:$GQ$111,$M$7+79)>=PEND_TO,"",SMALL(Grids!$EE$12:$GQ$111,$M$7+79)),"") | M88: =IF($L88="","",INT($L88/1000000000)) | N88: =IF($L88="","",INT(($L88-INT($L88/1000000)*1000000)/1000)) | O88: =IF($L88="","",$L88-INT($L88/1000)*1000) | P88: =IF($L88="","",INT(($L88-INT($L88/1000000000)*1000000000)/100000000))
B89: =IF($L89="","",$M89) | C89: =IF($L89="","",INDEX(HSI!$C$7:$C$106,$N89)) | D89: =IF($L89="","",INDEX(HSI!$D$7:$D$106,$N89)) | E89: =IF($L89="","",IF($P89=0,"TBA",IFERROR(INDEX(Grids!$C$12:$BO$111,$N89,$O89),"-"))) | F89: =IF($L89="","",INDEX(HSI!$F$7:$F$106,$N89)) | G89: =IF($L89="","",IF($P89=0,"TBA",IFERROR(INDEX(Grids!$BQ$12:$EC$111,$N89,$O89),"-"))) | H89: =IF($L89="","",SUM($G$10:$G89)) | I89: =IF($L89="","",IF(INT(($L89-INT($L89/10000000)*10000000)/1000000)=0,"Bloomberg projection",IF($P89=1,"ANNOUNCED","ANNOUNCED - amount TBA"))) | J89: =IF($L89="","",IF((OV_SWITCH="ON")*(COUNTIFS(OVR_TICKERS,INDEX(HSI!$C$7:$C$106,$N89),OVR_BASE,">=0")>0)>0,"stock overridden","")) | L89: =IFERROR(IF(SMALL(Grids!$EE$12:$GQ$111,$M$7+80)>=PEND_TO,"",SMALL(Grids!$EE$12:$GQ$111,$M$7+80)),"") | M89: =IF($L89="","",INT($L89/1000000000)) | N89: =IF($L89="","",INT(($L89-INT($L89/1000000)*1000000)/1000)) | O89: =IF($L89="","",$L89-INT($L89/1000)*1000) | P89: =IF($L89="","",INT(($L89-INT($L89/1000000000)*1000000000)/100000000))
B90: =IF($L90="","",$M90) | C90: =IF($L90="","",INDEX(HSI!$C$7:$C$106,$N90)) | D90: =IF($L90="","",INDEX(HSI!$D$7:$D$106,$N90)) | E90: =IF($L90="","",IF($P90=0,"TBA",IFERROR(INDEX(Grids!$C$12:$BO$111,$N90,$O90),"-"))) | F90: =IF($L90="","",INDEX(HSI!$F$7:$F$106,$N90)) | G90: =IF($L90="","",IF($P90=0,"TBA",IFERROR(INDEX(Grids!$BQ$12:$EC$111,$N90,$O90),"-"))) | H90: =IF($L90="","",SUM($G$10:$G90)) | I90: =IF($L90="","",IF(INT(($L90-INT($L90/10000000)*10000000)/1000000)=0,"Bloomberg projection",IF($P90=1,"ANNOUNCED","ANNOUNCED - amount TBA"))) | J90: =IF($L90="","",IF((OV_SWITCH="ON")*(COUNTIFS(OVR_TICKERS,INDEX(HSI!$C$7:$C$106,$N90),OVR_BASE,">=0")>0)>0,"stock overridden","")) | L90: =IFERROR(IF(SMALL(Grids!$EE$12:$GQ$111,$M$7+81)>=PEND_TO,"",SMALL(Grids!$EE$12:$GQ$111,$M$7+81)),"") | M90: =IF($L90="","",INT($L90/1000000000)) | N90: =IF($L90="","",INT(($L90-INT($L90/1000000)*1000000)/1000)) | O90: =IF($L90="","",$L90-INT($L90/1000)*1000) | P90: =IF($L90="","",INT(($L90-INT($L90/1000000000)*1000000000)/100000000))
B91: =IF($L91="","",$M91) | C91: =IF($L91="","",INDEX(HSI!$C$7:$C$106,$N91)) | D91: =IF($L91="","",INDEX(HSI!$D$7:$D$106,$N91)) | E91: =IF($L91="","",IF($P91=0,"TBA",IFERROR(INDEX(Grids!$C$12:$BO$111,$N91,$O91),"-"))) | F91: =IF($L91="","",INDEX(HSI!$F$7:$F$106,$N91)) | G91: =IF($L91="","",IF($P91=0,"TBA",IFERROR(INDEX(Grids!$BQ$12:$EC$111,$N91,$O91),"-"))) | H91: =IF($L91="","",SUM($G$10:$G91)) | I91: =IF($L91="","",IF(INT(($L91-INT($L91/10000000)*10000000)/1000000)=0,"Bloomberg projection",IF($P91=1,"ANNOUNCED","ANNOUNCED - amount TBA"))) | J91: =IF($L91="","",IF((OV_SWITCH="ON")*(COUNTIFS(OVR_TICKERS,INDEX(HSI!$C$7:$C$106,$N91),OVR_BASE,">=0")>0)>0,"stock overridden","")) | L91: =IFERROR(IF(SMALL(Grids!$EE$12:$GQ$111,$M$7+82)>=PEND_TO,"",SMALL(Grids!$EE$12:$GQ$111,$M$7+82)),"") | M91: =IF($L91="","",INT($L91/1000000000)) | N91: =IF($L91="","",INT(($L91-INT($L91/1000000)*1000000)/1000)) | O91: =IF($L91="","",$L91-INT($L91/1000)*1000) | P91: =IF($L91="","",INT(($L91-INT($L91/1000000000)*1000000000)/100000000))
B92: =IF($L92="","",$M92) | C92: =IF($L92="","",INDEX(HSI!$C$7:$C$106,$N92)) | D92: =IF($L92="","",INDEX(HSI!$D$7:$D$106,$N92)) | E92: =IF($L92="","",IF($P92=0,"TBA",IFERROR(INDEX(Grids!$C$12:$BO$111,$N92,$O92),"-"))) | F92: =IF($L92="","",INDEX(HSI!$F$7:$F$106,$N92)) | G92: =IF($L92="","",IF($P92=0,"TBA",IFERROR(INDEX(Grids!$BQ$12:$EC$111,$N92,$O92),"-"))) | H92: =IF($L92="","",SUM($G$10:$G92)) | I92: =IF($L92="","",IF(INT(($L92-INT($L92/10000000)*10000000)/1000000)=0,"Bloomberg projection",IF($P92=1,"ANNOUNCED","ANNOUNCED - amount TBA"))) | J92: =IF($L92="","",IF((OV_SWITCH="ON")*(COUNTIFS(OVR_TICKERS,INDEX(HSI!$C$7:$C$106,$N92),OVR_BASE,">=0")>0)>0,"stock overridden","")) | L92: =IFERROR(IF(SMALL(Grids!$EE$12:$GQ$111,$M$7+83)>=PEND_TO,"",SMALL(Grids!$EE$12:$GQ$111,$M$7+83)),"") | M92: =IF($L92="","",INT($L92/1000000000)) | N92: =IF($L92="","",INT(($L92-INT($L92/1000000)*1000000)/1000)) | O92: =IF($L92="","",$L92-INT($L92/1000)*1000) | P92: =IF($L92="","",INT(($L92-INT($L92/1000000000)*1000000000)/100000000))
B93: =IF($L93="","",$M93) | C93: =IF($L93="","",INDEX(HSI!$C$7:$C$106,$N93)) | D93: =IF($L93="","",INDEX(HSI!$D$7:$D$106,$N93)) | E93: =IF($L93="","",IF($P93=0,"TBA",IFERROR(INDEX(Grids!$C$12:$BO$111,$N93,$O93),"-"))) | F93: =IF($L93="","",INDEX(HSI!$F$7:$F$106,$N93)) | G93: =IF($L93="","",IF($P93=0,"TBA",IFERROR(INDEX(Grids!$BQ$12:$EC$111,$N93,$O93),"-"))) | H93: =IF($L93="","",SUM($G$10:$G93)) | I93: =IF($L93="","",IF(INT(($L93-INT($L93/10000000)*10000000)/1000000)=0,"Bloomberg projection",IF($P93=1,"ANNOUNCED","ANNOUNCED - amount TBA"))) | J93: =IF($L93="","",IF((OV_SWITCH="ON")*(COUNTIFS(OVR_TICKERS,INDEX(HSI!$C$7:$C$106,$N93),OVR_BASE,">=0")>0)>0,"stock overridden","")) | L93: =IFERROR(IF(SMALL(Grids!$EE$12:$GQ$111,$M$7+84)>=PEND_TO,"",SMALL(Grids!$EE$12:$GQ$111,$M$7+84)),"") | M93: =IF($L93="","",INT($L93/1000000000)) | N93: =IF($L93="","",INT(($L93-INT($L93/1000000)*1000000)/1000)) | O93: =IF($L93="","",$L93-INT($L93/1000)*1000) | P93: =IF($L93="","",INT(($L93-INT($L93/1000000000)*1000000000)/100000000))
B94: =IF($L94="","",$M94) | C94: =IF($L94="","",INDEX(HSI!$C$7:$C$106,$N94)) | D94: =IF($L94="","",INDEX(HSI!$D$7:$D$106,$N94)) | E94: =IF($L94="","",IF($P94=0,"TBA",IFERROR(INDEX(Grids!$C$12:$BO$111,$N94,$O94),"-"))) | F94: =IF($L94="","",INDEX(HSI!$F$7:$F$106,$N94)) | G94: =IF($L94="","",IF($P94=0,"TBA",IFERROR(INDEX(Grids!$BQ$12:$EC$111,$N94,$O94),"-"))) | H94: =IF($L94="","",SUM($G$10:$G94)) | I94: =IF($L94="","",IF(INT(($L94-INT($L94/10000000)*10000000)/1000000)=0,"Bloomberg projection",IF($P94=1,"ANNOUNCED","ANNOUNCED - amount TBA"))) | J94: =IF($L94="","",IF((OV_SWITCH="ON")*(COUNTIFS(OVR_TICKERS,INDEX(HSI!$C$7:$C$106,$N94),OVR_BASE,">=0")>0)>0,"stock overridden","")) | L94: =IFERROR(IF(SMALL(Grids!$EE$12:$GQ$111,$M$7+85)>=PEND_TO,"",SMALL(Grids!$EE$12:$GQ$111,$M$7+85)),"") | M94: =IF($L94="","",INT($L94/1000000000)) | N94: =IF($L94="","",INT(($L94-INT($L94/1000000)*1000000)/1000)) | O94: =IF($L94="","",$L94-INT($L94/1000)*1000) | P94: =IF($L94="","",INT(($L94-INT($L94/1000000000)*1000000000)/100000000))
B95: =IF($L95="","",$M95) | C95: =IF($L95="","",INDEX(HSI!$C$7:$C$106,$N95)) | D95: =IF($L95="","",INDEX(HSI!$D$7:$D$106,$N95)) | E95: =IF($L95="","",IF($P95=0,"TBA",IFERROR(INDEX(Grids!$C$12:$BO$111,$N95,$O95),"-"))) | F95: =IF($L95="","",INDEX(HSI!$F$7:$F$106,$N95)) | G95: =IF($L95="","",IF($P95=0,"TBA",IFERROR(INDEX(Grids!$BQ$12:$EC$111,$N95,$O95),"-"))) | H95: =IF($L95="","",SUM($G$10:$G95)) | I95: =IF($L95="","",IF(INT(($L95-INT($L95/10000000)*10000000)/1000000)=0,"Bloomberg projection",IF($P95=1,"ANNOUNCED","ANNOUNCED - amount TBA"))) | J95: =IF($L95="","",IF((OV_SWITCH="ON")*(COUNTIFS(OVR_TICKERS,INDEX(HSI!$C$7:$C$106,$N95),OVR_BASE,">=0")>0)>0,"stock overridden","")) | L95: =IFERROR(IF(SMALL(Grids!$EE$12:$GQ$111,$M$7+86)>=PEND_TO,"",SMALL(Grids!$EE$12:$GQ$111,$M$7+86)),"") | M95: =IF($L95="","",INT($L95/1000000000)) | N95: =IF($L95="","",INT(($L95-INT($L95/1000000)*1000000)/1000)) | O95: =IF($L95="","",$L95-INT($L95/1000)*1000) | P95: =IF($L95="","",INT(($L95-INT($L95/1000000000)*1000000000)/100000000))
B96: =IF($L96="","",$M96) | C96: =IF($L96="","",INDEX(HSI!$C$7:$C$106,$N96)) | D96: =IF($L96="","",INDEX(HSI!$D$7:$D$106,$N96)) | E96: =IF($L96="","",IF($P96=0,"TBA",IFERROR(INDEX(Grids!$C$12:$BO$111,$N96,$O96),"-"))) | F96: =IF($L96="","",INDEX(HSI!$F$7:$F$106,$N96)) | G96: =IF($L96="","",IF($P96=0,"TBA",IFERROR(INDEX(Grids!$BQ$12:$EC$111,$N96,$O96),"-"))) | H96: =IF($L96="","",SUM($G$10:$G96)) | I96: =IF($L96="","",IF(INT(($L96-INT($L96/10000000)*10000000)/1000000)=0,"Bloomberg projection",IF($P96=1,"ANNOUNCED","ANNOUNCED - amount TBA"))) | J96: =IF($L96="","",IF((OV_SWITCH="ON")*(COUNTIFS(OVR_TICKERS,INDEX(HSI!$C$7:$C$106,$N96),OVR_BASE,">=0")>0)>0,"stock overridden","")) | L96: =IFERROR(IF(SMALL(Grids!$EE$12:$GQ$111,$M$7+87)>=PEND_TO,"",SMALL(Grids!$EE$12:$GQ$111,$M$7+87)),"") | M96: =IF($L96="","",INT($L96/1000000000)) | N96: =IF($L96="","",INT(($L96-INT($L96/1000000)*1000000)/1000)) | O96: =IF($L96="","",$L96-INT($L96/1000)*1000) | P96: =IF($L96="","",INT(($L96-INT($L96/1000000000)*1000000000)/100000000))
B97: =IF($L97="","",$M97) | C97: =IF($L97="","",INDEX(HSI!$C$7:$C$106,$N97)) | D97: =IF($L97="","",INDEX(HSI!$D$7:$D$106,$N97)) | E97: =IF($L97="","",IF($P97=0,"TBA",IFERROR(INDEX(Grids!$C$12:$BO$111,$N97,$O97),"-"))) | F97: =IF($L97="","",INDEX(HSI!$F$7:$F$106,$N97)) | G97: =IF($L97="","",IF($P97=0,"TBA",IFERROR(INDEX(Grids!$BQ$12:$EC$111,$N97,$O97),"-"))) | H97: =IF($L97="","",SUM($G$10:$G97)) | I97: =IF($L97="","",IF(INT(($L97-INT($L97/10000000)*10000000)/1000000)=0,"Bloomberg projection",IF($P97=1,"ANNOUNCED","ANNOUNCED - amount TBA"))) | J97: =IF($L97="","",IF((OV_SWITCH="ON")*(COUNTIFS(OVR_TICKERS,INDEX(HSI!$C$7:$C$106,$N97),OVR_BASE,">=0")>0)>0,"stock overridden","")) | L97: =IFERROR(IF(SMALL(Grids!$EE$12:$GQ$111,$M$7+88)>=PEND_TO,"",SMALL(Grids!$EE$12:$GQ$111,$M$7+88)),"") | M97: =IF($L97="","",INT($L97/1000000000)) | N97: =IF($L97="","",INT(($L97-INT($L97/1000000)*1000000)/1000)) | O97: =IF($L97="","",$L97-INT($L97/1000)*1000) | P97: =IF($L97="","",INT(($L97-INT($L97/1000000000)*1000000000)/100000000))
B98: =IF($L98="","",$M98) | C98: =IF($L98="","",INDEX(HSI!$C$7:$C$106,$N98)) | D98: =IF($L98="","",INDEX(HSI!$D$7:$D$106,$N98)) | E98: =IF($L98="","",IF($P98=0,"TBA",IFERROR(INDEX(Grids!$C$12:$BO$111,$N98,$O98),"-"))) | F98: =IF($L98="","",INDEX(HSI!$F$7:$F$106,$N98)) | G98: =IF($L98="","",IF($P98=0,"TBA",IFERROR(INDEX(Grids!$BQ$12:$EC$111,$N98,$O98),"-"))) | H98: =IF($L98="","",SUM($G$10:$G98)) | I98: =IF($L98="","",IF(INT(($L98-INT($L98/10000000)*10000000)/1000000)=0,"Bloomberg projection",IF($P98=1,"ANNOUNCED","ANNOUNCED - amount TBA"))) | J98: =IF($L98="","",IF((OV_SWITCH="ON")*(COUNTIFS(OVR_TICKERS,INDEX(HSI!$C$7:$C$106,$N98),OVR_BASE,">=0")>0)>0,"stock overridden","")) | L98: =IFERROR(IF(SMALL(Grids!$EE$12:$GQ$111,$M$7+89)>=PEND_TO,"",SMALL(Grids!$EE$12:$GQ$111,$M$7+89)),"") | M98: =IF($L98="","",INT($L98/1000000000)) | N98: =IF($L98="","",INT(($L98-INT($L98/1000000)*1000000)/1000)) | O98: =IF($L98="","",$L98-INT($L98/1000)*1000) | P98: =IF($L98="","",INT(($L98-INT($L98/1000000000)*1000000000)/100000000))
B99: =IF($L99="","",$M99) | C99: =IF($L99="","",INDEX(HSI!$C$7:$C$106,$N99)) | D99: =IF($L99="","",INDEX(HSI!$D$7:$D$106,$N99)) | E99: =IF($L99="","",IF($P99=0,"TBA",IFERROR(INDEX(Grids!$C$12:$BO$111,$N99,$O99),"-"))) | F99: =IF($L99="","",INDEX(HSI!$F$7:$F$106,$N99)) | G99: =IF($L99="","",IF($P99=0,"TBA",IFERROR(INDEX(Grids!$BQ$12:$EC$111,$N99,$O99),"-"))) | H99: =IF($L99="","",SUM($G$10:$G99)) | I99: =IF($L99="","",IF(INT(($L99-INT($L99/10000000)*10000000)/1000000)=0,"Bloomberg projection",IF($P99=1,"ANNOUNCED","ANNOUNCED - amount TBA"))) | J99: =IF($L99="","",IF((OV_SWITCH="ON")*(COUNTIFS(OVR_TICKERS,INDEX(HSI!$C$7:$C$106,$N99),OVR_BASE,">=0")>0)>0,"stock overridden","")) | L99: =IFERROR(IF(SMALL(Grids!$EE$12:$GQ$111,$M$7+90)>=PEND_TO,"",SMALL(Grids!$EE$12:$GQ$111,$M$7+90)),"") | M99: =IF($L99="","",INT($L99/1000000000)) | N99: =IF($L99="","",INT(($L99-INT($L99/1000000)*1000000)/1000)) | O99: =IF($L99="","",$L99-INT($L99/1000)*1000) | P99: =IF($L99="","",INT(($L99-INT($L99/1000000000)*1000000000)/100000000))
B100: =IF($L100="","",$M100) | C100: =IF($L100="","",INDEX(HSI!$C$7:$C$106,$N100)) | D100: =IF($L100="","",INDEX(HSI!$D$7:$D$106,$N100)) | E100: =IF($L100="","",IF($P100=0,"TBA",IFERROR(INDEX(Grids!$C$12:$BO$111,$N100,$O100),"-"))) | F100: =IF($L100="","",INDEX(HSI!$F$7:$F$106,$N100)) | G100: =IF($L100="","",IF($P100=0,"TBA",IFERROR(INDEX(Grids!$BQ$12:$EC$111,$N100,$O100),"-"))) | H100: =IF($L100="","",SUM($G$10:$G100)) | I100: =IF($L100="","",IF(INT(($L100-INT($L100/10000000)*10000000)/1000000)=0,"Bloomberg projection",IF($P100=1,"ANNOUNCED","ANNOUNCED - amount TBA"))) | J100: =IF($L100="","",IF((OV_SWITCH="ON")*(COUNTIFS(OVR_TICKERS,INDEX(HSI!$C$7:$C$106,$N100),OVR_BASE,">=0")>0)>0,"stock overridden","")) | L100: =IFERROR(IF(SMALL(Grids!$EE$12:$GQ$111,$M$7+91)>=PEND_TO,"",SMALL(Grids!$EE$12:$GQ$111,$M$7+91)),"") | M100: =IF($L100="","",INT($L100/1000000000)) | N100: =IF($L100="","",INT(($L100-INT($L100/1000000)*1000000)/1000)) | O100: =IF($L100="","",$L100-INT($L100/1000)*1000) | P100: =IF($L100="","",INT(($L100-INT($L100/1000000000)*1000000000)/100000000))
B101: =IF($L101="","",$M101) | C101: =IF($L101="","",INDEX(HSI!$C$7:$C$106,$N101)) | D101: =IF($L101="","",INDEX(HSI!$D$7:$D$106,$N101)) | E101: =IF($L101="","",IF($P101=0,"TBA",IFERROR(INDEX(Grids!$C$12:$BO$111,$N101,$O101),"-"))) | F101: =IF($L101="","",INDEX(HSI!$F$7:$F$106,$N101)) | G101: =IF($L101="","",IF($P101=0,"TBA",IFERROR(INDEX(Grids!$BQ$12:$EC$111,$N101,$O101),"-"))) | H101: =IF($L101="","",SUM($G$10:$G101)) | I101: =IF($L101="","",IF(INT(($L101-INT($L101/10000000)*10000000)/1000000)=0,"Bloomberg projection",IF($P101=1,"ANNOUNCED","ANNOUNCED - amount TBA"))) | J101: =IF($L101="","",IF((OV_SWITCH="ON")*(COUNTIFS(OVR_TICKERS,INDEX(HSI!$C$7:$C$106,$N101),OVR_BASE,">=0")>0)>0,"stock overridden","")) | L101: =IFERROR(IF(SMALL(Grids!$EE$12:$GQ$111,$M$7+92)>=PEND_TO,"",SMALL(Grids!$EE$12:$GQ$111,$M$7+92)),"") | M101: =IF($L101="","",INT($L101/1000000000)) | N101: =IF($L101="","",INT(($L101-INT($L101/1000000)*1000000)/1000)) | O101: =IF($L101="","",$L101-INT($L101/1000)*1000) | P101: =IF($L101="","",INT(($L101-INT($L101/1000000000)*1000000000)/100000000))
B102: =IF($L102="","",$M102) | C102: =IF($L102="","",INDEX(HSI!$C$7:$C$106,$N102)) | D102: =IF($L102="","",INDEX(HSI!$D$7:$D$106,$N102)) | E102: =IF($L102="","",IF($P102=0,"TBA",IFERROR(INDEX(Grids!$C$12:$BO$111,$N102,$O102),"-"))) | F102: =IF($L102="","",INDEX(HSI!$F$7:$F$106,$N102)) | G102: =IF($L102="","",IF($P102=0,"TBA",IFERROR(INDEX(Grids!$BQ$12:$EC$111,$N102,$O102),"-"))) | H102: =IF($L102="","",SUM($G$10:$G102)) | I102: =IF($L102="","",IF(INT(($L102-INT($L102/10000000)*10000000)/1000000)=0,"Bloomberg projection",IF($P102=1,"ANNOUNCED","ANNOUNCED - amount TBA"))) | J102: =IF($L102="","",IF((OV_SWITCH="ON")*(COUNTIFS(OVR_TICKERS,INDEX(HSI!$C$7:$C$106,$N102),OVR_BASE,">=0")>0)>0,"stock overridden","")) | L102: =IFERROR(IF(SMALL(Grids!$EE$12:$GQ$111,$M$7+93)>=PEND_TO,"",SMALL(Grids!$EE$12:$GQ$111,$M$7+93)),"") | M102: =IF($L102="","",INT($L102/1000000000)) | N102: =IF($L102="","",INT(($L102-INT($L102/1000000)*1000000)/1000)) | O102: =IF($L102="","",$L102-INT($L102/1000)*1000) | P102: =IF($L102="","",INT(($L102-INT($L102/1000000000)*1000000000)/100000000))
B103: =IF($L103="","",$M103) | C103: =IF($L103="","",INDEX(HSI!$C$7:$C$106,$N103)) | D103: =IF($L103="","",INDEX(HSI!$D$7:$D$106,$N103)) | E103: =IF($L103="","",IF($P103=0,"TBA",IFERROR(INDEX(Grids!$C$12:$BO$111,$N103,$O103),"-"))) | F103: =IF($L103="","",INDEX(HSI!$F$7:$F$106,$N103)) | G103: =IF($L103="","",IF($P103=0,"TBA",IFERROR(INDEX(Grids!$BQ$12:$EC$111,$N103,$O103),"-"))) | H103: =IF($L103="","",SUM($G$10:$G103)) | I103: =IF($L103="","",IF(INT(($L103-INT($L103/10000000)*10000000)/1000000)=0,"Bloomberg projection",IF($P103=1,"ANNOUNCED","ANNOUNCED - amount TBA"))) | J103: =IF($L103="","",IF((OV_SWITCH="ON")*(COUNTIFS(OVR_TICKERS,INDEX(HSI!$C$7:$C$106,$N103),OVR_BASE,">=0")>0)>0,"stock overridden","")) | L103: =IFERROR(IF(SMALL(Grids!$EE$12:$GQ$111,$M$7+94)>=PEND_TO,"",SMALL(Grids!$EE$12:$GQ$111,$M$7+94)),"") | M103: =IF($L103="","",INT($L103/1000000000)) | N103: =IF($L103="","",INT(($L103-INT($L103/1000000)*1000000)/1000)) | O103: =IF($L103="","",$L103-INT($L103/1000)*1000) | P103: =IF($L103="","",INT(($L103-INT($L103/1000000000)*1000000000)/100000000))
...

Sheet Flow
B1: DIVIDEND FLOW - WHEN THE POINTS GO EX
B2: Year Y by ex-date. Up to the valuation date = realized, after it = still to come. Bloomberg's event view (with your cash-type rules).
B4: Year | C4: =YEAR_Y | D4: Valuation | E4: =VAL_DATE
B6: YEAR TOTALS (index points)
C7: Realized | D7: Still to come | E7: YEAR TOTAL | J7: BY MONTH (realized vs still to come) | R7: cumulative to month-end
B8: HSI | C8: =HSI!$O$5 | D8: =HSI!$P$5 | E8: =HSI!$Q$5 | J8: Month | K8: HSI realized | L8: HSI to come | M8: HSTECH realized | N8: HSTECH to come | O8: HSCEI realized | P8: HSCEI to come | R8: HSI | S8: HSTECH | T8: HSCEI
B9: HSTECH | C9: =HSTECH!$O$5 | D9: =HSTECH!$P$5 | E9: =HSTECH!$Q$5 | J9: =TEXT(DATE(YEAR_Y,1,1),"mmm") | K9: =SUMIFS($C$26:$C$395,$B$26:$B$395,">="&DATE(YEAR_Y,1,1),$B$26:$B$395,"<"&DATE(YEAR_Y+(1=12),MOD(1,12)+1,1),$B$26:$B$395,"<="&VAL_DATE) | L9: =SUMIFS($C$26:$C$395,$B$26:$B$395,">="&DATE(YEAR_Y,1,1),$B$26:$B$395,"<"&DATE(YEAR_Y+(1=12),MOD(1,12)+1,1),$B$26:$B$395,">"&VAL_DATE) | M9: =SUMIFS($D$26:$D$395,$B$26:$B$395,">="&DATE(YEAR_Y,1,1),$B$26:$B$395,"<"&DATE(YEAR_Y+(1=12),MOD(1,12)+1,1),$B$26:$B$395,"<="&VAL_DATE) | N9: =SUMIFS($D$26:$D$395,$B$26:$B$395,">="&DATE(YEAR_Y,1,1),$B$26:$B$395,"<"&DATE(YEAR_Y+(1=12),MOD(1,12)+1,1),$B$26:$B$395,">"&VAL_DATE) | O9: =SUMIFS($E$26:$E$395,$B$26:$B$395,">="&DATE(YEAR_Y,1,1),$B$26:$B$395,"<"&DATE(YEAR_Y+(1=12),MOD(1,12)+1,1),$B$26:$B$395,"<="&VAL_DATE) | P9: =SUMIFS($E$26:$E$395,$B$26:$B$395,">="&DATE(YEAR_Y,1,1),$B$26:$B$395,"<"&DATE(YEAR_Y+(1=12),MOD(1,12)+1,1),$B$26:$B$395,">"&VAL_DATE) | R9: =SUM($K$9:$L9) | S9: =SUM($M$9:$N9) | T9: =SUM($O$9:$P9)
B10: HSCEI | C10: =HSCEI!$O$5 | D10: =HSCEI!$P$5 | E10: =HSCEI!$Q$5 | J10: =TEXT(DATE(YEAR_Y,2,1),"mmm") | K10: =SUMIFS($C$26:$C$395,$B$26:$B$395,">="&DATE(YEAR_Y,2,1),$B$26:$B$395,"<"&DATE(YEAR_Y+(2=12),MOD(2,12)+1,1),$B$26:$B$395,"<="&VAL_DATE) | L10: =SUMIFS($C$26:$C$395,$B$26:$B$395,">="&DATE(YEAR_Y,2,1),$B$26:$B$395,"<"&DATE(YEAR_Y+(2=12),MOD(2,12)+1,1),$B$26:$B$395,">"&VAL_DATE) | M10: =SUMIFS($D$26:$D$395,$B$26:$B$395,">="&DATE(YEAR_Y,2,1),$B$26:$B$395,"<"&DATE(YEAR_Y+(2=12),MOD(2,12)+1,1),$B$26:$B$395,"<="&VAL_DATE) | N10: =SUMIFS($D$26:$D$395,$B$26:$B$395,">="&DATE(YEAR_Y,2,1),$B$26:$B$395,"<"&DATE(YEAR_Y+(2=12),MOD(2,12)+1,1),$B$26:$B$395,">"&VAL_DATE) | O10: =SUMIFS($E$26:$E$395,$B$26:$B$395,">="&DATE(YEAR_Y,2,1),$B$26:$B$395,"<"&DATE(YEAR_Y+(2=12),MOD(2,12)+1,1),$B$26:$B$395,"<="&VAL_DATE) | P10: =SUMIFS($E$26:$E$395,$B$26:$B$395,">="&DATE(YEAR_Y,2,1),$B$26:$B$395,"<"&DATE(YEAR_Y+(2=12),MOD(2,12)+1,1),$B$26:$B$395,">"&VAL_DATE) | R10: =SUM($K$9:$L10) | S10: =SUM($M$9:$N10) | T10: =SUM($O$9:$P10)
J11: =TEXT(DATE(YEAR_Y,3,1),"mmm") | K11: =SUMIFS($C$26:$C$395,$B$26:$B$395,">="&DATE(YEAR_Y,3,1),$B$26:$B$395,"<"&DATE(YEAR_Y+(3=12),MOD(3,12)+1,1),$B$26:$B$395,"<="&VAL_DATE) | L11: =SUMIFS($C$26:$C$395,$B$26:$B$395,">="&DATE(YEAR_Y,3,1),$B$26:$B$395,"<"&DATE(YEAR_Y+(3=12),MOD(3,12)+1,1),$B$26:$B$395,">"&VAL_DATE) | M11: =SUMIFS($D$26:$D$395,$B$26:$B$395,">="&DATE(YEAR_Y,3,1),$B$26:$B$395,"<"&DATE(YEAR_Y+(3=12),MOD(3,12)+1,1),$B$26:$B$395,"<="&VAL_DATE) | N11: =SUMIFS($D$26:$D$395,$B$26:$B$395,">="&DATE(YEAR_Y,3,1),$B$26:$B$395,"<"&DATE(YEAR_Y+(3=12),MOD(3,12)+1,1),$B$26:$B$395,">"&VAL_DATE) | O11: =SUMIFS($E$26:$E$395,$B$26:$B$395,">="&DATE(YEAR_Y,3,1),$B$26:$B$395,"<"&DATE(YEAR_Y+(3=12),MOD(3,12)+1,1),$B$26:$B$395,"<="&VAL_DATE) | P11: =SUMIFS($E$26:$E$395,$B$26:$B$395,">="&DATE(YEAR_Y,3,1),$B$26:$B$395,"<"&DATE(YEAR_Y+(3=12),MOD(3,12)+1,1),$B$26:$B$395,">"&VAL_DATE) | R11: =SUM($K$9:$L11) | S11: =SUM($M$9:$N11) | T11: =SUM($O$9:$P11)
J12: =TEXT(DATE(YEAR_Y,4,1),"mmm") | K12: =SUMIFS($C$26:$C$395,$B$26:$B$395,">="&DATE(YEAR_Y,4,1),$B$26:$B$395,"<"&DATE(YEAR_Y+(4=12),MOD(4,12)+1,1),$B$26:$B$395,"<="&VAL_DATE) | L12: =SUMIFS($C$26:$C$395,$B$26:$B$395,">="&DATE(YEAR_Y,4,1),$B$26:$B$395,"<"&DATE(YEAR_Y+(4=12),MOD(4,12)+1,1),$B$26:$B$395,">"&VAL_DATE) | M12: =SUMIFS($D$26:$D$395,$B$26:$B$395,">="&DATE(YEAR_Y,4,1),$B$26:$B$395,"<"&DATE(YEAR_Y+(4=12),MOD(4,12)+1,1),$B$26:$B$395,"<="&VAL_DATE) | N12: =SUMIFS($D$26:$D$395,$B$26:$B$395,">="&DATE(YEAR_Y,4,1),$B$26:$B$395,"<"&DATE(YEAR_Y+(4=12),MOD(4,12)+1,1),$B$26:$B$395,">"&VAL_DATE) | O12: =SUMIFS($E$26:$E$395,$B$26:$B$395,">="&DATE(YEAR_Y,4,1),$B$26:$B$395,"<"&DATE(YEAR_Y+(4=12),MOD(4,12)+1,1),$B$26:$B$395,"<="&VAL_DATE) | P12: =SUMIFS($E$26:$E$395,$B$26:$B$395,">="&DATE(YEAR_Y,4,1),$B$26:$B$395,"<"&DATE(YEAR_Y+(4=12),MOD(4,12)+1,1),$B$26:$B$395,">"&VAL_DATE) | R12: =SUM($K$9:$L12) | S12: =SUM($M$9:$N12) | T12: =SUM($O$9:$P12)
J13: =TEXT(DATE(YEAR_Y,5,1),"mmm") | K13: =SUMIFS($C$26:$C$395,$B$26:$B$395,">="&DATE(YEAR_Y,5,1),$B$26:$B$395,"<"&DATE(YEAR_Y+(5=12),MOD(5,12)+1,1),$B$26:$B$395,"<="&VAL_DATE) | L13: =SUMIFS($C$26:$C$395,$B$26:$B$395,">="&DATE(YEAR_Y,5,1),$B$26:$B$395,"<"&DATE(YEAR_Y+(5=12),MOD(5,12)+1,1),$B$26:$B$395,">"&VAL_DATE) | M13: =SUMIFS($D$26:$D$395,$B$26:$B$395,">="&DATE(YEAR_Y,5,1),$B$26:$B$395,"<"&DATE(YEAR_Y+(5=12),MOD(5,12)+1,1),$B$26:$B$395,"<="&VAL_DATE) | N13: =SUMIFS($D$26:$D$395,$B$26:$B$395,">="&DATE(YEAR_Y,5,1),$B$26:$B$395,"<"&DATE(YEAR_Y+(5=12),MOD(5,12)+1,1),$B$26:$B$395,">"&VAL_DATE) | O13: =SUMIFS($E$26:$E$395,$B$26:$B$395,">="&DATE(YEAR_Y,5,1),$B$26:$B$395,"<"&DATE(YEAR_Y+(5=12),MOD(5,12)+1,1),$B$26:$B$395,"<="&VAL_DATE) | P13: =SUMIFS($E$26:$E$395,$B$26:$B$395,">="&DATE(YEAR_Y,5,1),$B$26:$B$395,"<"&DATE(YEAR_Y+(5=12),MOD(5,12)+1,1),$B$26:$B$395,">"&VAL_DATE) | R13: =SUM($K$9:$L13) | S13: =SUM($M$9:$N13) | T13: =SUM($O$9:$P13)
J14: =TEXT(DATE(YEAR_Y,6,1),"mmm") | K14: =SUMIFS($C$26:$C$395,$B$26:$B$395,">="&DATE(YEAR_Y,6,1),$B$26:$B$395,"<"&DATE(YEAR_Y+(6=12),MOD(6,12)+1,1),$B$26:$B$395,"<="&VAL_DATE) | L14: =SUMIFS($C$26:$C$395,$B$26:$B$395,">="&DATE(YEAR_Y,6,1),$B$26:$B$395,"<"&DATE(YEAR_Y+(6=12),MOD(6,12)+1,1),$B$26:$B$395,">"&VAL_DATE) | M14: =SUMIFS($D$26:$D$395,$B$26:$B$395,">="&DATE(YEAR_Y,6,1),$B$26:$B$395,"<"&DATE(YEAR_Y+(6=12),MOD(6,12)+1,1),$B$26:$B$395,"<="&VAL_DATE) | N14: =SUMIFS($D$26:$D$395,$B$26:$B$395,">="&DATE(YEAR_Y,6,1),$B$26:$B$395,"<"&DATE(YEAR_Y+(6=12),MOD(6,12)+1,1),$B$26:$B$395,">"&VAL_DATE) | O14: =SUMIFS($E$26:$E$395,$B$26:$B$395,">="&DATE(YEAR_Y,6,1),$B$26:$B$395,"<"&DATE(YEAR_Y+(6=12),MOD(6,12)+1,1),$B$26:$B$395,"<="&VAL_DATE) | P14: =SUMIFS($E$26:$E$395,$B$26:$B$395,">="&DATE(YEAR_Y,6,1),$B$26:$B$395,"<"&DATE(YEAR_Y+(6=12),MOD(6,12)+1,1),$B$26:$B$395,">"&VAL_DATE) | R14: =SUM($K$9:$L14) | S14: =SUM($M$9:$N14) | T14: =SUM($O$9:$P14)
J15: =TEXT(DATE(YEAR_Y,7,1),"mmm") | K15: =SUMIFS($C$26:$C$395,$B$26:$B$395,">="&DATE(YEAR_Y,7,1),$B$26:$B$395,"<"&DATE(YEAR_Y+(7=12),MOD(7,12)+1,1),$B$26:$B$395,"<="&VAL_DATE) | L15: =SUMIFS($C$26:$C$395,$B$26:$B$395,">="&DATE(YEAR_Y,7,1),$B$26:$B$395,"<"&DATE(YEAR_Y+(7=12),MOD(7,12)+1,1),$B$26:$B$395,">"&VAL_DATE) | M15: =SUMIFS($D$26:$D$395,$B$26:$B$395,">="&DATE(YEAR_Y,7,1),$B$26:$B$395,"<"&DATE(YEAR_Y+(7=12),MOD(7,12)+1,1),$B$26:$B$395,"<="&VAL_DATE) | N15: =SUMIFS($D$26:$D$395,$B$26:$B$395,">="&DATE(YEAR_Y,7,1),$B$26:$B$395,"<"&DATE(YEAR_Y+(7=12),MOD(7,12)+1,1),$B$26:$B$395,">"&VAL_DATE) | O15: =SUMIFS($E$26:$E$395,$B$26:$B$395,">="&DATE(YEAR_Y,7,1),$B$26:$B$395,"<"&DATE(YEAR_Y+(7=12),MOD(7,12)+1,1),$B$26:$B$395,"<="&VAL_DATE) | P15: =SUMIFS($E$26:$E$395,$B$26:$B$395,">="&DATE(YEAR_Y,7,1),$B$26:$B$395,"<"&DATE(YEAR_Y+(7=12),MOD(7,12)+1,1),$B$26:$B$395,">"&VAL_DATE) | R15: =SUM($K$9:$L15) | S15: =SUM($M$9:$N15) | T15: =SUM($O$9:$P15)
J16: =TEXT(DATE(YEAR_Y,8,1),"mmm") | K16: =SUMIFS($C$26:$C$395,$B$26:$B$395,">="&DATE(YEAR_Y,8,1),$B$26:$B$395,"<"&DATE(YEAR_Y+(8=12),MOD(8,12)+1,1),$B$26:$B$395,"<="&VAL_DATE) | L16: =SUMIFS($C$26:$C$395,$B$26:$B$395,">="&DATE(YEAR_Y,8,1),$B$26:$B$395,"<"&DATE(YEAR_Y+(8=12),MOD(8,12)+1,1),$B$26:$B$395,">"&VAL_DATE) | M16: =SUMIFS($D$26:$D$395,$B$26:$B$395,">="&DATE(YEAR_Y,8,1),$B$26:$B$395,"<"&DATE(YEAR_Y+(8=12),MOD(8,12)+1,1),$B$26:$B$395,"<="&VAL_DATE) | N16: =SUMIFS($D$26:$D$395,$B$26:$B$395,">="&DATE(YEAR_Y,8,1),$B$26:$B$395,"<"&DATE(YEAR_Y+(8=12),MOD(8,12)+1,1),$B$26:$B$395,">"&VAL_DATE) | O16: =SUMIFS($E$26:$E$395,$B$26:$B$395,">="&DATE(YEAR_Y,8,1),$B$26:$B$395,"<"&DATE(YEAR_Y+(8=12),MOD(8,12)+1,1),$B$26:$B$395,"<="&VAL_DATE) | P16: =SUMIFS($E$26:$E$395,$B$26:$B$395,">="&DATE(YEAR_Y,8,1),$B$26:$B$395,"<"&DATE(YEAR_Y+(8=12),MOD(8,12)+1,1),$B$26:$B$395,">"&VAL_DATE) | R16: =SUM($K$9:$L16) | S16: =SUM($M$9:$N16) | T16: =SUM($O$9:$P16)
J17: =TEXT(DATE(YEAR_Y,9,1),"mmm") | K17: =SUMIFS($C$26:$C$395,$B$26:$B$395,">="&DATE(YEAR_Y,9,1),$B$26:$B$395,"<"&DATE(YEAR_Y+(9=12),MOD(9,12)+1,1),$B$26:$B$395,"<="&VAL_DATE) | L17: =SUMIFS($C$26:$C$395,$B$26:$B$395,">="&DATE(YEAR_Y,9,1),$B$26:$B$395,"<"&DATE(YEAR_Y+(9=12),MOD(9,12)+1,1),$B$26:$B$395,">"&VAL_DATE) | M17: =SUMIFS($D$26:$D$395,$B$26:$B$395,">="&DATE(YEAR_Y,9,1),$B$26:$B$395,"<"&DATE(YEAR_Y+(9=12),MOD(9,12)+1,1),$B$26:$B$395,"<="&VAL_DATE) | N17: =SUMIFS($D$26:$D$395,$B$26:$B$395,">="&DATE(YEAR_Y,9,1),$B$26:$B$395,"<"&DATE(YEAR_Y+(9=12),MOD(9,12)+1,1),$B$26:$B$395,">"&VAL_DATE) | O17: =SUMIFS($E$26:$E$395,$B$26:$B$395,">="&DATE(YEAR_Y,9,1),$B$26:$B$395,"<"&DATE(YEAR_Y+(9=12),MOD(9,12)+1,1),$B$26:$B$395,"<="&VAL_DATE) | P17: =SUMIFS($E$26:$E$395,$B$26:$B$395,">="&DATE(YEAR_Y,9,1),$B$26:$B$395,"<"&DATE(YEAR_Y+(9=12),MOD(9,12)+1,1),$B$26:$B$395,">"&VAL_DATE) | R17: =SUM($K$9:$L17) | S17: =SUM($M$9:$N17) | T17: =SUM($O$9:$P17)
J18: =TEXT(DATE(YEAR_Y,10,1),"mmm") | K18: =SUMIFS($C$26:$C$395,$B$26:$B$395,">="&DATE(YEAR_Y,10,1),$B$26:$B$395,"<"&DATE(YEAR_Y+(10=12),MOD(10,12)+1,1),$B$26:$B$395,"<="&VAL_DATE) | L18: =SUMIFS($C$26:$C$395,$B$26:$B$395,">="&DATE(YEAR_Y,10,1),$B$26:$B$395,"<"&DATE(YEAR_Y+(10=12),MOD(10,12)+1,1),$B$26:$B$395,">"&VAL_DATE) | M18: =SUMIFS($D$26:$D$395,$B$26:$B$395,">="&DATE(YEAR_Y,10,1),$B$26:$B$395,"<"&DATE(YEAR_Y+(10=12),MOD(10,12)+1,1),$B$26:$B$395,"<="&VAL_DATE) | N18: =SUMIFS($D$26:$D$395,$B$26:$B$395,">="&DATE(YEAR_Y,10,1),$B$26:$B$395,"<"&DATE(YEAR_Y+(10=12),MOD(10,12)+1,1),$B$26:$B$395,">"&VAL_DATE) | O18: =SUMIFS($E$26:$E$395,$B$26:$B$395,">="&DATE(YEAR_Y,10,1),$B$26:$B$395,"<"&DATE(YEAR_Y+(10=12),MOD(10,12)+1,1),$B$26:$B$395,"<="&VAL_DATE) | P18: =SUMIFS($E$26:$E$395,$B$26:$B$395,">="&DATE(YEAR_Y,10,1),$B$26:$B$395,"<"&DATE(YEAR_Y+(10=12),MOD(10,12)+1,1),$B$26:$B$395,">"&VAL_DATE) | R18: =SUM($K$9:$L18) | S18: =SUM($M$9:$N18) | T18: =SUM($O$9:$P18)
J19: =TEXT(DATE(YEAR_Y,11,1),"mmm") | K19: =SUMIFS($C$26:$C$395,$B$26:$B$395,">="&DATE(YEAR_Y,11,1),$B$26:$B$395,"<"&DATE(YEAR_Y+(11=12),MOD(11,12)+1,1),$B$26:$B$395,"<="&VAL_DATE) | L19: =SUMIFS($C$26:$C$395,$B$26:$B$395,">="&DATE(YEAR_Y,11,1),$B$26:$B$395,"<"&DATE(YEAR_Y+(11=12),MOD(11,12)+1,1),$B$26:$B$395,">"&VAL_DATE) | M19: =SUMIFS($D$26:$D$395,$B$26:$B$395,">="&DATE(YEAR_Y,11,1),$B$26:$B$395,"<"&DATE(YEAR_Y+(11=12),MOD(11,12)+1,1),$B$26:$B$395,"<="&VAL_DATE) | N19: =SUMIFS($D$26:$D$395,$B$26:$B$395,">="&DATE(YEAR_Y,11,1),$B$26:$B$395,"<"&DATE(YEAR_Y+(11=12),MOD(11,12)+1,1),$B$26:$B$395,">"&VAL_DATE) | O19: =SUMIFS($E$26:$E$395,$B$26:$B$395,">="&DATE(YEAR_Y,11,1),$B$26:$B$395,"<"&DATE(YEAR_Y+(11=12),MOD(11,12)+1,1),$B$26:$B$395,"<="&VAL_DATE) | P19: =SUMIFS($E$26:$E$395,$B$26:$B$395,">="&DATE(YEAR_Y,11,1),$B$26:$B$395,"<"&DATE(YEAR_Y+(11=12),MOD(11,12)+1,1),$B$26:$B$395,">"&VAL_DATE) | R19: =SUM($K$9:$L19) | S19: =SUM($M$9:$N19) | T19: =SUM($O$9:$P19)
J20: =TEXT(DATE(YEAR_Y,12,1),"mmm") | K20: =SUMIFS($C$26:$C$395,$B$26:$B$395,">="&DATE(YEAR_Y,12,1),$B$26:$B$395,"<"&DATE(YEAR_Y+(12=12),MOD(12,12)+1,1),$B$26:$B$395,"<="&VAL_DATE) | L20: =SUMIFS($C$26:$C$395,$B$26:$B$395,">="&DATE(YEAR_Y,12,1),$B$26:$B$395,"<"&DATE(YEAR_Y+(12=12),MOD(12,12)+1,1),$B$26:$B$395,">"&VAL_DATE) | M20: =SUMIFS($D$26:$D$395,$B$26:$B$395,">="&DATE(YEAR_Y,12,1),$B$26:$B$395,"<"&DATE(YEAR_Y+(12=12),MOD(12,12)+1,1),$B$26:$B$395,"<="&VAL_DATE) | N20: =SUMIFS($D$26:$D$395,$B$26:$B$395,">="&DATE(YEAR_Y,12,1),$B$26:$B$395,"<"&DATE(YEAR_Y+(12=12),MOD(12,12)+1,1),$B$26:$B$395,">"&VAL_DATE) | O20: =SUMIFS($E$26:$E$395,$B$26:$B$395,">="&DATE(YEAR_Y,12,1),$B$26:$B$395,"<"&DATE(YEAR_Y+(12=12),MOD(12,12)+1,1),$B$26:$B$395,"<="&VAL_DATE) | P20: =SUMIFS($E$26:$E$395,$B$26:$B$395,">="&DATE(YEAR_Y,12,1),$B$26:$B$395,"<"&DATE(YEAR_Y+(12=12),MOD(12,12)+1,1),$B$26:$B$395,">"&VAL_DATE) | R20: =SUM($K$9:$L20) | S20: =SUM($M$9:$N20) | T20: =SUM($O$9:$P20)
B24: BY DAY
B25: Date | C25: HSI pts | D25: HSTECH pts | E25: HSCEI pts | F25: HSI cumulative | G25: HSTECH cumulative | H25: HSCEI cumulative
B26: =IF(DATE(YEAR_Y,1,1)+0>DATE(YEAR_Y,12,31),"",DATE(YEAR_Y,1,1)+0) | C26: =IF($B26="","",SUMIFS(Grids!$BQ$12:$EC$111,Grids!$EE$12:$GQ$111,">="&$B26*1000000000,Grids!$EE$12:$GQ$111,"<"&($B26+1)*1000000000)) | D26: =IF($B26="","",SUMIFS(Grids!$BQ$116:$EC$155,Grids!$EE$116:$GQ$155,">="&$B26*1000000000,Grids!$EE$116:$GQ$155,"<"&($B26+1)*1000000000)) | E26: =IF($B26="","",SUMIFS(Grids!$BQ$160:$EC$219,Grids!$EE$160:$GQ$219,">="&$B26*1000000000,Grids!$EE$160:$GQ$219,"<"&($B26+1)*1000000000)) | F26: =IF($B26="","",SUM($C$26:$C26)) | G26: =IF($B26="","",SUM($D$26:$D26)) | H26: =IF($B26="","",SUM($E$26:$E26))
B27: =IF(DATE(YEAR_Y,1,1)+1>DATE(YEAR_Y,12,31),"",DATE(YEAR_Y,1,1)+1) | C27: =IF($B27="","",SUMIFS(Grids!$BQ$12:$EC$111,Grids!$EE$12:$GQ$111,">="&$B27*1000000000,Grids!$EE$12:$GQ$111,"<"&($B27+1)*1000000000)) | D27: =IF($B27="","",SUMIFS(Grids!$BQ$116:$EC$155,Grids!$EE$116:$GQ$155,">="&$B27*1000000000,Grids!$EE$116:$GQ$155,"<"&($B27+1)*1000000000)) | E27: =IF($B27="","",SUMIFS(Grids!$BQ$160:$EC$219,Grids!$EE$160:$GQ$219,">="&$B27*1000000000,Grids!$EE$160:$GQ$219,"<"&($B27+1)*1000000000)) | F27: =IF($B27="","",SUM($C$26:$C27)) | G27: =IF($B27="","",SUM($D$26:$D27)) | H27: =IF($B27="","",SUM($E$26:$E27))
B28: =IF(DATE(YEAR_Y,1,1)+2>DATE(YEAR_Y,12,31),"",DATE(YEAR_Y,1,1)+2) | C28: =IF($B28="","",SUMIFS(Grids!$BQ$12:$EC$111,Grids!$EE$12:$GQ$111,">="&$B28*1000000000,Grids!$EE$12:$GQ$111,"<"&($B28+1)*1000000000)) | D28: =IF($B28="","",SUMIFS(Grids!$BQ$116:$EC$155,Grids!$EE$116:$GQ$155,">="&$B28*1000000000,Grids!$EE$116:$GQ$155,"<"&($B28+1)*1000000000)) | E28: =IF($B28="","",SUMIFS(Grids!$BQ$160:$EC$219,Grids!$EE$160:$GQ$219,">="&$B28*1000000000,Grids!$EE$160:$GQ$219,"<"&($B28+1)*1000000000)) | F28: =IF($B28="","",SUM($C$26:$C28)) | G28: =IF($B28="","",SUM($D$26:$D28)) | H28: =IF($B28="","",SUM($E$26:$E28))
B29: =IF(DATE(YEAR_Y,1,1)+3>DATE(YEAR_Y,12,31),"",DATE(YEAR_Y,1,1)+3) | C29: =IF($B29="","",SUMIFS(Grids!$BQ$12:$EC$111,Grids!$EE$12:$GQ$111,">="&$B29*1000000000,Grids!$EE$12:$GQ$111,"<"&($B29+1)*1000000000)) | D29: =IF($B29="","",SUMIFS(Grids!$BQ$116:$EC$155,Grids!$EE$116:$GQ$155,">="&$B29*1000000000,Grids!$EE$116:$GQ$155,"<"&($B29+1)*1000000000)) | E29: =IF($B29="","",SUMIFS(Grids!$BQ$160:$EC$219,Grids!$EE$160:$GQ$219,">="&$B29*1000000000,Grids!$EE$160:$GQ$219,"<"&($B29+1)*1000000000)) | F29: =IF($B29="","",SUM($C$26:$C29)) | G29: =IF($B29="","",SUM($D$26:$D29)) | H29: =IF($B29="","",SUM($E$26:$E29))
B30: =IF(DATE(YEAR_Y,1,1)+4>DATE(YEAR_Y,12,31),"",DATE(YEAR_Y,1,1)+4) | C30: =IF($B30="","",SUMIFS(Grids!$BQ$12:$EC$111,Grids!$EE$12:$GQ$111,">="&$B30*1000000000,Grids!$EE$12:$GQ$111,"<"&($B30+1)*1000000000)) | D30: =IF($B30="","",SUMIFS(Grids!$BQ$116:$EC$155,Grids!$EE$116:$GQ$155,">="&$B30*1000000000,Grids!$EE$116:$GQ$155,"<"&($B30+1)*1000000000)) | E30: =IF($B30="","",SUMIFS(Grids!$BQ$160:$EC$219,Grids!$EE$160:$GQ$219,">="&$B30*1000000000,Grids!$EE$160:$GQ$219,"<"&($B30+1)*1000000000)) | F30: =IF($B30="","",SUM($C$26:$C30)) | G30: =IF($B30="","",SUM($D$26:$D30)) | H30: =IF($B30="","",SUM($E$26:$E30))
B31: =IF(DATE(YEAR_Y,1,1)+5>DATE(YEAR_Y,12,31),"",DATE(YEAR_Y,1,1)+5) | C31: =IF($B31="","",SUMIFS(Grids!$BQ$12:$EC$111,Grids!$EE$12:$GQ$111,">="&$B31*1000000000,Grids!$EE$12:$GQ$111,"<"&($B31+1)*1000000000)) | D31: =IF($B31="","",SUMIFS(Grids!$BQ$116:$EC$155,Grids!$EE$116:$GQ$155,">="&$B31*1000000000,Grids!$EE$116:$GQ$155,"<"&($B31+1)*1000000000)) | E31: =IF($B31="","",SUMIFS(Grids!$BQ$160:$EC$219,Grids!$EE$160:$GQ$219,">="&$B31*1000000000,Grids!$EE$160:$GQ$219,"<"&($B31+1)*1000000000)) | F31: =IF($B31="","",SUM($C$26:$C31)) | G31: =IF($B31="","",SUM($D$26:$D31)) | H31: =IF($B31="","",SUM($E$26:$E31))
B32: =IF(DATE(YEAR_Y,1,1)+6>DATE(YEAR_Y,12,31),"",DATE(YEAR_Y,1,1)+6) | C32: =IF($B32="","",SUMIFS(Grids!$BQ$12:$EC$111,Grids!$EE$12:$GQ$111,">="&$B32*1000000000,Grids!$EE$12:$GQ$111,"<"&($B32+1)*1000000000)) | D32: =IF($B32="","",SUMIFS(Grids!$BQ$116:$EC$155,Grids!$EE$116:$GQ$155,">="&$B32*1000000000,Grids!$EE$116:$GQ$155,"<"&($B32+1)*1000000000)) | E32: =IF($B32="","",SUMIFS(Grids!$BQ$160:$EC$219,Grids!$EE$160:$GQ$219,">="&$B32*1000000000,Grids!$EE$160:$GQ$219,"<"&($B32+1)*1000000000)) | F32: =IF($B32="","",SUM($C$26:$C32)) | G32: =IF($B32="","",SUM($D$26:$D32)) | H32: =IF($B32="","",SUM($E$26:$E32))
B33: =IF(DATE(YEAR_Y,1,1)+7>DATE(YEAR_Y,12,31),"",DATE(YEAR_Y,1,1)+7) | C33: =IF($B33="","",SUMIFS(Grids!$BQ$12:$EC$111,Grids!$EE$12:$GQ$111,">="&$B33*1000000000,Grids!$EE$12:$GQ$111,"<"&($B33+1)*1000000000)) | D33: =IF($B33="","",SUMIFS(Grids!$BQ$116:$EC$155,Grids!$EE$116:$GQ$155,">="&$B33*1000000000,Grids!$EE$116:$GQ$155,"<"&($B33+1)*1000000000)) | E33: =IF($B33="","",SUMIFS(Grids!$BQ$160:$EC$219,Grids!$EE$160:$GQ$219,">="&$B33*1000000000,Grids!$EE$160:$GQ$219,"<"&($B33+1)*1000000000)) | F33: =IF($B33="","",SUM($C$26:$C33)) | G33: =IF($B33="","",SUM($D$26:$D33)) | H33: =IF($B33="","",SUM($E$26:$E33))
B34: =IF(DATE(YEAR_Y,1,1)+8>DATE(YEAR_Y,12,31),"",DATE(YEAR_Y,1,1)+8) | C34: =IF($B34="","",SUMIFS(Grids!$BQ$12:$EC$111,Grids!$EE$12:$GQ$111,">="&$B34*1000000000,Grids!$EE$12:$GQ$111,"<"&($B34+1)*1000000000)) | D34: =IF($B34="","",SUMIFS(Grids!$BQ$116:$EC$155,Grids!$EE$116:$GQ$155,">="&$B34*1000000000,Grids!$EE$116:$GQ$155,"<"&($B34+1)*1000000000)) | E34: =IF($B34="","",SUMIFS(Grids!$BQ$160:$EC$219,Grids!$EE$160:$GQ$219,">="&$B34*1000000000,Grids!$EE$160:$GQ$219,"<"&($B34+1)*1000000000)) | F34: =IF($B34="","",SUM($C$26:$C34)) | G34: =IF($B34="","",SUM($D$26:$D34)) | H34: =IF($B34="","",SUM($E$26:$E34))
B35: =IF(DATE(YEAR_Y,1,1)+9>DATE(YEAR_Y,12,31),"",DATE(YEAR_Y,1,1)+9) | C35: =IF($B35="","",SUMIFS(Grids!$BQ$12:$EC$111,Grids!$EE$12:$GQ$111,">="&$B35*1000000000,Grids!$EE$12:$GQ$111,"<"&($B35+1)*1000000000)) | D35: =IF($B35="","",SUMIFS(Grids!$BQ$116:$EC$155,Grids!$EE$116:$GQ$155,">="&$B35*1000000000,Grids!$EE$116:$GQ$155,"<"&($B35+1)*1000000000)) | E35: =IF($B35="","",SUMIFS(Grids!$BQ$160:$EC$219,Grids!$EE$160:$GQ$219,">="&$B35*1000000000,Grids!$EE$160:$GQ$219,"<"&($B35+1)*1000000000)) | F35: =IF($B35="","",SUM($C$26:$C35)) | G35: =IF($B35="","",SUM($D$26:$D35)) | H35: =IF($B35="","",SUM($E$26:$E35))
B36: =IF(DATE(YEAR_Y,1,1)+10>DATE(YEAR_Y,12,31),"",DATE(YEAR_Y,1,1)+10) | C36: =IF($B36="","",SUMIFS(Grids!$BQ$12:$EC$111,Grids!$EE$12:$GQ$111,">="&$B36*1000000000,Grids!$EE$12:$GQ$111,"<"&($B36+1)*1000000000)) | D36: =IF($B36="","",SUMIFS(Grids!$BQ$116:$EC$155,Grids!$EE$116:$GQ$155,">="&$B36*1000000000,Grids!$EE$116:$GQ$155,"<"&($B36+1)*1000000000)) | E36: =IF($B36="","",SUMIFS(Grids!$BQ$160:$EC$219,Grids!$EE$160:$GQ$219,">="&$B36*1000000000,Grids!$EE$160:$GQ$219,"<"&($B36+1)*1000000000)) | F36: =IF($B36="","",SUM($C$26:$C36)) | G36: =IF($B36="","",SUM($D$26:$D36)) | H36: =IF($B36="","",SUM($E$26:$E36))
B37: =IF(DATE(YEAR_Y,1,1)+11>DATE(YEAR_Y,12,31),"",DATE(YEAR_Y,1,1)+11) | C37: =IF($B37="","",SUMIFS(Grids!$BQ$12:$EC$111,Grids!$EE$12:$GQ$111,">="&$B37*1000000000,Grids!$EE$12:$GQ$111,"<"&($B37+1)*1000000000)) | D37: =IF($B37="","",SUMIFS(Grids!$BQ$116:$EC$155,Grids!$EE$116:$GQ$155,">="&$B37*1000000000,Grids!$EE$116:$GQ$155,"<"&($B37+1)*1000000000)) | E37: =IF($B37="","",SUMIFS(Grids!$BQ$160:$EC$219,Grids!$EE$160:$GQ$219,">="&$B37*1000000000,Grids!$EE$160:$GQ$219,"<"&($B37+1)*1000000000)) | F37: =IF($B37="","",SUM($C$26:$C37)) | G37: =IF($B37="","",SUM($D$26:$D37)) | H37: =IF($B37="","",SUM($E$26:$E37))
B38: =IF(DATE(YEAR_Y,1,1)+12>DATE(YEAR_Y,12,31),"",DATE(YEAR_Y,1,1)+12) | C38: =IF($B38="","",SUMIFS(Grids!$BQ$12:$EC$111,Grids!$EE$12:$GQ$111,">="&$B38*1000000000,Grids!$EE$12:$GQ$111,"<"&($B38+1)*1000000000)) | D38: =IF($B38="","",SUMIFS(Grids!$BQ$116:$EC$155,Grids!$EE$116:$GQ$155,">="&$B38*1000000000,Grids!$EE$116:$GQ$155,"<"&($B38+1)*1000000000)) | E38: =IF($B38="","",SUMIFS(Grids!$BQ$160:$EC$219,Grids!$EE$160:$GQ$219,">="&$B38*1000000000,Grids!$EE$160:$GQ$219,"<"&($B38+1)*1000000000)) | F38: =IF($B38="","",SUM($C$26:$C38)) | G38: =IF($B38="","",SUM($D$26:$D38)) | H38: =IF($B38="","",SUM($E$26:$E38))
B39: =IF(DATE(YEAR_Y,1,1)+13>DATE(YEAR_Y,12,31),"",DATE(YEAR_Y,1,1)+13) | C39: =IF($B39="","",SUMIFS(Grids!$BQ$12:$EC$111,Grids!$EE$12:$GQ$111,">="&$B39*1000000000,Grids!$EE$12:$GQ$111,"<"&($B39+1)*1000000000)) | D39: =IF($B39="","",SUMIFS(Grids!$BQ$116:$EC$155,Grids!$EE$116:$GQ$155,">="&$B39*1000000000,Grids!$EE$116:$GQ$155,"<"&($B39+1)*1000000000)) | E39: =IF($B39="","",SUMIFS(Grids!$BQ$160:$EC$219,Grids!$EE$160:$GQ$219,">="&$B39*1000000000,Grids!$EE$160:$GQ$219,"<"&($B39+1)*1000000000)) | F39: =IF($B39="","",SUM($C$26:$C39)) | G39: =IF($B39="","",SUM($D$26:$D39)) | H39: =IF($B39="","",SUM($E$26:$E39))
B40: =IF(DATE(YEAR_Y,1,1)+14>DATE(YEAR_Y,12,31),"",DATE(YEAR_Y,1,1)+14) | C40: =IF($B40="","",SUMIFS(Grids!$BQ$12:$EC$111,Grids!$EE$12:$GQ$111,">="&$B40*1000000000,Grids!$EE$12:$GQ$111,"<"&($B40+1)*1000000000)) | D40: =IF($B40="","",SUMIFS(Grids!$BQ$116:$EC$155,Grids!$EE$116:$GQ$155,">="&$B40*1000000000,Grids!$EE$116:$GQ$155,"<"&($B40+1)*1000000000)) | E40: =IF($B40="","",SUMIFS(Grids!$BQ$160:$EC$219,Grids!$EE$160:$GQ$219,">="&$B40*1000000000,Grids!$EE$160:$GQ$219,"<"&($B40+1)*1000000000)) | F40: =IF($B40="","",SUM($C$26:$C40)) | G40: =IF($B40="","",SUM($D$26:$D40)) | H40: =IF($B40="","",SUM($E$26:$E40))
B41: =IF(DATE(YEAR_Y,1,1)+15>DATE(YEAR_Y,12,31),"",DATE(YEAR_Y,1,1)+15) | C41: =IF($B41="","",SUMIFS(Grids!$BQ$12:$EC$111,Grids!$EE$12:$GQ$111,">="&$B41*1000000000,Grids!$EE$12:$GQ$111,"<"&($B41+1)*1000000000)) | D41: =IF($B41="","",SUMIFS(Grids!$BQ$116:$EC$155,Grids!$EE$116:$GQ$155,">="&$B41*1000000000,Grids!$EE$116:$GQ$155,"<"&($B41+1)*1000000000)) | E41: =IF($B41="","",SUMIFS(Grids!$BQ$160:$EC$219,Grids!$EE$160:$GQ$219,">="&$B41*1000000000,Grids!$EE$160:$GQ$219,"<"&($B41+1)*1000000000)) | F41: =IF($B41="","",SUM($C$26:$C41)) | G41: =IF($B41="","",SUM($D$26:$D41)) | H41: =IF($B41="","",SUM($E$26:$E41))
B42: =IF(DATE(YEAR_Y,1,1)+16>DATE(YEAR_Y,12,31),"",DATE(YEAR_Y,1,1)+16) | C42: =IF($B42="","",SUMIFS(Grids!$BQ$12:$EC$111,Grids!$EE$12:$GQ$111,">="&$B42*1000000000,Grids!$EE$12:$GQ$111,"<"&($B42+1)*1000000000)) | D42: =IF($B42="","",SUMIFS(Grids!$BQ$116:$EC$155,Grids!$EE$116:$GQ$155,">="&$B42*1000000000,Grids!$EE$116:$GQ$155,"<"&($B42+1)*1000000000)) | E42: =IF($B42="","",SUMIFS(Grids!$BQ$160:$EC$219,Grids!$EE$160:$GQ$219,">="&$B42*1000000000,Grids!$EE$160:$GQ$219,"<"&($B42+1)*1000000000)) | F42: =IF($B42="","",SUM($C$26:$C42)) | G42: =IF($B42="","",SUM($D$26:$D42)) | H42: =IF($B42="","",SUM($E$26:$E42))
B43: =IF(DATE(YEAR_Y,1,1)+17>DATE(YEAR_Y,12,31),"",DATE(YEAR_Y,1,1)+17) | C43: =IF($B43="","",SUMIFS(Grids!$BQ$12:$EC$111,Grids!$EE$12:$GQ$111,">="&$B43*1000000000,Grids!$EE$12:$GQ$111,"<"&($B43+1)*1000000000)) | D43: =IF($B43="","",SUMIFS(Grids!$BQ$116:$EC$155,Grids!$EE$116:$GQ$155,">="&$B43*1000000000,Grids!$EE$116:$GQ$155,"<"&($B43+1)*1000000000)) | E43: =IF($B43="","",SUMIFS(Grids!$BQ$160:$EC$219,Grids!$EE$160:$GQ$219,">="&$B43*1000000000,Grids!$EE$160:$GQ$219,"<"&($B43+1)*1000000000)) | F43: =IF($B43="","",SUM($C$26:$C43)) | G43: =IF($B43="","",SUM($D$26:$D43)) | H43: =IF($B43="","",SUM($E$26:$E43))
B44: =IF(DATE(YEAR_Y,1,1)+18>DATE(YEAR_Y,12,31),"",DATE(YEAR_Y,1,1)+18) | C44: =IF($B44="","",SUMIFS(Grids!$BQ$12:$EC$111,Grids!$EE$12:$GQ$111,">="&$B44*1000000000,Grids!$EE$12:$GQ$111,"<"&($B44+1)*1000000000)) | D44: =IF($B44="","",SUMIFS(Grids!$BQ$116:$EC$155,Grids!$EE$116:$GQ$155,">="&$B44*1000000000,Grids!$EE$116:$GQ$155,"<"&($B44+1)*1000000000)) | E44: =IF($B44="","",SUMIFS(Grids!$BQ$160:$EC$219,Grids!$EE$160:$GQ$219,">="&$B44*1000000000,Grids!$EE$160:$GQ$219,"<"&($B44+1)*1000000000)) | F44: =IF($B44="","",SUM($C$26:$C44)) | G44: =IF($B44="","",SUM($D$26:$D44)) | H44: =IF($B44="","",SUM($E$26:$E44))
B45: =IF(DATE(YEAR_Y,1,1)+19>DATE(YEAR_Y,12,31),"",DATE(YEAR_Y,1,1)+19) | C45: =IF($B45="","",SUMIFS(Grids!$BQ$12:$EC$111,Grids!$EE$12:$GQ$111,">="&$B45*1000000000,Grids!$EE$12:$GQ$111,"<"&($B45+1)*1000000000)) | D45: =IF($B45="","",SUMIFS(Grids!$BQ$116:$EC$155,Grids!$EE$116:$GQ$155,">="&$B45*1000000000,Grids!$EE$116:$GQ$155,"<"&($B45+1)*1000000000)) | E45: =IF($B45="","",SUMIFS(Grids!$BQ$160:$EC$219,Grids!$EE$160:$GQ$219,">="&$B45*1000000000,Grids!$EE$160:$GQ$219,"<"&($B45+1)*1000000000)) | F45: =IF($B45="","",SUM($C$26:$C45)) | G45: =IF($B45="","",SUM($D$26:$D45)) | H45: =IF($B45="","",SUM($E$26:$E45))
B46: =IF(DATE(YEAR_Y,1,1)+20>DATE(YEAR_Y,12,31),"",DATE(YEAR_Y,1,1)+20) | C46: =IF($B46="","",SUMIFS(Grids!$BQ$12:$EC$111,Grids!$EE$12:$GQ$111,">="&$B46*1000000000,Grids!$EE$12:$GQ$111,"<"&($B46+1)*1000000000)) | D46: =IF($B46="","",SUMIFS(Grids!$BQ$116:$EC$155,Grids!$EE$116:$GQ$155,">="&$B46*1000000000,Grids!$EE$116:$GQ$155,"<"&($B46+1)*1000000000)) | E46: =IF($B46="","",SUMIFS(Grids!$BQ$160:$EC$219,Grids!$EE$160:$GQ$219,">="&$B46*1000000000,Grids!$EE$160:$GQ$219,"<"&($B46+1)*1000000000)) | F46: =IF($B46="","",SUM($C$26:$C46)) | G46: =IF($B46="","",SUM($D$26:$D46)) | H46: =IF($B46="","",SUM($E$26:$E46))
B47: =IF(DATE(YEAR_Y,1,1)+21>DATE(YEAR_Y,12,31),"",DATE(YEAR_Y,1,1)+21) | C47: =IF($B47="","",SUMIFS(Grids!$BQ$12:$EC$111,Grids!$EE$12:$GQ$111,">="&$B47*1000000000,Grids!$EE$12:$GQ$111,"<"&($B47+1)*1000000000)) | D47: =IF($B47="","",SUMIFS(Grids!$BQ$116:$EC$155,Grids!$EE$116:$GQ$155,">="&$B47*1000000000,Grids!$EE$116:$GQ$155,"<"&($B47+1)*1000000000)) | E47: =IF($B47="","",SUMIFS(Grids!$BQ$160:$EC$219,Grids!$EE$160:$GQ$219,">="&$B47*1000000000,Grids!$EE$160:$GQ$219,"<"&($B47+1)*1000000000)) | F47: =IF($B47="","",SUM($C$26:$C47)) | G47: =IF($B47="","",SUM($D$26:$D47)) | H47: =IF($B47="","",SUM($E$26:$E47))
B48: =IF(DATE(YEAR_Y,1,1)+22>DATE(YEAR_Y,12,31),"",DATE(YEAR_Y,1,1)+22) | C48: =IF($B48="","",SUMIFS(Grids!$BQ$12:$EC$111,Grids!$EE$12:$GQ$111,">="&$B48*1000000000,Grids!$EE$12:$GQ$111,"<"&($B48+1)*1000000000)) | D48: =IF($B48="","",SUMIFS(Grids!$BQ$116:$EC$155,Grids!$EE$116:$GQ$155,">="&$B48*1000000000,Grids!$EE$116:$GQ$155,"<"&($B48+1)*1000000000)) | E48: =IF($B48="","",SUMIFS(Grids!$BQ$160:$EC$219,Grids!$EE$160:$GQ$219,">="&$B48*1000000000,Grids!$EE$160:$GQ$219,"<"&($B48+1)*1000000000)) | F48: =IF($B48="","",SUM($C$26:$C48)) | G48: =IF($B48="","",SUM($D$26:$D48)) | H48: =IF($B48="","",SUM($E$26:$E48))
B49: =IF(DATE(YEAR_Y,1,1)+23>DATE(YEAR_Y,12,31),"",DATE(YEAR_Y,1,1)+23) | C49: =IF($B49="","",SUMIFS(Grids!$BQ$12:$EC$111,Grids!$EE$12:$GQ$111,">="&$B49*1000000000,Grids!$EE$12:$GQ$111,"<"&($B49+1)*1000000000)) | D49: =IF($B49="","",SUMIFS(Grids!$BQ$116:$EC$155,Grids!$EE$116:$GQ$155,">="&$B49*1000000000,Grids!$EE$116:$GQ$155,"<"&($B49+1)*1000000000)) | E49: =IF($B49="","",SUMIFS(Grids!$BQ$160:$EC$219,Grids!$EE$160:$GQ$219,">="&$B49*1000000000,Grids!$EE$160:$GQ$219,"<"&($B49+1)*1000000000)) | F49: =IF($B49="","",SUM($C$26:$C49)) | G49: =IF($B49="","",SUM($D$26:$D49)) | H49: =IF($B49="","",SUM($E$26:$E49))
B50: =IF(DATE(YEAR_Y,1,1)+24>DATE(YEAR_Y,12,31),"",DATE(YEAR_Y,1,1)+24) | C50: =IF($B50="","",SUMIFS(Grids!$BQ$12:$EC$111,Grids!$EE$12:$GQ$111,">="&$B50*1000000000,Grids!$EE$12:$GQ$111,"<"&($B50+1)*1000000000)) | D50: =IF($B50="","",SUMIFS(Grids!$BQ$116:$EC$155,Grids!$EE$116:$GQ$155,">="&$B50*1000000000,Grids!$EE$116:$GQ$155,"<"&($B50+1)*1000000000)) | E50: =IF($B50="","",SUMIFS(Grids!$BQ$160:$EC$219,Grids!$EE$160:$GQ$219,">="&$B50*1000000000,Grids!$EE$160:$GQ$219,"<"&($B50+1)*1000000000)) | F50: =IF($B50="","",SUM($C$26:$C50)) | G50: =IF($B50="","",SUM($D$26:$D50)) | H50: =IF($B50="","",SUM($E$26:$E50))
B51: =IF(DATE(YEAR_Y,1,1)+25>DATE(YEAR_Y,12,31),"",DATE(YEAR_Y,1,1)+25) | C51: =IF($B51="","",SUMIFS(Grids!$BQ$12:$EC$111,Grids!$EE$12:$GQ$111,">="&$B51*1000000000,Grids!$EE$12:$GQ$111,"<"&($B51+1)*1000000000)) | D51: =IF($B51="","",SUMIFS(Grids!$BQ$116:$EC$155,Grids!$EE$116:$GQ$155,">="&$B51*1000000000,Grids!$EE$116:$GQ$155,"<"&($B51+1)*1000000000)) | E51: =IF($B51="","",SUMIFS(Grids!$BQ$160:$EC$219,Grids!$EE$160:$GQ$219,">="&$B51*1000000000,Grids!$EE$160:$GQ$219,"<"&($B51+1)*1000000000)) | F51: =IF($B51="","",SUM($C$26:$C51)) | G51: =IF($B51="","",SUM($D$26:$D51)) | H51: =IF($B51="","",SUM($E$26:$E51))
B52: =IF(DATE(YEAR_Y,1,1)+26>DATE(YEAR_Y,12,31),"",DATE(YEAR_Y,1,1)+26) | C52: =IF($B52="","",SUMIFS(Grids!$BQ$12:$EC$111,Grids!$EE$12:$GQ$111,">="&$B52*1000000000,Grids!$EE$12:$GQ$111,"<"&($B52+1)*1000000000)) | D52: =IF($B52="","",SUMIFS(Grids!$BQ$116:$EC$155,Grids!$EE$116:$GQ$155,">="&$B52*1000000000,Grids!$EE$116:$GQ$155,"<"&($B52+1)*1000000000)) | E52: =IF($B52="","",SUMIFS(Grids!$BQ$160:$EC$219,Grids!$EE$160:$GQ$219,">="&$B52*1000000000,Grids!$EE$160:$GQ$219,"<"&($B52+1)*1000000000)) | F52: =IF($B52="","",SUM($C$26:$C52)) | G52: =IF($B52="","",SUM($D$26:$D52)) | H52: =IF($B52="","",SUM($E$26:$E52))
B53: =IF(DATE(YEAR_Y,1,1)+27>DATE(YEAR_Y,12,31),"",DATE(YEAR_Y,1,1)+27) | C53: =IF($B53="","",SUMIFS(Grids!$BQ$12:$EC$111,Grids!$EE$12:$GQ$111,">="&$B53*1000000000,Grids!$EE$12:$GQ$111,"<"&($B53+1)*1000000000)) | D53: =IF($B53="","",SUMIFS(Grids!$BQ$116:$EC$155,Grids!$EE$116:$GQ$155,">="&$B53*1000000000,Grids!$EE$116:$GQ$155,"<"&($B53+1)*1000000000)) | E53: =IF($B53="","",SUMIFS(Grids!$BQ$160:$EC$219,Grids!$EE$160:$GQ$219,">="&$B53*1000000000,Grids!$EE$160:$GQ$219,"<"&($B53+1)*1000000000)) | F53: =IF($B53="","",SUM($C$26:$C53)) | G53: =IF($B53="","",SUM($D$26:$D53)) | H53: =IF($B53="","",SUM($E$26:$E53))
B54: =IF(DATE(YEAR_Y,1,1)+28>DATE(YEAR_Y,12,31),"",DATE(YEAR_Y,1,1)+28) | C54: =IF($B54="","",SUMIFS(Grids!$BQ$12:$EC$111,Grids!$EE$12:$GQ$111,">="&$B54*1000000000,Grids!$EE$12:$GQ$111,"<"&($B54+1)*1000000000)) | D54: =IF($B54="","",SUMIFS(Grids!$BQ$116:$EC$155,Grids!$EE$116:$GQ$155,">="&$B54*1000000000,Grids!$EE$116:$GQ$155,"<"&($B54+1)*1000000000)) | E54: =IF($B54="","",SUMIFS(Grids!$BQ$160:$EC$219,Grids!$EE$160:$GQ$219,">="&$B54*1000000000,Grids!$EE$160:$GQ$219,"<"&($B54+1)*1000000000)) | F54: =IF($B54="","",SUM($C$26:$C54)) | G54: =IF($B54="","",SUM($D$26:$D54)) | H54: =IF($B54="","",SUM($E$26:$E54))
B55: =IF(DATE(YEAR_Y,1,1)+29>DATE(YEAR_Y,12,31),"",DATE(YEAR_Y,1,1)+29) | C55: =IF($B55="","",SUMIFS(Grids!$BQ$12:$EC$111,Grids!$EE$12:$GQ$111,">="&$B55*1000000000,Grids!$EE$12:$GQ$111,"<"&($B55+1)*1000000000)) | D55: =IF($B55="","",SUMIFS(Grids!$BQ$116:$EC$155,Grids!$EE$116:$GQ$155,">="&$B55*1000000000,Grids!$EE$116:$GQ$155,"<"&($B55+1)*1000000000)) | E55: =IF($B55="","",SUMIFS(Grids!$BQ$160:$EC$219,Grids!$EE$160:$GQ$219,">="&$B55*1000000000,Grids!$EE$160:$GQ$219,"<"&($B55+1)*1000000000)) | F55: =IF($B55="","",SUM($C$26:$C55)) | G55: =IF($B55="","",SUM($D$26:$D55)) | H55: =IF($B55="","",SUM($E$26:$E55))
B56: =IF(DATE(YEAR_Y,1,1)+30>DATE(YEAR_Y,12,31),"",DATE(YEAR_Y,1,1)+30) | C56: =IF($B56="","",SUMIFS(Grids!$BQ$12:$EC$111,Grids!$EE$12:$GQ$111,">="&$B56*1000000000,Grids!$EE$12:$GQ$111,"<"&($B56+1)*1000000000)) | D56: =IF($B56="","",SUMIFS(Grids!$BQ$116:$EC$155,Grids!$EE$116:$GQ$155,">="&$B56*1000000000,Grids!$EE$116:$GQ$155,"<"&($B56+1)*1000000000)) | E56: =IF($B56="","",SUMIFS(Grids!$BQ$160:$EC$219,Grids!$EE$160:$GQ$219,">="&$B56*1000000000,Grids!$EE$160:$GQ$219,"<"&($B56+1)*1000000000)) | F56: =IF($B56="","",SUM($C$26:$C56)) | G56: =IF($B56="","",SUM($D$26:$D56)) | H56: =IF($B56="","",SUM($E$26:$E56))
B57: =IF(DATE(YEAR_Y,1,1)+31>DATE(YEAR_Y,12,31),"",DATE(YEAR_Y,1,1)+31) | C57: =IF($B57="","",SUMIFS(Grids!$BQ$12:$EC$111,Grids!$EE$12:$GQ$111,">="&$B57*1000000000,Grids!$EE$12:$GQ$111,"<"&($B57+1)*1000000000)) | D57: =IF($B57="","",SUMIFS(Grids!$BQ$116:$EC$155,Grids!$EE$116:$GQ$155,">="&$B57*1000000000,Grids!$EE$116:$GQ$155,"<"&($B57+1)*1000000000)) | E57: =IF($B57="","",SUMIFS(Grids!$BQ$160:$EC$219,Grids!$EE$160:$GQ$219,">="&$B57*1000000000,Grids!$EE$160:$GQ$219,"<"&($B57+1)*1000000000)) | F57: =IF($B57="","",SUM($C$26:$C57)) | G57: =IF($B57="","",SUM($D$26:$D57)) | H57: =IF($B57="","",SUM($E$26:$E57))
B58: =IF(DATE(YEAR_Y,1,1)+32>DATE(YEAR_Y,12,31),"",DATE(YEAR_Y,1,1)+32) | C58: =IF($B58="","",SUMIFS(Grids!$BQ$12:$EC$111,Grids!$EE$12:$GQ$111,">="&$B58*1000000000,Grids!$EE$12:$GQ$111,"<"&($B58+1)*1000000000)) | D58: =IF($B58="","",SUMIFS(Grids!$BQ$116:$EC$155,Grids!$EE$116:$GQ$155,">="&$B58*1000000000,Grids!$EE$116:$GQ$155,"<"&($B58+1)*1000000000)) | E58: =IF($B58="","",SUMIFS(Grids!$BQ$160:$EC$219,Grids!$EE$160:$GQ$219,">="&$B58*1000000000,Grids!$EE$160:$GQ$219,"<"&($B58+1)*1000000000)) | F58: =IF($B58="","",SUM($C$26:$C58)) | G58: =IF($B58="","",SUM($D$26:$D58)) | H58: =IF($B58="","",SUM($E$26:$E58))
B59: =IF(DATE(YEAR_Y,1,1)+33>DATE(YEAR_Y,12,31),"",DATE(YEAR_Y,1,1)+33) | C59: =IF($B59="","",SUMIFS(Grids!$BQ$12:$EC$111,Grids!$EE$12:$GQ$111,">="&$B59*1000000000,Grids!$EE$12:$GQ$111,"<"&($B59+1)*1000000000)) | D59: =IF($B59="","",SUMIFS(Grids!$BQ$116:$EC$155,Grids!$EE$116:$GQ$155,">="&$B59*1000000000,Grids!$EE$116:$GQ$155,"<"&($B59+1)*1000000000)) | E59: =IF($B59="","",SUMIFS(Grids!$BQ$160:$EC$219,Grids!$EE$160:$GQ$219,">="&$B59*1000000000,Grids!$EE$160:$GQ$219,"<"&($B59+1)*1000000000)) | F59: =IF($B59="","",SUM($C$26:$C59)) | G59: =IF($B59="","",SUM($D$26:$D59)) | H59: =IF($B59="","",SUM($E$26:$E59))
B60: =IF(DATE(YEAR_Y,1,1)+34>DATE(YEAR_Y,12,31),"",DATE(YEAR_Y,1,1)+34) | C60: =IF($B60="","",SUMIFS(Grids!$BQ$12:$EC$111,Grids!$EE$12:$GQ$111,">="&$B60*1000000000,Grids!$EE$12:$GQ$111,"<"&($B60+1)*1000000000)) | D60: =IF($B60="","",SUMIFS(Grids!$BQ$116:$EC$155,Grids!$EE$116:$GQ$155,">="&$B60*1000000000,Grids!$EE$116:$GQ$155,"<"&($B60+1)*1000000000)) | E60: =IF($B60="","",SUMIFS(Grids!$BQ$160:$EC$219,Grids!$EE$160:$GQ$219,">="&$B60*1000000000,Grids!$EE$160:$GQ$219,"<"&($B60+1)*1000000000)) | F60: =IF($B60="","",SUM($C$26:$C60)) | G60: =IF($B60="","",SUM($D$26:$D60)) | H60: =IF($B60="","",SUM($E$26:$E60))
B61: =IF(DATE(YEAR_Y,1,1)+35>DATE(YEAR_Y,12,31),"",DATE(YEAR_Y,1,1)+35) | C61: =IF($B61="","",SUMIFS(Grids!$BQ$12:$EC$111,Grids!$EE$12:$GQ$111,">="&$B61*1000000000,Grids!$EE$12:$GQ$111,"<"&($B61+1)*1000000000)) | D61: =IF($B61="","",SUMIFS(Grids!$BQ$116:$EC$155,Grids!$EE$116:$GQ$155,">="&$B61*1000000000,Grids!$EE$116:$GQ$155,"<"&($B61+1)*1000000000)) | E61: =IF($B61="","",SUMIFS(Grids!$BQ$160:$EC$219,Grids!$EE$160:$GQ$219,">="&$B61*1000000000,Grids!$EE$160:$GQ$219,"<"&($B61+1)*1000000000)) | F61: =IF($B61="","",SUM($C$26:$C61)) | G61: =IF($B61="","",SUM($D$26:$D61)) | H61: =IF($B61="","",SUM($E$26:$E61))
B62: =IF(DATE(YEAR_Y,1,1)+36>DATE(YEAR_Y,12,31),"",DATE(YEAR_Y,1,1)+36) | C62: =IF($B62="","",SUMIFS(Grids!$BQ$12:$EC$111,Grids!$EE$12:$GQ$111,">="&$B62*1000000000,Grids!$EE$12:$GQ$111,"<"&($B62+1)*1000000000)) | D62: =IF($B62="","",SUMIFS(Grids!$BQ$116:$EC$155,Grids!$EE$116:$GQ$155,">="&$B62*1000000000,Grids!$EE$116:$GQ$155,"<"&($B62+1)*1000000000)) | E62: =IF($B62="","",SUMIFS(Grids!$BQ$160:$EC$219,Grids!$EE$160:$GQ$219,">="&$B62*1000000000,Grids!$EE$160:$GQ$219,"<"&($B62+1)*1000000000)) | F62: =IF($B62="","",SUM($C$26:$C62)) | G62: =IF($B62="","",SUM($D$26:$D62)) | H62: =IF($B62="","",SUM($E$26:$E62))
B63: =IF(DATE(YEAR_Y,1,1)+37>DATE(YEAR_Y,12,31),"",DATE(YEAR_Y,1,1)+37) | C63: =IF($B63="","",SUMIFS(Grids!$BQ$12:$EC$111,Grids!$EE$12:$GQ$111,">="&$B63*1000000000,Grids!$EE$12:$GQ$111,"<"&($B63+1)*1000000000)) | D63: =IF($B63="","",SUMIFS(Grids!$BQ$116:$EC$155,Grids!$EE$116:$GQ$155,">="&$B63*1000000000,Grids!$EE$116:$GQ$155,"<"&($B63+1)*1000000000)) | E63: =IF($B63="","",SUMIFS(Grids!$BQ$160:$EC$219,Grids!$EE$160:$GQ$219,">="&$B63*1000000000,Grids!$EE$160:$GQ$219,"<"&($B63+1)*1000000000)) | F63: =IF($B63="","",SUM($C$26:$C63)) | G63: =IF($B63="","",SUM($D$26:$D63)) | H63: =IF($B63="","",SUM($E$26:$E63))
B64: =IF(DATE(YEAR_Y,1,1)+38>DATE(YEAR_Y,12,31),"",DATE(YEAR_Y,1,1)+38) | C64: =IF($B64="","",SUMIFS(Grids!$BQ$12:$EC$111,Grids!$EE$12:$GQ$111,">="&$B64*1000000000,Grids!$EE$12:$GQ$111,"<"&($B64+1)*1000000000)) | D64: =IF($B64="","",SUMIFS(Grids!$BQ$116:$EC$155,Grids!$EE$116:$GQ$155,">="&$B64*1000000000,Grids!$EE$116:$GQ$155,"<"&($B64+1)*1000000000)) | E64: =IF($B64="","",SUMIFS(Grids!$BQ$160:$EC$219,Grids!$EE$160:$GQ$219,">="&$B64*1000000000,Grids!$EE$160:$GQ$219,"<"&($B64+1)*1000000000)) | F64: =IF($B64="","",SUM($C$26:$C64)) | G64: =IF($B64="","",SUM($D$26:$D64)) | H64: =IF($B64="","",SUM($E$26:$E64))
B65: =IF(DATE(YEAR_Y,1,1)+39>DATE(YEAR_Y,12,31),"",DATE(YEAR_Y,1,1)+39) | C65: =IF($B65="","",SUMIFS(Grids!$BQ$12:$EC$111,Grids!$EE$12:$GQ$111,">="&$B65*1000000000,Grids!$EE$12:$GQ$111,"<"&($B65+1)*1000000000)) | D65: =IF($B65="","",SUMIFS(Grids!$BQ$116:$EC$155,Grids!$EE$116:$GQ$155,">="&$B65*1000000000,Grids!$EE$116:$GQ$155,"<"&($B65+1)*1000000000)) | E65: =IF($B65="","",SUMIFS(Grids!$BQ$160:$EC$219,Grids!$EE$160:$GQ$219,">="&$B65*1000000000,Grids!$EE$160:$GQ$219,"<"&($B65+1)*1000000000)) | F65: =IF($B65="","",SUM($C$26:$C65)) | G65: =IF($B65="","",SUM($D$26:$D65)) | H65: =IF($B65="","",SUM($E$26:$E65))
B66: =IF(DATE(YEAR_Y,1,1)+40>DATE(YEAR_Y,12,31),"",DATE(YEAR_Y,1,1)+40) | C66: =IF($B66="","",SUMIFS(Grids!$BQ$12:$EC$111,Grids!$EE$12:$GQ$111,">="&$B66*1000000000,Grids!$EE$12:$GQ$111,"<"&($B66+1)*1000000000)) | D66: =IF($B66="","",SUMIFS(Grids!$BQ$116:$EC$155,Grids!$EE$116:$GQ$155,">="&$B66*1000000000,Grids!$EE$116:$GQ$155,"<"&($B66+1)*1000000000)) | E66: =IF($B66="","",SUMIFS(Grids!$BQ$160:$EC$219,Grids!$EE$160:$GQ$219,">="&$B66*1000000000,Grids!$EE$160:$GQ$219,"<"&($B66+1)*1000000000)) | F66: =IF($B66="","",SUM($C$26:$C66)) | G66: =IF($B66="","",SUM($D$26:$D66)) | H66: =IF($B66="","",SUM($E$26:$E66))
B67: =IF(DATE(YEAR_Y,1,1)+41>DATE(YEAR_Y,12,31),"",DATE(YEAR_Y,1,1)+41) | C67: =IF($B67="","",SUMIFS(Grids!$BQ$12:$EC$111,Grids!$EE$12:$GQ$111,">="&$B67*1000000000,Grids!$EE$12:$GQ$111,"<"&($B67+1)*1000000000)) | D67: =IF($B67="","",SUMIFS(Grids!$BQ$116:$EC$155,Grids!$EE$116:$GQ$155,">="&$B67*1000000000,Grids!$EE$116:$GQ$155,"<"&($B67+1)*1000000000)) | E67: =IF($B67="","",SUMIFS(Grids!$BQ$160:$EC$219,Grids!$EE$160:$GQ$219,">="&$B67*1000000000,Grids!$EE$160:$GQ$219,"<"&($B67+1)*1000000000)) | F67: =IF($B67="","",SUM($C$26:$C67)) | G67: =IF($B67="","",SUM($D$26:$D67)) | H67: =IF($B67="","",SUM($E$26:$E67))
B68: =IF(DATE(YEAR_Y,1,1)+42>DATE(YEAR_Y,12,31),"",DATE(YEAR_Y,1,1)+42) | C68: =IF($B68="","",SUMIFS(Grids!$BQ$12:$EC$111,Grids!$EE$12:$GQ$111,">="&$B68*1000000000,Grids!$EE$12:$GQ$111,"<"&($B68+1)*1000000000)) | D68: =IF($B68="","",SUMIFS(Grids!$BQ$116:$EC$155,Grids!$EE$116:$GQ$155,">="&$B68*1000000000,Grids!$EE$116:$GQ$155,"<"&($B68+1)*1000000000)) | E68: =IF($B68="","",SUMIFS(Grids!$BQ$160:$EC$219,Grids!$EE$160:$GQ$219,">="&$B68*1000000000,Grids!$EE$160:$GQ$219,"<"&($B68+1)*1000000000)) | F68: =IF($B68="","",SUM($C$26:$C68)) | G68: =IF($B68="","",SUM($D$26:$D68)) | H68: =IF($B68="","",SUM($E$26:$E68))
B69: =IF(DATE(YEAR_Y,1,1)+43>DATE(YEAR_Y,12,31),"",DATE(YEAR_Y,1,1)+43) | C69: =IF($B69="","",SUMIFS(Grids!$BQ$12:$EC$111,Grids!$EE$12:$GQ$111,">="&$B69*1000000000,Grids!$EE$12:$GQ$111,"<"&($B69+1)*1000000000)) | D69: =IF($B69="","",SUMIFS(Grids!$BQ$116:$EC$155,Grids!$EE$116:$GQ$155,">="&$B69*1000000000,Grids!$EE$116:$GQ$155,"<"&($B69+1)*1000000000)) | E69: =IF($B69="","",SUMIFS(Grids!$BQ$160:$EC$219,Grids!$EE$160:$GQ$219,">="&$B69*1000000000,Grids!$EE$160:$GQ$219,"<"&($B69+1)*1000000000)) | F69: =IF($B69="","",SUM($C$26:$C69)) | G69: =IF($B69="","",SUM($D$26:$D69)) | H69: =IF($B69="","",SUM($E$26:$E69))
B70: =IF(DATE(YEAR_Y,1,1)+44>DATE(YEAR_Y,12,31),"",DATE(YEAR_Y,1,1)+44) | C70: =IF($B70="","",SUMIFS(Grids!$BQ$12:$EC$111,Grids!$EE$12:$GQ$111,">="&$B70*1000000000,Grids!$EE$12:$GQ$111,"<"&($B70+1)*1000000000)) | D70: =IF($B70="","",SUMIFS(Grids!$BQ$116:$EC$155,Grids!$EE$116:$GQ$155,">="&$B70*1000000000,Grids!$EE$116:$GQ$155,"<"&($B70+1)*1000000000)) | E70: =IF($B70="","",SUMIFS(Grids!$BQ$160:$EC$219,Grids!$EE$160:$GQ$219,">="&$B70*1000000000,Grids!$EE$160:$GQ$219,"<"&($B70+1)*1000000000)) | F70: =IF($B70="","",SUM($C$26:$C70)) | G70: =IF($B70="","",SUM($D$26:$D70)) | H70: =IF($B70="","",SUM($E$26:$E70))
B71: =IF(DATE(YEAR_Y,1,1)+45>DATE(YEAR_Y,12,31),"",DATE(YEAR_Y,1,1)+45) | C71: =IF($B71="","",SUMIFS(Grids!$BQ$12:$EC$111,Grids!$EE$12:$GQ$111,">="&$B71*1000000000,Grids!$EE$12:$GQ$111,"<"&($B71+1)*1000000000)) | D71: =IF($B71="","",SUMIFS(Grids!$BQ$116:$EC$155,Grids!$EE$116:$GQ$155,">="&$B71*1000000000,Grids!$EE$116:$GQ$155,"<"&($B71+1)*1000000000)) | E71: =IF($B71="","",SUMIFS(Grids!$BQ$160:$EC$219,Grids!$EE$160:$GQ$219,">="&$B71*1000000000,Grids!$EE$160:$GQ$219,"<"&($B71+1)*1000000000)) | F71: =IF($B71="","",SUM($C$26:$C71)) | G71: =IF($B71="","",SUM($D$26:$D71)) | H71: =IF($B71="","",SUM($E$26:$E71))
B72: =IF(DATE(YEAR_Y,1,1)+46>DATE(YEAR_Y,12,31),"",DATE(YEAR_Y,1,1)+46) | C72: =IF($B72="","",SUMIFS(Grids!$BQ$12:$EC$111,Grids!$EE$12:$GQ$111,">="&$B72*1000000000,Grids!$EE$12:$GQ$111,"<"&($B72+1)*1000000000)) | D72: =IF($B72="","",SUMIFS(Grids!$BQ$116:$EC$155,Grids!$EE$116:$GQ$155,">="&$B72*1000000000,Grids!$EE$116:$GQ$155,"<"&($B72+1)*1000000000)) | E72: =IF($B72="","",SUMIFS(Grids!$BQ$160:$EC$219,Grids!$EE$160:$GQ$219,">="&$B72*1000000000,Grids!$EE$160:$GQ$219,"<"&($B72+1)*1000000000)) | F72: =IF($B72="","",SUM($C$26:$C72)) | G72: =IF($B72="","",SUM($D$26:$D72)) | H72: =IF($B72="","",SUM($E$26:$E72))
B73: =IF(DATE(YEAR_Y,1,1)+47>DATE(YEAR_Y,12,31),"",DATE(YEAR_Y,1,1)+47) | C73: =IF($B73="","",SUMIFS(Grids!$BQ$12:$EC$111,Grids!$EE$12:$GQ$111,">="&$B73*1000000000,Grids!$EE$12:$GQ$111,"<"&($B73+1)*1000000000)) | D73: =IF($B73="","",SUMIFS(Grids!$BQ$116:$EC$155,Grids!$EE$116:$GQ$155,">="&$B73*1000000000,Grids!$EE$116:$GQ$155,"<"&($B73+1)*1000000000)) | E73: =IF($B73="","",SUMIFS(Grids!$BQ$160:$EC$219,Grids!$EE$160:$GQ$219,">="&$B73*1000000000,Grids!$EE$160:$GQ$219,"<"&($B73+1)*1000000000)) | F73: =IF($B73="","",SUM($C$26:$C73)) | G73: =IF($B73="","",SUM($D$26:$D73)) | H73: =IF($B73="","",SUM($E$26:$E73))
B74: =IF(DATE(YEAR_Y,1,1)+48>DATE(YEAR_Y,12,31),"",DATE(YEAR_Y,1,1)+48) | C74: =IF($B74="","",SUMIFS(Grids!$BQ$12:$EC$111,Grids!$EE$12:$GQ$111,">="&$B74*1000000000,Grids!$EE$12:$GQ$111,"<"&($B74+1)*1000000000)) | D74: =IF($B74="","",SUMIFS(Grids!$BQ$116:$EC$155,Grids!$EE$116:$GQ$155,">="&$B74*1000000000,Grids!$EE$116:$GQ$155,"<"&($B74+1)*1000000000)) | E74: =IF($B74="","",SUMIFS(Grids!$BQ$160:$EC$219,Grids!$EE$160:$GQ$219,">="&$B74*1000000000,Grids!$EE$160:$GQ$219,"<"&($B74+1)*1000000000)) | F74: =IF($B74="","",SUM($C$26:$C74)) | G74: =IF($B74="","",SUM($D$26:$D74)) | H74: =IF($B74="","",SUM($E$26:$E74))
B75: =IF(DATE(YEAR_Y,1,1)+49>DATE(YEAR_Y,12,31),"",DATE(YEAR_Y,1,1)+49) | C75: =IF($B75="","",SUMIFS(Grids!$BQ$12:$EC$111,Grids!$EE$12:$GQ$111,">="&$B75*1000000000,Grids!$EE$12:$GQ$111,"<"&($B75+1)*1000000000)) | D75: =IF($B75="","",SUMIFS(Grids!$BQ$116:$EC$155,Grids!$EE$116:$GQ$155,">="&$B75*1000000000,Grids!$EE$116:$GQ$155,"<"&($B75+1)*1000000000)) | E75: =IF($B75="","",SUMIFS(Grids!$BQ$160:$EC$219,Grids!$EE$160:$GQ$219,">="&$B75*1000000000,Grids!$EE$160:$GQ$219,"<"&($B75+1)*1000000000)) | F75: =IF($B75="","",SUM($C$26:$C75)) | G75: =IF($B75="","",SUM($D$26:$D75)) | H75: =IF($B75="","",SUM($E$26:$E75))
B76: =IF(DATE(YEAR_Y,1,1)+50>DATE(YEAR_Y,12,31),"",DATE(YEAR_Y,1,1)+50) | C76: =IF($B76="","",SUMIFS(Grids!$BQ$12:$EC$111,Grids!$EE$12:$GQ$111,">="&$B76*1000000000,Grids!$EE$12:$GQ$111,"<"&($B76+1)*1000000000)) | D76: =IF($B76="","",SUMIFS(Grids!$BQ$116:$EC$155,Grids!$EE$116:$GQ$155,">="&$B76*1000000000,Grids!$EE$116:$GQ$155,"<"&($B76+1)*1000000000)) | E76: =IF($B76="","",SUMIFS(Grids!$BQ$160:$EC$219,Grids!$EE$160:$GQ$219,">="&$B76*1000000000,Grids!$EE$160:$GQ$219,"<"&($B76+1)*1000000000)) | F76: =IF($B76="","",SUM($C$26:$C76)) | G76: =IF($B76="","",SUM($D$26:$D76)) | H76: =IF($B76="","",SUM($E$26:$E76))
B77: =IF(DATE(YEAR_Y,1,1)+51>DATE(YEAR_Y,12,31),"",DATE(YEAR_Y,1,1)+51) | C77: =IF($B77="","",SUMIFS(Grids!$BQ$12:$EC$111,Grids!$EE$12:$GQ$111,">="&$B77*1000000000,Grids!$EE$12:$GQ$111,"<"&($B77+1)*1000000000)) | D77: =IF($B77="","",SUMIFS(Grids!$BQ$116:$EC$155,Grids!$EE$116:$GQ$155,">="&$B77*1000000000,Grids!$EE$116:$GQ$155,"<"&($B77+1)*1000000000)) | E77: =IF($B77="","",SUMIFS(Grids!$BQ$160:$EC$219,Grids!$EE$160:$GQ$219,">="&$B77*1000000000,Grids!$EE$160:$GQ$219,"<"&($B77+1)*1000000000)) | F77: =IF($B77="","",SUM($C$26:$C77)) | G77: =IF($B77="","",SUM($D$26:$D77)) | H77: =IF($B77="","",SUM($E$26:$E77))
B78: =IF(DATE(YEAR_Y,1,1)+52>DATE(YEAR_Y,12,31),"",DATE(YEAR_Y,1,1)+52) | C78: =IF($B78="","",SUMIFS(Grids!$BQ$12:$EC$111,Grids!$EE$12:$GQ$111,">="&$B78*1000000000,Grids!$EE$12:$GQ$111,"<"&($B78+1)*1000000000)) | D78: =IF($B78="","",SUMIFS(Grids!$BQ$116:$EC$155,Grids!$EE$116:$GQ$155,">="&$B78*1000000000,Grids!$EE$116:$GQ$155,"<"&($B78+1)*1000000000)) | E78: =IF($B78="","",SUMIFS(Grids!$BQ$160:$EC$219,Grids!$EE$160:$GQ$219,">="&$B78*1000000000,Grids!$EE$160:$GQ$219,"<"&($B78+1)*1000000000)) | F78: =IF($B78="","",SUM($C$26:$C78)) | G78: =IF($B78="","",SUM($D$26:$D78)) | H78: =IF($B78="","",SUM($E$26:$E78))
B79: =IF(DATE(YEAR_Y,1,1)+53>DATE(YEAR_Y,12,31),"",DATE(YEAR_Y,1,1)+53) | C79: =IF($B79="","",SUMIFS(Grids!$BQ$12:$EC$111,Grids!$EE$12:$GQ$111,">="&$B79*1000000000,Grids!$EE$12:$GQ$111,"<"&($B79+1)*1000000000)) | D79: =IF($B79="","",SUMIFS(Grids!$BQ$116:$EC$155,Grids!$EE$116:$GQ$155,">="&$B79*1000000000,Grids!$EE$116:$GQ$155,"<"&($B79+1)*1000000000)) | E79: =IF($B79="","",SUMIFS(Grids!$BQ$160:$EC$219,Grids!$EE$160:$GQ$219,">="&$B79*1000000000,Grids!$EE$160:$GQ$219,"<"&($B79+1)*1000000000)) | F79: =IF($B79="","",SUM($C$26:$C79)) | G79: =IF($B79="","",SUM($D$26:$D79)) | H79: =IF($B79="","",SUM($E$26:$E79))
B80: =IF(DATE(YEAR_Y,1,1)+54>DATE(YEAR_Y,12,31),"",DATE(YEAR_Y,1,1)+54) | C80: =IF($B80="","",SUMIFS(Grids!$BQ$12:$EC$111,Grids!$EE$12:$GQ$111,">="&$B80*1000000000,Grids!$EE$12:$GQ$111,"<"&($B80+1)*1000000000)) | D80: =IF($B80="","",SUMIFS(Grids!$BQ$116:$EC$155,Grids!$EE$116:$GQ$155,">="&$B80*1000000000,Grids!$EE$116:$GQ$155,"<"&($B80+1)*1000000000)) | E80: =IF($B80="","",SUMIFS(Grids!$BQ$160:$EC$219,Grids!$EE$160:$GQ$219,">="&$B80*1000000000,Grids!$EE$160:$GQ$219,"<"&($B80+1)*1000000000)) | F80: =IF($B80="","",SUM($C$26:$C80)) | G80: =IF($B80="","",SUM($D$26:$D80)) | H80: =IF($B80="","",SUM($E$26:$E80))
B81: =IF(DATE(YEAR_Y,1,1)+55>DATE(YEAR_Y,12,31),"",DATE(YEAR_Y,1,1)+55) | C81: =IF($B81="","",SUMIFS(Grids!$BQ$12:$EC$111,Grids!$EE$12:$GQ$111,">="&$B81*1000000000,Grids!$EE$12:$GQ$111,"<"&($B81+1)*1000000000)) | D81: =IF($B81="","",SUMIFS(Grids!$BQ$116:$EC$155,Grids!$EE$116:$GQ$155,">="&$B81*1000000000,Grids!$EE$116:$GQ$155,"<"&($B81+1)*1000000000)) | E81: =IF($B81="","",SUMIFS(Grids!$BQ$160:$EC$219,Grids!$EE$160:$GQ$219,">="&$B81*1000000000,Grids!$EE$160:$GQ$219,"<"&($B81+1)*1000000000)) | F81: =IF($B81="","",SUM($C$26:$C81)) | G81: =IF($B81="","",SUM($D$26:$D81)) | H81: =IF($B81="","",SUM($E$26:$E81))
B82: =IF(DATE(YEAR_Y,1,1)+56>DATE(YEAR_Y,12,31),"",DATE(YEAR_Y,1,1)+56) | C82: =IF($B82="","",SUMIFS(Grids!$BQ$12:$EC$111,Grids!$EE$12:$GQ$111,">="&$B82*1000000000,Grids!$EE$12:$GQ$111,"<"&($B82+1)*1000000000)) | D82: =IF($B82="","",SUMIFS(Grids!$BQ$116:$EC$155,Grids!$EE$116:$GQ$155,">="&$B82*1000000000,Grids!$EE$116:$GQ$155,"<"&($B82+1)*1000000000)) | E82: =IF($B82="","",SUMIFS(Grids!$BQ$160:$EC$219,Grids!$EE$160:$GQ$219,">="&$B82*1000000000,Grids!$EE$160:$GQ$219,"<"&($B82+1)*1000000000)) | F82: =IF($B82="","",SUM($C$26:$C82)) | G82: =IF($B82="","",SUM($D$26:$D82)) | H82: =IF($B82="","",SUM($E$26:$E82))
B83: =IF(DATE(YEAR_Y,1,1)+57>DATE(YEAR_Y,12,31),"",DATE(YEAR_Y,1,1)+57) | C83: =IF($B83="","",SUMIFS(Grids!$BQ$12:$EC$111,Grids!$EE$12:$GQ$111,">="&$B83*1000000000,Grids!$EE$12:$GQ$111,"<"&($B83+1)*1000000000)) | D83: =IF($B83="","",SUMIFS(Grids!$BQ$116:$EC$155,Grids!$EE$116:$GQ$155,">="&$B83*1000000000,Grids!$EE$116:$GQ$155,"<"&($B83+1)*1000000000)) | E83: =IF($B83="","",SUMIFS(Grids!$BQ$160:$EC$219,Grids!$EE$160:$GQ$219,">="&$B83*1000000000,Grids!$EE$160:$GQ$219,"<"&($B83+1)*1000000000)) | F83: =IF($B83="","",SUM($C$26:$C83)) | G83: =IF($B83="","",SUM($D$26:$D83)) | H83: =IF($B83="","",SUM($E$26:$E83))
B84: =IF(DATE(YEAR_Y,1,1)+58>DATE(YEAR_Y,12,31),"",DATE(YEAR_Y,1,1)+58) | C84: =IF($B84="","",SUMIFS(Grids!$BQ$12:$EC$111,Grids!$EE$12:$GQ$111,">="&$B84*1000000000,Grids!$EE$12:$GQ$111,"<"&($B84+1)*1000000000)) | D84: =IF($B84="","",SUMIFS(Grids!$BQ$116:$EC$155,Grids!$EE$116:$GQ$155,">="&$B84*1000000000,Grids!$EE$116:$GQ$155,"<"&($B84+1)*1000000000)) | E84: =IF($B84="","",SUMIFS(Grids!$BQ$160:$EC$219,Grids!$EE$160:$GQ$219,">="&$B84*1000000000,Grids!$EE$160:$GQ$219,"<"&($B84+1)*1000000000)) | F84: =IF($B84="","",SUM($C$26:$C84)) | G84: =IF($B84="","",SUM($D$26:$D84)) | H84: =IF($B84="","",SUM($E$26:$E84))
B85: =IF(DATE(YEAR_Y,1,1)+59>DATE(YEAR_Y,12,31),"",DATE(YEAR_Y,1,1)+59) | C85: =IF($B85="","",SUMIFS(Grids!$BQ$12:$EC$111,Grids!$EE$12:$GQ$111,">="&$B85*1000000000,Grids!$EE$12:$GQ$111,"<"&($B85+1)*1000000000)) | D85: =IF($B85="","",SUMIFS(Grids!$BQ$116:$EC$155,Grids!$EE$116:$GQ$155,">="&$B85*1000000000,Grids!$EE$116:$GQ$155,"<"&($B85+1)*1000000000)) | E85: =IF($B85="","",SUMIFS(Grids!$BQ$160:$EC$219,Grids!$EE$160:$GQ$219,">="&$B85*1000000000,Grids!$EE$160:$GQ$219,"<"&($B85+1)*1000000000)) | F85: =IF($B85="","",SUM($C$26:$C85)) | G85: =IF($B85="","",SUM($D$26:$D85)) | H85: =IF($B85="","",SUM($E$26:$E85))
B86: =IF(DATE(YEAR_Y,1,1)+60>DATE(YEAR_Y,12,31),"",DATE(YEAR_Y,1,1)+60) | C86: =IF($B86="","",SUMIFS(Grids!$BQ$12:$EC$111,Grids!$EE$12:$GQ$111,">="&$B86*1000000000,Grids!$EE$12:$GQ$111,"<"&($B86+1)*1000000000)) | D86: =IF($B86="","",SUMIFS(Grids!$BQ$116:$EC$155,Grids!$EE$116:$GQ$155,">="&$B86*1000000000,Grids!$EE$116:$GQ$155,"<"&($B86+1)*1000000000)) | E86: =IF($B86="","",SUMIFS(Grids!$BQ$160:$EC$219,Grids!$EE$160:$GQ$219,">="&$B86*1000000000,Grids!$EE$160:$GQ$219,"<"&($B86+1)*1000000000)) | F86: =IF($B86="","",SUM($C$26:$C86)) | G86: =IF($B86="","",SUM($D$26:$D86)) | H86: =IF($B86="","",SUM($E$26:$E86))
B87: =IF(DATE(YEAR_Y,1,1)+61>DATE(YEAR_Y,12,31),"",DATE(YEAR_Y,1,1)+61) | C87: =IF($B87="","",SUMIFS(Grids!$BQ$12:$EC$111,Grids!$EE$12:$GQ$111,">="&$B87*1000000000,Grids!$EE$12:$GQ$111,"<"&($B87+1)*1000000000)) | D87: =IF($B87="","",SUMIFS(Grids!$BQ$116:$EC$155,Grids!$EE$116:$GQ$155,">="&$B87*1000000000,Grids!$EE$116:$GQ$155,"<"&($B87+1)*1000000000)) | E87: =IF($B87="","",SUMIFS(Grids!$BQ$160:$EC$219,Grids!$EE$160:$GQ$219,">="&$B87*1000000000,Grids!$EE$160:$GQ$219,"<"&($B87+1)*1000000000)) | F87: =IF($B87="","",SUM($C$26:$C87)) | G87: =IF($B87="","",SUM($D$26:$D87)) | H87: =IF($B87="","",SUM($E$26:$E87))
B88: =IF(DATE(YEAR_Y,1,1)+62>DATE(YEAR_Y,12,31),"",DATE(YEAR_Y,1,1)+62) | C88: =IF($B88="","",SUMIFS(Grids!$BQ$12:$EC$111,Grids!$EE$12:$GQ$111,">="&$B88*1000000000,Grids!$EE$12:$GQ$111,"<"&($B88+1)*1000000000)) | D88: =IF($B88="","",SUMIFS(Grids!$BQ$116:$EC$155,Grids!$EE$116:$GQ$155,">="&$B88*1000000000,Grids!$EE$116:$GQ$155,"<"&($B88+1)*1000000000)) | E88: =IF($B88="","",SUMIFS(Grids!$BQ$160:$EC$219,Grids!$EE$160:$GQ$219,">="&$B88*1000000000,Grids!$EE$160:$GQ$219,"<"&($B88+1)*1000000000)) | F88: =IF($B88="","",SUM($C$26:$C88)) | G88: =IF($B88="","",SUM($D$26:$D88)) | H88: =IF($B88="","",SUM($E$26:$E88))
B89: =IF(DATE(YEAR_Y,1,1)+63>DATE(YEAR_Y,12,31),"",DATE(YEAR_Y,1,1)+63) | C89: =IF($B89="","",SUMIFS(Grids!$BQ$12:$EC$111,Grids!$EE$12:$GQ$111,">="&$B89*1000000000,Grids!$EE$12:$GQ$111,"<"&($B89+1)*1000000000)) | D89: =IF($B89="","",SUMIFS(Grids!$BQ$116:$EC$155,Grids!$EE$116:$GQ$155,">="&$B89*1000000000,Grids!$EE$116:$GQ$155,"<"&($B89+1)*1000000000)) | E89: =IF($B89="","",SUMIFS(Grids!$BQ$160:$EC$219,Grids!$EE$160:$GQ$219,">="&$B89*1000000000,Grids!$EE$160:$GQ$219,"<"&($B89+1)*1000000000)) | F89: =IF($B89="","",SUM($C$26:$C89)) | G89: =IF($B89="","",SUM($D$26:$D89)) | H89: =IF($B89="","",SUM($E$26:$E89))
B90: =IF(DATE(YEAR_Y,1,1)+64>DATE(YEAR_Y,12,31),"",DATE(YEAR_Y,1,1)+64) | C90: =IF($B90="","",SUMIFS(Grids!$BQ$12:$EC$111,Grids!$EE$12:$GQ$111,">="&$B90*1000000000,Grids!$EE$12:$GQ$111,"<"&($B90+1)*1000000000)) | D90: =IF($B90="","",SUMIFS(Grids!$BQ$116:$EC$155,Grids!$EE$116:$GQ$155,">="&$B90*1000000000,Grids!$EE$116:$GQ$155,"<"&($B90+1)*1000000000)) | E90: =IF($B90="","",SUMIFS(Grids!$BQ$160:$EC$219,Grids!$EE$160:$GQ$219,">="&$B90*1000000000,Grids!$EE$160:$GQ$219,"<"&($B90+1)*1000000000)) | F90: =IF($B90="","",SUM($C$26:$C90)) | G90: =IF($B90="","",SUM($D$26:$D90)) | H90: =IF($B90="","",SUM($E$26:$E90))
B91: =IF(DATE(YEAR_Y,1,1)+65>DATE(YEAR_Y,12,31),"",DATE(YEAR_Y,1,1)+65) | C91: =IF($B91="","",SUMIFS(Grids!$BQ$12:$EC$111,Grids!$EE$12:$GQ$111,">="&$B91*1000000000,Grids!$EE$12:$GQ$111,"<"&($B91+1)*1000000000)) | D91: =IF($B91="","",SUMIFS(Grids!$BQ$116:$EC$155,Grids!$EE$116:$GQ$155,">="&$B91*1000000000,Grids!$EE$116:$GQ$155,"<"&($B91+1)*1000000000)) | E91: =IF($B91="","",SUMIFS(Grids!$BQ$160:$EC$219,Grids!$EE$160:$GQ$219,">="&$B91*1000000000,Grids!$EE$160:$GQ$219,"<"&($B91+1)*1000000000)) | F91: =IF($B91="","",SUM($C$26:$C91)) | G91: =IF($B91="","",SUM($D$26:$D91)) | H91: =IF($B91="","",SUM($E$26:$E91))
B92: =IF(DATE(YEAR_Y,1,1)+66>DATE(YEAR_Y,12,31),"",DATE(YEAR_Y,1,1)+66) | C92: =IF($B92="","",SUMIFS(Grids!$BQ$12:$EC$111,Grids!$EE$12:$GQ$111,">="&$B92*1000000000,Grids!$EE$12:$GQ$111,"<"&($B92+1)*1000000000)) | D92: =IF($B92="","",SUMIFS(Grids!$BQ$116:$EC$155,Grids!$EE$116:$GQ$155,">="&$B92*1000000000,Grids!$EE$116:$GQ$155,"<"&($B92+1)*1000000000)) | E92: =IF($B92="","",SUMIFS(Grids!$BQ$160:$EC$219,Grids!$EE$160:$GQ$219,">="&$B92*1000000000,Grids!$EE$160:$GQ$219,"<"&($B92+1)*1000000000)) | F92: =IF($B92="","",SUM($C$26:$C92)) | G92: =IF($B92="","",SUM($D$26:$D92)) | H92: =IF($B92="","",SUM($E$26:$E92))
B93: =IF(DATE(YEAR_Y,1,1)+67>DATE(YEAR_Y,12,31),"",DATE(YEAR_Y,1,1)+67) | C93: =IF($B93="","",SUMIFS(Grids!$BQ$12:$EC$111,Grids!$EE$12:$GQ$111,">="&$B93*1000000000,Grids!$EE$12:$GQ$111,"<"&($B93+1)*1000000000)) | D93: =IF($B93="","",SUMIFS(Grids!$BQ$116:$EC$155,Grids!$EE$116:$GQ$155,">="&$B93*1000000000,Grids!$EE$116:$GQ$155,"<"&($B93+1)*1000000000)) | E93: =IF($B93="","",SUMIFS(Grids!$BQ$160:$EC$219,Grids!$EE$160:$GQ$219,">="&$B93*1000000000,Grids!$EE$160:$GQ$219,"<"&($B93+1)*1000000000)) | F93: =IF($B93="","",SUM($C$26:$C93)) | G93: =IF($B93="","",SUM($D$26:$D93)) | H93: =IF($B93="","",SUM($E$26:$E93))
B94: =IF(DATE(YEAR_Y,1,1)+68>DATE(YEAR_Y,12,31),"",DATE(YEAR_Y,1,1)+68) | C94: =IF($B94="","",SUMIFS(Grids!$BQ$12:$EC$111,Grids!$EE$12:$GQ$111,">="&$B94*1000000000,Grids!$EE$12:$GQ$111,"<"&($B94+1)*1000000000)) | D94: =IF($B94="","",SUMIFS(Grids!$BQ$116:$EC$155,Grids!$EE$116:$GQ$155,">="&$B94*1000000000,Grids!$EE$116:$GQ$155,"<"&($B94+1)*1000000000)) | E94: =IF($B94="","",SUMIFS(Grids!$BQ$160:$EC$219,Grids!$EE$160:$GQ$219,">="&$B94*1000000000,Grids!$EE$160:$GQ$219,"<"&($B94+1)*1000000000)) | F94: =IF($B94="","",SUM($C$26:$C94)) | G94: =IF($B94="","",SUM($D$26:$D94)) | H94: =IF($B94="","",SUM($E$26:$E94))
B95: =IF(DATE(YEAR_Y,1,1)+69>DATE(YEAR_Y,12,31),"",DATE(YEAR_Y,1,1)+69) | C95: =IF($B95="","",SUMIFS(Grids!$BQ$12:$EC$111,Grids!$EE$12:$GQ$111,">="&$B95*1000000000,Grids!$EE$12:$GQ$111,"<"&($B95+1)*1000000000)) | D95: =IF($B95="","",SUMIFS(Grids!$BQ$116:$EC$155,Grids!$EE$116:$GQ$155,">="&$B95*1000000000,Grids!$EE$116:$GQ$155,"<"&($B95+1)*1000000000)) | E95: =IF($B95="","",SUMIFS(Grids!$BQ$160:$EC$219,Grids!$EE$160:$GQ$219,">="&$B95*1000000000,Grids!$EE$160:$GQ$219,"<"&($B95+1)*1000000000)) | F95: =IF($B95="","",SUM($C$26:$C95)) | G95: =IF($B95="","",SUM($D$26:$D95)) | H95: =IF($B95="","",SUM($E$26:$E95))
B96: =IF(DATE(YEAR_Y,1,1)+70>DATE(YEAR_Y,12,31),"",DATE(YEAR_Y,1,1)+70) | C96: =IF($B96="","",SUMIFS(Grids!$BQ$12:$EC$111,Grids!$EE$12:$GQ$111,">="&$B96*1000000000,Grids!$EE$12:$GQ$111,"<"&($B96+1)*1000000000)) | D96: =IF($B96="","",SUMIFS(Grids!$BQ$116:$EC$155,Grids!$EE$116:$GQ$155,">="&$B96*1000000000,Grids!$EE$116:$GQ$155,"<"&($B96+1)*1000000000)) | E96: =IF($B96="","",SUMIFS(Grids!$BQ$160:$EC$219,Grids!$EE$160:$GQ$219,">="&$B96*1000000000,Grids!$EE$160:$GQ$219,"<"&($B96+1)*1000000000)) | F96: =IF($B96="","",SUM($C$26:$C96)) | G96: =IF($B96="","",SUM($D$26:$D96)) | H96: =IF($B96="","",SUM($E$26:$E96))
B97: =IF(DATE(YEAR_Y,1,1)+71>DATE(YEAR_Y,12,31),"",DATE(YEAR_Y,1,1)+71) | C97: =IF($B97="","",SUMIFS(Grids!$BQ$12:$EC$111,Grids!$EE$12:$GQ$111,">="&$B97*1000000000,Grids!$EE$12:$GQ$111,"<"&($B97+1)*1000000000)) | D97: =IF($B97="","",SUMIFS(Grids!$BQ$116:$EC$155,Grids!$EE$116:$GQ$155,">="&$B97*1000000000,Grids!$EE$116:$GQ$155,"<"&($B97+1)*1000000000)) | E97: =IF($B97="","",SUMIFS(Grids!$BQ$160:$EC$219,Grids!$EE$160:$GQ$219,">="&$B97*1000000000,Grids!$EE$160:$GQ$219,"<"&($B97+1)*1000000000)) | F97: =IF($B97="","",SUM($C$26:$C97)) | G97: =IF($B97="","",SUM($D$26:$D97)) | H97: =IF($B97="","",SUM($E$26:$E97))
B98: =IF(DATE(YEAR_Y,1,1)+72>DATE(YEAR_Y,12,31),"",DATE(YEAR_Y,1,1)+72) | C98: =IF($B98="","",SUMIFS(Grids!$BQ$12:$EC$111,Grids!$EE$12:$GQ$111,">="&$B98*1000000000,Grids!$EE$12:$GQ$111,"<"&($B98+1)*1000000000)) | D98: =IF($B98="","",SUMIFS(Grids!$BQ$116:$EC$155,Grids!$EE$116:$GQ$155,">="&$B98*1000000000,Grids!$EE$116:$GQ$155,"<"&($B98+1)*1000000000)) | E98: =IF($B98="","",SUMIFS(Grids!$BQ$160:$EC$219,Grids!$EE$160:$GQ$219,">="&$B98*1000000000,Grids!$EE$160:$GQ$219,"<"&($B98+1)*1000000000)) | F98: =IF($B98="","",SUM($C$26:$C98)) | G98: =IF($B98="","",SUM($D$26:$D98)) | H98: =IF($B98="","",SUM($E$26:$E98))
B99: =IF(DATE(YEAR_Y,1,1)+73>DATE(YEAR_Y,12,31),"",DATE(YEAR_Y,1,1)+73) | C99: =IF($B99="","",SUMIFS(Grids!$BQ$12:$EC$111,Grids!$EE$12:$GQ$111,">="&$B99*1000000000,Grids!$EE$12:$GQ$111,"<"&($B99+1)*1000000000)) | D99: =IF($B99="","",SUMIFS(Grids!$BQ$116:$EC$155,Grids!$EE$116:$GQ$155,">="&$B99*1000000000,Grids!$EE$116:$GQ$155,"<"&($B99+1)*1000000000)) | E99: =IF($B99="","",SUMIFS(Grids!$BQ$160:$EC$219,Grids!$EE$160:$GQ$219,">="&$B99*1000000000,Grids!$EE$160:$GQ$219,"<"&($B99+1)*1000000000)) | F99: =IF($B99="","",SUM($C$26:$C99)) | G99: =IF($B99="","",SUM($D$26:$D99)) | H99: =IF($B99="","",SUM($E$26:$E99))
B100: =IF(DATE(YEAR_Y,1,1)+74>DATE(YEAR_Y,12,31),"",DATE(YEAR_Y,1,1)+74) | C100: =IF($B100="","",SUMIFS(Grids!$BQ$12:$EC$111,Grids!$EE$12:$GQ$111,">="&$B100*1000000000,Grids!$EE$12:$GQ$111,"<"&($B100+1)*1000000000)) | D100: =IF($B100="","",SUMIFS(Grids!$BQ$116:$EC$155,Grids!$EE$116:$GQ$155,">="&$B100*1000000000,Grids!$EE$116:$GQ$155,"<"&($B100+1)*1000000000)) | E100: =IF($B100="","",SUMIFS(Grids!$BQ$160:$EC$219,Grids!$EE$160:$GQ$219,">="&$B100*1000000000,Grids!$EE$160:$GQ$219,"<"&($B100+1)*1000000000)) | F100: =IF($B100="","",SUM($C$26:$C100)) | G100: =IF($B100="","",SUM($D$26:$D100)) | H100: =IF($B100="","",SUM($E$26:$E100))
B101: =IF(DATE(YEAR_Y,1,1)+75>DATE(YEAR_Y,12,31),"",DATE(YEAR_Y,1,1)+75) | C101: =IF($B101="","",SUMIFS(Grids!$BQ$12:$EC$111,Grids!$EE$12:$GQ$111,">="&$B101*1000000000,Grids!$EE$12:$GQ$111,"<"&($B101+1)*1000000000)) | D101: =IF($B101="","",SUMIFS(Grids!$BQ$116:$EC$155,Grids!$EE$116:$GQ$155,">="&$B101*1000000000,Grids!$EE$116:$GQ$155,"<"&($B101+1)*1000000000)) | E101: =IF($B101="","",SUMIFS(Grids!$BQ$160:$EC$219,Grids!$EE$160:$GQ$219,">="&$B101*1000000000,Grids!$EE$160:$GQ$219,"<"&($B101+1)*1000000000)) | F101: =IF($B101="","",SUM($C$26:$C101)) | G101: =IF($B101="","",SUM($D$26:$D101)) | H101: =IF($B101="","",SUM($E$26:$E101))
B102: =IF(DATE(YEAR_Y,1,1)+76>DATE(YEAR_Y,12,31),"",DATE(YEAR_Y,1,1)+76) | C102: =IF($B102="","",SUMIFS(Grids!$BQ$12:$EC$111,Grids!$EE$12:$GQ$111,">="&$B102*1000000000,Grids!$EE$12:$GQ$111,"<"&($B102+1)*1000000000)) | D102: =IF($B102="","",SUMIFS(Grids!$BQ$116:$EC$155,Grids!$EE$116:$GQ$155,">="&$B102*1000000000,Grids!$EE$116:$GQ$155,"<"&($B102+1)*1000000000)) | E102: =IF($B102="","",SUMIFS(Grids!$BQ$160:$EC$219,Grids!$EE$160:$GQ$219,">="&$B102*1000000000,Grids!$EE$160:$GQ$219,"<"&($B102+1)*1000000000)) | F102: =IF($B102="","",SUM($C$26:$C102)) | G102: =IF($B102="","",SUM($D$26:$D102)) | H102: =IF($B102="","",SUM($E$26:$E102))
B103: =IF(DATE(YEAR_Y,1,1)+77>DATE(YEAR_Y,12,31),"",DATE(YEAR_Y,1,1)+77) | C103: =IF($B103="","",SUMIFS(Grids!$BQ$12:$EC$111,Grids!$EE$12:$GQ$111,">="&$B103*1000000000,Grids!$EE$12:$GQ$111,"<"&($B103+1)*1000000000)) | D103: =IF($B103="","",SUMIFS(Grids!$BQ$116:$EC$155,Grids!$EE$116:$GQ$155,">="&$B103*1000000000,Grids!$EE$116:$GQ$155,"<"&($B103+1)*1000000000)) | E103: =IF($B103="","",SUMIFS(Grids!$BQ$160:$EC$219,Grids!$EE$160:$GQ$219,">="&$B103*1000000000,Grids!$EE$160:$GQ$219,"<"&($B103+1)*1000000000)) | F103: =IF($B103="","",SUM($C$26:$C103)) | G103: =IF($B103="","",SUM($D$26:$D103)) | H103: =IF($B103="","",SUM($E$26:$E103))
B104: =IF(DATE(YEAR_Y,1,1)+78>DATE(YEAR_Y,12,31),"",DATE(YEAR_Y,1,1)+78) | C104: =IF($B104="","",SUMIFS(Grids!$BQ$12:$EC$111,Grids!$EE$12:$GQ$111,">="&$B104*1000000000,Grids!$EE$12:$GQ$111,"<"&($B104+1)*1000000000)) | D104: =IF($B104="","",SUMIFS(Grids!$BQ$116:$EC$155,Grids!$EE$116:$GQ$155,">="&$B104*1000000000,Grids!$EE$116:$GQ$155,"<"&($B104+1)*1000000000)) | E104: =IF($B104="","",SUMIFS(Grids!$BQ$160:$EC$219,Grids!$EE$160:$GQ$219,">="&$B104*1000000000,Grids!$EE$160:$GQ$219,"<"&($B104+1)*1000000000)) | F104: =IF($B104="","",SUM($C$26:$C104)) | G104: =IF($B104="","",SUM($D$26:$D104)) | H104: =IF($B104="","",SUM($E$26:$E104))
B105: =IF(DATE(YEAR_Y,1,1)+79>DATE(YEAR_Y,12,31),"",DATE(YEAR_Y,1,1)+79) | C105: =IF($B105="","",SUMIFS(Grids!$BQ$12:$EC$111,Grids!$EE$12:$GQ$111,">="&$B105*1000000000,Grids!$EE$12:$GQ$111,"<"&($B105+1)*1000000000)) | D105: =IF($B105="","",SUMIFS(Grids!$BQ$116:$EC$155,Grids!$EE$116:$GQ$155,">="&$B105*1000000000,Grids!$EE$116:$GQ$155,"<"&($B105+1)*1000000000)) | E105: =IF($B105="","",SUMIFS(Grids!$BQ$160:$EC$219,Grids!$EE$160:$GQ$219,">="&$B105*1000000000,Grids!$EE$160:$GQ$219,"<"&($B105+1)*1000000000)) | F105: =IF($B105="","",SUM($C$26:$C105)) | G105: =IF($B105="","",SUM($D$26:$D105)) | H105: =IF($B105="","",SUM($E$26:$E105))
...

Sheet Fundamentals
B1: FUNDAMENTALS - WHAT PAYS THE DIVIDEND
B2: DPS is per share, declared currency, on an ex-date clock; EPS and payout are fiscal; yield Y-n = DPS Y-n x FX / that year-end price. Filter with the header arrows; never sort.
B4: Flag thresholds | C4: payout above | D4: 1 | E4: FCF cover below | F4: 1 | G4: ND/EBITDA above | H4: 3
B5: Fundamentals pulls | C5: =IF(PULL_FUND="Y","ON - amber columns live","OFF - amber columns blank (Summary C16)")
B8: Jump to: | C8: DPS | D8: Yields | E8: EPS | F8: Payout | G8: Buybacks | H8: Balance sheet | I8: Sector tables
B10: WHO | F10: DPS BY EX-DATE YEAR (per share, declared ccy - cash types only) | P10: DIVIDEND YIELD BY YEAR | X10: EPS BY FISCAL YEAR | AE10: PAYOUT | AN10: BUYBACKS (LTM / mkt cap) | AS10: BALANCE SHEET & CASH
B11: Index | C11: Ticker | D11: Name | E11: GICS Sector | F11: DPS Y-5 | G11: DPS Y-4 | H11: DPS Y-3 | I11: DPS Y-2 | J11: DPS Y-1 | K11: DPS YTD | L11: DPS to come | M11: MODEL DPS yr Y | N11: Fwd DPS (street) | O11: 5Y avg DPS | P11: Yld Y-5 | Q11: Yld Y-4 | R11: Yld Y-3 | S11: Yld Y-2 | T11: Yld Y-1 | U11: Dvd yld 12M | V11: MODEL fwd yld | W11: Street fwd yld | X11: EPS Y-5 | Y11: EPS Y-4 | Z11: EPS Y-3 | AA11: EPS Y-2 | AB11: EPS Y-1 | AC11: 5Y avg EPS | AD11: Fwd EPS (street) | AE11: Payout Y-5 | AF11: Payout Y-4 | AG11: Payout Y-3 | AH11: Payout Y-2 | AI11: Payout Y-1 | AJ11: 5Y avg payout | AK11: Fwd payout (street) | AL11: MODEL payout (Y) | AM11: Payout trend | AN11: Buyback Y-4 | AO11: Buyback Y-3 | AP11: Buyback Y-2 | AQ11: Buyback Y-1 | AR11: Bb+dvd yield | AS11: ND/E Y-2 | AT11: ND/E Y-1 | AU11: Net debt /EBITDA | AV11: EBITDA /interest | AW11: FCF yld | AX11: FCF cover | AY11: Watch | AZ11: Dvd ccy
B12: HSI | C12: =IF(HSI!$C$7="","",HSI!$C$7) | D12: =IF($C12="","",HSI!$D$7) | E12: =IF($C12="","",HSI!$E$7) | F12: =IF($C12="","",SUMPRODUCT(('Dvd Calendar'!$E$11:$AR$11>=DATE(YEAR_Y-5,1,1))*('Dvd Calendar'!$E$11:$AR$11<=DATE(YEAR_Y-5,12,31))*'Dvd Calendar'!$E$14:$AR$14*(('Dvd Calendar'!$E$16:$AR$16=TYPE1)*(TYPE1<>"")+('Dvd Calendar'!$E$16:$AR$16=TYPE2)*(TYPE2<>"")+('Dvd Calendar'!$E$16:$AR$16=TYPE3)*(TYPE3<>"")+('Dvd Calendar'!$E$16:$AR$16=TYPE4)*(TYPE4<>"")+('Dvd Calendar'!$E$16:$AR$16=SPECIAL_LBL)*(INC_SPECIALS="Y")))) | G12: =IF($C12="","",SUMPRODUCT(('Dvd Calendar'!$E$11:$AR$11>=DATE(YEAR_Y-4,1,1))*('Dvd Calendar'!$E$11:$AR$11<=DATE(YEAR_Y-4,12,31))*'Dvd Calendar'!$E$14:$AR$14*(('Dvd Calendar'!$E$16:$AR$16=TYPE1)*(TYPE1<>"")+('Dvd Calendar'!$E$16:$AR$16=TYPE2)*(TYPE2<>"")+('Dvd Calendar'!$E$16:$AR$16=TYPE3)*(TYPE3<>"")+('Dvd Calendar'!$E$16:$AR$16=TYPE4)*(TYPE4<>"")+('Dvd Calendar'!$E$16:$AR$16=SPECIAL_LBL)*(INC_SPECIALS="Y")))) | H12: =IF($C12="","",SUMPRODUCT(('Dvd Calendar'!$E$11:$AR$11>=DATE(YEAR_Y-3,1,1))*('Dvd Calendar'!$E$11:$AR$11<=DATE(YEAR_Y-3,12,31))*'Dvd Calendar'!$E$14:$AR$14*(('Dvd Calendar'!$E$16:$AR$16=TYPE1)*(TYPE1<>"")+('Dvd Calendar'!$E$16:$AR$16=TYPE2)*(TYPE2<>"")+('Dvd Calendar'!$E$16:$AR$16=TYPE3)*(TYPE3<>"")+('Dvd Calendar'!$E$16:$AR$16=TYPE4)*(TYPE4<>"")+('Dvd Calendar'!$E$16:$AR$16=SPECIAL_LBL)*(INC_SPECIALS="Y")))) | I12: =IF($C12="","",SUMPRODUCT(('Dvd Calendar'!$E$11:$AR$11>=DATE(YEAR_Y-2,1,1))*('Dvd Calendar'!$E$11:$AR$11<=DATE(YEAR_Y-2,12,31))*'Dvd Calendar'!$E$14:$AR$14*(('Dvd Calendar'!$E$16:$AR$16=TYPE1)*(TYPE1<>"")+('Dvd Calendar'!$E$16:$AR$16=TYPE2)*(TYPE2<>"")+('Dvd Calendar'!$E$16:$AR$16=TYPE3)*(TYPE3<>"")+('Dvd Calendar'!$E$16:$AR$16=TYPE4)*(TYPE4<>"")+('Dvd Calendar'!$E$16:$AR$16=SPECIAL_LBL)*(INC_SPECIALS="Y")))) | J12: =IF($C12="","",SUMPRODUCT(('Dvd Calendar'!$E$11:$AR$11>=DATE(YEAR_Y-1,1,1))*('Dvd Calendar'!$E$11:$AR$11<=DATE(YEAR_Y-1,12,31))*'Dvd Calendar'!$E$14:$AR$14*(('Dvd Calendar'!$E$16:$AR$16=TYPE1)*(TYPE1<>"")+('Dvd Calendar'!$E$16:$AR$16=TYPE2)*(TYPE2<>"")+('Dvd Calendar'!$E$16:$AR$16=TYPE3)*(TYPE3<>"")+('Dvd Calendar'!$E$16:$AR$16=TYPE4)*(TYPE4<>"")+('Dvd Calendar'!$E$16:$AR$16=SPECIAL_LBL)*(INC_SPECIALS="Y")))) | K12: =IF($C12="","",HSI!$J$7) | L12: =IF($C12="","",HSI!$K$7) | M12: =IF($C12="","",HSI!$J$7+HSI!$L$7) | N12: =IF($C12="","",IF(PULL_FUND="N","",IFERROR(BDP($C12,BESTDPS_FIELD,FWD_OVERRIDE,TEXT(MOD(YEAR_Y,100),"00")&"Y"),""))) | O12: =IF($C12="","",AVERAGE(F12:J12)) | P12: =IF($C12="","",IF(PULL_FUND="N","",IF(COUNTIFS('Fund History'!$J$8:$J$12,">="&DATE(YEAR_Y-5,1,1),'Fund History'!$J$8:$J$12,"<="&DATE(YEAR_Y-5,12,31))=0,"",IFERROR($F12*HSI!$G$7/SUMIFS('Fund History'!$K$8:$K$12,'Fund History'!$J$8:$J$12,">="&DATE(YEAR_Y-5,1,1),'Fund History'!$J$8:$J$12,"<="&DATE(YEAR_Y-5,12,31)),"")))) | Q12: =IF($C12="","",IF(PULL_FUND="N","",IF(COUNTIFS('Fund History'!$J$8:$J$12,">="&DATE(YEAR_Y-4,1,1),'Fund History'!$J$8:$J$12,"<="&DATE(YEAR_Y-4,12,31))=0,"",IFERROR($G12*HSI!$G$7/SUMIFS('Fund History'!$K$8:$K$12,'Fund History'!$J$8:$J$12,">="&DATE(YEAR_Y-4,1,1),'Fund History'!$J$8:$J$12,"<="&DATE(YEAR_Y-4,12,31)),"")))) | R12: =IF($C12="","",IF(PULL_FUND="N","",IF(COUNTIFS('Fund History'!$J$8:$J$12,">="&DATE(YEAR_Y-3,1,1),'Fund History'!$J$8:$J$12,"<="&DATE(YEAR_Y-3,12,31))=0,"",IFERROR($H12*HSI!$G$7/SUMIFS('Fund History'!$K$8:$K$12,'Fund History'!$J$8:$J$12,">="&DATE(YEAR_Y-3,1,1),'Fund History'!$J$8:$J$12,"<="&DATE(YEAR_Y-3,12,31)),"")))) | S12: =IF($C12="","",IF(PULL_FUND="N","",IF(COUNTIFS('Fund History'!$J$8:$J$12,">="&DATE(YEAR_Y-2,1,1),'Fund History'!$J$8:$J$12,"<="&DATE(YEAR_Y-2,12,31))=0,"",IFERROR($I12*HSI!$G$7/SUMIFS('Fund History'!$K$8:$K$12,'Fund History'!$J$8:$J$12,">="&DATE(YEAR_Y-2,1,1),'Fund History'!$J$8:$J$12,"<="&DATE(YEAR_Y-2,12,31)),"")))) | T12: =IF($C12="","",IF(PULL_FUND="N","",IF(COUNTIFS('Fund History'!$J$8:$J$12,">="&DATE(YEAR_Y-1,1,1),'Fund History'!$J$8:$J$12,"<="&DATE(YEAR_Y-1,12,31))=0,"",IFERROR($J12*HSI!$G$7/SUMIFS('Fund History'!$K$8:$K$12,'Fund History'!$J$8:$J$12,">="&DATE(YEAR_Y-1,1,1),'Fund History'!$J$8:$J$12,"<="&DATE(YEAR_Y-1,12,31)),"")))) | U12: =IF($C12="","",IF(ISNUMBER(HSI!$I$7),HSI!$I$7/100,"")) | V12: =IF($C12="","",IF(ISNUMBER(HSI!$X$7),IFERROR($M12*HSI!$G$7/HSI!$X$7,""),"")) | W12: =IF($C12="","",IF(ISNUMBER($N12),IFERROR($N12*HSI!$G$7/HSI!$X$7,""),"")) | X12: =IF($C12="","",IF(PULL_FUND="N","",IFERROR(BDP($C12,EPS_FIELD,YR_OVERRIDE,TEXT(YEAR_Y-5,"0")),""))) | Y12: =IF($C12="","",IF(PULL_FUND="N","",IFERROR(BDP($C12,EPS_FIELD,YR_OVERRIDE,TEXT(YEAR_Y-4,"0")),""))) | Z12: =IF($C12="","",IF(PULL_FUND="N","",IFERROR(BDP($C12,EPS_FIELD,YR_OVERRIDE,TEXT(YEAR_Y-3,"0")),""))) | AA12: =IF($C12="","",IF(PULL_FUND="N","",IFERROR(BDP($C12,EPS_FIELD,YR_OVERRIDE,TEXT(YEAR_Y-2,"0")),""))) | AB12: =IF($C12="","",IF(PULL_FUND="N","",IFERROR(BDP($C12,EPS_FIELD,YR_OVERRIDE,TEXT(YEAR_Y-1,"0")),""))) | AC12: =IF($C12="","",IFERROR(AVERAGE(X12:AB12),"")) | AD12: =IF($C12="","",IF(PULL_FUND="N","",IFERROR(BDP($C12,BESTEPS_FIELD,FWD_OVERRIDE,TEXT(MOD(YEAR_Y,100),"00")&"Y"),""))) | AE12: =IF($C12="","",IF(PULL_FUND="N","",IFERROR(BDP($C12,PAYOUT_FIELD,YR_OVERRIDE,TEXT(YEAR_Y-5,"0"))/100,""))) | AF12: =IF($C12="","",IF(PULL_FUND="N","",IFERROR(BDP($C12,PAYOUT_FIELD,YR_OVERRIDE,TEXT(YEAR_Y-4,"0"))/100,""))) | AG12: =IF($C12="","",IF(PULL_FUND="N","",IFERROR(BDP($C12,PAYOUT_FIELD,YR_OVERRIDE,TEXT(YEAR_Y-3,"0"))/100,""))) | AH12: =IF($C12="","",IF(PULL_FUND="N","",IFERROR(BDP($C12,PAYOUT_FIELD,YR_OVERRIDE,TEXT(YEAR_Y-2,"0"))/100,""))) | AI12: =IF($C12="","",IF(PULL_FUND="N","",IFERROR(BDP($C12,PAYOUT_FIELD,YR_OVERRIDE,TEXT(YEAR_Y-1,"0"))/100,""))) | AJ12: =IF($C12="","",IFERROR(AVERAGE(AE12:AI12),"")) | AK12: =IF($C12="","",IF(ISNUMBER($AD12)*ISNUMBER($N12)*($AD12<>0)=0,"",$N12/$AD12)) | AL12: =IF($C12="","",IF(ISNUMBER($AD12)*($AD12<>0)=0,"",$M12/$AD12)) | AM12: =IF($C12="","",IF(ISNUMBER($AE12)*ISNUMBER($AI12)=0,"",IF($AI12>$AE12+0.05,"rising",IF($AI12<$AE12-0.05,"falling","stable")))) | AN12: =IF($C12="","",IF(PULL_FUND="N","",IF(COUNTIFS('Fund History'!$G$8:$G$12,">="&DATE(YEAR_Y-4,1,1),'Fund History'!$G$8:$G$12,"<="&DATE(YEAR_Y-4,12,31))=0,"",SUMIFS('Fund History'!$H$8:$H$12,'Fund History'!$G$8:$G$12,">="&DATE(YEAR_Y-4,1,1),'Fund History'!$G$8:$G$12,"<="&DATE(YEAR_Y-4,12,31))/100))) | AO12: =IF($C12="","",IF(PULL_FUND="N","",IF(COUNTIFS('Fund History'!$G$8:$G$12,">="&DATE(YEAR_Y-3,1,1),'Fund History'!$G$8:$G$12,"<="&DATE(YEAR_Y-3,12,31))=0,"",SUMIFS('Fund History'!$H$8:$H$12,'Fund History'!$G$8:$G$12,">="&DATE(YEAR_Y-3,1,1),'Fund History'!$G$8:$G$12,"<="&DATE(YEAR_Y-3,12,31))/100))) | AP12: =IF($C12="","",IF(PULL_FUND="N","",IF(COUNTIFS('Fund History'!$G$8:$G$12,">="&DATE(YEAR_Y-2,1,1),'Fund History'!$G$8:$G$12,"<="&DATE(YEAR_Y-2,12,31))=0,"",SUMIFS('Fund History'!$H$8:$H$12,'Fund History'!$G$8:$G$12,">="&DATE(YEAR_Y-2,1,1),'Fund History'!$G$8:$G$12,"<="&DATE(YEAR_Y-2,12,31))/100))) | AQ12: =IF($C12="","",IF(PULL_FUND="N","",IF(COUNTIFS('Fund History'!$G$8:$G$12,">="&DATE(YEAR_Y-1,1,1),'Fund History'!$G$8:$G$12,"<="&DATE(YEAR_Y-1,12,31))=0,"",SUMIFS('Fund History'!$H$8:$H$12,'Fund History'!$G$8:$G$12,">="&DATE(YEAR_Y-1,1,1),'Fund History'!$G$8:$G$12,"<="&DATE(YEAR_Y-1,12,31))/100))) | AR12: =IF($C12="","",IF(N($AQ12)+N(HSI!$I$7)=0,"",N($AQ12)+N(HSI!$I$7)/100)) | AS12: =IF($C12="","",IF(PULL_FUND="N","",IF(COUNTIFS('Fund History'!$D$8:$D$12,">="&DATE(YEAR_Y-2,1,1),'Fund History'!$D$8:$D$12,"<="&DATE(YEAR_Y-2,12,31))=0,"",SUMIFS('Fund History'!$E$8:$E$12,'Fund History'!$D$8:$D$12,">="&DATE(YEAR_Y-2,1,1),'Fund History'!$D$8:$D$12,"<="&DATE(YEAR_Y-2,12,31))))) | AT12: =IF($C12="","",IF(PULL_FUND="N","",IF(COUNTIFS('Fund History'!$D$8:$D$12,">="&DATE(YEAR_Y-1,1,1),'Fund History'!$D$8:$D$12,"<="&DATE(YEAR_Y-1,12,31))=0,"",SUMIFS('Fund History'!$E$8:$E$12,'Fund History'!$D$8:$D$12,">="&DATE(YEAR_Y-1,1,1),'Fund History'!$D$8:$D$12,"<="&DATE(YEAR_Y-1,12,31))))) | AU12: =IF($C12="","",IF(PULL_FUND="N","",IFERROR(BDP($C12,NDEBITDA_FIELD),""))) | AV12: =IF($C12="","",IF(PULL_FUND="N","",IFERROR(BDP($C12,EBINT_FIELD),""))) | AW12: =IF($C12="","",IF(PULL_FUND="N","",IFERROR(BDP($C12,FCF_FIELD)/100,""))) | AX12: =IF($C12="","",IF(N($U12)=0,"",IFERROR($AW12/$U12,""))) | AY12: =IF($C12="","",TRIM(IF(ISNUMBER($AJ12)*(N($AJ12)>$D$4)>0,"payout high ","")&IF(ISNUMBER($AX12)*(N($AX12)<$F$4)>0,"FCF below dvd ","")&IF(ISNUMBER($AU12)*(N($AU12)>$H$4)>0,"leverage high",""))) | AZ12: =IF($C12="","",IF(HSI!$F$7="HKD","",HSI!$F$7))
B13: HSI | C13: =IF(HSI!$C$8="","",HSI!$C$8) | D13: =IF($C13="","",HSI!$D$8) | E13: =IF($C13="","",HSI!$E$8) | F13: =IF($C13="","",SUMPRODUCT(('Dvd Calendar'!$E$22:$AR$22>=DATE(YEAR_Y-5,1,1))*('Dvd Calendar'!$E$22:$AR$22<=DATE(YEAR_Y-5,12,31))*'Dvd Calendar'!$E$25:$AR$25*(('Dvd Calendar'!$E$27:$AR$27=TYPE1)*(TYPE1<>"")+('Dvd Calendar'!$E$27:$AR$27=TYPE2)*(TYPE2<>"")+('Dvd Calendar'!$E$27:$AR$27=TYPE3)*(TYPE3<>"")+('Dvd Calendar'!$E$27:$AR$27=TYPE4)*(TYPE4<>"")+('Dvd Calendar'!$E$27:$AR$27=SPECIAL_LBL)*(INC_SPECIALS="Y")))) | G13: =IF($C13="","",SUMPRODUCT(('Dvd Calendar'!$E$22:$AR$22>=DATE(YEAR_Y-4,1,1))*('Dvd Calendar'!$E$22:$AR$22<=DATE(YEAR_Y-4,12,31))*'Dvd Calendar'!$E$25:$AR$25*(('Dvd Calendar'!$E$27:$AR$27=TYPE1)*(TYPE1<>"")+('Dvd Calendar'!$E$27:$AR$27=TYPE2)*(TYPE2<>"")+('Dvd Calendar'!$E$27:$AR$27=TYPE3)*(TYPE3<>"")+('Dvd Calendar'!$E$27:$AR$27=TYPE4)*(TYPE4<>"")+('Dvd Calendar'!$E$27:$AR$27=SPECIAL_LBL)*(INC_SPECIALS="Y")))) | H13: =IF($C13="","",SUMPRODUCT(('Dvd Calendar'!$E$22:$AR$22>=DATE(YEAR_Y-3,1,1))*('Dvd Calendar'!$E$22:$AR$22<=DATE(YEAR_Y-3,12,31))*'Dvd Calendar'!$E$25:$AR$25*(('Dvd Calendar'!$E$27:$AR$27=TYPE1)*(TYPE1<>"")+('Dvd Calendar'!$E$27:$AR$27=TYPE2)*(TYPE2<>"")+('Dvd Calendar'!$E$27:$AR$27=TYPE3)*(TYPE3<>"")+('Dvd Calendar'!$E$27:$AR$27=TYPE4)*(TYPE4<>"")+('Dvd Calendar'!$E$27:$AR$27=SPECIAL_LBL)*(INC_SPECIALS="Y")))) | I13: =IF($C13="","",SUMPRODUCT(('Dvd Calendar'!$E$22:$AR$22>=DATE(YEAR_Y-2,1,1))*('Dvd Calendar'!$E$22:$AR$22<=DATE(YEAR_Y-2,12,31))*'Dvd Calendar'!$E$25:$AR$25*(('Dvd Calendar'!$E$27:$AR$27=TYPE1)*(TYPE1<>"")+('Dvd Calendar'!$E$27:$AR$27=TYPE2)*(TYPE2<>"")+('Dvd Calendar'!$E$27:$AR$27=TYPE3)*(TYPE3<>"")+('Dvd Calendar'!$E$27:$AR$27=TYPE4)*(TYPE4<>"")+('Dvd Calendar'!$E$27:$AR$27=SPECIAL_LBL)*(INC_SPECIALS="Y")))) | J13: =IF($C13="","",SUMPRODUCT(('Dvd Calendar'!$E$22:$AR$22>=DATE(YEAR_Y-1,1,1))*('Dvd Calendar'!$E$22:$AR$22<=DATE(YEAR_Y-1,12,31))*'Dvd Calendar'!$E$25:$AR$25*(('Dvd Calendar'!$E$27:$AR$27=TYPE1)*(TYPE1<>"")+('Dvd Calendar'!$E$27:$AR$27=TYPE2)*(TYPE2<>"")+('Dvd Calendar'!$E$27:$AR$27=TYPE3)*(TYPE3<>"")+('Dvd Calendar'!$E$27:$AR$27=TYPE4)*(TYPE4<>"")+('Dvd Calendar'!$E$27:$AR$27=SPECIAL_LBL)*(INC_SPECIALS="Y")))) | K13: =IF($C13="","",HSI!$J$8) | L13: =IF($C13="","",HSI!$K$8) | M13: =IF($C13="","",HSI!$J$8+HSI!$L$8) | N13: =IF($C13="","",IF(PULL_FUND="N","",IFERROR(BDP($C13,BESTDPS_FIELD,FWD_OVERRIDE,TEXT(MOD(YEAR_Y,100),"00")&"Y"),""))) | O13: =IF($C13="","",AVERAGE(F13:J13)) | P13: =IF($C13="","",IF(PULL_FUND="N","",IF(COUNTIFS('Fund History'!$J$14:$J$18,">="&DATE(YEAR_Y-5,1,1),'Fund History'!$J$14:$J$18,"<="&DATE(YEAR_Y-5,12,31))=0,"",IFERROR($F13*HSI!$G$8/SUMIFS('Fund History'!$K$14:$K$18,'Fund History'!$J$14:$J$18,">="&DATE(YEAR_Y-5,1,1),'Fund History'!$J$14:$J$18,"<="&DATE(YEAR_Y-5,12,31)),"")))) | Q13: =IF($C13="","",IF(PULL_FUND="N","",IF(COUNTIFS('Fund History'!$J$14:$J$18,">="&DATE(YEAR_Y-4,1,1),'Fund History'!$J$14:$J$18,"<="&DATE(YEAR_Y-4,12,31))=0,"",IFERROR($G13*HSI!$G$8/SUMIFS('Fund History'!$K$14:$K$18,'Fund History'!$J$14:$J$18,">="&DATE(YEAR_Y-4,1,1),'Fund History'!$J$14:$J$18,"<="&DATE(YEAR_Y-4,12,31)),"")))) | R13: =IF($C13="","",IF(PULL_FUND="N","",IF(COUNTIFS('Fund History'!$J$14:$J$18,">="&DATE(YEAR_Y-3,1,1),'Fund History'!$J$14:$J$18,"<="&DATE(YEAR_Y-3,12,31))=0,"",IFERROR($H13*HSI!$G$8/SUMIFS('Fund History'!$K$14:$K$18,'Fund History'!$J$14:$J$18,">="&DATE(YEAR_Y-3,1,1),'Fund History'!$J$14:$J$18,"<="&DATE(YEAR_Y-3,12,31)),"")))) | S13: =IF($C13="","",IF(PULL_FUND="N","",IF(COUNTIFS('Fund History'!$J$14:$J$18,">="&DATE(YEAR_Y-2,1,1),'Fund History'!$J$14:$J$18,"<="&DATE(YEAR_Y-2,12,31))=0,"",IFERROR($I13*HSI!$G$8/SUMIFS('Fund History'!$K$14:$K$18,'Fund History'!$J$14:$J$18,">="&DATE(YEAR_Y-2,1,1),'Fund History'!$J$14:$J$18,"<="&DATE(YEAR_Y-2,12,31)),"")))) | T13: =IF($C13="","",IF(PULL_FUND="N","",IF(COUNTIFS('Fund History'!$J$14:$J$18,">="&DATE(YEAR_Y-1,1,1),'Fund History'!$J$14:$J$18,"<="&DATE(YEAR_Y-1,12,31))=0,"",IFERROR($J13*HSI!$G$8/SUMIFS('Fund History'!$K$14:$K$18,'Fund History'!$J$14:$J$18,">="&DATE(YEAR_Y-1,1,1),'Fund History'!$J$14:$J$18,"<="&DATE(YEAR_Y-1,12,31)),"")))) | U13: =IF($C13="","",IF(ISNUMBER(HSI!$I$8),HSI!$I$8/100,"")) | V13: =IF($C13="","",IF(ISNUMBER(HSI!$X$8),IFERROR($M13*HSI!$G$8/HSI!$X$8,""),"")) | W13: =IF($C13="","",IF(ISNUMBER($N13),IFERROR($N13*HSI!$G$8/HSI!$X$8,""),"")) | X13: =IF($C13="","",IF(PULL_FUND="N","",IFERROR(BDP($C13,EPS_FIELD,YR_OVERRIDE,TEXT(YEAR_Y-5,"0")),""))) | Y13: =IF($C13="","",IF(PULL_FUND="N","",IFERROR(BDP($C13,EPS_FIELD,YR_OVERRIDE,TEXT(YEAR_Y-4,"0")),""))) | Z13: =IF($C13="","",IF(PULL_FUND="N","",IFERROR(BDP($C13,EPS_FIELD,YR_OVERRIDE,TEXT(YEAR_Y-3,"0")),""))) | AA13: =IF($C13="","",IF(PULL_FUND="N","",IFERROR(BDP($C13,EPS_FIELD,YR_OVERRIDE,TEXT(YEAR_Y-2,"0")),""))) | AB13: =IF($C13="","",IF(PULL_FUND="N","",IFERROR(BDP($C13,EPS_FIELD,YR_OVERRIDE,TEXT(YEAR_Y-1,"0")),""))) | AC13: =IF($C13="","",IFERROR(AVERAGE(X13:AB13),"")) | AD13: =IF($C13="","",IF(PULL_FUND="N","",IFERROR(BDP($C13,BESTEPS_FIELD,FWD_OVERRIDE,TEXT(MOD(YEAR_Y,100),"00")&"Y"),""))) | AE13: =IF($C13="","",IF(PULL_FUND="N","",IFERROR(BDP($C13,PAYOUT_FIELD,YR_OVERRIDE,TEXT(YEAR_Y-5,"0"))/100,""))) | AF13: =IF($C13="","",IF(PULL_FUND="N","",IFERROR(BDP($C13,PAYOUT_FIELD,YR_OVERRIDE,TEXT(YEAR_Y-4,"0"))/100,""))) | AG13: =IF($C13="","",IF(PULL_FUND="N","",IFERROR(BDP($C13,PAYOUT_FIELD,YR_OVERRIDE,TEXT(YEAR_Y-3,"0"))/100,""))) | AH13: =IF($C13="","",IF(PULL_FUND="N","",IFERROR(BDP($C13,PAYOUT_FIELD,YR_OVERRIDE,TEXT(YEAR_Y-2,"0"))/100,""))) | AI13: =IF($C13="","",IF(PULL_FUND="N","",IFERROR(BDP($C13,PAYOUT_FIELD,YR_OVERRIDE,TEXT(YEAR_Y-1,"0"))/100,""))) | AJ13: =IF($C13="","",IFERROR(AVERAGE(AE13:AI13),"")) | AK13: =IF($C13="","",IF(ISNUMBER($AD13)*ISNUMBER($N13)*($AD13<>0)=0,"",$N13/$AD13)) | AL13: =IF($C13="","",IF(ISNUMBER($AD13)*($AD13<>0)=0,"",$M13/$AD13)) | AM13: =IF($C13="","",IF(ISNUMBER($AE13)*ISNUMBER($AI13)=0,"",IF($AI13>$AE13+0.05,"rising",IF($AI13<$AE13-0.05,"falling","stable")))) | AN13: =IF($C13="","",IF(PULL_FUND="N","",IF(COUNTIFS('Fund History'!$G$14:$G$18,">="&DATE(YEAR_Y-4,1,1),'Fund History'!$G$14:$G$18,"<="&DATE(YEAR_Y-4,12,31))=0,"",SUMIFS('Fund History'!$H$14:$H$18,'Fund History'!$G$14:$G$18,">="&DATE(YEAR_Y-4,1,1),'Fund History'!$G$14:$G$18,"<="&DATE(YEAR_Y-4,12,31))/100))) | AO13: =IF($C13="","",IF(PULL_FUND="N","",IF(COUNTIFS('Fund History'!$G$14:$G$18,">="&DATE(YEAR_Y-3,1,1),'Fund History'!$G$14:$G$18,"<="&DATE(YEAR_Y-3,12,31))=0,"",SUMIFS('Fund History'!$H$14:$H$18,'Fund History'!$G$14:$G$18,">="&DATE(YEAR_Y-3,1,1),'Fund History'!$G$14:$G$18,"<="&DATE(YEAR_Y-3,12,31))/100))) | AP13: =IF($C13="","",IF(PULL_FUND="N","",IF(COUNTIFS('Fund History'!$G$14:$G$18,">="&DATE(YEAR_Y-2,1,1),'Fund History'!$G$14:$G$18,"<="&DATE(YEAR_Y-2,12,31))=0,"",SUMIFS('Fund History'!$H$14:$H$18,'Fund History'!$G$14:$G$18,">="&DATE(YEAR_Y-2,1,1),'Fund History'!$G$14:$G$18,"<="&DATE(YEAR_Y-2,12,31))/100))) | AQ13: =IF($C13="","",IF(PULL_FUND="N","",IF(COUNTIFS('Fund History'!$G$14:$G$18,">="&DATE(YEAR_Y-1,1,1),'Fund History'!$G$14:$G$18,"<="&DATE(YEAR_Y-1,12,31))=0,"",SUMIFS('Fund History'!$H$14:$H$18,'Fund History'!$G$14:$G$18,">="&DATE(YEAR_Y-1,1,1),'Fund History'!$G$14:$G$18,"<="&DATE(YEAR_Y-1,12,31))/100))) | AR13: =IF($C13="","",IF(N($AQ13)+N(HSI!$I$8)=0,"",N($AQ13)+N(HSI!$I$8)/100)) | AS13: =IF($C13="","",IF(PULL_FUND="N","",IF(COUNTIFS('Fund History'!$D$14:$D$18,">="&DATE(YEAR_Y-2,1,1),'Fund History'!$D$14:$D$18,"<="&DATE(YEAR_Y-2,12,31))=0,"",SUMIFS('Fund History'!$E$14:$E$18,'Fund History'!$D$14:$D$18,">="&DATE(YEAR_Y-2,1,1),'Fund History'!$D$14:$D$18,"<="&DATE(YEAR_Y-2,12,31))))) | AT13: =IF($C13="","",IF(PULL_FUND="N","",IF(COUNTIFS('Fund History'!$D$14:$D$18,">="&DATE(YEAR_Y-1,1,1),'Fund History'!$D$14:$D$18,"<="&DATE(YEAR_Y-1,12,31))=0,"",SUMIFS('Fund History'!$E$14:$E$18,'Fund History'!$D$14:$D$18,">="&DATE(YEAR_Y-1,1,1),'Fund History'!$D$14:$D$18,"<="&DATE(YEAR_Y-1,12,31))))) | AU13: =IF($C13="","",IF(PULL_FUND="N","",IFERROR(BDP($C13,NDEBITDA_FIELD),""))) | AV13: =IF($C13="","",IF(PULL_FUND="N","",IFERROR(BDP($C13,EBINT_FIELD),""))) | AW13: =IF($C13="","",IF(PULL_FUND="N","",IFERROR(BDP($C13,FCF_FIELD)/100,""))) | AX13: =IF($C13="","",IF(N($U13)=0,"",IFERROR($AW13/$U13,""))) | AY13: =IF($C13="","",TRIM(IF(ISNUMBER($AJ13)*(N($AJ13)>$D$4)>0,"payout high ","")&IF(ISNUMBER($AX13)*(N($AX13)<$F$4)>0,"FCF below dvd ","")&IF(ISNUMBER($AU13)*(N($AU13)>$H$4)>0,"leverage high",""))) | AZ13: =IF($C13="","",IF(HSI!$F$8="HKD","",HSI!$F$8))
